Workbook

Sheet Overview
C4: Financial Model
C7: https://tobe.energy
C10: Table of Contents
C12: Model Assumptions
C13: Financials
C14: Project Overview
C15: H2 Cost Assumptions
C16: H2 Production Costs
C17: Personnel
C18: Volumes at Electric Loads
C19: Facility AFE
C20: Additional Engineering Detail

Sheet Model Assumptions
B1: Year Counter | G1: 1 | H1: 1 | I1: 1 | J1: 1 | K1: 1 | L1: 1 | M1: 1 | N1: 1 | O1: 1 | P1: 1 | Q1: 1 | R1: 1 | S1: 2 | T1: 2 | U1: 2 | V1: 2 | W1: 2 | X1: 2 | Y1: 2 | Z1: 2 | AA1: 2 | AB1: 2 | AC1: 2 | AD1: 2 | AE1: 3 | AF1: 3 | AG1: 3 | AH1: 3 | AI1: 3 | AJ1: 3 | AK1: 3 | AL1: 3 | AM1: 3 | AN1: 3 | AO1: 3 | AP1: 3 | AQ1: 4 | AR1: 4 | AS1: 4 | AT1: 4 | AU1: 4 | AV1: 4 | AW1: 4 | AX1: 4 | AY1: 4 | AZ1: 4 | BA1: 4 | BB1: 4 | BC1: 5 | BD1: 5 | BE1: 5 | BF1: 5 | BG1: 5 | BH1: 5 | BI1: 5 | BJ1: 5 | BK1: 5 | BL1: 5 | BM1: 5 | BN1: 5 | BO1: 6 | BP1: 6 | BQ1: 6 | BR1: 6 | BS1: 6 | BT1: 6 | BU1: 6 | BV1: 6 | BW1: 6 | BX1: 6 | BY1: 6 | BZ1: 6 | CA1: 7 | CB1: 7 | CC1: 7 | CD1: 7 | CE1: 7 | CF1: 7 | CG1: 7 | CH1: 7 | CI1: 7 | CJ1: 7 | CK1: 7 | CL1: 7
B2: Year | G2: 2025 | H2: 2025 | I2: 2025 | J2: 2025 | K2: 2025 | L2: 2025 | M2: 2026 | N2: 2026 | O2: 2026 | P2: 2026 | Q2: 2026 | R2: 2026 | S2: 2026 | T2: 2026 | U2: 2026 | V2: 2026 | W2: 2026 | X2: 2026 | Y2: 2027 | Z2: 2027 | AA2: 2027 | AB2: 2027 | AC2: 2027 | AD2: 2027 | AE2: 2027 | AF2: 2027 | AG2: 2027 | AH2: 2027 | AI2: 2027 | AJ2: 2027 | AK2: 2028 | AL2: 2028 | AM2: 2028 | AN2: 2028 | AO2: 2028 | AP2: 2028 | AQ2: 2028 | AR2: 2028 | AS2: 2028 | AT2: 2028 | AU2: 2028 | AV2: 2028 | AW2: 2029 | AX2: 2029 | AY2: 2029 | AZ2: 2029 | BA2: 2029 | BB2: 2029 | BC2: 2029 | BD2: 2029 | BE2: 2029 | BF2: 2029 | BG2: 2029 | BH2: 2029 | BI2: 2030 | BJ2: 2030 | BK2: 2030 | BL2: 2030 | BM2: 2030 | BN2: 2030 | BO2: 2030 | BP2: 2030 | BQ2: 2030 | BR2: 2030 | BS2: 2030 | BT2: 2030 | BU2: 2031 | BV2: 2031 | BW2: 2031 | BX2: 2031 | BY2: 2031 | BZ2: 2031 | CA2: =2024+CA1 -> 2031 | CB2: =2024+CB1 -> 2031 | CC2: =2024+CC1 -> 2031 | CD2: =2024+CD1 -> 2031 | CE2: =2024+CE1 -> 2031 | CF2: =2024+CF1 -> 2031 | CG2: 2032 | CH2: 2032 | CI2: 2032 | CJ2: 2032 | CK2: 2032 | CL2: 2032
B3: Month Counter | G3: 1 | H3: 2 | I3: 3 | J3: 4 | K3: 5 | L3: 6 | M3: 7 | N3: 8 | O3: 9 | P3: 10 | Q3: 11 | R3: 12 | S3: 13 | T3: 14 | U3: 15 | V3: 16 | W3: 17 | X3: 18 | Y3: 19 | Z3: 20 | AA3: 21 | AB3: 22 | AC3: 23 | AD3: 24 | AE3: 25 | AF3: 26 | AG3: 27 | AH3: 28 | AI3: 29 | AJ3: 30 | AK3: 31 | AL3: 32 | AM3: 33 | AN3: 34 | AO3: 35 | AP3: 36 | AQ3: 37 | AR3: 38 | AS3: 39 | AT3: 40 | AU3: 41 | AV3: 42 | AW3: 43 | AX3: 44 | AY3: 45 | AZ3: 46 | BA3: 47 | BB3: 48 | BC3: 49 | BD3: 50 | BE3: 51 | BF3: 52 | BG3: 53 | BH3: 54 | BI3: 55 | BJ3: 56 | BK3: 57 | BL3: 58 | BM3: 59 | BN3: 60 | BO3: 61 | BP3: 62 | BQ3: 63 | BR3: 64 | BS3: 65 | BT3: 66 | BU3: 67 | BV3: 68 | BW3: 69 | BX3: 70 | BY3: 71 | BZ3: 72 | CA3: 73 | CB3: 74 | CC3: 75 | CD3: 76 | CE3: 77 | CF3: 78 | CG3: 79 | CH3: 80 | CI3: 81 | CJ3: 82 | CK3: 83 | CL3: 84
B4: Date | G4: 45839 | H4: 45870 | I4: 45901 | J4: 45931 | K4: 45962 | L4: 45992 | M4: 46023 | N4: 46054 | O4: 46082 | P4: 46113 | Q4: 46143 | R4: 46174 | S4: 46204 | T4: 46235 | U4: 46266 | V4: 46296 | W4: 46327 | X4: 46357 | Y4: 46388 | Z4: 46419 | AA4: 46447 | AB4: 46478 | AC4: 46508 | AD4: 46539 | AE4: 46569 | AF4: 46600 | AG4: 46631 | AH4: 46661 | AI4: 46692 | AJ4: 46722 | AK4: 46753 | AL4: 46784 | AM4: 46813 | AN4: 46844 | AO4: 46874 | AP4: 46905 | AQ4: 46935 | AR4: 46966 | AS4: 46997 | AT4: 47027 | AU4: 47058 | AV4: 47088 | AW4: 47119 | AX4: 47150 | AY4: 47178 | AZ4: 47209 | BA4: 47239 | BB4: 47270 | BC4: 47300 | BD4: 47331 | BE4: 47362 | BF4: 47392 | BG4: 47423 | BH4: 47453 | BI4: 47484 | BJ4: 47515 | BK4: 47543 | BL4: 47574 | BM4: 47604 | BN4: 47635 | BO4: 47665 | BP4: 47696 | BQ4: 47727 | BR4: 47757 | BS4: 47788 | BT4: 47818 | BU4: 47849 | BV4: 47880 | BW4: 47908 | BX4: 47939 | BY4: 47969 | BZ4: 48000 | CA4: 48030 | CB4: 48061 | CC4: 48092 | CD4: 48122 | CE4: 48153 | CF4: 48183 | CG4: 48214 | CH4: 48245 | CI4: 48274 | CJ4: 48305 | CK4: 48335 | CL4: 48366
B6: Tobe Energy Corp. Overall
C7: Total Cost | G7: =G12+G13+G20+G21+G28+G29+G36+G37+G44+G45+G52+G53+G60+G61 -> 370833.33 | H7: =H12+H13+H20+H21+H28+H29+H36+H37+H44+H45+H52+H53+H60+H61 -> 370833.33 | I7: =I12+I13+I20+I21+I28+I29+I36+I37+I44+I45+I52+I53+I60+I61 -> 370833.33 | J7: =J12+J13+J20+J21+J28+J29+J36+J37+J44+J45+J52+J53+J60+J61 -> 370833.33 | K7: =K12+K13+K20+K21+K28+K29+K36+K37+K44+K45+K52+K53+K60+K61 -> 370833.33 | L7: =L12+L13+L20+L21+L28+L29+L36+L37+L44+L45+L52+L53+L60+L61 -> 370833.33 | M7: =M12+M13+M20+M21+M28+M29+M36+M37+M44+M45+M52+M53+M60+M61 -> 370833.33 | N7: =N12+N13+N20+N21+N28+N29+N36+N37+N44+N45+N52+N53+N60+N61 -> 370833.33 | ... CL7: =CL12+CL13+CL20+CL21+CL28+CL29+CL36+CL37+CL44+CL45+CL52+CL53+CL60+CL61 -> 1457151.8
C8: Total Production | G8: =G14+G22+G30+G38+G46+G54+G62 -> 0 | H8: =H14+H22+H30+H38+H46+H54+H62 -> 0 | I8: =I14+I22+I30+I38+I46+I54+I62 -> 0 | J8: =J14+J22+J30+J38+J46+J54+J62 -> 0 | K8: =K14+K22+K30+K38+K46+K54+K62 -> 0 | L8: =L14+L22+L30+L38+L46+L54+L62 -> 0 | M8: =M14+M22+M30+M38+M46+M54+M62 -> 0 | N8: =N14+N22+N30+N38+N46+N54+N62 -> 0 | ... CL8: =CL14+CL22+CL30+CL38+CL46+CL54+CL62 -> 900000
C9: Total Profit | G9: =(G17+G25+G33+G41+G49+G57+G65)-G7 -> -370833.33 | H9: =(H17+H25+H33+H41+H49+H57+H65)-H7 -> -370833.33 | I9: =(I17+I25+I33+I41+I49+I57+I65)-I7 -> -370833.33 | J9: =(J17+J25+J33+J41+J49+J57+J65)-J7 -> -370833.33 | K9: =(K17+K25+K33+K41+K49+K57+K65)-K7 -> -370833.33 | L9: =(L17+L25+L33+L41+L49+L57+L65)-L7 -> -370833.33 | M9: =(M17+M25+M33+M41+M49+M57+M65)-M7 -> -370833.33 | N9: =(N17+N25+N33+N41+N49+N57+N65)-N7 -> -370833.33 | ... CL9: =(CL17+CL25+CL33+CL41+CL49+CL57+CL65)-CL7 -> 18684967
B11: GH2x - OKC
B12: kg Opex | C12: Capital Costs | G12: =('Project Overview'!$C$4/12) -> 266666.67 | H12: =('Project Overview'!$C$4/12) -> 266666.67 | I12: =('Project Overview'!$C$4/12) -> 266666.67 | J12: =('Project Overview'!$C$4/12) -> 266666.67 | K12: =('Project Overview'!$C$4/12) -> 266666.67 | L12: =('Project Overview'!$C$4/12) -> 266666.67 | M12: =('Project Overview'!$C$4/12) -> 266666.67 | N12: =('Project Overview'!$C$4/12) -> 266666.67 | ... R12: =('Project Overview'!$C$4/12) -> 266666.67 | S12: ='Project Overview'!$D$4/12 -> 83333.333 | T12: ='Project Overview'!$D$4/12 -> 83333.333 | U12: ='Project Overview'!$D$4/12 -> 83333.333 | V12: ='Project Overview'!$D$4/12 -> 83333.333 | W12: ='Project Overview'!$D$4/12 -> 83333.333 | X12: ='Project Overview'!$D$4/12 -> 83333.333 | Y12: ='Project Overview'!$D$4/12 -> 83333.333 | Z12: ='Project Overview'!$D$4/12 -> 83333.333 | ... AD12: ='Project Overview'!$D$4/12 -> 83333.333 | AE12: =('Project Overview'!$E$4/12) -> 125000 | AF12: =('Project Overview'!$E$4/12) -> 125000 | AG12: =('Project Overview'!$E$4/12) -> 125000 | AH12: =('Project Overview'!$E$4/12) -> 125000 | AI12: =('Project Overview'!$E$4/12) -> 125000 | AJ12: =('Project Overview'!$E$4/12) -> 125000 | AK12: =('Project Overview'!$E$4/12) -> 125000 | AL12: =('Project Overview'!$E$4/12) -> 125000 | ... AP12: =('Project Overview'!$E$4/12) -> 125000 | AQ12: ='Project Overview'!$F$4/12 -> 0 | AR12: ='Project Overview'!$F$4/12 -> 0 | AS12: ='Project Overview'!$F$4/12 -> 0 | AT12: ='Project Overview'!$F$4/12 -> 0 | AU12: ='Project Overview'!$F$4/12 -> 0 | AV12: ='Project Overview'!$F$4/12 -> 0 | AW12: ='Project Overview'!$F$4/12 -> 0 | AX12: ='Project Overview'!$F$4/12 -> 0 | ... BB12: ='Project Overview'!$F$4/12 -> 0 | BC12: ='Project Overview'!$G$4/12 -> 0 | BD12: ='Project Overview'!$G$4/12 -> 0 | BE12: ='Project Overview'!$G$4/12 -> 0 | BF12: ='Project Overview'!$G$4/12 -> 0 | BG12: ='Project Overview'!$G$4/12 -> 0 | BH12: ='Project Overview'!$G$4/12 -> 0 | BI12: ='Project Overview'!$G$4/12 -> 0 | BJ12: ='Project Overview'!$G$4/12 -> 0 | ... CL12: ='Project Overview'!$G$4/12 -> 0
B13: ='H2 Production Costs'!$D$9 -> 2.6198684 | C13: Personnel | G13: ='Project Overview'!$C$5/12 -> 104166.67 | H13: ='Project Overview'!$C$5/12 -> 104166.67 | I13: ='Project Overview'!$C$5/12 -> 104166.67 | J13: ='Project Overview'!$C$5/12 -> 104166.67 | K13: ='Project Overview'!$C$5/12 -> 104166.67 | L13: ='Project Overview'!$C$5/12 -> 104166.67 | M13: ='Project Overview'!$C$5/12 -> 104166.67 | N13: ='Project Overview'!$C$5/12 -> 104166.67 | ... R13: ='Project Overview'!$C$5/12 -> 104166.67 | S13: ='Project Overview'!$D$5/12 -> 147828.67 | T13: ='Project Overview'!$D$5/12 -> 147828.67 | U13: ='Project Overview'!$D$5/12 -> 147828.67 | V13: ='Project Overview'!$D$5/12 -> 147828.67 | W13: ='Project Overview'!$D$5/12 -> 147828.67 | X13: ='Project Overview'!$D$5/12 -> 147828.67 | Y13: ='Project Overview'!$D$5/12 -> 147828.67 | Z13: ='Project Overview'!$D$5/12 -> 147828.67 | ... AD13: ='Project Overview'!$D$5/12 -> 147828.67 | AE13: ='Project Overview'!$E$5/12 -> 190158.65 | AF13: ='Project Overview'!$E$5/12 -> 190158.65 | AG13: ='Project Overview'!$E$5/12 -> 190158.65 | AH13: ='Project Overview'!$E$5/12 -> 190158.65 | AI13: ='Project Overview'!$E$5/12 -> 190158.65 | AJ13: ='Project Overview'!$E$5/12 -> 190158.65 | AK13: ='Project Overview'!$E$5/12 -> 190158.65 | AL13: ='Project Overview'!$E$5/12 -> 190158.65 | ... AP13: ='Project Overview'!$E$5/12 -> 190158.65 | AQ13: ='Project Overview'!$F$5/12 -> 238714.63 | AR13: ='Project Overview'!$F$5/12 -> 238714.63 | AS13: ='Project Overview'!$F$5/12 -> 238714.63 | AT13: ='Project Overview'!$F$5/12 -> 238714.63 | AU13: ='Project Overview'!$F$5/12 -> 238714.63 | AV13: ='Project Overview'!$F$5/12 -> 238714.63 | AW13: ='Project Overview'!$F$5/12 -> 238714.63 | AX13: ='Project Overview'!$F$5/12 -> 238714.63 | ... BB13: ='Project Overview'!$F$5/12 -> 238714.63 | BC13: ='Project Overview'!$G$5/12 -> 238714.63 | BD13: ='Project Overview'!$G$5/12 -> 238714.63 | BE13: ='Project Overview'!$G$5/12 -> 238714.63 | BF13: ='Project Overview'!$G$5/12 -> 238714.63 | BG13: ='Project Overview'!$G$5/12 -> 238714.63 | BH13: ='Project Overview'!$G$5/12 -> 238714.63 | BI13: ='Project Overview'!$G$5/12 -> 238714.63 | BJ13: ='Project Overview'!$G$5/12 -> 238714.63 | ... CL13: ='Project Overview'!$G$5/12 -> 238714.63
B14: kg Market | C14: Production | G14: 0 | H14: 0 | I14: 0 | J14: 0 | K14: 0 | L14: 0 | M14: 0 | N14: 0 | O14: 0 | P14: 0 | Q14: 0 | R14: 0 | S14: 7500 | T14: 7500 | U14: 7500 | V14: 7500 | W14: 7500 | X14: 7500 | Y14: 37500 | Z14: 37500 | AA14: 37500 | AB14: 37500 | AC14: 37500 | AD14: 37500 | AE14: 37500 | AF14: 37500 | AG14: 37500 | AH14: 37500 | AI14: 37500 | AJ14: 37500 | AK14: 75000 | AL14: 75000 | AM14: 75000 | AN14: 75000 | AO14: 75000 | AP14: 75000 | AQ14: 75000 | AR14: 75000 | AS14: 75000 | AT14: 75000 | AU14: 75000 | AV14: 75000 | AW14: 75000 | AX14: 75000 | AY14: 75000 | AZ14: 75000 | BA14: 75000 | BB14: 75000 | BC14: 75000 | BD14: 75000 | BE14: 75000 | BF14: 75000 | BG14: 75000 | BH14: 75000 | BI14: 75000 | BJ14: 75000 | BK14: 75000 | BL14: 75000 | BM14: 75000 | BN14: 75000 | BO14: 75000 | BP14: 75000 | BQ14: 75000 | BR14: 75000 | BS14: 75000 | BT14: 75000 | BU14: 75000 | BV14: 75000 | BW14: 75000 | BX14: 75000 | BY14: 75000 | BZ14: 75000 | CA14: 75000 | CB14: 75000 | CC14: 75000 | CD14: 75000 | CE14: 75000 | CF14: 75000 | CG14: 75000 | CH14: 75000 | CI14: 75000 | CJ14: 75000 | CK14: 75000 | CL14: 75000
B15: 25 | C15: Revenue | G15: =G14*$B$15 -> 0 | H15: =H14*$B$15 -> 0 | I15: =I14*$B$15 -> 0 | J15: =J14*$B$15 -> 0 | K15: =K14*$B$15 -> 0 | L15: =L14*$B$15 -> 0 | M15: =M14*$B$15 -> 0 | N15: =N14*$B$15 -> 0 | ... CL15: =CL14*$B$15 -> 1875000
C16: COGS | G16: =G14*$B$13 -> 0 | H16: =H14*$B$13 -> 0 | I16: =I14*$B$13 -> 0 | J16: =J14*$B$13 -> 0 | K16: =K14*$B$13 -> 0 | L16: =L14*$B$13 -> 0 | M16: =M14*$B$13 -> 0 | N16: =N14*$B$13 -> 0 | ... CL16: =CL14*$B$13 -> 196490.13
C17: Gross Profit | G17: =G14*($B$15-$B$13) -> 0 | H17: =H14*($B$15-$B$13) -> 0 | I17: =I14*($B$15-$B$13) -> 0 | J17: =J14*($B$15-$B$13) -> 0 | K17: =K14*($B$15-$B$13) -> 0 | L17: =L14*($B$15-$B$13) -> 0 | M17: =M14*($B$15-$B$13) -> 0 | N17: =N14*($B$15-$B$13) -> 0 | ... CL17: =CL14*($B$15-$B$13) -> 1678509.9
F18: =G12*12 -> 3200000
B19: GH2x2 - Tulsa
B20: kg Opex | C20: Capital Costs | S20: ='Project Overview'!$C$12/12 -> 270000 | T20: ='Project Overview'!$C$12/12 -> 270000 | U20: ='Project Overview'!$C$12/12 -> 270000 | V20: ='Project Overview'!$C$12/12 -> 270000 | W20: ='Project Overview'!$C$12/12 -> 270000 | X20: ='Project Overview'!$C$12/12 -> 270000 | Y20: ='Project Overview'!$C$12/12 -> 270000 | Z20: ='Project Overview'!$C$12/12 -> 270000 | ... AD20: ='Project Overview'!$C$12/12 -> 270000 | AE20: ='Project Overview'!$D$12/12 -> 125000 | AF20: ='Project Overview'!$D$12/12 -> 125000 | AG20: ='Project Overview'!$D$12/12 -> 125000 | AH20: ='Project Overview'!$D$12/12 -> 125000 | AI20: ='Project Overview'!$D$12/12 -> 125000 | AJ20: ='Project Overview'!$D$12/12 -> 125000 | AK20: ='Project Overview'!$D$12/12 -> 125000 | AL20: ='Project Overview'!$D$12/12 -> 125000 | ... AP20: ='Project Overview'!$D$12/12 -> 125000 | AQ20: ='Project Overview'!$E$12/12 -> 0 | AR20: ='Project Overview'!$E$12/12 -> 0 | AS20: ='Project Overview'!$E$12/12 -> 0 | AT20: ='Project Overview'!$E$12/12 -> 0 | AU20: ='Project Overview'!$E$12/12 -> 0 | AV20: ='Project Overview'!$E$12/12 -> 0 | AW20: ='Project Overview'!$E$12/12 -> 0 | AX20: ='Project Overview'!$E$12/12 -> 0 | ... BB20: ='Project Overview'!$E$12/12 -> 0 | BC20: ='Project Overview'!$F$12/12 -> 0 | BD20: ='Project Overview'!$F$12/12 -> 0 | BE20: ='Project Overview'!$F$12/12 -> 0 | BF20: ='Project Overview'!$F$12/12 -> 0 | BG20: ='Project Overview'!$F$12/12 -> 0 | BH20: ='Project Overview'!$F$12/12 -> 0 | BI20: ='Project Overview'!$F$12/12 -> 0 | BJ20: ='Project Overview'!$F$12/12 -> 0 | ... BN20: ='Project Overview'!$F$12/12 -> 0 | BO20: ='Project Overview'!$G$12/12 -> 0 | BP20: ='Project Overview'!$G$12/12 -> 0 | BQ20: ='Project Overview'!$G$12/12 -> 0 | BR20: ='Project Overview'!$G$12/12 -> 0 | BS20: ='Project Overview'!$G$12/12 -> 0 | BT20: ='Project Overview'!$G$12/12 -> 0 | BU20: ='Project Overview'!$G$12/12 -> 0 | BV20: ='Project Overview'!$G$12/12 -> 0 | ... CL20: ='Project Overview'!$G$12/12 -> 0
B21: ='H2 Production Costs'!$D$9 -> 2.6198684 | C21: Personnel | S21: ='Project Overview'!$C$13/12 -> 68107.667 | T21: ='Project Overview'!$C$13/12 -> 68107.667 | U21: ='Project Overview'!$C$13/12 -> 68107.667 | V21: ='Project Overview'!$C$13/12 -> 68107.667 | W21: ='Project Overview'!$C$13/12 -> 68107.667 | X21: ='Project Overview'!$C$13/12 -> 68107.667 | Y21: ='Project Overview'!$C$13/12 -> 68107.667 | Z21: ='Project Overview'!$C$13/12 -> 68107.667 | ... AD21: ='Project Overview'!$C$13/12 -> 68107.667 | AE21: ='Project Overview'!$D$13/12 -> 90171.117 | AF21: ='Project Overview'!$D$13/12 -> 90171.117 | AG21: ='Project Overview'!$D$13/12 -> 90171.117 | AH21: ='Project Overview'!$D$13/12 -> 90171.117 | AI21: ='Project Overview'!$D$13/12 -> 90171.117 | AJ21: ='Project Overview'!$D$13/12 -> 90171.117 | AK21: ='Project Overview'!$D$13/12 -> 90171.117 | AL21: ='Project Overview'!$D$13/12 -> 90171.117 | ... AP21: ='Project Overview'!$D$13/12 -> 90171.117 | AQ21: ='Project Overview'!$E$13/12 -> 103696.78 | AR21: ='Project Overview'!$E$13/12 -> 103696.78 | AS21: ='Project Overview'!$E$13/12 -> 103696.78 | AT21: ='Project Overview'!$E$13/12 -> 103696.78 | AU21: ='Project Overview'!$E$13/12 -> 103696.78 | AV21: ='Project Overview'!$E$13/12 -> 103696.78 | AW21: ='Project Overview'!$E$13/12 -> 103696.78 | AX21: ='Project Overview'!$E$13/12 -> 103696.78 | ... BB21: ='Project Overview'!$E$13/12 -> 103696.78 | BC21: ='Project Overview'!$F$13/12 -> 119251.3 | BD21: ='Project Overview'!$F$13/12 -> 119251.3 | BE21: ='Project Overview'!$F$13/12 -> 119251.3 | BF21: ='Project Overview'!$F$13/12 -> 119251.3 | BG21: ='Project Overview'!$F$13/12 -> 119251.3 | BH21: ='Project Overview'!$F$13/12 -> 119251.3 | BI21: ='Project Overview'!$F$13/12 -> 119251.3 | BJ21: ='Project Overview'!$F$13/12 -> 119251.3 | ... BN21: ='Project Overview'!$F$13/12 -> 119251.3 | BO21: ='Project Overview'!$G$13/12 -> 119251.3 | BP21: ='Project Overview'!$G$13/12 -> 119251.3 | BQ21: ='Project Overview'!$G$13/12 -> 119251.3 | BR21: ='Project Overview'!$G$13/12 -> 119251.3 | BS21: ='Project Overview'!$G$13/12 -> 119251.3 | BT21: ='Project Overview'!$G$13/12 -> 119251.3 | BU21: ='Project Overview'!$G$13/12 -> 119251.3 | BV21: ='Project Overview'!$G$13/12 -> 119251.3 | ... CL21: ='Project Overview'!$G$13/12 -> 119251.3
B22: kg Market | C22: Production | S22: 0 | T22: 0 | U22: 0 | V22: 0 | W22: 0 | X22: 0 | Y22: 0 | Z22: 0 | AA22: 0 | AB22: 0 | AC22: 0 | AD22: 0 | AE22: 37500 | AF22: 37500 | AG22: 37500 | AH22: 37500 | AI22: 37500 | AJ22: 37500 | AK22: 37500 | AL22: 37500 | AM22: 37500 | AN22: 37500 | AO22: 37500 | AP22: 37500 | AQ22: 75000 | AR22: 75000 | AS22: 75000 | AT22: 75000 | AU22: 75000 | AV22: 75000 | AW22: 75000 | AX22: 75000 | AY22: 75000 | AZ22: 75000 | BA22: 75000 | BB22: 75000 | BC22: 75000 | BD22: 75000 | BE22: 75000 | BF22: 75000 | BG22: 75000 | BH22: 75000 | BI22: 75000 | BJ22: 75000 | BK22: 75000 | BL22: 75000 | BM22: 75000 | BN22: 75000 | BO22: 75000 | BP22: 75000 | BQ22: 75000 | BR22: 75000 | BS22: 75000 | BT22: 75000 | BU22: 75000 | BV22: 75000 | BW22: 75000 | BX22: 75000 | BY22: 75000 | BZ22: 75000 | CA22: 75000 | CB22: 75000 | CC22: 75000 | CD22: 75000 | CE22: 75000 | CF22: 75000 | CG22: 75000 | CH22: 75000 | CI22: 75000 | CJ22: 75000 | CK22: 75000 | CL22: 75000
B23: 25 | C23: Revenue | G23: =G22*$B$15 -> 0 | H23: =H22*$B$15 -> 0 | I23: =I22*$B$15 -> 0 | J23: =J22*$B$15 -> 0 | K23: =K22*$B$15 -> 0 | L23: =L22*$B$15 -> 0 | M23: =M22*$B$15 -> 0 | N23: =N22*$B$15 -> 0 | ... CL23: =CL22*$B$15 -> 1875000
C24: COGS | G24: =G22*$B$13 -> 0 | H24: =H22*$B$13 -> 0 | I24: =I22*$B$13 -> 0 | J24: =J22*$B$13 -> 0 | K24: =K22*$B$13 -> 0 | L24: =L22*$B$13 -> 0 | M24: =M22*$B$13 -> 0 | N24: =N22*$B$13 -> 0 | ... CL24: =CL22*$B$13 -> 196490.13
C25: Gross Profit | S25: =S22*($B$23-$B$21) -> 0 | T25: =T22*($B$23-$B$21) -> 0 | U25: =U22*($B$23-$B$21) -> 0 | V25: =V22*($B$23-$B$21) -> 0 | W25: =W22*($B$23-$B$21) -> 0 | X25: =X22*($B$23-$B$21) -> 0 | Y25: =Y22*($B$23-$B$21) -> 0 | Z25: =Z22*($B$23-$B$21) -> 0 | ... CL25: =CL22*($B$23-$B$21) -> 1678509.9
S26: =S20*12 -> 3240000 | AE26: =AE20*12 -> 1500000
B27: GH2x3 - Seattle | S27: =S20*12+S12*12 -> 4240000
B28: kg Opex | C28: Capital Costs | AE28: ='Project Overview'!$C$12/12 -> 270000 | AF28: ='Project Overview'!$C$12/12 -> 270000 | AG28: ='Project Overview'!$C$12/12 -> 270000 | AH28: ='Project Overview'!$C$12/12 -> 270000 | AI28: ='Project Overview'!$C$12/12 -> 270000 | AJ28: ='Project Overview'!$C$12/12 -> 270000 | AK28: ='Project Overview'!$C$12/12 -> 270000 | AL28: ='Project Overview'!$C$12/12 -> 270000 | ... AP28: ='Project Overview'!$C$12/12 -> 270000 | AQ28: ='Project Overview'!$D$12/12 -> 125000 | AR28: ='Project Overview'!$D$12/12 -> 125000 | AS28: ='Project Overview'!$D$12/12 -> 125000 | AT28: ='Project Overview'!$D$12/12 -> 125000 | AU28: ='Project Overview'!$D$12/12 -> 125000 | AV28: ='Project Overview'!$D$12/12 -> 125000 | AW28: ='Project Overview'!$D$12/12 -> 125000 | AX28: ='Project Overview'!$D$12/12 -> 125000 | ... BB28: ='Project Overview'!$D$12/12 -> 125000 | BC28: ='Project Overview'!$E$12/12 -> 0 | BD28: ='Project Overview'!$E$12/12 -> 0 | BE28: ='Project Overview'!$E$12/12 -> 0 | BF28: ='Project Overview'!$E$12/12 -> 0 | BG28: ='Project Overview'!$E$12/12 -> 0 | BH28: ='Project Overview'!$E$12/12 -> 0 | BI28: ='Project Overview'!$E$12/12 -> 0 | BJ28: ='Project Overview'!$E$12/12 -> 0 | ... BN28: ='Project Overview'!$E$12/12 -> 0 | BO28: ='Project Overview'!$F$12/12 -> 0 | BP28: ='Project Overview'!$F$12/12 -> 0 | BQ28: ='Project Overview'!$F$12/12 -> 0 | BR28: ='Project Overview'!$F$12/12 -> 0 | BS28: ='Project Overview'!$F$12/12 -> 0 | BT28: ='Project Overview'!$F$12/12 -> 0 | BU28: ='Project Overview'!$F$12/12 -> 0 | BV28: ='Project Overview'!$F$12/12 -> 0 | ... BZ28: ='Project Overview'!$F$12/12 -> 0 | CA28: ='Project Overview'!$G$12/12 -> 0 | CB28: ='Project Overview'!$G$12/12 -> 0 | CC28: ='Project Overview'!$G$12/12 -> 0 | CD28: ='Project Overview'!$G$12/12 -> 0 | CE28: ='Project Overview'!$G$12/12 -> 0 | CF28: ='Project Overview'!$G$12/12 -> 0 | CG28: ='Project Overview'!$G$12/12 -> 0 | CH28: ='Project Overview'!$G$12/12 -> 0 | ... CL28: ='Project Overview'!$G$12/12 -> 0
B29: ='H2 Production Costs'!$D$9 -> 2.6198684 | C29: Personnel | AE29: ='Project Overview'!$C$13/12 -> 68107.667 | AF29: ='Project Overview'!$C$13/12 -> 68107.667 | AG29: ='Project Overview'!$C$13/12 -> 68107.667 | AH29: ='Project Overview'!$C$13/12 -> 68107.667 | AI29: ='Project Overview'!$C$13/12 -> 68107.667 | AJ29: ='Project Overview'!$C$13/12 -> 68107.667 | AK29: ='Project Overview'!$C$13/12 -> 68107.667 | AL29: ='Project Overview'!$C$13/12 -> 68107.667 | ... AP29: ='Project Overview'!$C$13/12 -> 68107.667 | AQ29: ='Project Overview'!$D$13/12 -> 90171.117 | AR29: ='Project Overview'!$D$13/12 -> 90171.117 | AS29: ='Project Overview'!$D$13/12 -> 90171.117 | AT29: ='Project Overview'!$D$13/12 -> 90171.117 | AU29: ='Project Overview'!$D$13/12 -> 90171.117 | AV29: ='Project Overview'!$D$13/12 -> 90171.117 | AW29: ='Project Overview'!$D$13/12 -> 90171.117 | AX29: ='Project Overview'!$D$13/12 -> 90171.117 | ... BB29: ='Project Overview'!$D$13/12 -> 90171.117 | BC29: ='Project Overview'!$E$13/12 -> 103696.78 | BD29: ='Project Overview'!$E$13/12 -> 103696.78 | BE29: ='Project Overview'!$E$13/12 -> 103696.78 | BF29: ='Project Overview'!$E$13/12 -> 103696.78 | BG29: ='Project Overview'!$E$13/12 -> 103696.78 | BH29: ='Project Overview'!$E$13/12 -> 103696.78 | BI29: ='Project Overview'!$E$13/12 -> 103696.78 | BJ29: ='Project Overview'!$E$13/12 -> 103696.78 | ... BN29: ='Project Overview'!$E$13/12 -> 103696.78 | BO29: ='Project Overview'!$F$13/12 -> 119251.3 | BP29: ='Project Overview'!$F$13/12 -> 119251.3 | BQ29: ='Project Overview'!$F$13/12 -> 119251.3 | BR29: ='Project Overview'!$F$13/12 -> 119251.3 | BS29: ='Project Overview'!$F$13/12 -> 119251.3 | BT29: ='Project Overview'!$F$13/12 -> 119251.3 | BU29: ='Project Overview'!$F$13/12 -> 119251.3 | BV29: ='Project Overview'!$F$13/12 -> 119251.3 | ... BZ29: ='Project Overview'!$F$13/12 -> 119251.3 | CA29: ='Project Overview'!$G$13/12 -> 119251.3 | CB29: ='Project Overview'!$G$13/12 -> 119251.3 | CC29: ='Project Overview'!$G$13/12 -> 119251.3 | CD29: ='Project Overview'!$G$13/12 -> 119251.3 | CE29: ='Project Overview'!$G$13/12 -> 119251.3 | CF29: ='Project Overview'!$G$13/12 -> 119251.3 | CG29: ='Project Overview'!$G$13/12 -> 119251.3 | CH29: ='Project Overview'!$G$13/12 -> 119251.3 | ... CL29: ='Project Overview'!$G$13/12 -> 119251.3
B30: kg Market | C30: Production | AE30: 0 | AF30: 0 | AG30: 0 | AH30: 0 | AI30: 0 | AJ30: 0 | AK30: 0 | AL30: 0 | AM30: 0 | AN30: 0 | AO30: 0 | AP30: 0 | AQ30: 37500 | AR30: 37500 | AS30: 37500 | AT30: 37500 | AU30: 37500 | AV30: 37500 | AW30: 37500 | AX30: 37500 | AY30: 37500 | AZ30: 37500 | BA30: 37500 | BB30: 37500 | BC30: 75000 | BD30: 75000 | BE30: 75000 | BF30: 75000 | BG30: 75000 | BH30: 75000 | BI30: 75000 | BJ30: 75000 | BK30: 75000 | BL30: 75000 | BM30: 75000 | BN30: 75000 | BO30: 75000 | BP30: 75000 | BQ30: 75000 | BR30: 75000 | BS30: 75000 | BT30: 75000 | BU30: 75000 | BV30: 75000 | BW30: 75000 | BX30: 75000 | BY30: 75000 | BZ30: 75000 | CA30: 75000 | CB30: 75000 | CC30: 75000 | CD30: 75000 | CE30: 75000 | CF30: 75000 | CG30: 75000 | CH30: 75000 | CI30: 75000 | CJ30: 75000 | CK30: 75000 | CL30: 75000
B31: 25 | C31: Revenue | G31: =G30*$B$15 -> 0 | H31: =H30*$B$15 -> 0 | I31: =I30*$B$15 -> 0 | J31: =J30*$B$15 -> 0 | K31: =K30*$B$15 -> 0 | L31: =L30*$B$15 -> 0 | M31: =M30*$B$15 -> 0 | N31: =N30*$B$15 -> 0 | ... CL31: =CL30*$B$15 -> 1875000
C32: COGS | G32: =G30*$B$13 -> 0 | H32: =H30*$B$13 -> 0 | I32: =I30*$B$13 -> 0 | J32: =J30*$B$13 -> 0 | K32: =K30*$B$13 -> 0 | L32: =L30*$B$13 -> 0 | M32: =M30*$B$13 -> 0 | N32: =N30*$B$13 -> 0 | ... CL32: =CL30*$B$13 -> 196490.13
C33: Gross Profit | AE33: =AE30*($B$31-$B$29) -> 0 | AF33: =AF30*($B$31-$B$29) -> 0 | AG33: =AG30*($B$31-$B$29) -> 0 | AH33: =AH30*($B$31-$B$29) -> 0 | AI33: =AI30*($B$31-$B$29) -> 0 | AJ33: =AJ30*($B$31-$B$29) -> 0 | AK33: =AK30*($B$31-$B$29) -> 0 | AL33: =AL30*($B$31-$B$29) -> 0 | ... CL33: =CL30*($B$31-$B$29) -> 1678509.9
B35: GH2x4 - Spokane | AE35: =AE28*12+AE20*12+AE12*12+AE36*12 -> 9480000
B36: kg Opex | C36: Capital Costs | AE36: ='Project Overview'!$C$12/12 -> 270000 | AF36: ='Project Overview'!$C$12/12 -> 270000 | AG36: ='Project Overview'!$C$12/12 -> 270000 | AH36: ='Project Overview'!$C$12/12 -> 270000 | AI36: ='Project Overview'!$C$12/12 -> 270000 | AJ36: ='Project Overview'!$C$12/12 -> 270000 | AK36: ='Project Overview'!$C$12/12 -> 270000 | AL36: ='Project Overview'!$C$12/12 -> 270000 | ... AP36: ='Project Overview'!$C$12/12 -> 270000 | AQ36: ='Project Overview'!$D$12/12 -> 125000 | AR36: ='Project Overview'!$D$12/12 -> 125000 | AS36: ='Project Overview'!$D$12/12 -> 125000 | AT36: ='Project Overview'!$D$12/12 -> 125000 | AU36: ='Project Overview'!$D$12/12 -> 125000 | AV36: ='Project Overview'!$D$12/12 -> 125000 | AW36: ='Project Overview'!$D$12/12 -> 125000 | AX36: ='Project Overview'!$D$12/12 -> 125000 | ... BB36: ='Project Overview'!$D$12/12 -> 125000 | BC36: ='Project Overview'!$E$12/12 -> 0 | BD36: ='Project Overview'!$E$12/12 -> 0 | BE36: ='Project Overview'!$E$12/12 -> 0 | BF36: ='Project Overview'!$E$12/12 -> 0 | BG36: ='Project Overview'!$E$12/12 -> 0 | BH36: ='Project Overview'!$E$12/12 -> 0 | BI36: ='Project Overview'!$E$12/12 -> 0 | BJ36: ='Project Overview'!$E$12/12 -> 0 | ... BN36: ='Project Overview'!$E$12/12 -> 0 | BO36: ='Project Overview'!$F$12/12 -> 0 | BP36: ='Project Overview'!$F$12/12 -> 0 | BQ36: ='Project Overview'!$F$12/12 -> 0 | BR36: ='Project Overview'!$F$12/12 -> 0 | BS36: ='Project Overview'!$F$12/12 -> 0 | BT36: ='Project Overview'!$F$12/12 -> 0 | BU36: ='Project Overview'!$F$12/12 -> 0 | BV36: ='Project Overview'!$F$12/12 -> 0 | ... BZ36: ='Project Overview'!$F$12/12 -> 0 | CA36: ='Project Overview'!$G$12/12 -> 0 | CB36: ='Project Overview'!$G$12/12 -> 0 | CC36: ='Project Overview'!$G$12/12 -> 0 | CD36: ='Project Overview'!$G$12/12 -> 0 | CE36: ='Project Overview'!$G$12/12 -> 0 | CF36: ='Project Overview'!$G$12/12 -> 0 | CG36: ='Project Overview'!$G$12/12 -> 0 | CH36: ='Project Overview'!$G$12/12 -> 0 | ... CL36: ='Project Overview'!$G$12/12 -> 0
B37: ='H2 Production Costs'!$D$9 -> 2.6198684 | C37: Personnel | AE37: ='Project Overview'!$C$13/12 -> 68107.667 | AF37: ='Project Overview'!$C$13/12 -> 68107.667 | AG37: ='Project Overview'!$C$13/12 -> 68107.667 | AH37: ='Project Overview'!$C$13/12 -> 68107.667 | AI37: ='Project Overview'!$C$13/12 -> 68107.667 | AJ37: ='Project Overview'!$C$13/12 -> 68107.667 | AK37: ='Project Overview'!$C$13/12 -> 68107.667 | AL37: ='Project Overview'!$C$13/12 -> 68107.667 | ... AP37: ='Project Overview'!$C$13/12 -> 68107.667 | AQ37: ='Project Overview'!$D$13/12 -> 90171.117 | AR37: ='Project Overview'!$D$13/12 -> 90171.117 | AS37: ='Project Overview'!$D$13/12 -> 90171.117 | AT37: ='Project Overview'!$D$13/12 -> 90171.117 | AU37: ='Project Overview'!$D$13/12 -> 90171.117 | AV37: ='Project Overview'!$D$13/12 -> 90171.117 | AW37: ='Project Overview'!$D$13/12 -> 90171.117 | AX37: ='Project Overview'!$D$13/12 -> 90171.117 | ... BB37: ='Project Overview'!$D$13/12 -> 90171.117 | BC37: ='Project Overview'!$E$13/12 -> 103696.78 | BD37: ='Project Overview'!$E$13/12 -> 103696.78 | BE37: ='Project Overview'!$E$13/12 -> 103696.78 | BF37: ='Project Overview'!$E$13/12 -> 103696.78 | BG37: ='Project Overview'!$E$13/12 -> 103696.78 | BH37: ='Project Overview'!$E$13/12 -> 103696.78 | BI37: ='Project Overview'!$E$13/12 -> 103696.78 | BJ37: ='Project Overview'!$E$13/12 -> 103696.78 | ... BN37: ='Project Overview'!$E$13/12 -> 103696.78 | BO37: ='Project Overview'!$F$13/12 -> 119251.3 | BP37: ='Project Overview'!$F$13/12 -> 119251.3 | BQ37: ='Project Overview'!$F$13/12 -> 119251.3 | BR37: ='Project Overview'!$F$13/12 -> 119251.3 | BS37: ='Project Overview'!$F$13/12 -> 119251.3 | BT37: ='Project Overview'!$F$13/12 -> 119251.3 | BU37: ='Project Overview'!$F$13/12 -> 119251.3 | BV37: ='Project Overview'!$F$13/12 -> 119251.3 | ... BZ37: ='Project Overview'!$F$13/12 -> 119251.3 | CA37: ='Project Overview'!$G$13/12 -> 119251.3 | CB37: ='Project Overview'!$G$13/12 -> 119251.3 | CC37: ='Project Overview'!$G$13/12 -> 119251.3 | CD37: ='Project Overview'!$G$13/12 -> 119251.3 | CE37: ='Project Overview'!$G$13/12 -> 119251.3 | CF37: ='Project Overview'!$G$13/12 -> 119251.3 | CG37: ='Project Overview'!$G$13/12 -> 119251.3 | CH37: ='Project Overview'!$G$13/12 -> 119251.3 | ... CL37: ='Project Overview'!$G$13/12 -> 119251.3
B38: kg Market | C38: Production | AE38: 0 | AF38: 0 | AG38: 0 | AH38: 0 | AI38: 0 | AJ38: 0 | AK38: 0 | AL38: 0 | AM38: 0 | AN38: 0 | AO38: 0 | AP38: 0 | AQ38: 37500 | AR38: 37500 | AS38: 37500 | AT38: 37500 | AU38: 37500 | AV38: 37500 | AW38: 37500 | AX38: 37500 | AY38: 37500 | AZ38: 37500 | BA38: 37500 | BB38: 37500 | BC38: 75000 | BD38: 75000 | BE38: 75000 | BF38: 75000 | BG38: 75000 | BH38: 75000 | BI38: 75000 | BJ38: 75000 | BK38: 75000 | BL38: 75000 | BM38: 75000 | BN38: 75000 | BO38: 75000 | BP38: 75000 | BQ38: 75000 | BR38: 75000 | BS38: 75000 | BT38: 75000 | BU38: 75000 | BV38: 75000 | BW38: 75000 | BX38: 75000 | BY38: 75000 | BZ38: 75000 | CA38: 75000 | CB38: 75000 | CC38: 75000 | CD38: 75000 | CE38: 75000 | CF38: 75000 | CG38: 75000 | CH38: 75000 | CI38: 75000 | CJ38: 75000 | CK38: 75000 | CL38: 75000
B39: 25 | C39: Revenue | G39: =G38*$B$15 -> 0 | H39: =H38*$B$15 -> 0 | I39: =I38*$B$15 -> 0 | J39: =J38*$B$15 -> 0 | K39: =K38*$B$15 -> 0 | L39: =L38*$B$15 -> 0 | M39: =M38*$B$15 -> 0 | N39: =N38*$B$15 -> 0 | ... CL39: =CL38*$B$15 -> 1875000
C40: COGS | G40: =G38*$B$13 -> 0 | H40: =H38*$B$13 -> 0 | I40: =I38*$B$13 -> 0 | J40: =J38*$B$13 -> 0 | K40: =K38*$B$13 -> 0 | L40: =L38*$B$13 -> 0 | M40: =M38*$B$13 -> 0 | N40: =N38*$B$13 -> 0 | ... CL40: =CL38*$B$13 -> 196490.13
C41: Gross Profit | AE41: =AE38*($B$39-$B$37) -> 0 | AF41: =AF38*($B$39-$B$37) -> 0 | AG41: =AG38*($B$39-$B$37) -> 0 | AH41: =AH38*($B$39-$B$37) -> 0 | AI41: =AI38*($B$39-$B$37) -> 0 | AJ41: =AJ38*($B$39-$B$37) -> 0 | AK41: =AK38*($B$39-$B$37) -> 0 | AL41: =AL38*($B$39-$B$37) -> 0 | ... CL41: =CL38*($B$39-$B$37) -> 1678509.9
B43: GH2x5 - Albuquerque | AQ43: =(AQ28+AQ36+AQ44+AQ52)*12 -> 9480000
B44: kg Opex | C44: Capital Costs | AQ44: ='Project Overview'!$C$12/12 -> 270000 | AR44: ='Project Overview'!$C$12/12 -> 270000 | AS44: ='Project Overview'!$C$12/12 -> 270000 | AT44: ='Project Overview'!$C$12/12 -> 270000 | AU44: ='Project Overview'!$C$12/12 -> 270000 | AV44: ='Project Overview'!$C$12/12 -> 270000 | AW44: ='Project Overview'!$C$12/12 -> 270000 | AX44: ='Project Overview'!$C$12/12 -> 270000 | ... BB44: ='Project Overview'!$C$12/12 -> 270000 | BC44: ='Project Overview'!$D$12/12 -> 125000 | BD44: ='Project Overview'!$D$12/12 -> 125000 | BE44: ='Project Overview'!$D$12/12 -> 125000 | BF44: ='Project Overview'!$D$12/12 -> 125000 | BG44: ='Project Overview'!$D$12/12 -> 125000 | BH44: ='Project Overview'!$D$12/12 -> 125000 | BI44: ='Project Overview'!$D$12/12 -> 125000 | BJ44: ='Project Overview'!$D$12/12 -> 125000 | ... BN44: ='Project Overview'!$D$12/12 -> 125000 | BO44: ='Project Overview'!$E$12/12 -> 0 | BP44: ='Project Overview'!$E$12/12 -> 0 | BQ44: ='Project Overview'!$E$12/12 -> 0 | BR44: ='Project Overview'!$E$12/12 -> 0 | BS44: ='Project Overview'!$E$12/12 -> 0 | BT44: ='Project Overview'!$E$12/12 -> 0 | BU44: ='Project Overview'!$E$12/12 -> 0 | BV44: ='Project Overview'!$E$12/12 -> 0 | ... BZ44: ='Project Overview'!$E$12/12 -> 0 | CA44: ='Project Overview'!$G$12/12 -> 0 | CB44: ='Project Overview'!$G$12/12 -> 0 | CC44: ='Project Overview'!$G$12/12 -> 0 | CD44: ='Project Overview'!$G$12/12 -> 0 | CE44: ='Project Overview'!$G$12/12 -> 0 | CF44: ='Project Overview'!$G$12/12 -> 0 | CG44: ='Project Overview'!$G$12/12 -> 0 | CH44: ='Project Overview'!$G$12/12 -> 0 | ... CL44: ='Project Overview'!$G$12/12 -> 0
B45: ='H2 Production Costs'!$D$9 -> 2.6198684 | C45: Personnel | AQ45: ='Project Overview'!$C$13/12 -> 68107.667 | AR45: ='Project Overview'!$C$13/12 -> 68107.667 | AS45: ='Project Overview'!$C$13/12 -> 68107.667 | AT45: ='Project Overview'!$C$13/12 -> 68107.667 | AU45: ='Project Overview'!$C$13/12 -> 68107.667 | AV45: ='Project Overview'!$C$13/12 -> 68107.667 | AW45: ='Project Overview'!$C$13/12 -> 68107.667 | AX45: ='Project Overview'!$C$13/12 -> 68107.667 | ... BB45: ='Project Overview'!$C$13/12 -> 68107.667 | BC45: ='Project Overview'!$D$13/12 -> 90171.117 | BD45: ='Project Overview'!$D$13/12 -> 90171.117 | BE45: ='Project Overview'!$D$13/12 -> 90171.117 | BF45: ='Project Overview'!$D$13/12 -> 90171.117 | BG45: ='Project Overview'!$D$13/12 -> 90171.117 | BH45: ='Project Overview'!$D$13/12 -> 90171.117 | BI45: ='Project Overview'!$D$13/12 -> 90171.117 | BJ45: ='Project Overview'!$D$13/12 -> 90171.117 | ... BN45: ='Project Overview'!$D$13/12 -> 90171.117 | BO45: ='Project Overview'!$E$13/12 -> 103696.78 | BP45: ='Project Overview'!$E$13/12 -> 103696.78 | BQ45: ='Project Overview'!$E$13/12 -> 103696.78 | BR45: ='Project Overview'!$E$13/12 -> 103696.78 | BS45: ='Project Overview'!$E$13/12 -> 103696.78 | BT45: ='Project Overview'!$E$13/12 -> 103696.78 | BU45: ='Project Overview'!$E$13/12 -> 103696.78 | BV45: ='Project Overview'!$E$13/12 -> 103696.78 | ... BZ45: ='Project Overview'!$E$13/12 -> 103696.78 | CA45: ='Project Overview'!$G$13/12 -> 119251.3 | CB45: ='Project Overview'!$G$13/12 -> 119251.3 | CC45: ='Project Overview'!$G$13/12 -> 119251.3 | CD45: ='Project Overview'!$G$13/12 -> 119251.3 | CE45: ='Project Overview'!$G$13/12 -> 119251.3 | CF45: ='Project Overview'!$G$13/12 -> 119251.3 | CG45: ='Project Overview'!$G$13/12 -> 119251.3 | CH45: ='Project Overview'!$G$13/12 -> 119251.3 | ... CL45: ='Project Overview'!$G$13/12 -> 119251.3
B46: kg Market | C46: Production | AQ46: 0 | AR46: 0 | AS46: 0 | AT46: 0 | AU46: 0 | AV46: 0 | AW46: 0 | AX46: 0 | AY46: 0 | AZ46: 0 | BA46: 0 | BB46: 0 | BC46: 37500 | BD46: 37500 | BE46: 37500 | BF46: 37500 | BG46: 37500 | BH46: 37500 | BI46: 37500 | BJ46: 37500 | BK46: 37500 | BL46: 37500 | BM46: 37500 | BN46: 37500 | BO46: 75000 | BP46: 75000 | BQ46: 75000 | BR46: 75000 | BS46: 75000 | BT46: 75000 | BU46: 75000 | BV46: 75000 | BW46: 75000 | BX46: 75000 | BY46: 75000 | BZ46: 75000 | CA46: 75000 | CB46: 75000 | CC46: 75000 | CD46: 75000 | CE46: 75000 | CF46: 75000 | CG46: 75000 | CH46: 75000 | CI46: 75000 | CJ46: 75000 | CK46: 75000 | CL46: 75000
B47: 25 | C47: Revenue | G47: =G46*$B$15 -> 0 | H47: =H46*$B$15 -> 0 | I47: =I46*$B$15 -> 0 | J47: =J46*$B$15 -> 0 | K47: =K46*$B$15 -> 0 | L47: =L46*$B$15 -> 0 | M47: =M46*$B$15 -> 0 | N47: =N46*$B$15 -> 0 | ... CL47: =CL46*$B$15 -> 1875000
C48: COGS | G48: =G46*$B$13 -> 0 | H48: =H46*$B$13 -> 0 | I48: =I46*$B$13 -> 0 | J48: =J46*$B$13 -> 0 | K48: =K46*$B$13 -> 0 | L48: =L46*$B$13 -> 0 | M48: =M46*$B$13 -> 0 | N48: =N46*$B$13 -> 0 | ... CL48: =CL46*$B$13 -> 196490.13
C49: Gross Profit | AQ49: =AQ46*($B$47-$B$45) -> 0 | AR49: =AR46*($B$47-$B$45) -> 0 | AS49: =AS46*($B$47-$B$45) -> 0 | AT49: =AT46*($B$47-$B$45) -> 0 | AU49: =AU46*($B$47-$B$45) -> 0 | AV49: =AV46*($B$47-$B$45) -> 0 | AW49: =AW46*($B$47-$B$45) -> 0 | AX49: =AX46*($B$47-$B$45) -> 0 | ... CL49: =CL46*($B$47-$B$45) -> 1678509.9
B51: GH2x6 - Des Moines
B52: kg Opex | C52: Capital Costs | AQ52: ='Project Overview'!$C$12/12 -> 270000 | AR52: ='Project Overview'!$C$12/12 -> 270000 | AS52: ='Project Overview'!$C$12/12 -> 270000 | AT52: ='Project Overview'!$C$12/12 -> 270000 | AU52: ='Project Overview'!$C$12/12 -> 270000 | AV52: ='Project Overview'!$C$12/12 -> 270000 | AW52: ='Project Overview'!$C$12/12 -> 270000 | AX52: ='Project Overview'!$C$12/12 -> 270000 | ... BB52: ='Project Overview'!$C$12/12 -> 270000 | BC52: ='Project Overview'!$D$12/12 -> 125000 | BD52: ='Project Overview'!$D$12/12 -> 125000 | BE52: ='Project Overview'!$D$12/12 -> 125000 | BF52: ='Project Overview'!$D$12/12 -> 125000 | BG52: ='Project Overview'!$D$12/12 -> 125000 | BH52: ='Project Overview'!$D$12/12 -> 125000 | BI52: ='Project Overview'!$D$12/12 -> 125000 | BJ52: ='Project Overview'!$D$12/12 -> 125000 | ... BN52: ='Project Overview'!$D$12/12 -> 125000 | BO52: ='Project Overview'!$E$12/12 -> 0 | BP52: ='Project Overview'!$E$12/12 -> 0 | BQ52: ='Project Overview'!$E$12/12 -> 0 | BR52: ='Project Overview'!$E$12/12 -> 0 | BS52: ='Project Overview'!$E$12/12 -> 0 | BT52: ='Project Overview'!$E$12/12 -> 0 | BU52: ='Project Overview'!$E$12/12 -> 0 | BV52: ='Project Overview'!$E$12/12 -> 0 | ... BZ52: ='Project Overview'!$E$12/12 -> 0 | CA52: ='Project Overview'!$G$12/12 -> 0 | CB52: ='Project Overview'!$G$12/12 -> 0 | CC52: ='Project Overview'!$G$12/12 -> 0 | CD52: ='Project Overview'!$G$12/12 -> 0 | CE52: ='Project Overview'!$G$12/12 -> 0 | CF52: ='Project Overview'!$G$12/12 -> 0 | CG52: ='Project Overview'!$G$12/12 -> 0 | CH52: ='Project Overview'!$G$12/12 -> 0 | ... CL52: ='Project Overview'!$G$12/12 -> 0
B53: ='H2 Production Costs'!$D$9 -> 2.6198684 | C53: Personnel | AQ53: ='Project Overview'!$C$13/12 -> 68107.667 | AR53: ='Project Overview'!$C$13/12 -> 68107.667 | AS53: ='Project Overview'!$C$13/12 -> 68107.667 | AT53: ='Project Overview'!$C$13/12 -> 68107.667 | AU53: ='Project Overview'!$C$13/12 -> 68107.667 | AV53: ='Project Overview'!$C$13/12 -> 68107.667 | AW53: ='Project Overview'!$C$13/12 -> 68107.667 | AX53: ='Project Overview'!$C$13/12 -> 68107.667 | ... BB53: ='Project Overview'!$C$13/12 -> 68107.667 | BC53: ='Project Overview'!$D$13/12 -> 90171.117 | BD53: ='Project Overview'!$D$13/12 -> 90171.117 | BE53: ='Project Overview'!$D$13/12 -> 90171.117 | BF53: ='Project Overview'!$D$13/12 -> 90171.117 | BG53: ='Project Overview'!$D$13/12 -> 90171.117 | BH53: ='Project Overview'!$D$13/12 -> 90171.117 | BI53: ='Project Overview'!$D$13/12 -> 90171.117 | BJ53: ='Project Overview'!$D$13/12 -> 90171.117 | ... BN53: ='Project Overview'!$D$13/12 -> 90171.117 | BO53: ='Project Overview'!$E$13/12 -> 103696.78 | BP53: ='Project Overview'!$E$13/12 -> 103696.78 | BQ53: ='Project Overview'!$E$13/12 -> 103696.78 | BR53: ='Project Overview'!$E$13/12 -> 103696.78 | BS53: ='Project Overview'!$E$13/12 -> 103696.78 | BT53: ='Project Overview'!$E$13/12 -> 103696.78 | BU53: ='Project Overview'!$E$13/12 -> 103696.78 | BV53: ='Project Overview'!$E$13/12 -> 103696.78 | ... BZ53: ='Project Overview'!$E$13/12 -> 103696.78 | CA53: ='Project Overview'!$G$13/12 -> 119251.3 | CB53: ='Project Overview'!$G$13/12 -> 119251.3 | CC53: ='Project Overview'!$G$13/12 -> 119251.3 | CD53: ='Project Overview'!$G$13/12 -> 119251.3 | CE53: ='Project Overview'!$G$13/12 -> 119251.3 | CF53: ='Project Overview'!$G$13/12 -> 119251.3 | CG53: ='Project Overview'!$G$13/12 -> 119251.3 | CH53: ='Project Overview'!$G$13/12 -> 119251.3 | ... CL53: ='Project Overview'!$G$13/12 -> 119251.3
B54: kg Market | C54: Production | AQ54: 0 | AR54: 0 | AS54: 0 | AT54: 0 | AU54: 0 | AV54: 0 | AW54: 0 | AX54: 0 | AY54: 0 | AZ54: 0 | BA54: 0 | BB54: 0 | BC54: 37500 | BD54: 37500 | BE54: 37500 | BF54: 37500 | BG54: 37500 | BH54: 37500 | BI54: 37500 | BJ54: 37500 | BK54: 37500 | BL54: 37500 | BM54: 37500 | BN54: 37500 | BO54: 75000 | BP54: 75000 | BQ54: 75000 | BR54: 75000 | BS54: 75000 | BT54: 75000 | BU54: 75000 | BV54: 75000 | BW54: 75000 | BX54: 75000 | BY54: 75000 | BZ54: 75000 | CA54: 75000 | CB54: 75000 | CC54: 75000 | CD54: 75000 | CE54: 75000 | CF54: 75000 | CG54: 75000 | CH54: 75000 | CI54: 75000 | CJ54: 75000 | CK54: 75000 | CL54: 75000
B55: 25 | C55: Revenue | G55: =G54*$B$15 -> 0 | H55: =H54*$B$15 -> 0 | I55: =I54*$B$15 -> 0 | J55: =J54*$B$15 -> 0 | K55: =K54*$B$15 -> 0 | L55: =L54*$B$15 -> 0 | M55: =M54*$B$15 -> 0 | N55: =N54*$B$15 -> 0 | ... CL55: =CL54*$B$15 -> 1875000
C56: COGS | G56: =G54*$B$13 -> 0 | H56: =H54*$B$13 -> 0 | I56: =I54*$B$13 -> 0 | J56: =J54*$B$13 -> 0 | K56: =K54*$B$13 -> 0 | L56: =L54*$B$13 -> 0 | M56: =M54*$B$13 -> 0 | N56: =N54*$B$13 -> 0 | ... CL56: =CL54*$B$13 -> 196490.13
C57: Gross Profit | AQ57: =AQ54*($B$55-$B$53) -> 0 | AR57: =AR54*($B$55-$B$53) -> 0 | AS57: =AS54*($B$55-$B$53) -> 0 | AT57: =AT54*($B$55-$B$53) -> 0 | AU57: =AU54*($B$55-$B$53) -> 0 | AV57: =AV54*($B$55-$B$53) -> 0 | AW57: =AW54*($B$55-$B$53) -> 0 | AX57: =AX54*($B$55-$B$53) -> 0 | ... CL57: =CL54*($B$55-$B$53) -> 1678509.9
B59: GH2x7-12 | BC59: =(BC44+BC52+BC60)*12 -> 22440000 | BD59: =BD60*12 -> 19440000 | BO59: =BO60*12 -> 9000000
B60: kg Opex | C60: Capital Costs | BC60: =('Project Overview'!$C$12/12)*6 -> 1620000 | BD60: =('Project Overview'!$C$12/12)*6 -> 1620000 | BE60: =('Project Overview'!$C$12/12)*6 -> 1620000 | BF60: =('Project Overview'!$C$12/12)*6 -> 1620000 | BG60: =('Project Overview'!$C$12/12)*6 -> 1620000 | BH60: =('Project Overview'!$C$12/12)*6 -> 1620000 | BI60: =('Project Overview'!$C$12/12)*6 -> 1620000 | BJ60: =('Project Overview'!$C$12/12)*6 -> 1620000 | ... BN60: =('Project Overview'!$C$12/12)*6 -> 1620000 | BO60: =('Project Overview'!$D$12/12)*6 -> 750000 | BP60: =('Project Overview'!$D$12/12)*6 -> 750000 | BQ60: =('Project Overview'!$D$12/12)*6 -> 750000 | BR60: =('Project Overview'!$D$12/12)*6 -> 750000 | BS60: =('Project Overview'!$D$12/12)*6 -> 750000 | BT60: =('Project Overview'!$D$12/12)*6 -> 750000 | BU60: =('Project Overview'!$D$12/12)*6 -> 750000 | BV60: =('Project Overview'!$D$12/12)*6 -> 750000 | ... BZ60: =('Project Overview'!$D$12/12)*6 -> 750000 | CA60: =('Project Overview'!$E$12/12)*6 -> 0 | CB60: =('Project Overview'!$E$12/12)*6 -> 0 | CC60: =('Project Overview'!$E$12/12)*6 -> 0 | CD60: =('Project Overview'!$E$12/12)*6 -> 0 | CE60: =('Project Overview'!$E$12/12)*6 -> 0 | CF60: =('Project Overview'!$E$12/12)*6 -> 0 | CG60: =('Project Overview'!$E$12/12)*6 -> 0 | CH60: =('Project Overview'!$E$12/12)*6 -> 0 | ... CL60: =('Project Overview'!$E$12/12)*6 -> 0
B61: ='H2 Production Costs'!$D$9 -> 2.6198684 | C61: Personnel | BC61: =('Project Overview'!$C$13/12)*6 -> 408646 | BD61: =('Project Overview'!$C$13/12)*6 -> 408646 | BE61: =('Project Overview'!$C$13/12)*6 -> 408646 | BF61: =('Project Overview'!$C$13/12)*6 -> 408646 | BG61: =('Project Overview'!$C$13/12)*6 -> 408646 | BH61: =('Project Overview'!$C$13/12)*6 -> 408646 | BI61: =('Project Overview'!$C$13/12)*6 -> 408646 | BJ61: =('Project Overview'!$C$13/12)*6 -> 408646 | ... BN61: =('Project Overview'!$C$13/12)*6 -> 408646 | BO61: =('Project Overview'!$D$13/12)*6 -> 541026.7 | BP61: =('Project Overview'!$D$13/12)*6 -> 541026.7 | BQ61: =('Project Overview'!$D$13/12)*6 -> 541026.7 | BR61: =('Project Overview'!$D$13/12)*6 -> 541026.7 | BS61: =('Project Overview'!$D$13/12)*6 -> 541026.7 | BT61: =('Project Overview'!$D$13/12)*6 -> 541026.7 | BU61: =('Project Overview'!$D$13/12)*6 -> 541026.7 | BV61: =('Project Overview'!$D$13/12)*6 -> 541026.7 | ... BZ61: =('Project Overview'!$D$13/12)*6 -> 541026.7 | CA61: =('Project Overview'!$E$13/12)*6 -> 622180.7 | CB61: =('Project Overview'!$E$13/12)*6 -> 622180.7 | CC61: =('Project Overview'!$E$13/12)*6 -> 622180.7 | CD61: =('Project Overview'!$E$13/12)*6 -> 622180.7 | CE61: =('Project Overview'!$E$13/12)*6 -> 622180.7 | CF61: =('Project Overview'!$E$13/12)*6 -> 622180.7 | CG61: =('Project Overview'!$E$13/12)*6 -> 622180.7 | CH61: =('Project Overview'!$E$13/12)*6 -> 622180.7 | ... CL61: =('Project Overview'!$E$13/12)*6 -> 622180.7
B62: kg Market | C62: Production | BC62: =0*6 -> 0 | BD62: =0*6 -> 0 | BE62: =0*6 -> 0 | BF62: =0*6 -> 0 | BG62: =0*6 -> 0 | BH62: =0*6 -> 0 | BI62: =0*6 -> 0 | BJ62: =0*6 -> 0 | ... BN62: =0*6 -> 0 | BO62: =37500*6 -> 225000 | BP62: =37500*6 -> 225000 | BQ62: =37500*6 -> 225000 | BR62: =37500*6 -> 225000 | BS62: =37500*6 -> 225000 | BT62: =37500*6 -> 225000 | BU62: =37500*6 -> 225000 | BV62: =37500*6 -> 225000 | ... BZ62: =37500*6 -> 225000 | CA62: =75000*6 -> 450000 | CB62: =75000*6 -> 450000 | CC62: =75000*6 -> 450000 | CD62: =75000*6 -> 450000 | CE62: =75000*6 -> 450000 | CF62: =75000*6 -> 450000 | CG62: =75000*6 -> 450000 | CH62: =75000*6 -> 450000 | ... CL62: =75000*6 -> 450000
B63: 25 | C63: Revenue | G63: =G62*$B$15 -> 0 | H63: =H62*$B$15 -> 0 | I63: =I62*$B$15 -> 0 | J63: =J62*$B$15 -> 0 | K63: =K62*$B$15 -> 0 | L63: =L62*$B$15 -> 0 | M63: =M62*$B$15 -> 0 | N63: =N62*$B$15 -> 0 | ... CL63: =CL62*$B$15 -> 11250000
C64: COGS | G64: =G62*$B$13 -> 0 | H64: =H62*$B$13 -> 0 | I64: =I62*$B$13 -> 0 | J64: =J62*$B$13 -> 0 | K64: =K62*$B$13 -> 0 | L64: =L62*$B$13 -> 0 | M64: =M62*$B$13 -> 0 | N64: =N62*$B$13 -> 0 | ... CL64: =CL62*$B$13 -> 1178940.8
C65: Gross Profit | BC65: =BC62*($B$63-$B$61) -> 0 | BD65: =BD62*($B$63-$B$61) -> 0 | BE65: =BE62*($B$63-$B$61) -> 0 | BF65: =BF62*($B$63-$B$61) -> 0 | BG65: =BG62*($B$63-$B$61) -> 0 | BH65: =BH62*($B$63-$B$61) -> 0 | BI65: =BI62*($B$63-$B$61) -> 0 | BJ65: =BJ62*($B$63-$B$61) -> 0 | ... CL65: =CL62*($B$63-$B$61) -> 10071059
B67: Income Tax Rate | C67: 0.27
B69: Balance Sheet:
B71: Assets
B73: Starting Cash Balance | C73: 60000
B75: Average days Receivable | C75: 15 | D75: (payment terms for customers) | G75: =SUM(G15,G23,G31,G47,G63,)*($C75/30) -> 0 | H75: =SUM(H15,H23,H31,H47,H63,)*($C75/30) -> 0 | I75: =SUM(I15,I23,I31,I47,I63,)*($C75/30) -> 0 | J75: =SUM(J15,J23,J31,J47,J63,)*($C75/30) -> 0 | K75: =SUM(K15,K23,K31,K47,K63,)*($C75/30) -> 0 | L75: =SUM(L15,L23,L31,L47,L63,)*($C75/30) -> 0 | M75: =SUM(M15,M23,M31,M47,M63,)*($C75/30) -> 0 | N75: =SUM(N15,N23,N31,N47,N63,)*($C75/30) -> 0 | ... CL75: =SUM(CL15,CL23,CL31,CL47,CL63,)*($C75/30) -> 9375000
B77: Fixed Assets | C77: Cost | D77: Purchase date | E77: Useful Life (yrs) | G77: Fixed Assets --->
B78: Facility 1 Assets | C78: 3200000 | D78: 45839 | E78: 9 | G78: 3200000 | H78: 3200000 | I78: 3200000 | J78: 3200000 | K78: 3200000 | L78: 3200000 | M78: 3200000 | N78: 3200000 | O78: 3200000 | P78: 3200000 | Q78: 3200000 | R78: 3200000 | S78: 3200000 | T78: 3200000 | U78: 3200000 | V78: 3200000 | W78: 3200000 | X78: 3200000 | Y78: 3200000 | Z78: 3200000 | AA78: 3200000 | AB78: 3200000 | AC78: 3200000 | AD78: 3200000 | AE78: 3200000 | AF78: 3200000 | AG78: 3200000 | AH78: 3200000 | AI78: 3200000 | AJ78: 3200000 | AK78: 3200000 | AL78: 3200000 | AM78: 3200000 | AN78: 3200000 | AO78: 3200000 | AP78: 3200000 | AQ78: 3200000 | AR78: 3200000 | AS78: 3200000 | AT78: 3200000 | AU78: 3200000 | AV78: 3200000 | AW78: 3200000 | AX78: 3200000 | AY78: 3200000 | AZ78: 3200000 | BA78: 3200000 | BB78: 3200000 | BC78: 3200000 | BD78: 3200000 | BE78: 3200000 | BF78: 3200000 | BG78: 3200000 | BH78: 3200000 | BI78: 3200000 | BJ78: 3200000 | BK78: 3200000 | BL78: 3200000 | BM78: 3200000 | BN78: 3200000 | BO78: 3200000 | BP78: 3200000 | BQ78: 3200000 | BR78: 3200000 | BS78: 3200000 | BT78: 3200000 | BU78: 3200000 | BV78: 3200000 | BW78: 3200000 | BX78: 3200000 | BY78: 3200000 | BZ78: 3200000 | CA78: 3200000 | CB78: 3200000 | CC78: 3200000 | CD78: 3200000 | CE78: 3200000 | CF78: 3200000 | CG78: 3200000 | CH78: 3200000 | CI78: 3200000 | CJ78: 3200000 | CK78: 3200000 | CL78: 3200000
B79: Facility 1 Assets Expansion 1 | C79: 1000000 | D79: 46204 | E79: 9 | S79: 1000000 | T79: 1000000 | U79: 1000000 | V79: 1000000 | W79: 1000000 | X79: 1000000 | Y79: 1000000 | Z79: 1000000 | AA79: 1000000 | AB79: 1000000 | AC79: 1000000 | AD79: 1000000 | AE79: 1000000 | AF79: 1000000 | AG79: 1000000 | AH79: 1000000 | AI79: 1000000 | AJ79: 1000000 | AK79: 1000000 | AL79: 1000000 | AM79: 1000000 | AN79: 1000000 | AO79: 1000000 | AP79: 1000000 | AQ79: 1000000 | AR79: 1000000 | AS79: 1000000 | AT79: 1000000 | AU79: 1000000 | AV79: 1000000 | AW79: 1000000 | AX79: 1000000 | AY79: 1000000 | AZ79: 1000000 | BA79: 1000000 | BB79: 1000000 | BC79: 1000000 | BD79: 1000000 | BE79: 1000000 | BF79: 1000000 | BG79: 1000000 | BH79: 1000000 | BI79: 1000000 | BJ79: 1000000 | BK79: 1000000 | BL79: 1000000 | BM79: 1000000 | BN79: 1000000 | BO79: 1000000 | BP79: 1000000 | BQ79: 1000000 | BR79: 1000000 | BS79: 1000000 | BT79: 1000000 | BU79: 1000000 | BV79: 1000000 | BW79: 1000000 | BX79: 1000000 | BY79: 1000000 | BZ79: 1000000 | CA79: 1000000 | CB79: 1000000 | CC79: 1000000 | CD79: 1000000 | CE79: 1000000 | CF79: 1000000 | CG79: 1000000 | CH79: 1000000 | CI79: 1000000 | CJ79: 1000000 | CK79: 1000000 | CL79: 1000000
B80: Facility 1 Assets Expansion 2 | C80: 1500000 | D80: 46569 | E80: 9 | AE80: 1500000 | AF80: 1500000 | AG80: 1500000 | AH80: 1500000 | AI80: 1500000 | AJ80: 1500000 | AK80: 1500000 | AL80: 1500000 | AM80: 1500000 | AN80: 1500000 | AO80: 1500000 | AP80: 1500000 | AQ80: 1500000 | AR80: 1500000 | AS80: 1500000 | AT80: 1500000 | AU80: 1500000 | AV80: 1500000 | AW80: 1500000 | AX80: 1500000 | AY80: 1500000 | AZ80: 1500000 | BA80: 1500000 | BB80: 1500000 | BC80: 1500000 | BD80: 1500000 | BE80: 1500000 | BF80: 1500000 | BG80: 1500000 | BH80: 1500000 | BI80: 1500000 | BJ80: 1500000 | BK80: 1500000 | BL80: 1500000 | BM80: 1500000 | BN80: 1500000 | BO80: 1500000 | BP80: 1500000 | BQ80: 1500000 | BR80: 1500000 | BS80: 1500000 | BT80: 1500000 | BU80: 1500000 | BV80: 1500000 | BW80: 1500000 | BX80: 1500000 | BY80: 1500000 | BZ80: 1500000 | CA80: 1500000 | CB80: 1500000 | CC80: 1500000 | CD80: 1500000 | CE80: 1500000 | CF80: 1500000 | CG80: 1500000 | CH80: 1500000 | CI80: 1500000 | CJ80: 1500000 | CK80: 1500000 | CL80: 1500000
B81: Facility 2 Assets | C81: 3240000 | D81: 46204 | E81: 9 | G81: =IF(G$4>=$D81,$C81,0) -> 0 | H81: =IF(H$4>=$D81,$C81,0) -> 0 | I81: =IF(I$4>=$D81,$C81,0) -> 0 | J81: =IF(J$4>=$D81,$C81,0) -> 0 | K81: =IF(K$4>=$D81,$C81,0) -> 0 | L81: =IF(L$4>=$D81,$C81,0) -> 0 | M81: =IF(M$4>=$D81,$C81,0) -> 0 | N81: =IF(N$4>=$D81,$C81,0) -> 0 | ... R81: =IF(R$4>=$D81,$C81,0) -> 0 | S81: 3240000 | T81: 3240000 | U81: 3240000 | V81: 3240000 | W81: 3240000 | X81: 3240000 | Y81: 3240000 | Z81: 3240000 | AA81: 3240000 | AB81: 3240000 | AC81: 3240000 | AD81: 3240000 | AE81: 3240000 | AF81: 3240000 | AG81: 3240000 | AH81: 3240000 | AI81: 3240000 | AJ81: 3240000 | AK81: 3240000 | AL81: 3240000 | AM81: 3240000 | AN81: 3240000 | AO81: 3240000 | AP81: 3240000 | AQ81: 3240000 | AR81: 3240000 | AS81: 3240000 | AT81: 3240000 | AU81: 3240000 | AV81: 3240000 | AW81: 3240000 | AX81: 3240000 | AY81: 3240000 | AZ81: 3240000 | BA81: 3240000 | BB81: 3240000 | BC81: 3240000 | BD81: 3240000 | BE81: 3240000 | BF81: 3240000 | BG81: 3240000 | BH81: 3240000 | BI81: 3240000 | BJ81: 3240000 | BK81: 3240000 | BL81: 3240000 | BM81: 3240000 | BN81: 3240000 | BO81: 3240000 | BP81: 3240000 | BQ81: 3240000 | BR81: 3240000 | BS81: 3240000 | BT81: 3240000 | BU81: 3240000 | BV81: 3240000 | BW81: 3240000 | BX81: 3240000 | BY81: 3240000 | BZ81: 3240000 | CA81: 3240000 | CB81: 3240000 | CC81: 3240000 | CD81: 3240000 | CE81: 3240000 | CF81: 3240000 | CG81: 3240000 | CH81: 3240000 | CI81: 3240000 | CJ81: 3240000 | CK81: 3240000 | CL81: 3240000
B82: Facility 2 Assets Expansion 1 | C82: 1500000 | D82: 46569 | E82: 9 | AE82: 1500000 | AF82: 1500000 | AG82: 1500000 | AH82: 1500000 | AI82: 1500000 | AJ82: 1500000 | AK82: 1500000 | AL82: 1500000 | AM82: 1500000 | AN82: 1500000 | AO82: 1500000 | AP82: 1500000 | AQ82: 1500000 | AR82: 1500000 | AS82: 1500000 | AT82: 1500000 | AU82: 1500000 | AV82: 1500000 | AW82: 1500000 | AX82: 1500000 | AY82: 1500000 | AZ82: 1500000 | BA82: 1500000 | BB82: 1500000 | BC82: 1500000 | BD82: 1500000 | BE82: 1500000 | BF82: 1500000 | BG82: 1500000 | BH82: 1500000 | BI82: 1500000 | BJ82: 1500000 | BK82: 1500000 | BL82: 1500000 | BM82: 1500000 | BN82: 1500000 | BO82: 1500000 | BP82: 1500000 | BQ82: 1500000 | BR82: 1500000 | BS82: 1500000 | BT82: 1500000 | BU82: 1500000 | BV82: 1500000 | BW82: 1500000 | BX82: 1500000 | BY82: 1500000 | BZ82: 1500000 | CA82: 1500000 | CB82: 1500000 | CC82: 1500000 | CD82: 1500000 | CE82: 1500000 | CF82: 1500000 | CG82: 1500000 | CH82: 1500000 | CI82: 1500000 | CJ82: 1500000 | CK82: 1500000 | CL82: 1500000
B83: Facility 3 Assets | C83: 3240000 | D83: 46569 | E83: 9 | G83: =IF(G$4>=$D83,$C83,0) -> 0 | H83: =IF(H$4>=$D83,$C83,0) -> 0 | I83: =IF(I$4>=$D83,$C83,0) -> 0 | J83: =IF(J$4>=$D83,$C83,0) -> 0 | K83: =IF(K$4>=$D83,$C83,0) -> 0 | L83: =IF(L$4>=$D83,$C83,0) -> 0 | M83: =IF(M$4>=$D83,$C83,0) -> 0 | N83: =IF(N$4>=$D83,$C83,0) -> 0 | ... AD83: =IF(AD$4>=$D83,$C83,0) -> 0 | AE83: 3240000 | AF83: 3240000 | AG83: 3240000 | AH83: 3240000 | AI83: 3240000 | AJ83: 3240000 | AK83: 3240000 | AL83: 3240000 | AM83: 3240000 | AN83: 3240000 | AO83: 3240000 | AP83: 3240000 | AQ83: 3240000 | AR83: 3240000 | AS83: 3240000 | AT83: 3240000 | AU83: 3240000 | AV83: 3240000 | AW83: 3240000 | AX83: 3240000 | AY83: 3240000 | AZ83: 3240000 | BA83: 3240000 | BB83: 3240000 | BC83: 3240000 | BD83: 3240000 | BE83: 3240000 | BF83: 3240000 | BG83: 3240000 | BH83: 3240000 | BI83: 3240000 | BJ83: 3240000 | BK83: 3240000 | BL83: 3240000 | BM83: 3240000 | BN83: 3240000 | BO83: 3240000 | BP83: 3240000 | BQ83: 3240000 | BR83: 3240000 | BS83: 3240000 | BT83: 3240000 | BU83: 3240000 | BV83: 3240000 | BW83: 3240000 | BX83: 3240000 | BY83: 3240000 | BZ83: 3240000 | CA83: 3240000 | CB83: 3240000 | CC83: 3240000 | CD83: 3240000 | CE83: 3240000 | CF83: 3240000 | CG83: 3240000 | CH83: 3240000 | CI83: 3240000 | CJ83: 3240000 | CK83: 3240000 | CL83: 3240000
B84: Facility 3 Assets Expansion 1 | C84: 1500000 | D84: 46935 | E84: 9 | AQ84: 1500000 | AR84: 1500000 | AS84: 1500000 | AT84: 1500000 | AU84: 1500000 | AV84: 1500000 | AW84: 1500000 | AX84: 1500000 | AY84: 1500000 | AZ84: 1500000 | BA84: 1500000 | BB84: 1500000 | BC84: 1500000 | BD84: 1500000 | BE84: 1500000 | BF84: 1500000 | BG84: 1500000 | BH84: 1500000 | BI84: 1500000 | BJ84: 1500000 | BK84: 1500000 | BL84: 1500000 | BM84: 1500000 | BN84: 1500000 | BO84: 1500000 | BP84: 1500000 | BQ84: 1500000 | BR84: 1500000 | BS84: 1500000 | BT84: 1500000 | BU84: 1500000 | BV84: 1500000 | BW84: 1500000 | BX84: 1500000 | BY84: 1500000 | BZ84: 1500000 | CA84: 1500000 | CB84: 1500000 | CC84: 1500000 | CD84: 1500000 | CE84: 1500000 | CF84: 1500000 | CG84: 1500000 | CH84: 1500000 | CI84: 1500000 | CJ84: 1500000 | CK84: 1500000 | CL84: 1500000
B85: Facility 4 Assets | C85: 3240000 | D85: 46569 | E85: 9 | G85: =IF(G$4>=$D85,$C85,0) -> 0 | H85: =IF(H$4>=$D85,$C85,0) -> 0 | I85: =IF(I$4>=$D85,$C85,0) -> 0 | J85: =IF(J$4>=$D85,$C85,0) -> 0 | K85: =IF(K$4>=$D85,$C85,0) -> 0 | L85: =IF(L$4>=$D85,$C85,0) -> 0 | M85: =IF(M$4>=$D85,$C85,0) -> 0 | N85: =IF(N$4>=$D85,$C85,0) -> 0 | ... AD85: =IF(AD$4>=$D85,$C85,0) -> 0 | AE85: 3240000 | AF85: 3240000 | AG85: 3240000 | AH85: 3240000 | AI85: 3240000 | AJ85: 3240000 | AK85: 3240000 | AL85: 3240000 | AM85: 3240000 | AN85: 3240000 | AO85: 3240000 | AP85: 3240000 | AQ85: 3240000 | AR85: 3240000 | AS85: 3240000 | AT85: 3240000 | AU85: 3240000 | AV85: 3240000 | AW85: 3240000 | AX85: 3240000 | AY85: 3240000 | AZ85: 3240000 | BA85: 3240000 | BB85: 3240000 | BC85: 3240000 | BD85: 3240000 | BE85: 3240000 | BF85: 3240000 | BG85: 3240000 | BH85: 3240000 | BI85: 3240000 | BJ85: 3240000 | BK85: 3240000 | BL85: 3240000 | BM85: 3240000 | BN85: 3240000 | BO85: 3240000 | BP85: 3240000 | BQ85: 3240000 | BR85: 3240000 | BS85: 3240000 | BT85: 3240000 | BU85: 3240000 | BV85: 3240000 | BW85: 3240000 | BX85: 3240000 | BY85: 3240000 | BZ85: 3240000 | CA85: 3240000 | CB85: 3240000 | CC85: 3240000 | CD85: 3240000 | CE85: 3240000 | CF85: 3240000 | CG85: 3240000 | CH85: 3240000 | CI85: 3240000 | CJ85: 3240000 | CK85: 3240000 | CL85: 3240000
B86: Facility 4 Assets Expansion 1 | C86: 1500000 | D86: 46935 | E86: 9 | AQ86: 1500000 | AR86: 1500000 | AS86: 1500000 | AT86: 1500000 | AU86: 1500000 | AV86: 1500000 | AW86: 1500000 | AX86: 1500000 | AY86: 1500000 | AZ86: 1500000 | BA86: 1500000 | BB86: 1500000 | BC86: 1500000 | BD86: 1500000 | BE86: 1500000 | BF86: 1500000 | BG86: 1500000 | BH86: 1500000 | BI86: 1500000 | BJ86: 1500000 | BK86: 1500000 | BL86: 1500000 | BM86: 1500000 | BN86: 1500000 | BO86: 1500000 | BP86: 1500000 | BQ86: 1500000 | BR86: 1500000 | BS86: 1500000 | BT86: 1500000 | BU86: 1500000 | BV86: 1500000 | BW86: 1500000 | BX86: 1500000 | BY86: 1500000 | BZ86: 1500000 | CA86: 1500000 | CB86: 1500000 | CC86: 1500000 | CD86: 1500000 | CE86: 1500000 | CF86: 1500000 | CG86: 1500000 | CH86: 1500000 | CI86: 1500000 | CJ86: 1500000 | CK86: 1500000 | CL86: 1500000
B87: Facility 5 Assets | C87: 3240000 | D87: 46935 | E87: 9 | G87: =IF(G$4>=$D87,$C87,0) -> 0 | H87: =IF(H$4>=$D87,$C87,0) -> 0 | I87: =IF(I$4>=$D87,$C87,0) -> 0 | J87: =IF(J$4>=$D87,$C87,0) -> 0 | K87: =IF(K$4>=$D87,$C87,0) -> 0 | L87: =IF(L$4>=$D87,$C87,0) -> 0 | M87: =IF(M$4>=$D87,$C87,0) -> 0 | N87: =IF(N$4>=$D87,$C87,0) -> 0 | ... AP87: =IF(AP$4>=$D87,$C87,0) -> 0 | AQ87: 3240000 | AR87: 3240000 | AS87: 3240000 | AT87: 3240000 | AU87: 3240000 | AV87: 3240000 | AW87: 3240000 | AX87: 3240000 | AY87: 3240000 | AZ87: 3240000 | BA87: 3240000 | BB87: 3240000 | BC87: 3240000 | BD87: 3240000 | BE87: 3240000 | BF87: 3240000 | BG87: 3240000 | BH87: 3240000 | BI87: 3240000 | BJ87: 3240000 | BK87: 3240000 | BL87: 3240000 | BM87: 3240000 | BN87: 3240000 | BO87: 3240000 | BP87: 3240000 | BQ87: 3240000 | BR87: 3240000 | BS87: 3240000 | BT87: 3240000 | BU87: 3240000 | BV87: 3240000 | BW87: 3240000 | BX87: 3240000 | BY87: 3240000 | BZ87: 3240000 | CA87: 3240000 | CB87: 3240000 | CC87: 3240000 | CD87: 3240000 | CE87: 3240000 | CF87: 3240000 | CG87: 3240000 | CH87: 3240000 | CI87: 3240000 | CJ87: 3240000 | CK87: 3240000 | CL87: 3240000
B88: Facility 5 Assets Expansion 1 | C88: 1500000 | D88: 47300 | E88: 9 | BC88: 1500000 | BD88: 1500000 | BE88: 1500000 | BF88: 1500000 | BG88: 1500000 | BH88: 1500000 | BI88: 1500000 | BJ88: 1500000 | BK88: 1500000 | BL88: 1500000 | BM88: 1500000 | BN88: 1500000 | BO88: 1500000 | BP88: 1500000 | BQ88: 1500000 | BR88: 1500000 | BS88: 1500000 | BT88: 1500000 | BU88: 1500000 | BV88: 1500000 | BW88: 1500000 | BX88: 1500000 | BY88: 1500000 | BZ88: 1500000 | CA88: 1500000 | CB88: 1500000 | CC88: 1500000 | CD88: 1500000 | CE88: 1500000 | CF88: 1500000 | CG88: 1500000 | CH88: 1500000 | CI88: 1500000 | CJ88: 1500000 | CK88: 1500000 | CL88: 1500000
B89: Facility 6 Assets | C89: 3240000 | D89: 46935 | E89: 9 | G89: =IF(G$4>=$D89,$C89,0) -> 0 | H89: =IF(H$4>=$D89,$C89,0) -> 0 | I89: =IF(I$4>=$D89,$C89,0) -> 0 | J89: =IF(J$4>=$D89,$C89,0) -> 0 | K89: =IF(K$4>=$D89,$C89,0) -> 0 | L89: =IF(L$4>=$D89,$C89,0) -> 0 | M89: =IF(M$4>=$D89,$C89,0) -> 0 | N89: =IF(N$4>=$D89,$C89,0) -> 0 | ... AP89: =IF(AP$4>=$D89,$C89,0) -> 0 | AQ89: 3240000 | AR89: 3240000 | AS89: 3240000 | AT89: 3240000 | AU89: 3240000 | AV89: 3240000 | AW89: 3240000 | AX89: 3240000 | AY89: 3240000 | AZ89: 3240000 | BA89: 3240000 | BB89: 3240000 | BC89: 3240000 | BD89: 3240000 | BE89: 3240000 | BF89: 3240000 | BG89: 3240000 | BH89: 3240000 | BI89: 3240000 | BJ89: 3240000 | BK89: 3240000 | BL89: 3240000 | BM89: 3240000 | BN89: 3240000 | BO89: 3240000 | BP89: 3240000 | BQ89: 3240000 | BR89: 3240000 | BS89: 3240000 | BT89: 3240000 | BU89: 3240000 | BV89: 3240000 | BW89: 3240000 | BX89: 3240000 | BY89: 3240000 | BZ89: 3240000 | CA89: 3240000 | CB89: 3240000 | CC89: 3240000 | CD89: 3240000 | CE89: 3240000 | CF89: 3240000 | CG89: 3240000 | CH89: 3240000 | CI89: 3240000 | CJ89: 3240000 | CK89: 3240000 | CL89: 3240000
B90: Facility 6 Assets Expansion 1 | C90: 1500000 | D90: 47300 | E90: 9 | BC90: 1500000 | BD90: 1500000 | BE90: 1500000 | BF90: 1500000 | BG90: 1500000 | BH90: 1500000 | BI90: 1500000 | BJ90: 1500000 | BK90: 1500000 | BL90: 1500000 | BM90: 1500000 | BN90: 1500000 | BO90: 1500000 | BP90: 1500000 | BQ90: 1500000 | BR90: 1500000 | BS90: 1500000 | BT90: 1500000 | BU90: 1500000 | BV90: 1500000 | BW90: 1500000 | BX90: 1500000 | BY90: 1500000 | BZ90: 1500000 | CA90: 1500000 | CB90: 1500000 | CC90: 1500000 | CD90: 1500000 | CE90: 1500000 | CF90: 1500000 | CG90: 1500000 | CH90: 1500000 | CI90: 1500000 | CJ90: 1500000 | CK90: 1500000 | CL90: 1500000
B91: Facility 7-12 Assets | C91: 19440000 | D91: 47300 | E91: 9 | G91: =IF(G$4>=$D91,$C91,0) -> 0 | H91: =IF(H$4>=$D91,$C91,0) -> 0 | I91: =IF(I$4>=$D91,$C91,0) -> 0 | J91: =IF(J$4>=$D91,$C91,0) -> 0 | K91: =IF(K$4>=$D91,$C91,0) -> 0 | L91: =IF(L$4>=$D91,$C91,0) -> 0 | M91: =IF(M$4>=$D91,$C91,0) -> 0 | N91: =IF(N$4>=$D91,$C91,0) -> 0 | ... AW91: =IF(AW$4>=$D91,$C91,0) -> 0 | BC91: 19440000 | BD91: 19440000 | BE91: 19440000 | BF91: 19440000 | BG91: 19440000 | BH91: 19440000 | BI91: 19440000 | BJ91: 19440000 | BK91: 19440000 | BL91: 19440000 | BM91: 19440000 | BN91: 19440000 | BO91: 19440000 | BP91: 19440000 | BQ91: 19440000 | BR91: 19440000 | BS91: 19440000 | BT91: 19440000 | BU91: 19440000 | BV91: 19440000 | BW91: 19440000 | BX91: 19440000 | BY91: 19440000 | BZ91: 19440000 | CA91: 19440000 | CB91: 19440000 | CC91: 19440000 | CD91: 19440000 | CE91: 19440000 | CF91: 19440000 | CG91: 19440000 | CH91: 19440000 | CI91: 19440000 | CJ91: 19440000 | CK91: 19440000 | CL91: 19440000
B92: Facility 7-12 Assets Expansion 1 | C92: =750000*12 -> 9000000 | D92: 47665 | E92: 9 | BO92: 9000000 | BP92: 9000000 | BQ92: 9000000 | BR92: 9000000 | BS92: 9000000 | BT92: 9000000 | BU92: 9000000 | BV92: 9000000 | BW92: 9000000 | BX92: 9000000 | BY92: 9000000 | BZ92: 9000000 | CA92: 9000000 | CB92: 9000000 | CC92: 9000000 | CD92: 9000000 | CE92: 9000000 | CF92: 9000000 | CG92: 9000000 | CH92: 9000000 | CI92: 9000000 | CJ92: 9000000 | CK92: 9000000 | CL92: 9000000
G94: Accumulated Depreciation --->
B95: =B78 -> Facility 1 Assets | G95: =MIN(F95+ IF(G$4>=$D78,$C78/($E78*12),0),$C78) -> 29629.63 | H95: =MIN(G95+ IF(H$4>=$D78,$C78/($E78*12),0),$C78) -> 59259.259 | I95: =MIN(H95+ IF(I$4>=$D78,$C78/($E78*12),0),$C78) -> 88888.889 | J95: =MIN(I95+ IF(J$4>=$D78,$C78/($E78*12),0),$C78) -> 118518.52 | K95: =MIN(J95+ IF(K$4>=$D78,$C78/($E78*12),0),$C78) -> 148148.15 | L95: =MIN(K95+ IF(L$4>=$D78,$C78/($E78*12),0),$C78) -> 177777.78 | M95: =MIN(L95+ IF(M$4>=$D78,$C78/($E78*12),0),$C78) -> 207407.41 | N95: =MIN(M95+ IF(N$4>=$D78,$C78/($E78*12),0),$C78) -> 237037.04 | ... CL95: =MIN(CK95+ IF(CL$4>=$D78,$C78/($E78*12),0),$C78) -> 2488888.9
B96: =B79 -> Facility 1 Assets Expansion 1 | G96: =MIN(F96+ IF(G$4>=$D79,$C79/($E79*12),0),$C79) -> 0 | H96: =MIN(G96+ IF(H$4>=$D79,$C79/($E79*12),0),$C79) -> 0 | I96: =MIN(H96+ IF(I$4>=$D79,$C79/($E79*12),0),$C79) -> 0 | J96: =MIN(I96+ IF(J$4>=$D79,$C79/($E79*12),0),$C79) -> 0 | K96: =MIN(J96+ IF(K$4>=$D79,$C79/($E79*12),0),$C79) -> 0 | L96: =MIN(K96+ IF(L$4>=$D79,$C79/($E79*12),0),$C79) -> 0 | M96: =MIN(L96+ IF(M$4>=$D79,$C79/($E79*12),0),$C79) -> 0 | N96: =MIN(M96+ IF(N$4>=$D79,$C79/($E79*12),0),$C79) -> 0 | ... CL96: =MIN(CK96+ IF(CL$4>=$D79,$C79/($E79*12),0),$C79) -> 666666.67
B97: =B80 -> Facility 1 Assets Expansion 2 | G97: =MIN(F97+ IF(G$4>=$D80,$C80/($E80*12),0),$C80) -> 0 | H97: =MIN(G97+ IF(H$4>=$D80,$C80/($E80*12),0),$C80) -> 0 | I97: =MIN(H97+ IF(I$4>=$D80,$C80/($E80*12),0),$C80) -> 0 | J97: =MIN(I97+ IF(J$4>=$D80,$C80/($E80*12),0),$C80) -> 0 | K97: =MIN(J97+ IF(K$4>=$D80,$C80/($E80*12),0),$C80) -> 0 | L97: =MIN(K97+ IF(L$4>=$D80,$C80/($E80*12),0),$C80) -> 0 | M97: =MIN(L97+ IF(M$4>=$D80,$C80/($E80*12),0),$C80) -> 0 | N97: =MIN(M97+ IF(N$4>=$D80,$C80/($E80*12),0),$C80) -> 0 | ... CL97: =MIN(CK97+ IF(CL$4>=$D80,$C80/($E80*12),0),$C80) -> 833333.33
B98: =B81 -> Facility 2 Assets | G98: =MIN(F98+ IF(G$4>=$D81,$C81/($E81*12),0),$C81) -> 0 | H98: =MIN(G98+ IF(H$4>=$D81,$C81/($E81*12),0),$C81) -> 0 | I98: =MIN(H98+ IF(I$4>=$D81,$C81/($E81*12),0),$C81) -> 0 | J98: =MIN(I98+ IF(J$4>=$D81,$C81/($E81*12),0),$C81) -> 0 | K98: =MIN(J98+ IF(K$4>=$D81,$C81/($E81*12),0),$C81) -> 0 | L98: =MIN(K98+ IF(L$4>=$D81,$C81/($E81*12),0),$C81) -> 0 | M98: =MIN(L98+ IF(M$4>=$D81,$C81/($E81*12),0),$C81) -> 0 | N98: =MIN(M98+ IF(N$4>=$D81,$C81/($E81*12),0),$C81) -> 0 | ... CL98: =MIN(CK98+ IF(CL$4>=$D81,$C81/($E81*12),0),$C81) -> 2160000
B99: =B82 -> Facility 2 Assets Expansion 1 | G99: =MIN(F99+ IF(G$4>=$D82,$C82/($E82*12),0),$C82) -> 0 | H99: =MIN(G99+ IF(H$4>=$D82,$C82/($E82*12),0),$C82) -> 0 | I99: =MIN(H99+ IF(I$4>=$D82,$C82/($E82*12),0),$C82) -> 0 | J99: =MIN(I99+ IF(J$4>=$D82,$C82/($E82*12),0),$C82) -> 0 | K99: =MIN(J99+ IF(K$4>=$D82,$C82/($E82*12),0),$C82) -> 0 | L99: =MIN(K99+ IF(L$4>=$D82,$C82/($E82*12),0),$C82) -> 0 | M99: =MIN(L99+ IF(M$4>=$D82,$C82/($E82*12),0),$C82) -> 0 | N99: =MIN(M99+ IF(N$4>=$D82,$C82/($E82*12),0),$C82) -> 0 | ... CL99: =MIN(CK99+ IF(CL$4>=$D82,$C82/($E82*12),0),$C82) -> 833333.33
B100: =B83 -> Facility 3 Assets | G100: =MIN(F100+ IF(G$4>=$D83,$C83/($E83*12),0),$C83) -> 0 | H100: =MIN(G100+ IF(H$4>=$D83,$C83/($E83*12),0),$C83) -> 0 | I100: =MIN(H100+ IF(I$4>=$D83,$C83/($E83*12),0),$C83) -> 0 | J100: =MIN(I100+ IF(J$4>=$D83,$C83/($E83*12),0),$C83) -> 0 | K100: =MIN(J100+ IF(K$4>=$D83,$C83/($E83*12),0),$C83) -> 0 | L100: =MIN(K100+ IF(L$4>=$D83,$C83/($E83*12),0),$C83) -> 0 | M100: =MIN(L100+ IF(M$4>=$D83,$C83/($E83*12),0),$C83) -> 0 | N100: =MIN(M100+ IF(N$4>=$D83,$C83/($E83*12),0),$C83) -> 0 | ... CL100: =MIN(CK100+ IF(CL$4>=$D83,$C83/($E83*12),0),$C83) -> 1800000
B101: =B84 -> Facility 3 Assets Expansion 1 | G101: =MIN(F101+ IF(G$4>=$D84,$C84/($E84*12),0),$C84) -> 0 | H101: =MIN(G101+ IF(H$4>=$D84,$C84/($E84*12),0),$C84) -> 0 | I101: =MIN(H101+ IF(I$4>=$D84,$C84/($E84*12),0),$C84) -> 0 | J101: =MIN(I101+ IF(J$4>=$D84,$C84/($E84*12),0),$C84) -> 0 | K101: =MIN(J101+ IF(K$4>=$D84,$C84/($E84*12),0),$C84) -> 0 | L101: =MIN(K101+ IF(L$4>=$D84,$C84/($E84*12),0),$C84) -> 0 | M101: =MIN(L101+ IF(M$4>=$D84,$C84/($E84*12),0),$C84) -> 0 | N101: =MIN(M101+ IF(N$4>=$D84,$C84/($E84*12),0),$C84) -> 0 | ... CL101: =MIN(CK101+ IF(CL$4>=$D84,$C84/($E84*12),0),$C84) -> 666666.67
B102: =B85 -> Facility 4 Assets | G102: =MIN(F102+ IF(G$4>=$D85,$C85/($E85*12),0),$C85) -> 0 | H102: =MIN(G102+ IF(H$4>=$D85,$C85/($E85*12),0),$C85) -> 0 | I102: =MIN(H102+ IF(I$4>=$D85,$C85/($E85*12),0),$C85) -> 0 | J102: =MIN(I102+ IF(J$4>=$D85,$C85/($E85*12),0),$C85) -> 0 | K102: =MIN(J102+ IF(K$4>=$D85,$C85/($E85*12),0),$C85) -> 0 | L102: =MIN(K102+ IF(L$4>=$D85,$C85/($E85*12),0),$C85) -> 0 | M102: =MIN(L102+ IF(M$4>=$D85,$C85/($E85*12),0),$C85) -> 0 | N102: =MIN(M102+ IF(N$4>=$D85,$C85/($E85*12),0),$C85) -> 0 | ... CL102: =MIN(CK102+ IF(CL$4>=$D85,$C85/($E85*12),0),$C85) -> 1800000
B103: =B86 -> Facility 4 Assets Expansion 1 | G103: =MIN(F103+ IF(G$4>=$D86,$C86/($E86*12),0),$C86) -> 0 | H103: =MIN(G103+ IF(H$4>=$D86,$C86/($E86*12),0),$C86) -> 0 | I103: =MIN(H103+ IF(I$4>=$D86,$C86/($E86*12),0),$C86) -> 0 | J103: =MIN(I103+ IF(J$4>=$D86,$C86/($E86*12),0),$C86) -> 0 | K103: =MIN(J103+ IF(K$4>=$D86,$C86/($E86*12),0),$C86) -> 0 | L103: =MIN(K103+ IF(L$4>=$D86,$C86/($E86*12),0),$C86) -> 0 | M103: =MIN(L103+ IF(M$4>=$D86,$C86/($E86*12),0),$C86) -> 0 | N103: =MIN(M103+ IF(N$4>=$D86,$C86/($E86*12),0),$C86) -> 0 | ... CL103: =MIN(CK103+ IF(CL$4>=$D86,$C86/($E86*12),0),$C86) -> 666666.67
B104: =B87 -> Facility 5 Assets | G104: =MIN(F104+ IF(G$4>=$D87,$C87/($E87*12),0),$C87) -> 0 | H104: =MIN(G104+ IF(H$4>=$D87,$C87/($E87*12),0),$C87) -> 0 | I104: =MIN(H104+ IF(I$4>=$D87,$C87/($E87*12),0),$C87) -> 0 | J104: =MIN(I104+ IF(J$4>=$D87,$C87/($E87*12),0),$C87) -> 0 | K104: =MIN(J104+ IF(K$4>=$D87,$C87/($E87*12),0),$C87) -> 0 | L104: =MIN(K104+ IF(L$4>=$D87,$C87/($E87*12),0),$C87) -> 0 | M104: =MIN(L104+ IF(M$4>=$D87,$C87/($E87*12),0),$C87) -> 0 | N104: =MIN(M104+ IF(N$4>=$D87,$C87/($E87*12),0),$C87) -> 0 | ... CL104: =MIN(CK104+ IF(CL$4>=$D87,$C87/($E87*12),0),$C87) -> 1440000
B105: =B88 -> Facility 5 Assets Expansion 1 | G105: =MIN(F105+ IF(G$4>=$D88,$C88/($E88*12),0),$C88) -> 0 | H105: =MIN(G105+ IF(H$4>=$D88,$C88/($E88*12),0),$C88) -> 0 | I105: =MIN(H105+ IF(I$4>=$D88,$C88/($E88*12),0),$C88) -> 0 | J105: =MIN(I105+ IF(J$4>=$D88,$C88/($E88*12),0),$C88) -> 0 | K105: =MIN(J105+ IF(K$4>=$D88,$C88/($E88*12),0),$C88) -> 0 | L105: =MIN(K105+ IF(L$4>=$D88,$C88/($E88*12),0),$C88) -> 0 | M105: =MIN(L105+ IF(M$4>=$D88,$C88/($E88*12),0),$C88) -> 0 | N105: =MIN(M105+ IF(N$4>=$D88,$C88/($E88*12),0),$C88) -> 0 | ... CL105: =MIN(CK105+ IF(CL$4>=$D88,$C88/($E88*12),0),$C88) -> 500000
B106: =B89 -> Facility 6 Assets | G106: =MIN(F106+ IF(G$4>=$D89,$C89/($E89*12),0),$C89) -> 0 | H106: =MIN(G106+ IF(H$4>=$D89,$C89/($E89*12),0),$C89) -> 0 | I106: =MIN(H106+ IF(I$4>=$D89,$C89/($E89*12),0),$C89) -> 0 | J106: =MIN(I106+ IF(J$4>=$D89,$C89/($E89*12),0),$C89) -> 0 | K106: =MIN(J106+ IF(K$4>=$D89,$C89/($E89*12),0),$C89) -> 0 | L106: =MIN(K106+ IF(L$4>=$D89,$C89/($E89*12),0),$C89) -> 0 | M106: =MIN(L106+ IF(M$4>=$D89,$C89/($E89*12),0),$C89) -> 0 | N106: =MIN(M106+ IF(N$4>=$D89,$C89/($E89*12),0),$C89) -> 0 | ... CL106: =MIN(CK106+ IF(CL$4>=$D89,$C89/($E89*12),0),$C89) -> 1440000
... B109: =B92 -> Facility 7-12 Assets Expansion 1 | G109: =MIN(F109+ IF(G$4>=$D92,$C92/($E92*12),0),$C92) -> 0 | H109: =MIN(G109+ IF(H$4>=$D92,$C92/($E92*12),0),$C92) -> 0 | I109: =MIN(H109+ IF(I$4>=$D92,$C92/($E92*12),0),$C92) -> 0 | J109: =MIN(I109+ IF(J$4>=$D92,$C92/($E92*12),0),$C92) -> 0 | K109: =MIN(J109+ IF(K$4>=$D92,$C92/($E92*12),0),$C92) -> 0 | L109: =MIN(K109+ IF(L$4>=$D92,$C92/($E92*12),0),$C92) -> 0 | M109: =MIN(L109+ IF(M$4>=$D92,$C92/($E92*12),0),$C92) -> 0 | N109: =MIN(M109+ IF(N$4>=$D92,$C92/($E92*12),0),$C92) -> 0 | ... CL109: =MIN(CK109+ IF(CL$4>=$D92,$C92/($E92*12),0),$C92) -> 2000000
B112: Liabilities
B114: Average days Payable | C114: 15 | D114: (payment terms for you) | G114: =SUM(G16,G24,G32,G40,G48,G56,G64,Financials!E26,Financials!E27,Financials!E25)*$C114/30 -> 4375 | H114: =SUM(H16,H24,H32,H40,H48,H56,H64,Financials!F26,Financials!F27,Financials!F25)*$C114/30 -> 4375 | I114: =SUM(I16,I24,I32,I40,I48,I56,I64,Financials!G26,Financials!G27,Financials!G25)*$C114/30 -> 4375 | J114: =SUM(J16,J24,J32,J40,J48,J56,J64,Financials!H26,Financials!H27,Financials!H25)*$C114/30 -> 4375 | K114: =SUM(K16,K24,K32,K40,K48,K56,K64,Financials!I26,Financials!I27,Financials!I25)*$C114/30 -> 4375 | L114: =SUM(L16,L24,L32,L40,L48,L56,L64,Financials!J26,Financials!J27,Financials!J25)*$C114/30 -> 4375 | M114: =SUM(M16,M24,M32,M40,M48,M56,M64,Financials!K26,Financials!K27,Financials!K25)*$C114/30 -> 4375 | N114: =SUM(N16,N24,N32,N40,N48,N56,N64,Financials!L26,Financials!L27,Financials!L25)*$C114/30 -> 4375 | ... CL114: =SUM(CL16,CL24,CL32,CL40,CL48,CL56,CL64,Financials!CJ26,Financials!CJ27,Financials!CJ25)*$C114/30 -> 1734993.8
B116: Equity
B118: Starting Paid in Capital | C118: 120000
B119: Current Equity Dilution | C119: 0.09
B121: New Equity
...

Sheet Overall
B1: Tobe Energy Corp. Overall | E1: GH2x - OKC | I1: GH2x2 - Tulsa | M1: GH2x3 - Seattle | Q1: GH2x4 - Spokane | U1: GH2x5 - Albuquerque | Y1: GH2x6 - Des Moines | AC1: GH2x7-12
E2: kg Opex | F2: ='H2 Production Costs'!$D$9 -> 2.6198684 | G2: kg Market | H2: 25 | I2: kg Opex | J2: ='H2 Production Costs'!$D$9 -> 2.6198684 | K2: kg Market | L2: 25 | M2: kg Opex | N2: ='H2 Production Costs'!$D$9 -> 2.6198684 | O2: kg Market | P2: 25 | Q2: kg Opex | R2: ='H2 Production Costs'!$D$9 -> 2.6198684 | S2: kg Market | T2: 25 | U2: kg Opex | V2: ='H2 Production Costs'!$D$9 -> 2.6198684 | W2: kg Market | X2: 25 | Y2: kg Opex | Z2: ='H2 Production Costs'!$D$9 -> 2.6198684 | AA2: kg Market | AB2: 25 | AC2: kg Opex | AD2: ='H2 Production Costs'!$D$9 -> 2.6198684 | AE2: kg Market | AF2: 25
A3: Month | B3: Total Cost | C3: Total Production | D3: Total Profit | E3: Capital Costs | F3: Personnel | G3: Production | H3: Profit | I3: Capital Costs | J3: Personnel | K3: Production | L3: Profit | M3: Capital Costs | N3: Personnel | O3: Production | P3: Profit | Q3: Capital Costs | R3: Personnel | S3: Production | T3: Profit | U3: Capital Costs | V3: Personnel | W3: Production | X3: Profit | Y3: Capital Costs | Z3: Personnel | AA3: Production | AB3: Profit | AC3: Capital Costs | AD3: Personnel | AE3: Production | AF3: Profit
A4: 1 | B4: =E4+F4+I4+J4+M4+N4+Q4+R4+U4+V4+Y4+Z4+AC4+AD4 -> 370833.33 | C4: =G4+K4+O4+S4+W4+AA4+AE4 -> 0 | D4: =(H4+L4+P4+T4+X4+AB4+AF4)-B4 -> -370833.33 | E4: =('Project Overview'!$C$4/12) -> 266666.67 | F4: ='Project Overview'!$C$5/12 -> 104166.67 | G4: 0 | H4: =G4*($H$2-$F$2) -> 0
A5: 2 | B5: =E5+F5+I5+J5+M5+N5+Q5+R5+U5+V5+Y5+Z5+AC5+AD5 -> 370833.33 | C5: =G5+K5+O5+S5+W5+AA5+AE5 -> 0 | D5: =(H5+L5+P5+T5+X5+AB5+AF5)-B5 -> -370833.33 | E5: =('Project Overview'!$C$4/12) -> 266666.67 | F5: ='Project Overview'!$C$5/12 -> 104166.67 | G5: 0 | H5: =G5*($H$2-$F$2) -> 0
A6: 3 | B6: =E6+F6+I6+J6+M6+N6+Q6+R6+U6+V6+Y6+Z6+AC6+AD6 -> 370833.33 | C6: =G6+K6+O6+S6+W6+AA6+AE6 -> 0 | D6: =(H6+L6+P6+T6+X6+AB6+AF6)-B6 -> -370833.33 | E6: =('Project Overview'!$C$4/12) -> 266666.67 | F6: ='Project Overview'!$C$5/12 -> 104166.67 | G6: 0 | H6: =G6*($H$2-$F$2) -> 0
A7: 4 | B7: =E7+F7+I7+J7+M7+N7+Q7+R7+U7+V7+Y7+Z7+AC7+AD7 -> 370833.33 | C7: =G7+K7+O7+S7+W7+AA7+AE7 -> 0 | D7: =(H7+L7+P7+T7+X7+AB7+AF7)-B7 -> -370833.33 | E7: =('Project Overview'!$C$4/12) -> 266666.67 | F7: ='Project Overview'!$C$5/12 -> 104166.67 | G7: 0 | H7: =G7*($H$2-$F$2) -> 0
A8: 5 | B8: =E8+F8+I8+J8+M8+N8+Q8+R8+U8+V8+Y8+Z8+AC8+AD8 -> 370833.33 | C8: =G8+K8+O8+S8+W8+AA8+AE8 -> 0 | D8: =(H8+L8+P8+T8+X8+AB8+AF8)-B8 -> -370833.33 | E8: =('Project Overview'!$C$4/12) -> 266666.67 | F8: ='Project Overview'!$C$5/12 -> 104166.67 | G8: 0 | H8: =G8*($H$2-$F$2) -> 0
A9: 6 | B9: =E9+F9+I9+J9+M9+N9+Q9+R9+U9+V9+Y9+Z9+AC9+AD9 -> 370833.33 | C9: =G9+K9+O9+S9+W9+AA9+AE9 -> 0 | D9: =(H9+L9+P9+T9+X9+AB9+AF9)-B9 -> -370833.33 | E9: =('Project Overview'!$C$4/12) -> 266666.67 | F9: ='Project Overview'!$C$5/12 -> 104166.67 | G9: 0 | H9: =G9*($H$2-$F$2) -> 0
A10: 7 | B10: =E10+F10+I10+J10+M10+N10+Q10+R10+U10+V10+Y10+Z10+AC10+AD10 -> 370833.33 | C10: =G10+K10+O10+S10+W10+AA10+AE10 -> 0 | D10: =(H10+L10+P10+T10+X10+AB10+AF10)-B10 -> -370833.33 | E10: =('Project Overview'!$C$4/12) -> 266666.67 | F10: ='Project Overview'!$C$5/12 -> 104166.67 | G10: 0 | H10: =G10*($H$2-$F$2) -> 0
A11: 8 | B11: =E11+F11+I11+J11+M11+N11+Q11+R11+U11+V11+Y11+Z11+AC11+AD11 -> 370833.33 | C11: =G11+K11+O11+S11+W11+AA11+AE11 -> 0 | D11: =(H11+L11+P11+T11+X11+AB11+AF11)-B11 -> -370833.33 | E11: =('Project Overview'!$C$4/12) -> 266666.67 | F11: ='Project Overview'!$C$5/12 -> 104166.67 | G11: 0 | H11: =G11*($H$2-$F$2) -> 0
A12: 9 | B12: =E12+F12+I12+J12+M12+N12+Q12+R12+U12+V12+Y12+Z12+AC12+AD12 -> 370833.33 | C12: =G12+K12+O12+S12+W12+AA12+AE12 -> 0 | D12: =(H12+L12+P12+T12+X12+AB12+AF12)-B12 -> -370833.33 | E12: =('Project Overview'!$C$4/12) -> 266666.67 | F12: ='Project Overview'!$C$5/12 -> 104166.67 | G12: 0 | H12: =G12*($H$2-$F$2) -> 0
A13: 10 | B13: =E13+F13+I13+J13+M13+N13+Q13+R13+U13+V13+Y13+Z13+AC13+AD13 -> 370833.33 | C13: =G13+K13+O13+S13+W13+AA13+AE13 -> 0 | D13: =(H13+L13+P13+T13+X13+AB13+AF13)-B13 -> -370833.33 | E13: =('Project Overview'!$C$4/12) -> 266666.67 | F13: ='Project Overview'!$C$5/12 -> 104166.67 | G13: 0 | H13: =G13*($H$2-$F$2) -> 0
A14: 11 | B14: =E14+F14+I14+J14+M14+N14+Q14+R14+U14+V14+Y14+Z14+AC14+AD14 -> 370833.33 | C14: =G14+K14+O14+S14+W14+AA14+AE14 -> 0 | D14: =(H14+L14+P14+T14+X14+AB14+AF14)-B14 -> -370833.33 | E14: =('Project Overview'!$C$4/12) -> 266666.67 | F14: ='Project Overview'!$C$5/12 -> 104166.67 | G14: 0 | H14: =G14*($H$2-$F$2) -> 0
A15: 12 | B15: =E15+F15+I15+J15+M15+N15+Q15+R15+U15+V15+Y15+Z15+AC15+AD15 -> 370833.33 | C15: =G15+K15+O15+S15+W15+AA15+AE15 -> 0 | D15: =(H15+L15+P15+T15+X15+AB15+AF15)-B15 -> -370833.33 | E15: =('Project Overview'!$C$4/12) -> 266666.67 | F15: ='Project Overview'!$C$5/12 -> 104166.67 | G15: 0 | H15: =G15*($H$2-$F$2) -> 0
A16: Total | B16: =SUM(B4:B15) -> 4450000 | C16: =SUM(C4:C15) -> 0 | D16: =SUM(D4:D15) -> -4450000 | E16: =SUM(E4:E15) -> 3200000 | F16: =SUM(F4:F15) -> 1250000 | G16: =SUM(G4:G15) -> 0 | H16: =SUM(H4:H15) -> 0
A17: 13 | B17: =E17+F17+I17+J17+M17+N17+Q17+R17+U17+V17+Y17+Z17+AC17+AD17 -> 569269.67 | C17: =G17+K17+O17+S17+W17+AA17+AE17 -> 7500 | D17: =(H17+L17+P17+T17+X17+AB17+AF17)-B17 -> -401418.68 | E17: ='Project Overview'!$D$4/12 -> 83333.333 | F17: ='Project Overview'!$D$5/12 -> 147828.67 | G17: 7500 | H17: =G17*($H$2-$F$2) -> 167850.99 | I17: ='Project Overview'!$C$12/12 -> 270000 | J17: ='Project Overview'!$C$13/12 -> 68107.667 | K17: 0 | L17: =K17*($L$2-$J$2) -> 0
A18: 14 | B18: =E18+F18+I18+J18+M18+N18+Q18+R18+U18+V18+Y18+Z18+AC18+AD18 -> 569269.67 | C18: =G18+K18+O18+S18+W18+AA18+AE18 -> 7500 | D18: =(H18+L18+P18+T18+X18+AB18+AF18)-B18 -> -401418.68 | E18: ='Project Overview'!$D$4/12 -> 83333.333 | F18: ='Project Overview'!$D$5/12 -> 147828.67 | G18: 7500 | H18: =G18*($H$2-$F$2) -> 167850.99 | I18: ='Project Overview'!$C$12/12 -> 270000 | J18: ='Project Overview'!$C$13/12 -> 68107.667 | K18: 0 | L18: =K18*($L$2-$J$2) -> 0
A19: 15 | B19: =E19+F19+I19+J19+M19+N19+Q19+R19+U19+V19+Y19+Z19+AC19+AD19 -> 569269.67 | C19: =G19+K19+O19+S19+W19+AA19+AE19 -> 7500 | D19: =(H19+L19+P19+T19+X19+AB19+AF19)-B19 -> -401418.68 | E19: ='Project Overview'!$D$4/12 -> 83333.333 | F19: ='Project Overview'!$D$5/12 -> 147828.67 | G19: 7500 | H19: =G19*($H$2-$F$2) -> 167850.99 | I19: ='Project Overview'!$C$12/12 -> 270000 | J19: ='Project Overview'!$C$13/12 -> 68107.667 | K19: 0 | L19: =K19*($L$2-$J$2) -> 0
A20: 16 | B20: =E20+F20+I20+J20+M20+N20+Q20+R20+U20+V20+Y20+Z20+AC20+AD20 -> 569269.67 | C20: =G20+K20+O20+S20+W20+AA20+AE20 -> 7500 | D20: =(H20+L20+P20+T20+X20+AB20+AF20)-B20 -> -401418.68 | E20: ='Project Overview'!$D$4/12 -> 83333.333 | F20: ='Project Overview'!$D$5/12 -> 147828.67 | G20: 7500 | H20: =G20*($H$2-$F$2) -> 167850.99 | I20: ='Project Overview'!$C$12/12 -> 270000 | J20: ='Project Overview'!$C$13/12 -> 68107.667 | K20: 0 | L20: =K20*($L$2-$J$2) -> 0
A21: 17 | B21: =E21+F21+I21+J21+M21+N21+Q21+R21+U21+V21+Y21+Z21+AC21+AD21 -> 569269.67 | C21: =G21+K21+O21+S21+W21+AA21+AE21 -> 7500 | D21: =(H21+L21+P21+T21+X21+AB21+AF21)-B21 -> -401418.68 | E21: ='Project Overview'!$D$4/12 -> 83333.333 | F21: ='Project Overview'!$D$5/12 -> 147828.67 | G21: 7500 | H21: =G21*($H$2-$F$2) -> 167850.99 | I21: ='Project Overview'!$C$12/12 -> 270000 | J21: ='Project Overview'!$C$13/12 -> 68107.667 | K21: 0 | L21: =K21*($L$2-$J$2) -> 0
A22: 18 | B22: =E22+F22+I22+J22+M22+N22+Q22+R22+U22+V22+Y22+Z22+AC22+AD22 -> 569269.67 | C22: =G22+K22+O22+S22+W22+AA22+AE22 -> 7500 | D22: =(H22+L22+P22+T22+X22+AB22+AF22)-B22 -> -401418.68 | E22: ='Project Overview'!$D$4/12 -> 83333.333 | F22: ='Project Overview'!$D$5/12 -> 147828.67 | G22: 7500 | H22: =G22*($H$2-$F$2) -> 167850.99 | I22: ='Project Overview'!$C$12/12 -> 270000 | J22: ='Project Overview'!$C$13/12 -> 68107.667 | K22: 0 | L22: =K22*($L$2-$J$2) -> 0
A23: 19 | B23: =E23+F23+I23+J23+M23+N23+Q23+R23+U23+V23+Y23+Z23+AC23+AD23 -> 569269.67 | C23: =G23+K23+O23+S23+W23+AA23+AE23 -> 37500 | D23: =(H23+L23+P23+T23+X23+AB23+AF23)-B23 -> 269985.27 | E23: ='Project Overview'!$D$4/12 -> 83333.333 | F23: ='Project Overview'!$D$5/12 -> 147828.67 | G23: 37500 | H23: =G23*($H$2-$F$2) -> 839254.93 | I23: ='Project Overview'!$C$12/12 -> 270000 | J23: ='Project Overview'!$C$13/12 -> 68107.667 | K23: 0 | L23: =K23*($L$2-$J$2) -> 0
A24: 20 | B24: =E24+F24+I24+J24+M24+N24+Q24+R24+U24+V24+Y24+Z24+AC24+AD24 -> 569269.67 | C24: =G24+K24+O24+S24+W24+AA24+AE24 -> 37500 | D24: =(H24+L24+P24+T24+X24+AB24+AF24)-B24 -> 269985.27 | E24: ='Project Overview'!$D$4/12 -> 83333.333 | F24: ='Project Overview'!$D$5/12 -> 147828.67 | G24: 37500 | H24: =G24*($H$2-$F$2) -> 839254.93 | I24: ='Project Overview'!$C$12/12 -> 270000 | J24: ='Project Overview'!$C$13/12 -> 68107.667 | K24: 0 | L24: =K24*($L$2-$J$2) -> 0
A25: 21 | B25: =E25+F25+I25+J25+M25+N25+Q25+R25+U25+V25+Y25+Z25+AC25+AD25 -> 569269.67 | C25: =G25+K25+O25+S25+W25+AA25+AE25 -> 37500 | D25: =(H25+L25+P25+T25+X25+AB25+AF25)-B25 -> 269985.27 | E25: ='Project Overview'!$D$4/12 -> 83333.333 | F25: ='Project Overview'!$D$5/12 -> 147828.67 | G25: 37500 | H25: =G25*($H$2-$F$2) -> 839254.93 | I25: ='Project Overview'!$C$12/12 -> 270000 | J25: ='Project Overview'!$C$13/12 -> 68107.667 | K25: 0 | L25: =K25*($L$2-$J$2) -> 0
A26: 22 | B26: =E26+F26+I26+J26+M26+N26+Q26+R26+U26+V26+Y26+Z26+AC26+AD26 -> 569269.67 | C26: =G26+K26+O26+S26+W26+AA26+AE26 -> 37500 | D26: =(H26+L26+P26+T26+X26+AB26+AF26)-B26 -> 269985.27 | E26: ='Project Overview'!$D$4/12 -> 83333.333 | F26: ='Project Overview'!$D$5/12 -> 147828.67 | G26: 37500 | H26: =G26*($H$2-$F$2) -> 839254.93 | I26: ='Project Overview'!$C$12/12 -> 270000 | J26: ='Project Overview'!$C$13/12 -> 68107.667 | K26: 0 | L26: =K26*($L$2-$J$2) -> 0
A27: 23 | B27: =E27+F27+I27+J27+M27+N27+Q27+R27+U27+V27+Y27+Z27+AC27+AD27 -> 569269.67 | C27: =G27+K27+O27+S27+W27+AA27+AE27 -> 37500 | D27: =(H27+L27+P27+T27+X27+AB27+AF27)-B27 -> 269985.27 | E27: ='Project Overview'!$D$4/12 -> 83333.333 | F27: ='Project Overview'!$D$5/12 -> 147828.67 | G27: 37500 | H27: =G27*($H$2-$F$2) -> 839254.93 | I27: ='Project Overview'!$C$12/12 -> 270000 | J27: ='Project Overview'!$C$13/12 -> 68107.667 | K27: 0 | L27: =K27*($L$2-$J$2) -> 0
A28: 24 | B28: =E28+F28+I28+J28+M28+N28+Q28+R28+U28+V28+Y28+Z28+AC28+AD28 -> 569269.67 | C28: =G28+K28+O28+S28+W28+AA28+AE28 -> 37500 | D28: =(H28+L28+P28+T28+X28+AB28+AF28)-B28 -> 269985.27 | E28: ='Project Overview'!$D$4/12 -> 83333.333 | F28: ='Project Overview'!$D$5/12 -> 147828.67 | G28: 37500 | H28: =G28*($H$2-$F$2) -> 839254.93 | I28: ='Project Overview'!$C$12/12 -> 270000 | J28: ='Project Overview'!$C$13/12 -> 68107.667 | K28: 0 | L28: =K28*($L$2-$J$2) -> 0
A29: Total | B29: =SUM(B17:B28) -> 6831236 | C29: =SUM(C17:C28) -> 270000 | D29: =SUM(D17:D28) -> -788600.47 | E29: =SUM(E17:E28) -> 1000000 | F29: =SUM(F17:F28) -> 1773944 | G29: =SUM(G17:G28) -> 270000 | H29: =SUM(H17:H28) -> 6042635.5 | I29: =SUM(I17:I28) -> 3240000 | ... L29: =SUM(L17:L28) -> 0
A30: 25 | B30: =E30+F30+I30+J30+M30+N30+Q30+R30+U30+V30+Y30+Z30+AC30+AD30 -> 1206545.1 | C30: =G30+K30+O30+S30+W30+AA30+AE30 -> 75000 | D30: =(H30+L30+P30+T30+X30+AB30+AF30)-B30 -> 471964.76 | E30: =('Project Overview'!$E$4/12) -> 125000 | F30: ='Project Overview'!$E$5/12 -> 190158.65 | G30: 37500 | H30: =G30*($H$2-$F$2) -> 839254.93 | I30: ='Project Overview'!$D$12/12 -> 125000 | J30: ='Project Overview'!$D$13/12 -> 90171.117 | K30: 37500 | L30: =K30*($L$2-$J$2) -> 839254.93 | M30: ='Project Overview'!$C$12/12 -> 270000 | N30: ='Project Overview'!$C$13/12 -> 68107.667 | O30: 0 | P30: =O30*($P$2-$N$2) -> 0 | Q30: ='Project Overview'!$C$12/12 -> 270000 | R30: ='Project Overview'!$C$13/12 -> 68107.667 | S30: 0 | T30: =S30*($T$2-$R$2) -> 0
A31: 26 | B31: =E31+F31+I31+J31+M31+N31+Q31+R31+U31+V31+Y31+Z31+AC31+AD31 -> 1206545.1 | C31: =G31+K31+O31+S31+W31+AA31+AE31 -> 75000 | D31: =(H31+L31+P31+T31+X31+AB31+AF31)-B31 -> 471964.76 | E31: =('Project Overview'!$E$4/12) -> 125000 | F31: ='Project Overview'!$E$5/12 -> 190158.65 | G31: 37500 | H31: =G31*($H$2-$F$2) -> 839254.93 | I31: ='Project Overview'!$D$12/12 -> 125000 | J31: ='Project Overview'!$D$13/12 -> 90171.117 | K31: 37500 | L31: =K31*($L$2-$J$2) -> 839254.93 | M31: ='Project Overview'!$C$12/12 -> 270000 | N31: ='Project Overview'!$C$13/12 -> 68107.667 | O31: 0 | P31: =O31*($P$2-$N$2) -> 0 | Q31: ='Project Overview'!$C$12/12 -> 270000 | R31: ='Project Overview'!$C$13/12 -> 68107.667 | S31: 0 | T31: =S31*($T$2-$R$2) -> 0
A32: 27 | B32: =E32+F32+I32+J32+M32+N32+Q32+R32+U32+V32+Y32+Z32+AC32+AD32 -> 1206545.1 | C32: =G32+K32+O32+S32+W32+AA32+AE32 -> 75000 | D32: =(H32+L32+P32+T32+X32+AB32+AF32)-B32 -> 471964.76 | E32: =('Project Overview'!$E$4/12) -> 125000 | F32: ='Project Overview'!$E$5/12 -> 190158.65 | G32: 37500 | H32: =G32*($H$2-$F$2) -> 839254.93 | I32: ='Project Overview'!$D$12/12 -> 125000 | J32: ='Project Overview'!$D$13/12 -> 90171.117 | K32: 37500 | L32: =K32*($L$2-$J$2) -> 839254.93 | M32: ='Project Overview'!$C$12/12 -> 270000 | N32: ='Project Overview'!$C$13/12 -> 68107.667 | O32: 0 | P32: =O32*($P$2-$N$2) -> 0 | Q32: ='Project Overview'!$C$12/12 -> 270000 | R32: ='Project Overview'!$C$13/12 -> 68107.667 | S32: 0 | T32: =S32*($T$2-$R$2) -> 0
A33: 28 | B33: =E33+F33+I33+J33+M33+N33+Q33+R33+U33+V33+Y33+Z33+AC33+AD33 -> 1206545.1 | C33: =G33+K33+O33+S33+W33+AA33+AE33 -> 75000 | D33: =(H33+L33+P33+T33+X33+AB33+AF33)-B33 -> 471964.76 | E33: =('Project Overview'!$E$4/12) -> 125000 | F33: ='Project Overview'!$E$5/12 -> 190158.65 | G33: 37500 | H33: =G33*($H$2-$F$2) -> 839254.93 | I33: ='Project Overview'!$D$12/12 -> 125000 | J33: ='Project Overview'!$D$13/12 -> 90171.117 | K33: 37500 | L33: =K33*($L$2-$J$2) -> 839254.93 | M33: ='Project Overview'!$C$12/12 -> 270000 | N33: ='Project Overview'!$C$13/12 -> 68107.667 | O33: 0 | P33: =O33*($P$2-$N$2) -> 0 | Q33: ='Project Overview'!$C$12/12 -> 270000 | R33: ='Project Overview'!$C$13/12 -> 68107.667 | S33: 0 | T33: =S33*($T$2-$R$2) -> 0
A34: 29 | B34: =E34+F34+I34+J34+M34+N34+Q34+R34+U34+V34+Y34+Z34+AC34+AD34 -> 1206545.1 | C34: =G34+K34+O34+S34+W34+AA34+AE34 -> 75000 | D34: =(H34+L34+P34+T34+X34+AB34+AF34)-B34 -> 471964.76 | E34: =('Project Overview'!$E$4/12) -> 125000 | F34: ='Project Overview'!$E$5/12 -> 190158.65 | G34: 37500 | H34: =G34*($H$2-$F$2) -> 839254.93 | I34: ='Project Overview'!$D$12/12 -> 125000 | J34: ='Project Overview'!$D$13/12 -> 90171.117 | K34: 37500 | L34: =K34*($L$2-$J$2) -> 839254.93 | M34: ='Project Overview'!$C$12/12 -> 270000 | N34: ='Project Overview'!$C$13/12 -> 68107.667 | O34: 0 | P34: =O34*($P$2-$N$2) -> 0 | Q34: ='Project Overview'!$C$12/12 -> 270000 | R34: ='Project Overview'!$C$13/12 -> 68107.667 | S34: 0 | T34: =S34*($T$2-$R$2) -> 0
A35: 30 | B35: =E35+F35+I35+J35+M35+N35+Q35+R35+U35+V35+Y35+Z35+AC35+AD35 -> 1206545.1 | C35: =G35+K35+O35+S35+W35+AA35+AE35 -> 75000 | D35: =(H35+L35+P35+T35+X35+AB35+AF35)-B35 -> 471964.76 | E35: =('Project Overview'!$E$4/12) -> 125000 | F35: ='Project Overview'!$E$5/12 -> 190158.65 | G35: 37500 | H35: =G35*($H$2-$F$2) -> 839254.93 | I35: ='Project Overview'!$D$12/12 -> 125000 | J35: ='Project Overview'!$D$13/12 -> 90171.117 | K35: 37500 | L35: =K35*($L$2-$J$2) -> 839254.93 | M35: ='Project Overview'!$C$12/12 -> 270000 | N35: ='Project Overview'!$C$13/12 -> 68107.667 | O35: 0 | P35: =O35*($P$2-$N$2) -> 0 | Q35: ='Project Overview'!$C$12/12 -> 270000 | R35: ='Project Overview'!$C$13/12 -> 68107.667 | S35: 0 | T35: =S35*($T$2-$R$2) -> 0
A36: 31 | B36: =E36+F36+I36+J36+M36+N36+Q36+R36+U36+V36+Y36+Z36+AC36+AD36 -> 1206545.1 | C36: =G36+K36+O36+S36+W36+AA36+AE36 -> 112500 | D36: =(H36+L36+P36+T36+X36+AB36+AF36)-B36 -> 1311219.7 | E36: =('Project Overview'!$E$4/12) -> 125000 | F36: ='Project Overview'!$E$5/12 -> 190158.65 | G36: 75000 | H36: =G36*($H$2-$F$2) -> 1678509.9 | I36: ='Project Overview'!$D$12/12 -> 125000 | J36: ='Project Overview'!$D$13/12 -> 90171.117 | K36: 37500 | L36: =K36*($L$2-$J$2) -> 839254.93 | M36: ='Project Overview'!$C$12/12 -> 270000 | N36: ='Project Overview'!$C$13/12 -> 68107.667 | O36: 0 | P36: =O36*($P$2-$N$2) -> 0 | Q36: ='Project Overview'!$C$12/12 -> 270000 | R36: ='Project Overview'!$C$13/12 -> 68107.667 | S36: 0 | T36: =S36*($T$2-$R$2) -> 0
A37: 32 | B37: =E37+F37+I37+J37+M37+N37+Q37+R37+U37+V37+Y37+Z37+AC37+AD37 -> 1206545.1 | C37: =G37+K37+O37+S37+W37+AA37+AE37 -> 112500 | D37: =(H37+L37+P37+T37+X37+AB37+AF37)-B37 -> 1311219.7 | E37: =('Project Overview'!$E$4/12) -> 125000 | F37: ='Project Overview'!$E$5/12 -> 190158.65 | G37: 75000 | H37: =G37*($H$2-$F$2) -> 1678509.9 | I37: ='Project Overview'!$D$12/12 -> 125000 | J37: ='Project Overview'!$D$13/12 -> 90171.117 | K37: 37500 | L37: =K37*($L$2-$J$2) -> 839254.93 | M37: ='Project Overview'!$C$12/12 -> 270000 | N37: ='Project Overview'!$C$13/12 -> 68107.667 | O37: 0 | P37: =O37*($P$2-$N$2) -> 0 | Q37: ='Project Overview'!$C$12/12 -> 270000 | R37: ='Project Overview'!$C$13/12 -> 68107.667 | S37: 0 | T37: =S37*($T$2-$R$2) -> 0
A38: 33 | B38: =E38+F38+I38+J38+M38+N38+Q38+R38+U38+V38+Y38+Z38+AC38+AD38 -> 1206545.1 | C38: =G38+K38+O38+S38+W38+AA38+AE38 -> 112500 | D38: =(H38+L38+P38+T38+X38+AB38+AF38)-B38 -> 1311219.7 | E38: =('Project Overview'!$E$4/12) -> 125000 | F38: ='Project Overview'!$E$5/12 -> 190158.65 | G38: 75000 | H38: =G38*($H$2-$F$2) -> 1678509.9 | I38: ='Project Overview'!$D$12/12 -> 125000 | J38: ='Project Overview'!$D$13/12 -> 90171.117 | K38: 37500 | L38: =K38*($L$2-$J$2) -> 839254.93 | M38: ='Project Overview'!$C$12/12 -> 270000 | N38: ='Project Overview'!$C$13/12 -> 68107.667 | O38: 0 | P38: =O38*($P$2-$N$2) -> 0 | Q38: ='Project Overview'!$C$12/12 -> 270000 | R38: ='Project Overview'!$C$13/12 -> 68107.667 | S38: 0 | T38: =S38*($T$2-$R$2) -> 0
A39: 34 | B39: =E39+F39+I39+J39+M39+N39+Q39+R39+U39+V39+Y39+Z39+AC39+AD39 -> 1206545.1 | C39: =G39+K39+O39+S39+W39+AA39+AE39 -> 112500 | D39: =(H39+L39+P39+T39+X39+AB39+AF39)-B39 -> 1311219.7 | E39: =('Project Overview'!$E$4/12) -> 125000 | F39: ='Project Overview'!$E$5/12 -> 190158.65 | G39: 75000 | H39: =G39*($H$2-$F$2) -> 1678509.9 | I39: ='Project Overview'!$D$12/12 -> 125000 | J39: ='Project Overview'!$D$13/12 -> 90171.117 | K39: 37500 | L39: =K39*($L$2-$J$2) -> 839254.93 | M39: ='Project Overview'!$C$12/12 -> 270000 | N39: ='Project Overview'!$C$13/12 -> 68107.667 | O39: 0 | P39: =O39*($P$2-$N$2) -> 0 | Q39: ='Project Overview'!$C$12/12 -> 270000 | R39: ='Project Overview'!$C$13/12 -> 68107.667 | S39: 0 | T39: =S39*($T$2-$R$2) -> 0
A40: 35 | B40: =E40+F40+I40+J40+M40+N40+Q40+R40+U40+V40+Y40+Z40+AC40+AD40 -> 1206545.1 | C40: =G40+K40+O40+S40+W40+AA40+AE40 -> 112500 | D40: =(H40+L40+P40+T40+X40+AB40+AF40)-B40 -> 1311219.7 | E40: =('Project Overview'!$E$4/12) -> 125000 | F40: ='Project Overview'!$E$5/12 -> 190158.65 | G40: 75000 | H40: =G40*($H$2-$F$2) -> 1678509.9 | I40: ='Project Overview'!$D$12/12 -> 125000 | J40: ='Project Overview'!$D$13/12 -> 90171.117 | K40: 37500 | L40: =K40*($L$2-$J$2) -> 839254.93 | M40: ='Project Overview'!$C$12/12 -> 270000 | N40: ='Project Overview'!$C$13/12 -> 68107.667 | O40: 0 | P40: =O40*($P$2-$N$2) -> 0 | Q40: ='Project Overview'!$C$12/12 -> 270000 | R40: ='Project Overview'!$C$13/12 -> 68107.667 | S40: 0 | T40: =S40*($T$2-$R$2) -> 0
A41: 36 | B41: =E41+F41+I41+J41+M41+N41+Q41+R41+U41+V41+Y41+Z41+AC41+AD41 -> 1206545.1 | C41: =G41+K41+O41+S41+W41+AA41+AE41 -> 112500 | D41: =(H41+L41+P41+T41+X41+AB41+AF41)-B41 -> 1311219.7 | E41: =('Project Overview'!$E$4/12) -> 125000 | F41: ='Project Overview'!$E$5/12 -> 190158.65 | G41: 75000 | H41: =G41*($H$2-$F$2) -> 1678509.9 | I41: ='Project Overview'!$D$12/12 -> 125000 | J41: ='Project Overview'!$D$13/12 -> 90171.117 | K41: 37500 | L41: =K41*($L$2-$J$2) -> 839254.93 | M41: ='Project Overview'!$C$12/12 -> 270000 | N41: ='Project Overview'!$C$13/12 -> 68107.667 | O41: 0 | P41: =O41*($P$2-$N$2) -> 0 | Q41: ='Project Overview'!$C$12/12 -> 270000 | R41: ='Project Overview'!$C$13/12 -> 68107.667 | S41: 0 | T41: =S41*($T$2-$R$2) -> 0
A42: Total | B42: =SUM(B30:B41) -> 14478541 | C42: =SUM(C30:C41) -> 1125000 | D42: =SUM(D30:D41) -> 10699107 | E42: =SUM(E30:E41) -> 1500000 | F42: =SUM(F30:F41) -> 2281903.8 | G42: =SUM(G30:G41) -> 675000 | H42: =SUM(H30:H41) -> 15106589 | I42: =SUM(I30:I41) -> 1500000 | ... T42: =SUM(T30:T41) -> 0
A43: 37 | B43: =E43+F43+I43+J43+M43+N43+Q43+R43+U43+V43+Y43+Z43+AC43+AD43 -> 1448969 | C43: =G43+K43+O43+S43+W43+AA43+AE43 -> 225000 | D43: =(H43+L43+P43+T43+X43+AB43+AF43)-B43 -> 3586560.6 | E43: ='Project Overview'!$F$4/12 -> 0 | F43: ='Project Overview'!$F$5/12 -> 238714.63 | G43: 75000 | H43: =G43*($H$2-$F$2) -> 1678509.9 | I43: ='Project Overview'!$E$12/12 -> 0 | J43: ='Project Overview'!$E$13/12 -> 103696.78 | K43: 75000 | L43: =K43*($L$2-$J$2) -> 1678509.9 | M43: ='Project Overview'!$D$12/12 -> 125000 | N43: ='Project Overview'!$D$13/12 -> 90171.117 | O43: 37500 | P43: =O43*($P$2-$N$2) -> 839254.93 | Q43: ='Project Overview'!$D$12/12 -> 125000 | R43: ='Project Overview'!$D$13/12 -> 90171.117 | S43: 37500 | T43: =S43*($T$2-$R$2) -> 839254.93 | U43: ='Project Overview'!$C$12/12 -> 270000 | V43: ='Project Overview'!$C$13/12 -> 68107.667 | W43: 0 | X43: =W43*($X$2-$V$2) -> 0 | Y43: ='Project Overview'!$C$12/12 -> 270000 | Z43: ='Project Overview'!$C$13/12 -> 68107.667 | AA43: 0 | AB43: =AA43*($AB$2-$Z$2) -> 0
A44: 38 | B44: =E44+F44+I44+J44+M44+N44+Q44+R44+U44+V44+Y44+Z44+AC44+AD44 -> 1448969 | C44: =G44+K44+O44+S44+W44+AA44+AE44 -> 225000 | D44: =(H44+L44+P44+T44+X44+AB44+AF44)-B44 -> 3586560.6 | E44: ='Project Overview'!$F$4/12 -> 0 | F44: ='Project Overview'!$F$5/12 -> 238714.63 | G44: 75000 | H44: =G44*($H$2-$F$2) -> 1678509.9 | I44: ='Project Overview'!$E$12/12 -> 0 | J44: ='Project Overview'!$E$13/12 -> 103696.78 | K44: 75000 | L44: =K44*($L$2-$J$2) -> 1678509.9 | M44: ='Project Overview'!$D$12/12 -> 125000 | N44: ='Project Overview'!$D$13/12 -> 90171.117 | O44: 37500 | P44: =O44*($P$2-$N$2) -> 839254.93 | Q44: ='Project Overview'!$D$12/12 -> 125000 | R44: ='Project Overview'!$D$13/12 -> 90171.117 | S44: 37500 | T44: =S44*($T$2-$R$2) -> 839254.93 | U44: ='Project Overview'!$C$12/12 -> 270000 | V44: ='Project Overview'!$C$13/12 -> 68107.667 | W44: 0 | X44: =W44*($X$2-$V$2) -> 0 | Y44: ='Project Overview'!$C$12/12 -> 270000 | Z44: ='Project Overview'!$C$13/12 -> 68107.667 | AA44: 0 | AB44: =AA44*($AB$2-$Z$2) -> 0
A45: 39 | B45: =E45+F45+I45+J45+M45+N45+Q45+R45+U45+V45+Y45+Z45+AC45+AD45 -> 1448969 | C45: =G45+K45+O45+S45+W45+AA45+AE45 -> 225000 | D45: =(H45+L45+P45+T45+X45+AB45+AF45)-B45 -> 3586560.6 | E45: ='Project Overview'!$F$4/12 -> 0 | F45: ='Project Overview'!$F$5/12 -> 238714.63 | G45: 75000 | H45: =G45*($H$2-$F$2) -> 1678509.9 | I45: ='Project Overview'!$E$12/12 -> 0 | J45: ='Project Overview'!$E$13/12 -> 103696.78 | K45: 75000 | L45: =K45*($L$2-$J$2) -> 1678509.9 | M45: ='Project Overview'!$D$12/12 -> 125000 | N45: ='Project Overview'!$D$13/12 -> 90171.117 | O45: 37500 | P45: =O45*($P$2-$N$2) -> 839254.93 | Q45: ='Project Overview'!$D$12/12 -> 125000 | R45: ='Project Overview'!$D$13/12 -> 90171.117 | S45: 37500 | T45: =S45*($T$2-$R$2) -> 839254.93 | U45: ='Project Overview'!$C$12/12 -> 270000 | V45: ='Project Overview'!$C$13/12 -> 68107.667 | W45: 0 | X45: =W45*($X$2-$V$2) -> 0 | Y45: ='Project Overview'!$C$12/12 -> 270000 | Z45: ='Project Overview'!$C$13/12 -> 68107.667 | AA45: 0 | AB45: =AA45*($AB$2-$Z$2) -> 0
A46: 40 | B46: =E46+F46+I46+J46+M46+N46+Q46+R46+U46+V46+Y46+Z46+AC46+AD46 -> 1448969 | C46: =G46+K46+O46+S46+W46+AA46+AE46 -> 225000 | D46: =(H46+L46+P46+T46+X46+AB46+AF46)-B46 -> 3586560.6 | E46: ='Project Overview'!$F$4/12 -> 0 | F46: ='Project Overview'!$F$5/12 -> 238714.63 | G46: 75000 | H46: =G46*($H$2-$F$2) -> 1678509.9 | I46: ='Project Overview'!$E$12/12 -> 0 | J46: ='Project Overview'!$E$13/12 -> 103696.78 | K46: 75000 | L46: =K46*($L$2-$J$2) -> 1678509.9 | M46: ='Project Overview'!$D$12/12 -> 125000 | N46: ='Project Overview'!$D$13/12 -> 90171.117 | O46: 37500 | P46: =O46*($P$2-$N$2) -> 839254.93 | Q46: ='Project Overview'!$D$12/12 -> 125000 | R46: ='Project Overview'!$D$13/12 -> 90171.117 | S46: 37500 | T46: =S46*($T$2-$R$2) -> 839254.93 | U46: ='Project Overview'!$C$12/12 -> 270000 | V46: ='Project Overview'!$C$13/12 -> 68107.667 | W46: 0 | X46: =W46*($X$2-$V$2) -> 0 | Y46: ='Project Overview'!$C$12/12 -> 270000 | Z46: ='Project Overview'!$C$13/12 -> 68107.667 | AA46: 0 | AB46: =AA46*($AB$2-$Z$2) -> 0
A47: 41 | B47: =E47+F47+I47+J47+M47+N47+Q47+R47+U47+V47+Y47+Z47+AC47+AD47 -> 1448969 | C47: =G47+K47+O47+S47+W47+AA47+AE47 -> 225000 | D47: =(H47+L47+P47+T47+X47+AB47+AF47)-B47 -> 3586560.6 | E47: ='Project Overview'!$F$4/12 -> 0 | F47: ='Project Overview'!$F$5/12 -> 238714.63 | G47: 75000 | H47: =G47*($H$2-$F$2) -> 1678509.9 | I47: ='Project Overview'!$E$12/12 -> 0 | J47: ='Project Overview'!$E$13/12 -> 103696.78 | K47: 75000 | L47: =K47*($L$2-$J$2) -> 1678509.9 | M47: ='Project Overview'!$D$12/12 -> 125000 | N47: ='Project Overview'!$D$13/12 -> 90171.117 | O47: 37500 | P47: =O47*($P$2-$N$2) -> 839254.93 | Q47: ='Project Overview'!$D$12/12 -> 125000 | R47: ='Project Overview'!$D$13/12 -> 90171.117 | S47: 37500 | T47: =S47*($T$2-$R$2) -> 839254.93 | U47: ='Project Overview'!$C$12/12 -> 270000 | V47: ='Project Overview'!$C$13/12 -> 68107.667 | W47: 0 | X47: =W47*($X$2-$V$2) -> 0 | Y47: ='Project Overview'!$C$12/12 -> 270000 | Z47: ='Project Overview'!$C$13/12 -> 68107.667 | AA47: 0 | AB47: =AA47*($AB$2-$Z$2) -> 0
A48: 42 | B48: =E48+F48+I48+J48+M48+N48+Q48+R48+U48+V48+Y48+Z48+AC48+AD48 -> 1448969 | C48: =G48+K48+O48+S48+W48+AA48+AE48 -> 225000 | D48: =(H48+L48+P48+T48+X48+AB48+AF48)-B48 -> 3586560.6 | E48: ='Project Overview'!$F$4/12 -> 0 | F48: ='Project Overview'!$F$5/12 -> 238714.63 | G48: 75000 | H48: =G48*($H$2-$F$2) -> 1678509.9 | I48: ='Project Overview'!$E$12/12 -> 0 | J48: ='Project Overview'!$E$13/12 -> 103696.78 | K48: 75000 | L48: =K48*($L$2-$J$2) -> 1678509.9 | M48: ='Project Overview'!$D$12/12 -> 125000 | N48: ='Project Overview'!$D$13/12 -> 90171.117 | O48: 37500 | P48: =O48*($P$2-$N$2) -> 839254.93 | Q48: ='Project Overview'!$D$12/12 -> 125000 | R48: ='Project Overview'!$D$13/12 -> 90171.117 | S48: 37500 | T48: =S48*($T$2-$R$2) -> 839254.93 | U48: ='Project Overview'!$C$12/12 -> 270000 | V48: ='Project Overview'!$C$13/12 -> 68107.667 | W48: 0 | X48: =W48*($X$2-$V$2) -> 0 | Y48: ='Project Overview'!$C$12/12 -> 270000 | Z48: ='Project Overview'!$C$13/12 -> 68107.667 | AA48: 0 | AB48: =AA48*($AB$2-$Z$2) -> 0
A49: 43 | B49: =E49+F49+I49+J49+M49+N49+Q49+R49+U49+V49+Y49+Z49+AC49+AD49 -> 1448969 | C49: =G49+K49+O49+S49+W49+AA49+AE49 -> 225000 | D49: =(H49+L49+P49+T49+X49+AB49+AF49)-B49 -> 3586560.6 | E49: ='Project Overview'!$F$4/12 -> 0 | F49: ='Project Overview'!$F$5/12 -> 238714.63 | G49: 75000 | H49: =G49*($H$2-$F$2) -> 1678509.9 | I49: ='Project Overview'!$E$12/12 -> 0 | J49: ='Project Overview'!$E$13/12 -> 103696.78 | K49: 75000 | L49: =K49*($L$2-$J$2) -> 1678509.9 | M49: ='Project Overview'!$D$12/12 -> 125000 | N49: ='Project Overview'!$D$13/12 -> 90171.117 | O49: 37500 | P49: =O49*($P$2-$N$2) -> 839254.93 | Q49: ='Project Overview'!$D$12/12 -> 125000 | R49: ='Project Overview'!$D$13/12 -> 90171.117 | S49: 37500 | T49: =S49*($T$2-$R$2) -> 839254.93 | U49: ='Project Overview'!$C$12/12 -> 270000 | V49: ='Project Overview'!$C$13/12 -> 68107.667 | W49: 0 | X49: =W49*($X$2-$V$2) -> 0 | Y49: ='Project Overview'!$C$12/12 -> 270000 | Z49: ='Project Overview'!$C$13/12 -> 68107.667 | AA49: 0 | AB49: =AA49*($AB$2-$Z$2) -> 0
A50: 44 | B50: =E50+F50+I50+J50+M50+N50+Q50+R50+U50+V50+Y50+Z50+AC50+AD50 -> 1448969 | C50: =G50+K50+O50+S50+W50+AA50+AE50 -> 225000 | D50: =(H50+L50+P50+T50+X50+AB50+AF50)-B50 -> 3586560.6 | E50: ='Project Overview'!$F$4/12 -> 0 | F50: ='Project Overview'!$F$5/12 -> 238714.63 | G50: 75000 | H50: =G50*($H$2-$F$2) -> 1678509.9 | I50: ='Project Overview'!$E$12/12 -> 0 | J50: ='Project Overview'!$E$13/12 -> 103696.78 | K50: 75000 | L50: =K50*($L$2-$J$2) -> 1678509.9 | M50: ='Project Overview'!$D$12/12 -> 125000 | N50: ='Project Overview'!$D$13/12 -> 90171.117 | O50: 37500 | P50: =O50*($P$2-$N$2) -> 839254.93 | Q50: ='Project Overview'!$D$12/12 -> 125000 | R50: ='Project Overview'!$D$13/12 -> 90171.117 | S50: 37500 | T50: =S50*($T$2-$R$2) -> 839254.93 | U50: ='Project Overview'!$C$12/12 -> 270000 | V50: ='Project Overview'!$C$13/12 -> 68107.667 | W50: 0 | X50: =W50*($X$2-$V$2) -> 0 | Y50: ='Project Overview'!$C$12/12 -> 270000 | Z50: ='Project Overview'!$C$13/12 -> 68107.667 | AA50: 0 | AB50: =AA50*($AB$2-$Z$2) -> 0
A51: 45 | B51: =E51+F51+I51+J51+M51+N51+Q51+R51+U51+V51+Y51+Z51+AC51+AD51 -> 1448969 | C51: =G51+K51+O51+S51+W51+AA51+AE51 -> 225000 | D51: =(H51+L51+P51+T51+X51+AB51+AF51)-B51 -> 3586560.6 | E51: ='Project Overview'!$F$4/12 -> 0 | F51: ='Project Overview'!$F$5/12 -> 238714.63 | G51: 75000 | H51: =G51*($H$2-$F$2) -> 1678509.9 | I51: ='Project Overview'!$E$12/12 -> 0 | J51: ='Project Overview'!$E$13/12 -> 103696.78 | K51: 75000 | L51: =K51*($L$2-$J$2) -> 1678509.9 | M51: ='Project Overview'!$D$12/12 -> 125000 | N51: ='Project Overview'!$D$13/12 -> 90171.117 | O51: 37500 | P51: =O51*($P$2-$N$2) -> 839254.93 | Q51: ='Project Overview'!$D$12/12 -> 125000 | R51: ='Project Overview'!$D$13/12 -> 90171.117 | S51: 37500 | T51: =S51*($T$2-$R$2) -> 839254.93 | U51: ='Project Overview'!$C$12/12 -> 270000 | V51: ='Project Overview'!$C$13/12 -> 68107.667 | W51: 0 | X51: =W51*($X$2-$V$2) -> 0 | Y51: ='Project Overview'!$C$12/12 -> 270000 | Z51: ='Project Overview'!$C$13/12 -> 68107.667 | AA51: 0 | AB51: =AA51*($AB$2-$Z$2) -> 0
A52: 46 | B52: =E52+F52+I52+J52+M52+N52+Q52+R52+U52+V52+Y52+Z52+AC52+AD52 -> 1448969 | C52: =G52+K52+O52+S52+W52+AA52+AE52 -> 225000 | D52: =(H52+L52+P52+T52+X52+AB52+AF52)-B52 -> 3586560.6 | E52: ='Project Overview'!$F$4/12 -> 0 | F52: ='Project Overview'!$F$5/12 -> 238714.63 | G52: 75000 | H52: =G52*($H$2-$F$2) -> 1678509.9 | I52: ='Project Overview'!$E$12/12 -> 0 | J52: ='Project Overview'!$E$13/12 -> 103696.78 | K52: 75000 | L52: =K52*($L$2-$J$2) -> 1678509.9 | M52: ='Project Overview'!$D$12/12 -> 125000 | N52: ='Project Overview'!$D$13/12 -> 90171.117 | O52: 37500 | P52: =O52*($P$2-$N$2) -> 839254.93 | Q52: ='Project Overview'!$D$12/12 -> 125000 | R52: ='Project Overview'!$D$13/12 -> 90171.117 | S52: 37500 | T52: =S52*($T$2-$R$2) -> 839254.93 | U52: ='Project Overview'!$C$12/12 -> 270000 | V52: ='Project Overview'!$C$13/12 -> 68107.667 | W52: 0 | X52: =W52*($X$2-$V$2) -> 0 | Y52: ='Project Overview'!$C$12/12 -> 270000 | Z52: ='Project Overview'!$C$13/12 -> 68107.667 | AA52: 0 | AB52: =AA52*($AB$2-$Z$2) -> 0
A53: 47 | B53: =E53+F53+I53+J53+M53+N53+Q53+R53+U53+V53+Y53+Z53+AC53+AD53 -> 1448969 | C53: =G53+K53+O53+S53+W53+AA53+AE53 -> 225000 | D53: =(H53+L53+P53+T53+X53+AB53+AF53)-B53 -> 3586560.6 | E53: ='Project Overview'!$F$4/12 -> 0 | F53: ='Project Overview'!$F$5/12 -> 238714.63 | G53: 75000 | H53: =G53*($H$2-$F$2) -> 1678509.9 | I53: ='Project Overview'!$E$12/12 -> 0 | J53: ='Project Overview'!$E$13/12 -> 103696.78 | K53: 75000 | L53: =K53*($L$2-$J$2) -> 1678509.9 | M53: ='Project Overview'!$D$12/12 -> 125000 | N53: ='Project Overview'!$D$13/12 -> 90171.117 | O53: 37500 | P53: =O53*($P$2-$N$2) -> 839254.93 | Q53: ='Project Overview'!$D$12/12 -> 125000 | R53: ='Project Overview'!$D$13/12 -> 90171.117 | S53: 37500 | T53: =S53*($T$2-$R$2) -> 839254.93 | U53: ='Project Overview'!$C$12/12 -> 270000 | V53: ='Project Overview'!$C$13/12 -> 68107.667 | W53: 0 | X53: =W53*($X$2-$V$2) -> 0 | Y53: ='Project Overview'!$C$12/12 -> 270000 | Z53: ='Project Overview'!$C$13/12 -> 68107.667 | AA53: 0 | AB53: =AA53*($AB$2-$Z$2) -> 0
A54: 48 | B54: =E54+F54+I54+J54+M54+N54+Q54+R54+U54+V54+Y54+Z54+AC54+AD54 -> 1448969 | C54: =G54+K54+O54+S54+W54+AA54+AE54 -> 225000 | D54: =(H54+L54+P54+T54+X54+AB54+AF54)-B54 -> 3586560.6 | E54: ='Project Overview'!$F$4/12 -> 0 | F54: ='Project Overview'!$F$5/12 -> 238714.63 | G54: 75000 | H54: =G54*($H$2-$F$2) -> 1678509.9 | I54: ='Project Overview'!$E$12/12 -> 0 | J54: ='Project Overview'!$E$13/12 -> 103696.78 | K54: 75000 | L54: =K54*($L$2-$J$2) -> 1678509.9 | M54: ='Project Overview'!$D$12/12 -> 125000 | N54: ='Project Overview'!$D$13/12 -> 90171.117 | O54: 37500 | P54: =O54*($P$2-$N$2) -> 839254.93 | Q54: ='Project Overview'!$D$12/12 -> 125000 | R54: ='Project Overview'!$D$13/12 -> 90171.117 | S54: 37500 | T54: =S54*($T$2-$R$2) -> 839254.93 | U54: ='Project Overview'!$C$12/12 -> 270000 | V54: ='Project Overview'!$C$13/12 -> 68107.667 | W54: 0 | X54: =W54*($X$2-$V$2) -> 0 | Y54: ='Project Overview'!$C$12/12 -> 270000 | Z54: ='Project Overview'!$C$13/12 -> 68107.667 | AA54: 0 | AB54: =AA54*($AB$2-$Z$2) -> 0
A55: Total | B55: =SUM(B43:B54) -> 17387628 | C55: =SUM(C43:C54) -> 2700000 | D55: =SUM(D43:D54) -> 43038728 | E55: =SUM(E43:E54) -> 0 | F55: =SUM(F43:F54) -> 2864575.5 | G55: =SUM(G43:G54) -> 900000 | H55: =SUM(H43:H54) -> 20142118 | I55: =SUM(I43:I54) -> 0 | ... AB55: =SUM(AB43:AB54) -> 0
A56: 49 | B56: =E56+F56+I56+J56+M56+N56+Q56+R56+U56+V56+Y56+Z56+AC56+AD56 -> 3024347.7 | C56: =G56+K56+O56+S56+W56+AA56+AE56 -> 375000 | D56: =(H56+L56+P56+T56+X56+AB56+AF56)-B56 -> 5368201.6 | E56: ='Project Overview'!$G$4/12 -> 0 | F56: ='Project Overview'!$G$5/12 -> 238714.63 | G56: 75000 | H56: =G56*($H$2-$F$2) -> 1678509.9 | I56: ='Project Overview'!$F$12/12 -> 0 | J56: ='Project Overview'!$F$13/12 -> 119251.3 | K56: 75000 | L56: =K56*($L$2-$J$2) -> 1678509.9 | M56: ='Project Overview'!$E$12/12 -> 0 | N56: ='Project Overview'!$E$13/12 -> 103696.78 | O56: 75000 | P56: =O56*($P$2-$N$2) -> 1678509.9 | Q56: ='Project Overview'!$E$12/12 -> 0 | R56: ='Project Overview'!$E$13/12 -> 103696.78 | S56: 75000 | T56: =S56*($T$2-$R$2) -> 1678509.9 | U56: ='Project Overview'!$D$12/12 -> 125000 | V56: ='Project Overview'!$D$13/12 -> 90171.117 | W56: 37500 | X56: =W56*($X$2-$V$2) -> 839254.93 | Y56: ='Project Overview'!$D$12/12 -> 125000 | Z56: ='Project Overview'!$D$13/12 -> 90171.117 | AA56: 37500 | AB56: =AA56*($AB$2-$Z$2) -> 839254.93 | AC56: =('Project Overview'!$C$12/12)*6 -> 1620000 | AD56: =('Project Overview'!$C$13/12)*6 -> 408646 | AE56: =0*6 -> 0 | AF56: =AE56*($AF$2-$AD$2) -> 0
A57: 50 | B57: =E57+F57+I57+J57+M57+N57+Q57+R57+U57+V57+Y57+Z57+AC57+AD57 -> 3024347.7 | C57: =G57+K57+O57+S57+W57+AA57+AE57 -> 375000 | D57: =(H57+L57+P57+T57+X57+AB57+AF57)-B57 -> 5368201.6 | E57: ='Project Overview'!$G$4/12 -> 0 | F57: ='Project Overview'!$G$5/12 -> 238714.63 | G57: 75000 | H57: =G57*($H$2-$F$2) -> 1678509.9 | I57: ='Project Overview'!$F$12/12 -> 0 | J57: ='Project Overview'!$F$13/12 -> 119251.3 | K57: 75000 | L57: =K57*($L$2-$J$2) -> 1678509.9 | M57: ='Project Overview'!$E$12/12 -> 0 | N57: ='Project Overview'!$E$13/12 -> 103696.78 | O57: 75000 | P57: =O57*($P$2-$N$2) -> 1678509.9 | Q57: ='Project Overview'!$E$12/12 -> 0 | R57: ='Project Overview'!$E$13/12 -> 103696.78 | S57: 75000 | T57: =S57*($T$2-$R$2) -> 1678509.9 | U57: ='Project Overview'!$D$12/12 -> 125000 | V57: ='Project Overview'!$D$13/12 -> 90171.117 | W57: 37500 | X57: =W57*($X$2-$V$2) -> 839254.93 | Y57: ='Project Overview'!$D$12/12 -> 125000 | Z57: ='Project Overview'!$D$13/12 -> 90171.117 | AA57: 37500 | AB57: =AA57*($AB$2-$Z$2) -> 839254.93 | AC57: =('Project Overview'!$C$12/12)*6 -> 1620000 | AD57: =('Project Overview'!$C$13/12)*6 -> 408646 | AE57: =0*6 -> 0 | AF57: =AE57*($AF$2-$AD$2) -> 0
A58: 51 | B58: =E58+F58+I58+J58+M58+N58+Q58+R58+U58+V58+Y58+Z58+AC58+AD58 -> 3024347.7 | C58: =G58+K58+O58+S58+W58+AA58+AE58 -> 375000 | D58: =(H58+L58+P58+T58+X58+AB58+AF58)-B58 -> 5368201.6 | E58: ='Project Overview'!$G$4/12 -> 0 | F58: ='Project Overview'!$G$5/12 -> 238714.63 | G58: 75000 | H58: =G58*($H$2-$F$2) -> 1678509.9 | I58: ='Project Overview'!$F$12/12 -> 0 | J58: ='Project Overview'!$F$13/12 -> 119251.3 | K58: 75000 | L58: =K58*($L$2-$J$2) -> 1678509.9 | M58: ='Project Overview'!$E$12/12 -> 0 | N58: ='Project Overview'!$E$13/12 -> 103696.78 | O58: 75000 | P58: =O58*($P$2-$N$2) -> 1678509.9 | Q58: ='Project Overview'!$E$12/12 -> 0 | R58: ='Project Overview'!$E$13/12 -> 103696.78 | S58: 75000 | T58: =S58*($T$2-$R$2) -> 1678509.9 | U58: ='Project Overview'!$D$12/12 -> 125000 | V58: ='Project Overview'!$D$13/12 -> 90171.117 | W58: 37500 | X58: =W58*($X$2-$V$2) -> 839254.93 | Y58: ='Project Overview'!$D$12/12 -> 125000 | Z58: ='Project Overview'!$D$13/12 -> 90171.117 | AA58: 37500 | AB58: =AA58*($AB$2-$Z$2) -> 839254.93 | AC58: =('Project Overview'!$C$12/12)*6 -> 1620000 | AD58: =('Project Overview'!$C$13/12)*6 -> 408646 | AE58: =0*6 -> 0 | AF58: =AE58*($AF$2-$AD$2) -> 0
A59: 52 | B59: =E59+F59+I59+J59+M59+N59+Q59+R59+U59+V59+Y59+Z59+AC59+AD59 -> 3024347.7 | C59: =G59+K59+O59+S59+W59+AA59+AE59 -> 375000 | D59: =(H59+L59+P59+T59+X59+AB59+AF59)-B59 -> 5368201.6 | E59: ='Project Overview'!$G$4/12 -> 0 | F59: ='Project Overview'!$G$5/12 -> 238714.63 | G59: 75000 | H59: =G59*($H$2-$F$2) -> 1678509.9 | I59: ='Project Overview'!$F$12/12 -> 0 | J59: ='Project Overview'!$F$13/12 -> 119251.3 | K59: 75000 | L59: =K59*($L$2-$J$2) -> 1678509.9 | M59: ='Project Overview'!$E$12/12 -> 0 | N59: ='Project Overview'!$E$13/12 -> 103696.78 | O59: 75000 | P59: =O59*($P$2-$N$2) -> 1678509.9 | Q59: ='Project Overview'!$E$12/12 -> 0 | R59: ='Project Overview'!$E$13/12 -> 103696.78 | S59: 75000 | T59: =S59*($T$2-$R$2) -> 1678509.9 | U59: ='Project Overview'!$D$12/12 -> 125000 | V59: ='Project Overview'!$D$13/12 -> 90171.117 | W59: 37500 | X59: =W59*($X$2-$V$2) -> 839254.93 | Y59: ='Project Overview'!$D$12/12 -> 125000 | Z59: ='Project Overview'!$D$13/12 -> 90171.117 | AA59: 37500 | AB59: =AA59*($AB$2-$Z$2) -> 839254.93 | AC59: =('Project Overview'!$C$12/12)*6 -> 1620000 | AD59: =('Project Overview'!$C$13/12)*6 -> 408646 | AE59: =0*6 -> 0 | AF59: =AE59*($AF$2-$AD$2) -> 0
A60: 53 | B60: =E60+F60+I60+J60+M60+N60+Q60+R60+U60+V60+Y60+Z60+AC60+AD60 -> 3024347.7 | C60: =G60+K60+O60+S60+W60+AA60+AE60 -> 375000 | D60: =(H60+L60+P60+T60+X60+AB60+AF60)-B60 -> 5368201.6 | E60: ='Project Overview'!$G$4/12 -> 0 | F60: ='Project Overview'!$G$5/12 -> 238714.63 | G60: 75000 | H60: =G60*($H$2-$F$2) -> 1678509.9 | I60: ='Project Overview'!$F$12/12 -> 0 | J60: ='Project Overview'!$F$13/12 -> 119251.3 | K60: 75000 | L60: =K60*($L$2-$J$2) -> 1678509.9 | M60: ='Project Overview'!$E$12/12 -> 0 | N60: ='Project Overview'!$E$13/12 -> 103696.78 | O60: 75000 | P60: =O60*($P$2-$N$2) -> 1678509.9 | Q60: ='Project Overview'!$E$12/12 -> 0 | R60: ='Project Overview'!$E$13/12 -> 103696.78 | S60: 75000 | T60: =S60*($T$2-$R$2) -> 1678509.9 | U60: ='Project Overview'!$D$12/12 -> 125000 | V60: ='Project Overview'!$D$13/12 -> 90171.117 | W60: 37500 | X60: =W60*($X$2-$V$2) -> 839254.93 | Y60: ='Project Overview'!$D$12/12 -> 125000 | Z60: ='Project Overview'!$D$13/12 -> 90171.117 | AA60: 37500 | AB60: =AA60*($AB$2-$Z$2) -> 839254.93 | AC60: =('Project Overview'!$C$12/12)*6 -> 1620000 | AD60: =('Project Overview'!$C$13/12)*6 -> 408646 | AE60: =0*6 -> 0 | AF60: =AE60*($AF$2-$AD$2) -> 0
A61: 54 | B61: =E61+F61+I61+J61+M61+N61+Q61+R61+U61+V61+Y61+Z61+AC61+AD61 -> 3024347.7 | C61: =G61+K61+O61+S61+W61+AA61+AE61 -> 375000 | D61: =(H61+L61+P61+T61+X61+AB61+AF61)-B61 -> 5368201.6 | E61: ='Project Overview'!$G$4/12 -> 0 | F61: ='Project Overview'!$G$5/12 -> 238714.63 | G61: 75000 | H61: =G61*($H$2-$F$2) -> 1678509.9 | I61: ='Project Overview'!$F$12/12 -> 0 | J61: ='Project Overview'!$F$13/12 -> 119251.3 | K61: 75000 | L61: =K61*($L$2-$J$2) -> 1678509.9 | M61: ='Project Overview'!$E$12/12 -> 0 | N61: ='Project Overview'!$E$13/12 -> 103696.78 | O61: 75000 | P61: =O61*($P$2-$N$2) -> 1678509.9 | Q61: ='Project Overview'!$E$12/12 -> 0 | R61: ='Project Overview'!$E$13/12 -> 103696.78 | S61: 75000 | T61: =S61*($T$2-$R$2) -> 1678509.9 | U61: ='Project Overview'!$D$12/12 -> 125000 | V61: ='Project Overview'!$D$13/12 -> 90171.117 | W61: 37500 | X61: =W61*($X$2-$V$2) -> 839254.93 | Y61: ='Project Overview'!$D$12/12 -> 125000 | Z61: ='Project Overview'!$D$13/12 -> 90171.117 | AA61: 37500 | AB61: =AA61*($AB$2-$Z$2) -> 839254.93 | AC61: =('Project Overview'!$C$12/12)*6 -> 1620000 | AD61: =('Project Overview'!$C$13/12)*6 -> 408646 | AE61: =0*6 -> 0 | AF61: =AE61*($AF$2-$AD$2) -> 0
A62: 55 | B62: =E62+F62+I62+J62+M62+N62+Q62+R62+U62+V62+Y62+Z62+AC62+AD62 -> 3024347.7 | C62: =G62+K62+O62+S62+W62+AA62+AE62 -> 375000 | D62: =(H62+L62+P62+T62+X62+AB62+AF62)-B62 -> 5368201.6 | E62: ='Project Overview'!$G$4/12 -> 0 | F62: ='Project Overview'!$G$5/12 -> 238714.63 | G62: 75000 | H62: =G62*($H$2-$F$2) -> 1678509.9 | I62: ='Project Overview'!$F$12/12 -> 0 | J62: ='Project Overview'!$F$13/12 -> 119251.3 | K62: 75000 | L62: =K62*($L$2-$J$2) -> 1678509.9 | M62: ='Project Overview'!$E$12/12 -> 0 | N62: ='Project Overview'!$E$13/12 -> 103696.78 | O62: 75000 | P62: =O62*($P$2-$N$2) -> 1678509.9 | Q62: ='Project Overview'!$E$12/12 -> 0 | R62: ='Project Overview'!$E$13/12 -> 103696.78 | S62: 75000 | T62: =S62*($T$2-$R$2) -> 1678509.9 | U62: ='Project Overview'!$D$12/12 -> 125000 | V62: ='Project Overview'!$D$13/12 -> 90171.117 | W62: 37500 | X62: =W62*($X$2-$V$2) -> 839254.93 | Y62: ='Project Overview'!$D$12/12 -> 125000 | Z62: ='Project Overview'!$D$13/12 -> 90171.117 | AA62: 37500 | AB62: =AA62*($AB$2-$Z$2) -> 839254.93 | AC62: =('Project Overview'!$C$12/12)*6 -> 1620000 | AD62: =('Project Overview'!$C$13/12)*6 -> 408646 | AE62: =0*6 -> 0 | AF62: =AE62*($AF$2-$AD$2) -> 0
A63: 56 | B63: =E63+F63+I63+J63+M63+N63+Q63+R63+U63+V63+Y63+Z63+AC63+AD63 -> 3024347.7 | C63: =G63+K63+O63+S63+W63+AA63+AE63 -> 375000 | D63: =(H63+L63+P63+T63+X63+AB63+AF63)-B63 -> 5368201.6 | E63: ='Project Overview'!$G$4/12 -> 0 | F63: ='Project Overview'!$G$5/12 -> 238714.63 | G63: 75000 | H63: =G63*($H$2-$F$2) -> 1678509.9 | I63: ='Project Overview'!$F$12/12 -> 0 | J63: ='Project Overview'!$F$13/12 -> 119251.3 | K63: 75000 | L63: =K63*($L$2-$J$2) -> 1678509.9 | M63: ='Project Overview'!$E$12/12 -> 0 | N63: ='Project Overview'!$E$13/12 -> 103696.78 | O63: 75000 | P63: =O63*($P$2-$N$2) -> 1678509.9 | Q63: ='Project Overview'!$E$12/12 -> 0 | R63: ='Project Overview'!$E$13/12 -> 103696.78 | S63: 75000 | T63: =S63*($T$2-$R$2) -> 1678509.9 | U63: ='Project Overview'!$D$12/12 -> 125000 | V63: ='Project Overview'!$D$13/12 -> 90171.117 | W63: 37500 | X63: =W63*($X$2-$V$2) -> 839254.93 | Y63: ='Project Overview'!$D$12/12 -> 125000 | Z63: ='Project Overview'!$D$13/12 -> 90171.117 | AA63: 37500 | AB63: =AA63*($AB$2-$Z$2) -> 839254.93 | AC63: =('Project Overview'!$C$12/12)*6 -> 1620000 | AD63: =('Project Overview'!$C$13/12)*6 -> 408646 | AE63: =0*6 -> 0 | AF63: =AE63*($AF$2-$AD$2) -> 0
A64: 57 | B64: =E64+F64+I64+J64+M64+N64+Q64+R64+U64+V64+Y64+Z64+AC64+AD64 -> 3024347.7 | C64: =G64+K64+O64+S64+W64+AA64+AE64 -> 375000 | D64: =(H64+L64+P64+T64+X64+AB64+AF64)-B64 -> 5368201.6 | E64: ='Project Overview'!$G$4/12 -> 0 | F64: ='Project Overview'!$G$5/12 -> 238714.63 | G64: 75000 | H64: =G64*($H$2-$F$2) -> 1678509.9 | I64: ='Project Overview'!$F$12/12 -> 0 | J64: ='Project Overview'!$F$13/12 -> 119251.3 | K64: 75000 | L64: =K64*($L$2-$J$2) -> 1678509.9 | M64: ='Project Overview'!$E$12/12 -> 0 | N64: ='Project Overview'!$E$13/12 -> 103696.78 | O64: 75000 | P64: =O64*($P$2-$N$2) -> 1678509.9 | Q64: ='Project Overview'!$E$12/12 -> 0 | R64: ='Project Overview'!$E$13/12 -> 103696.78 | S64: 75000 | T64: =S64*($T$2-$R$2) -> 1678509.9 | U64: ='Project Overview'!$D$12/12 -> 125000 | V64: ='Project Overview'!$D$13/12 -> 90171.117 | W64: 37500 | X64: =W64*($X$2-$V$2) -> 839254.93 | Y64: ='Project Overview'!$D$12/12 -> 125000 | Z64: ='Project Overview'!$D$13/12 -> 90171.117 | AA64: 37500 | AB64: =AA64*($AB$2-$Z$2) -> 839254.93 | AC64: =('Project Overview'!$C$12/12)*6 -> 1620000 | AD64: =('Project Overview'!$C$13/12)*6 -> 408646 | AE64: =0*6 -> 0 | AF64: =AE64*($AF$2-$AD$2) -> 0
A65: 58 | B65: =E65+F65+I65+J65+M65+N65+Q65+R65+U65+V65+Y65+Z65+AC65+AD65 -> 3024347.7 | C65: =G65+K65+O65+S65+W65+AA65+AE65 -> 375000 | D65: =(H65+L65+P65+T65+X65+AB65+AF65)-B65 -> 5368201.6 | E65: ='Project Overview'!$G$4/12 -> 0 | F65: ='Project Overview'!$G$5/12 -> 238714.63 | G65: 75000 | H65: =G65*($H$2-$F$2) -> 1678509.9 | I65: ='Project Overview'!$F$12/12 -> 0 | J65: ='Project Overview'!$F$13/12 -> 119251.3 | K65: 75000 | L65: =K65*($L$2-$J$2) -> 1678509.9 | M65: ='Project Overview'!$E$12/12 -> 0 | N65: ='Project Overview'!$E$13/12 -> 103696.78 | O65: 75000 | P65: =O65*($P$2-$N$2) -> 1678509.9 | Q65: ='Project Overview'!$E$12/12 -> 0 | R65: ='Project Overview'!$E$13/12 -> 103696.78 | S65: 75000 | T65: =S65*($T$2-$R$2) -> 1678509.9 | U65: ='Project Overview'!$D$12/12 -> 125000 | V65: ='Project Overview'!$D$13/12 -> 90171.117 | W65: 37500 | X65: =W65*($X$2-$V$2) -> 839254.93 | Y65: ='Project Overview'!$D$12/12 -> 125000 | Z65: ='Project Overview'!$D$13/12 -> 90171.117 | AA65: 37500 | AB65: =AA65*($AB$2-$Z$2) -> 839254.93 | AC65: =('Project Overview'!$C$12/12)*6 -> 1620000 | AD65: =('Project Overview'!$C$13/12)*6 -> 408646 | AE65: =0*6 -> 0 | AF65: =AE65*($AF$2-$AD$2) -> 0
A66: 59 | B66: =E66+F66+I66+J66+M66+N66+Q66+R66+U66+V66+Y66+Z66+AC66+AD66 -> 3024347.7 | C66: =G66+K66+O66+S66+W66+AA66+AE66 -> 375000 | D66: =(H66+L66+P66+T66+X66+AB66+AF66)-B66 -> 5368201.6 | E66: ='Project Overview'!$G$4/12 -> 0 | F66: ='Project Overview'!$G$5/12 -> 238714.63 | G66: 75000 | H66: =G66*($H$2-$F$2) -> 1678509.9 | I66: ='Project Overview'!$F$12/12 -> 0 | J66: ='Project Overview'!$F$13/12 -> 119251.3 | K66: 75000 | L66: =K66*($L$2-$J$2) -> 1678509.9 | M66: ='Project Overview'!$E$12/12 -> 0 | N66: ='Project Overview'!$E$13/12 -> 103696.78 | O66: 75000 | P66: =O66*($P$2-$N$2) -> 1678509.9 | Q66: ='Project Overview'!$E$12/12 -> 0 | R66: ='Project Overview'!$E$13/12 -> 103696.78 | S66: 75000 | T66: =S66*($T$2-$R$2) -> 1678509.9 | U66: ='Project Overview'!$D$12/12 -> 125000 | V66: ='Project Overview'!$D$13/12 -> 90171.117 | W66: 37500 | X66: =W66*($X$2-$V$2) -> 839254.93 | Y66: ='Project Overview'!$D$12/12 -> 125000 | Z66: ='Project Overview'!$D$13/12 -> 90171.117 | AA66: 37500 | AB66: =AA66*($AB$2-$Z$2) -> 839254.93 | AC66: =('Project Overview'!$C$12/12)*6 -> 1620000 | AD66: =('Project Overview'!$C$13/12)*6 -> 408646 | AE66: =0*6 -> 0 | AF66: =AE66*($AF$2-$AD$2) -> 0
A67: 60 | B67: =E67+F67+I67+J67+M67+N67+Q67+R67+U67+V67+Y67+Z67+AC67+AD67 -> 3024347.7 | C67: =G67+K67+O67+S67+W67+AA67+AE67 -> 375000 | D67: =(H67+L67+P67+T67+X67+AB67+AF67)-B67 -> 5368201.6 | E67: ='Project Overview'!$G$4/12 -> 0 | F67: ='Project Overview'!$G$5/12 -> 238714.63 | G67: 75000 | H67: =G67*($H$2-$F$2) -> 1678509.9 | I67: ='Project Overview'!$F$12/12 -> 0 | J67: ='Project Overview'!$F$13/12 -> 119251.3 | K67: 75000 | L67: =K67*($L$2-$J$2) -> 1678509.9 | M67: ='Project Overview'!$E$12/12 -> 0 | N67: ='Project Overview'!$E$13/12 -> 103696.78 | O67: 75000 | P67: =O67*($P$2-$N$2) -> 1678509.9 | Q67: ='Project Overview'!$E$12/12 -> 0 | R67: ='Project Overview'!$E$13/12 -> 103696.78 | S67: 75000 | T67: =S67*($T$2-$R$2) -> 1678509.9 | U67: ='Project Overview'!$D$12/12 -> 125000 | V67: ='Project Overview'!$D$13/12 -> 90171.117 | W67: 37500 | X67: =W67*($X$2-$V$2) -> 839254.93 | Y67: ='Project Overview'!$D$12/12 -> 125000 | Z67: ='Project Overview'!$D$13/12 -> 90171.117 | AA67: 37500 | AB67: =AA67*($AB$2-$Z$2) -> 839254.93 | AC67: =('Project Overview'!$C$12/12)*6 -> 1620000 | AD67: =('Project Overview'!$C$13/12)*6 -> 408646 | AE67: =0*6 -> 0 | AF67: =AE67*($AF$2-$AD$2) -> 0
A68: Total | B68: =SUM(B56:B67) -> 36292173 | C68: =SUM(C56:C67) -> 4500000 | D68: =SUM(D56:D67) -> 64418419 | E68: =SUM(E56:E67) -> 0 | F68: =SUM(F56:F67) -> 2864575.5 | G68: =SUM(G56:G67) -> 900000 | H68: =SUM(H56:H67) -> 20142118 | I68: =SUM(I56:I67) -> 0 | ... AF68: =SUM(AF56:AF67) -> 0
A69: 61 | B69: =E69+F69+I69+J69+M69+N69+Q69+R69+U69+V69+Y69+Z69+AC69+AD69 -> 2094888.8 | C69: =G69+K69+O69+S69+W69+AA69+AE69 -> 675000 | D69: =(H69+L69+P69+T69+X69+AB69+AF69)-B69 -> 13011700 | E69: ='Project Overview'!$G$4/12 -> 0 | F69: ='Project Overview'!$G$5/12 -> 238714.63 | G69: 75000 | H69: =G69*($H$2-$F$2) -> 1678509.9 | I69: ='Project Overview'!$G$12/12 -> 0 | J69: ='Project Overview'!$G$13/12 -> 119251.3 | K69: 75000 | L69: =K69*($L$2-$J$2) -> 1678509.9 | M69: ='Project Overview'!$F$12/12 -> 0 | N69: ='Project Overview'!$F$13/12 -> 119251.3 | O69: 75000 | P69: =O69*($P$2-$N$2) -> 1678509.9 | Q69: ='Project Overview'!$F$12/12 -> 0 | R69: ='Project Overview'!$F$13/12 -> 119251.3 | S69: 75000 | T69: =S69*($T$2-$R$2) -> 1678509.9 | U69: ='Project Overview'!$E$12/12 -> 0 | V69: ='Project Overview'!$E$13/12 -> 103696.78 | W69: 75000 | X69: =W69*($X$2-$V$2) -> 1678509.9 | Y69: ='Project Overview'!$E$12/12 -> 0 | Z69: ='Project Overview'!$E$13/12 -> 103696.78 | AA69: 75000 | AB69: =AA69*($AB$2-$Z$2) -> 1678509.9 | AC69: =('Project Overview'!$D$12/12)*6 -> 750000 | AD69: =('Project Overview'!$D$13/12)*6 -> 541026.7 | AE69: =37500*6 -> 225000 | AF69: =AE69*($AF$2-$AD$2) -> 5035529.6
A70: 62 | B70: =E70+F70+I70+J70+M70+N70+Q70+R70+U70+V70+Y70+Z70+AC70+AD70 -> 2094888.8 | C70: =G70+K70+O70+S70+W70+AA70+AE70 -> 675000 | D70: =(H70+L70+P70+T70+X70+AB70+AF70)-B70 -> 13011700 | E70: ='Project Overview'!$G$4/12 -> 0 | F70: ='Project Overview'!$G$5/12 -> 238714.63 | G70: 75000 | H70: =G70*($H$2-$F$2) -> 1678509.9 | I70: ='Project Overview'!$G$12/12 -> 0 | J70: ='Project Overview'!$G$13/12 -> 119251.3 | K70: 75000 | L70: =K70*($L$2-$J$2) -> 1678509.9 | M70: ='Project Overview'!$F$12/12 -> 0 | N70: ='Project Overview'!$F$13/12 -> 119251.3 | O70: 75000 | P70: =O70*($P$2-$N$2) -> 1678509.9 | Q70: ='Project Overview'!$F$12/12 -> 0 | R70: ='Project Overview'!$F$13/12 -> 119251.3 | S70: 75000 | T70: =S70*($T$2-$R$2) -> 1678509.9 | U70: ='Project Overview'!$E$12/12 -> 0 | V70: ='Project Overview'!$E$13/12 -> 103696.78 | W70: 75000 | X70: =W70*($X$2-$V$2) -> 1678509.9 | Y70: ='Project Overview'!$E$12/12 -> 0 | Z70: ='Project Overview'!$E$13/12 -> 103696.78 | AA70: 75000 | AB70: =AA70*($AB$2-$Z$2) -> 1678509.9 | AC70: =('Project Overview'!$D$12/12)*6 -> 750000 | AD70: =('Project Overview'!$D$13/12)*6 -> 541026.7 | AE70: =37500*6 -> 225000 | AF70: =AE70*($AF$2-$AD$2) -> 5035529.6
A71: 63 | B71: =E71+F71+I71+J71+M71+N71+Q71+R71+U71+V71+Y71+Z71+AC71+AD71 -> 2094888.8 | C71: =G71+K71+O71+S71+W71+AA71+AE71 -> 675000 | D71: =(H71+L71+P71+T71+X71+AB71+AF71)-B71 -> 13011700 | E71: ='Project Overview'!$G$4/12 -> 0 | F71: ='Project Overview'!$G$5/12 -> 238714.63 | G71: 75000 | H71: =G71*($H$2-$F$2) -> 1678509.9 | I71: ='Project Overview'!$G$12/12 -> 0 | J71: ='Project Overview'!$G$13/12 -> 119251.3 | K71: 75000 | L71: =K71*($L$2-$J$2) -> 1678509.9 | M71: ='Project Overview'!$F$12/12 -> 0 | N71: ='Project Overview'!$F$13/12 -> 119251.3 | O71: 75000 | P71: =O71*($P$2-$N$2) -> 1678509.9 | Q71: ='Project Overview'!$F$12/12 -> 0 | R71: ='Project Overview'!$F$13/12 -> 119251.3 | S71: 75000 | T71: =S71*($T$2-$R$2) -> 1678509.9 | U71: ='Project Overview'!$E$12/12 -> 0 | V71: ='Project Overview'!$E$13/12 -> 103696.78 | W71: 75000 | X71: =W71*($X$2-$V$2) -> 1678509.9 | Y71: ='Project Overview'!$E$12/12 -> 0 | Z71: ='Project Overview'!$E$13/12 -> 103696.78 | AA71: 75000 | AB71: =AA71*($AB$2-$Z$2) -> 1678509.9 | AC71: =('Project Overview'!$D$12/12)*6 -> 750000 | AD71: =('Project Overview'!$D$13/12)*6 -> 541026.7 | AE71: =37500*6 -> 225000 | AF71: =AE71*($AF$2-$AD$2) -> 5035529.6
A72: 64 | B72: =E72+F72+I72+J72+M72+N72+Q72+R72+U72+V72+Y72+Z72+AC72+AD72 -> 2094888.8 | C72: =G72+K72+O72+S72+W72+AA72+AE72 -> 675000 | D72: =(H72+L72+P72+T72+X72+AB72+AF72)-B72 -> 13011700 | E72: ='Project Overview'!$G$4/12 -> 0 | F72: ='Project Overview'!$G$5/12 -> 238714.63 | G72: 75000 | H72: =G72*($H$2-$F$2) -> 1678509.9 | I72: ='Project Overview'!$G$12/12 -> 0 | J72: ='Project Overview'!$G$13/12 -> 119251.3 | K72: 75000 | L72: =K72*($L$2-$J$2) -> 1678509.9 | M72: ='Project Overview'!$F$12/12 -> 0 | N72: ='Project Overview'!$F$13/12 -> 119251.3 | O72: 75000 | P72: =O72*($P$2-$N$2) -> 1678509.9 | Q72: ='Project Overview'!$F$12/12 -> 0 | R72: ='Project Overview'!$F$13/12 -> 119251.3 | S72: 75000 | T72: =S72*($T$2-$R$2) -> 1678509.9 | U72: ='Project Overview'!$E$12/12 -> 0 | V72: ='Project Overview'!$E$13/12 -> 103696.78 | W72: 75000 | X72: =W72*($X$2-$V$2) -> 1678509.9 | Y72: ='Project Overview'!$E$12/12 -> 0 | Z72: ='Project Overview'!$E$13/12 -> 103696.78 | AA72: 75000 | AB72: =AA72*($AB$2-$Z$2) -> 1678509.9 | AC72: =('Project Overview'!$D$12/12)*6 -> 750000 | AD72: =('Project Overview'!$D$13/12)*6 -> 541026.7 | AE72: =37500*6 -> 225000 | AF72: =AE72*($AF$2-$AD$2) -> 5035529.6
A73: 65 | B73: =E73+F73+I73+J73+M73+N73+Q73+R73+U73+V73+Y73+Z73+AC73+AD73 -> 2094888.8 | C73: =G73+K73+O73+S73+W73+AA73+AE73 -> 675000 | D73: =(H73+L73+P73+T73+X73+AB73+AF73)-B73 -> 13011700 | E73: ='Project Overview'!$G$4/12 -> 0 | F73: ='Project Overview'!$G$5/12 -> 238714.63 | G73: 75000 | H73: =G73*($H$2-$F$2) -> 1678509.9 | I73: ='Project Overview'!$G$12/12 -> 0 | J73: ='Project Overview'!$G$13/12 -> 119251.3 | K73: 75000 | L73: =K73*($L$2-$J$2) -> 1678509.9 | M73: ='Project Overview'!$F$12/12 -> 0 | N73: ='Project Overview'!$F$13/12 -> 119251.3 | O73: 75000 | P73: =O73*($P$2-$N$2) -> 1678509.9 | Q73: ='Project Overview'!$F$12/12 -> 0 | R73: ='Project Overview'!$F$13/12 -> 119251.3 | S73: 75000 | T73: =S73*($T$2-$R$2) -> 1678509.9 | U73: ='Project Overview'!$E$12/12 -> 0 | V73: ='Project Overview'!$E$13/12 -> 103696.78 | W73: 75000 | X73: =W73*($X$2-$V$2) -> 1678509.9 | Y73: ='Project Overview'!$E$12/12 -> 0 | Z73: ='Project Overview'!$E$13/12 -> 103696.78 | AA73: 75000 | AB73: =AA73*($AB$2-$Z$2) -> 1678509.9 | AC73: =('Project Overview'!$D$12/12)*6 -> 750000 | AD73: =('Project Overview'!$D$13/12)*6 -> 541026.7 | AE73: =37500*6 -> 225000 | AF73: =AE73*($AF$2-$AD$2) -> 5035529.6
A74: 66 | B74: =E74+F74+I74+J74+M74+N74+Q74+R74+U74+V74+Y74+Z74+AC74+AD74 -> 2094888.8 | C74: =G74+K74+O74+S74+W74+AA74+AE74 -> 675000 | D74: =(H74+L74+P74+T74+X74+AB74+AF74)-B74 -> 13011700 | E74: ='Project Overview'!$G$4/12 -> 0 | F74: ='Project Overview'!$G$5/12 -> 238714.63 | G74: 75000 | H74: =G74*($H$2-$F$2) -> 1678509.9 | I74: ='Project Overview'!$G$12/12 -> 0 | J74: ='Project Overview'!$G$13/12 -> 119251.3 | K74: 75000 | L74: =K74*($L$2-$J$2) -> 1678509.9 | M74: ='Project Overview'!$F$12/12 -> 0 | N74: ='Project Overview'!$F$13/12 -> 119251.3 | O74: 75000 | P74: =O74*($P$2-$N$2) -> 1678509.9 | Q74: ='Project Overview'!$F$12/12 -> 0 | R74: ='Project Overview'!$F$13/12 -> 119251.3 | S74: 75000 | T74: =S74*($T$2-$R$2) -> 1678509.9 | U74: ='Project Overview'!$E$12/12 -> 0 | V74: ='Project Overview'!$E$13/12 -> 103696.78 | W74: 75000 | X74: =W74*($X$2-$V$2) -> 1678509.9 | Y74: ='Project Overview'!$E$12/12 -> 0 | Z74: ='Project Overview'!$E$13/12 -> 103696.78 | AA74: 75000 | AB74: =AA74*($AB$2-$Z$2) -> 1678509.9 | AC74: =('Project Overview'!$D$12/12)*6 -> 750000 | AD74: =('Project Overview'!$D$13/12)*6 -> 541026.7 | AE74: =37500*6 -> 225000 | AF74: =AE74*($AF$2-$AD$2) -> 5035529.6
A75: 67 | B75: =E75+F75+I75+J75+M75+N75+Q75+R75+U75+V75+Y75+Z75+AC75+AD75 -> 2094888.8 | C75: =G75+K75+O75+S75+W75+AA75+AE75 -> 675000 | D75: =(H75+L75+P75+T75+X75+AB75+AF75)-B75 -> 13011700 | E75: ='Project Overview'!$G$4/12 -> 0 | F75: ='Project Overview'!$G$5/12 -> 238714.63 | G75: 75000 | H75: =G75*($H$2-$F$2) -> 1678509.9 | I75: ='Project Overview'!$G$12/12 -> 0 | J75: ='Project Overview'!$G$13/12 -> 119251.3 | K75: 75000 | L75: =K75*($L$2-$J$2) -> 1678509.9 | M75: ='Project Overview'!$F$12/12 -> 0 | N75: ='Project Overview'!$F$13/12 -> 119251.3 | O75: 75000 | P75: =O75*($P$2-$N$2) -> 1678509.9 | Q75: ='Project Overview'!$F$12/12 -> 0 | R75: ='Project Overview'!$F$13/12 -> 119251.3 | S75: 75000 | T75: =S75*($T$2-$R$2) -> 1678509.9 | U75: ='Project Overview'!$E$12/12 -> 0 | V75: ='Project Overview'!$E$13/12 -> 103696.78 | W75: 75000 | X75: =W75*($X$2-$V$2) -> 1678509.9 | Y75: ='Project Overview'!$E$12/12 -> 0 | Z75: ='Project Overview'!$E$13/12 -> 103696.78 | AA75: 75000 | AB75: =AA75*($AB$2-$Z$2) -> 1678509.9 | AC75: =('Project Overview'!$D$12/12)*6 -> 750000 | AD75: =('Project Overview'!$D$13/12)*6 -> 541026.7 | AE75: =37500*6 -> 225000 | AF75: =AE75*($AF$2-$AD$2) -> 5035529.6
A76: 68 | B76: =E76+F76+I76+J76+M76+N76+Q76+R76+U76+V76+Y76+Z76+AC76+AD76 -> 2094888.8 | C76: =G76+K76+O76+S76+W76+AA76+AE76 -> 675000 | D76: =(H76+L76+P76+T76+X76+AB76+AF76)-B76 -> 13011700 | E76: ='Project Overview'!$G$4/12 -> 0 | F76: ='Project Overview'!$G$5/12 -> 238714.63 | G76: 75000 | H76: =G76*($H$2-$F$2) -> 1678509.9 | I76: ='Project Overview'!$G$12/12 -> 0 | J76: ='Project Overview'!$G$13/12 -> 119251.3 | K76: 75000 | L76: =K76*($L$2-$J$2) -> 1678509.9 | M76: ='Project Overview'!$F$12/12 -> 0 | N76: ='Project Overview'!$F$13/12 -> 119251.3 | O76: 75000 | P76: =O76*($P$2-$N$2) -> 1678509.9 | Q76: ='Project Overview'!$F$12/12 -> 0 | R76: ='Project Overview'!$F$13/12 -> 119251.3 | S76: 75000 | T76: =S76*($T$2-$R$2) -> 1678509.9 | U76: ='Project Overview'!$E$12/12 -> 0 | V76: ='Project Overview'!$E$13/12 -> 103696.78 | W76: 75000 | X76: =W76*($X$2-$V$2) -> 1678509.9 | Y76: ='Project Overview'!$E$12/12 -> 0 | Z76: ='Project Overview'!$E$13/12 -> 103696.78 | AA76: 75000 | AB76: =AA76*($AB$2-$Z$2) -> 1678509.9 | AC76: =('Project Overview'!$D$12/12)*6 -> 750000 | AD76: =('Project Overview'!$D$13/12)*6 -> 541026.7 | AE76: =37500*6 -> 225000 | AF76: =AE76*($AF$2-$AD$2) -> 5035529.6
A77: 69 | B77: =E77+F77+I77+J77+M77+N77+Q77+R77+U77+V77+Y77+Z77+AC77+AD77 -> 2094888.8 | C77: =G77+K77+O77+S77+W77+AA77+AE77 -> 675000 | D77: =(H77+L77+P77+T77+X77+AB77+AF77)-B77 -> 13011700 | E77: ='Project Overview'!$G$4/12 -> 0 | F77: ='Project Overview'!$G$5/12 -> 238714.63 | G77: 75000 | H77: =G77*($H$2-$F$2) -> 1678509.9 | I77: ='Project Overview'!$G$12/12 -> 0 | J77: ='Project Overview'!$G$13/12 -> 119251.3 | K77: 75000 | L77: =K77*($L$2-$J$2) -> 1678509.9 | M77: ='Project Overview'!$F$12/12 -> 0 | N77: ='Project Overview'!$F$13/12 -> 119251.3 | O77: 75000 | P77: =O77*($P$2-$N$2) -> 1678509.9 | Q77: ='Project Overview'!$F$12/12 -> 0 | R77: ='Project Overview'!$F$13/12 -> 119251.3 | S77: 75000 | T77: =S77*($T$2-$R$2) -> 1678509.9 | U77: ='Project Overview'!$E$12/12 -> 0 | V77: ='Project Overview'!$E$13/12 -> 103696.78 | W77: 75000 | X77: =W77*($X$2-$V$2) -> 1678509.9 | Y77: ='Project Overview'!$E$12/12 -> 0 | Z77: ='Project Overview'!$E$13/12 -> 103696.78 | AA77: 75000 | AB77: =AA77*($AB$2-$Z$2) -> 1678509.9 | AC77: =('Project Overview'!$D$12/12)*6 -> 750000 | AD77: =('Project Overview'!$D$13/12)*6 -> 541026.7 | AE77: =37500*6 -> 225000 | AF77: =AE77*($AF$2-$AD$2) -> 5035529.6
A78: 70 | B78: =E78+F78+I78+J78+M78+N78+Q78+R78+U78+V78+Y78+Z78+AC78+AD78 -> 2094888.8 | C78: =G78+K78+O78+S78+W78+AA78+AE78 -> 675000 | D78: =(H78+L78+P78+T78+X78+AB78+AF78)-B78 -> 13011700 | E78: ='Project Overview'!$G$4/12 -> 0 | F78: ='Project Overview'!$G$5/12 -> 238714.63 | G78: 75000 | H78: =G78*($H$2-$F$2) -> 1678509.9 | I78: ='Project Overview'!$G$12/12 -> 0 | J78: ='Project Overview'!$G$13/12 -> 119251.3 | K78: 75000 | L78: =K78*($L$2-$J$2) -> 1678509.9 | M78: ='Project Overview'!$F$12/12 -> 0 | N78: ='Project Overview'!$F$13/12 -> 119251.3 | O78: 75000 | P78: =O78*($P$2-$N$2) -> 1678509.9 | Q78: ='Project Overview'!$F$12/12 -> 0 | R78: ='Project Overview'!$F$13/12 -> 119251.3 | S78: 75000 | T78: =S78*($T$2-$R$2) -> 1678509.9 | U78: ='Project Overview'!$E$12/12 -> 0 | V78: ='Project Overview'!$E$13/12 -> 103696.78 | W78: 75000 | X78: =W78*($X$2-$V$2) -> 1678509.9 | Y78: ='Project Overview'!$E$12/12 -> 0 | Z78: ='Project Overview'!$E$13/12 -> 103696.78 | AA78: 75000 | AB78: =AA78*($AB$2-$Z$2) -> 1678509.9 | AC78: =('Project Overview'!$D$12/12)*6 -> 750000 | AD78: =('Project Overview'!$D$13/12)*6 -> 541026.7 | AE78: =37500*6 -> 225000 | AF78: =AE78*($AF$2-$AD$2) -> 5035529.6
A79: 71 | B79: =E79+F79+I79+J79+M79+N79+Q79+R79+U79+V79+Y79+Z79+AC79+AD79 -> 2094888.8 | C79: =G79+K79+O79+S79+W79+AA79+AE79 -> 675000 | D79: =(H79+L79+P79+T79+X79+AB79+AF79)-B79 -> 13011700 | E79: ='Project Overview'!$G$4/12 -> 0 | F79: ='Project Overview'!$G$5/12 -> 238714.63 | G79: 75000 | H79: =G79*($H$2-$F$2) -> 1678509.9 | I79: ='Project Overview'!$G$12/12 -> 0 | J79: ='Project Overview'!$G$13/12 -> 119251.3 | K79: 75000 | L79: =K79*($L$2-$J$2) -> 1678509.9 | M79: ='Project Overview'!$F$12/12 -> 0 | N79: ='Project Overview'!$F$13/12 -> 119251.3 | O79: 75000 | P79: =O79*($P$2-$N$2) -> 1678509.9 | Q79: ='Project Overview'!$F$12/12 -> 0 | R79: ='Project Overview'!$F$13/12 -> 119251.3 | S79: 75000 | T79: =S79*($T$2-$R$2) -> 1678509.9 | U79: ='Project Overview'!$E$12/12 -> 0 | V79: ='Project Overview'!$E$13/12 -> 103696.78 | W79: 75000 | X79: =W79*($X$2-$V$2) -> 1678509.9 | Y79: ='Project Overview'!$E$12/12 -> 0 | Z79: ='Project Overview'!$E$13/12 -> 103696.78 | AA79: 75000 | AB79: =AA79*($AB$2-$Z$2) -> 1678509.9 | AC79: =('Project Overview'!$D$12/12)*6 -> 750000 | AD79: =('Project Overview'!$D$13/12)*6 -> 541026.7 | AE79: =37500*6 -> 225000 | AF79: =AE79*($AF$2-$AD$2) -> 5035529.6
A80: 72 | B80: =E80+F80+I80+J80+M80+N80+Q80+R80+U80+V80+Y80+Z80+AC80+AD80 -> 2094888.8 | C80: =G80+K80+O80+S80+W80+AA80+AE80 -> 675000 | D80: =(H80+L80+P80+T80+X80+AB80+AF80)-B80 -> 13011700 | E80: ='Project Overview'!$G$4/12 -> 0 | F80: ='Project Overview'!$G$5/12 -> 238714.63 | G80: 75000 | H80: =G80*($H$2-$F$2) -> 1678509.9 | I80: ='Project Overview'!$G$12/12 -> 0 | J80: ='Project Overview'!$G$13/12 -> 119251.3 | K80: 75000 | L80: =K80*($L$2-$J$2) -> 1678509.9 | M80: ='Project Overview'!$F$12/12 -> 0 | N80: ='Project Overview'!$F$13/12 -> 119251.3 | O80: 75000 | P80: =O80*($P$2-$N$2) -> 1678509.9 | Q80: ='Project Overview'!$F$12/12 -> 0 | R80: ='Project Overview'!$F$13/12 -> 119251.3 | S80: 75000 | T80: =S80*($T$2-$R$2) -> 1678509.9 | U80: ='Project Overview'!$E$12/12 -> 0 | V80: ='Project Overview'!$E$13/12 -> 103696.78 | W80: 75000 | X80: =W80*($X$2-$V$2) -> 1678509.9 | Y80: ='Project Overview'!$E$12/12 -> 0 | Z80: ='Project Overview'!$E$13/12 -> 103696.78 | AA80: 75000 | AB80: =AA80*($AB$2-$Z$2) -> 1678509.9 | AC80: =('Project Overview'!$D$12/12)*6 -> 750000 | AD80: =('Project Overview'!$D$13/12)*6 -> 541026.7 | AE80: =37500*6 -> 225000 | AF80: =AE80*($AF$2-$AD$2) -> 5035529.6
A81: Total | B81: =SUM(B69:B80) -> 25138666 | C81: =SUM(C69:C80) -> 8100000 | D81: =SUM(D69:D80) -> 1.561404e+08 | E81: =SUM(E69:E80) -> 0 | F81: =SUM(F69:F80) -> 2864575.5 | G81: =SUM(G69:G80) -> 900000 | H81: =SUM(H69:H80) -> 20142118 | I81: =SUM(I69:I80) -> 0 | ... AF81: =SUM(AF69:AF80) -> 60426355
A82: 73 | B82: =E82+F82+I82+J82+M82+N82+Q82+R82+U82+V82+Y82+Z82+AC82+AD82 -> 1457151.8 | C82: =G82+K82+O82+S82+W82+AA82+AE82 -> 900000 | D82: =(H82+L82+P82+T82+X82+AB82+AF82)-B82 -> 18684967 | E82: ='Project Overview'!$G$4/12 -> 0 | F82: ='Project Overview'!$G$5/12 -> 238714.63 | G82: 75000 | H82: =G82*($H$2-$F$2) -> 1678509.9 | I82: ='Project Overview'!$G$12/12 -> 0 | J82: ='Project Overview'!$G$13/12 -> 119251.3 | K82: 75000 | L82: =K82*($L$2-$J$2) -> 1678509.9 | M82: ='Project Overview'!$G$12/12 -> 0 | N82: ='Project Overview'!$G$13/12 -> 119251.3 | O82: 75000 | P82: =O82*($P$2-$N$2) -> 1678509.9 | Q82: ='Project Overview'!$G$12/12 -> 0 | R82: ='Project Overview'!$G$13/12 -> 119251.3 | S82: 75000 | T82: =S82*($T$2-$R$2) -> 1678509.9 | U82: ='Project Overview'!$G$12/12 -> 0 | V82: ='Project Overview'!$G$13/12 -> 119251.3 | W82: 75000 | X82: =W82*($X$2-$V$2) -> 1678509.9 | Y82: ='Project Overview'!$G$12/12 -> 0 | Z82: ='Project Overview'!$G$13/12 -> 119251.3 | AA82: 75000 | AB82: =AA82*($AB$2-$Z$2) -> 1678509.9 | AC82: =('Project Overview'!$E$12/12)*6 -> 0 | AD82: =('Project Overview'!$E$13/12)*6 -> 622180.7 | AE82: =75000*6 -> 450000 | AF82: =AE82*($AF$2-$AD$2) -> 10071059
A83: 74 | B83: =E83+F83+I83+J83+M83+N83+Q83+R83+U83+V83+Y83+Z83+AC83+AD83 -> 1457151.8 | C83: =G83+K83+O83+S83+W83+AA83+AE83 -> 900000 | D83: =(H83+L83+P83+T83+X83+AB83+AF83)-B83 -> 18684967 | E83: ='Project Overview'!$G$4/12 -> 0 | F83: ='Project Overview'!$G$5/12 -> 238714.63 | G83: 75000 | H83: =G83*($H$2-$F$2) -> 1678509.9 | I83: ='Project Overview'!$G$12/12 -> 0 | J83: ='Project Overview'!$G$13/12 -> 119251.3 | K83: 75000 | L83: =K83*($L$2-$J$2) -> 1678509.9 | M83: ='Project Overview'!$G$12/12 -> 0 | N83: ='Project Overview'!$G$13/12 -> 119251.3 | O83: 75000 | P83: =O83*($P$2-$N$2) -> 1678509.9 | Q83: ='Project Overview'!$G$12/12 -> 0 | R83: ='Project Overview'!$G$13/12 -> 119251.3 | S83: 75000 | T83: =S83*($T$2-$R$2) -> 1678509.9 | U83: ='Project Overview'!$G$12/12 -> 0 | V83: ='Project Overview'!$G$13/12 -> 119251.3 | W83: 75000 | X83: =W83*($X$2-$V$2) -> 1678509.9 | Y83: ='Project Overview'!$G$12/12 -> 0 | Z83: ='Project Overview'!$G$13/12 -> 119251.3 | AA83: 75000 | AB83: =AA83*($AB$2-$Z$2) -> 1678509.9 | AC83: =('Project Overview'!$E$12/12)*6 -> 0 | AD83: =('Project Overview'!$E$13/12)*6 -> 622180.7 | AE83: =75000*6 -> 450000 | AF83: =AE83*($AF$2-$AD$2) -> 10071059
A84: 75 | B84: =E84+F84+I84+J84+M84+N84+Q84+R84+U84+V84+Y84+Z84+AC84+AD84 -> 1457151.8 | C84: =G84+K84+O84+S84+W84+AA84+AE84 -> 900000 | D84: =(H84+L84+P84+T84+X84+AB84+AF84)-B84 -> 18684967 | E84: ='Project Overview'!$G$4/12 -> 0 | F84: ='Project Overview'!$G$5/12 -> 238714.63 | G84: 75000 | H84: =G84*($H$2-$F$2) -> 1678509.9 | I84: ='Project Overview'!$G$12/12 -> 0 | J84: ='Project Overview'!$G$13/12 -> 119251.3 | K84: 75000 | L84: =K84*($L$2-$J$2) -> 1678509.9 | M84: ='Project Overview'!$G$12/12 -> 0 | N84: ='Project Overview'!$G$13/12 -> 119251.3 | O84: 75000 | P84: =O84*($P$2-$N$2) -> 1678509.9 | Q84: ='Project Overview'!$G$12/12 -> 0 | R84: ='Project Overview'!$G$13/12 -> 119251.3 | S84: 75000 | T84: =S84*($T$2-$R$2) -> 1678509.9 | U84: ='Project Overview'!$G$12/12 -> 0 | V84: ='Project Overview'!$G$13/12 -> 119251.3 | W84: 75000 | X84: =W84*($X$2-$V$2) -> 1678509.9 | Y84: ='Project Overview'!$G$12/12 -> 0 | Z84: ='Project Overview'!$G$13/12 -> 119251.3 | AA84: 75000 | AB84: =AA84*($AB$2-$Z$2) -> 1678509.9 | AC84: =('Project Overview'!$E$12/12)*6 -> 0 | AD84: =('Project Overview'!$E$13/12)*6 -> 622180.7 | AE84: =75000*6 -> 450000 | AF84: =AE84*($AF$2-$AD$2) -> 10071059
A85: 76 | B85: =E85+F85+I85+J85+M85+N85+Q85+R85+U85+V85+Y85+Z85+AC85+AD85 -> 1457151.8 | C85: =G85+K85+O85+S85+W85+AA85+AE85 -> 900000 | D85: =(H85+L85+P85+T85+X85+AB85+AF85)-B85 -> 18684967 | E85: ='Project Overview'!$G$4/12 -> 0 | F85: ='Project Overview'!$G$5/12 -> 238714.63 | G85: 75000 | H85: =G85*($H$2-$F$2) -> 1678509.9 | I85: ='Project Overview'!$G$12/12 -> 0 | J85: ='Project Overview'!$G$13/12 -> 119251.3 | K85: 75000 | L85: =K85*($L$2-$J$2) -> 1678509.9 | M85: ='Project Overview'!$G$12/12 -> 0 | N85: ='Project Overview'!$G$13/12 -> 119251.3 | O85: 75000 | P85: =O85*($P$2-$N$2) -> 1678509.9 | Q85: ='Project Overview'!$G$12/12 -> 0 | R85: ='Project Overview'!$G$13/12 -> 119251.3 | S85: 75000 | T85: =S85*($T$2-$R$2) -> 1678509.9 | U85: ='Project Overview'!$G$12/12 -> 0 | V85: ='Project Overview'!$G$13/12 -> 119251.3 | W85: 75000 | X85: =W85*($X$2-$V$2) -> 1678509.9 | Y85: ='Project Overview'!$G$12/12 -> 0 | Z85: ='Project Overview'!$G$13/12 -> 119251.3 | AA85: 75000 | AB85: =AA85*($AB$2-$Z$2) -> 1678509.9 | AC85: =('Project Overview'!$E$12/12)*6 -> 0 | AD85: =('Project Overview'!$E$13/12)*6 -> 622180.7 | AE85: =75000*6 -> 450000 | AF85: =AE85*($AF$2-$AD$2) -> 10071059
A86: 77 | B86: =E86+F86+I86+J86+M86+N86+Q86+R86+U86+V86+Y86+Z86+AC86+AD86 -> 1457151.8 | C86: =G86+K86+O86+S86+W86+AA86+AE86 -> 900000 | D86: =(H86+L86+P86+T86+X86+AB86+AF86)-B86 -> 18684967 | E86: ='Project Overview'!$G$4/12 -> 0 | F86: ='Project Overview'!$G$5/12 -> 238714.63 | G86: 75000 | H86: =G86*($H$2-$F$2) -> 1678509.9 | I86: ='Project Overview'!$G$12/12 -> 0 | J86: ='Project Overview'!$G$13/12 -> 119251.3 | K86: 75000 | L86: =K86*($L$2-$J$2) -> 1678509.9 | M86: ='Project Overview'!$G$12/12 -> 0 | N86: ='Project Overview'!$G$13/12 -> 119251.3 | O86: 75000 | P86: =O86*($P$2-$N$2) -> 1678509.9 | Q86: ='Project Overview'!$G$12/12 -> 0 | R86: ='Project Overview'!$G$13/12 -> 119251.3 | S86: 75000 | T86: =S86*($T$2-$R$2) -> 1678509.9 | U86: ='Project Overview'!$G$12/12 -> 0 | V86: ='Project Overview'!$G$13/12 -> 119251.3 | W86: 75000 | X86: =W86*($X$2-$V$2) -> 1678509.9 | Y86: ='Project Overview'!$G$12/12 -> 0 | Z86: ='Project Overview'!$G$13/12 -> 119251.3 | AA86: 75000 | AB86: =AA86*($AB$2-$Z$2) -> 1678509.9 | AC86: =('Project Overview'!$E$12/12)*6 -> 0 | AD86: =('Project Overview'!$E$13/12)*6 -> 622180.7 | AE86: =75000*6 -> 450000 | AF86: =AE86*($AF$2-$AD$2) -> 10071059
A87: 78 | B87: =E87+F87+I87+J87+M87+N87+Q87+R87+U87+V87+Y87+Z87+AC87+AD87 -> 1457151.8 | C87: =G87+K87+O87+S87+W87+AA87+AE87 -> 900000 | D87: =(H87+L87+P87+T87+X87+AB87+AF87)-B87 -> 18684967 | E87: ='Project Overview'!$G$4/12 -> 0 | F87: ='Project Overview'!$G$5/12 -> 238714.63 | G87: 75000 | H87: =G87*($H$2-$F$2) -> 1678509.9 | I87: ='Project Overview'!$G$12/12 -> 0 | J87: ='Project Overview'!$G$13/12 -> 119251.3 | K87: 75000 | L87: =K87*($L$2-$J$2) -> 1678509.9 | M87: ='Project Overview'!$G$12/12 -> 0 | N87: ='Project Overview'!$G$13/12 -> 119251.3 | O87: 75000 | P87: =O87*($P$2-$N$2) -> 1678509.9 | Q87: ='Project Overview'!$G$12/12 -> 0 | R87: ='Project Overview'!$G$13/12 -> 119251.3 | S87: 75000 | T87: =S87*($T$2-$R$2) -> 1678509.9 | U87: ='Project Overview'!$G$12/12 -> 0 | V87: ='Project Overview'!$G$13/12 -> 119251.3 | W87: 75000 | X87: =W87*($X$2-$V$2) -> 1678509.9 | Y87: ='Project Overview'!$G$12/12 -> 0 | Z87: ='Project Overview'!$G$13/12 -> 119251.3 | AA87: 75000 | AB87: =AA87*($AB$2-$Z$2) -> 1678509.9 | AC87: =('Project Overview'!$E$12/12)*6 -> 0 | AD87: =('Project Overview'!$E$13/12)*6 -> 622180.7 | AE87: =75000*6 -> 450000 | AF87: =AE87*($AF$2-$AD$2) -> 10071059
A88: 79 | B88: =E88+F88+I88+J88+M88+N88+Q88+R88+U88+V88+Y88+Z88+AC88+AD88 -> 1457151.8 | C88: =G88+K88+O88+S88+W88+AA88+AE88 -> 900000 | D88: =(H88+L88+P88+T88+X88+AB88+AF88)-B88 -> 18684967 | E88: ='Project Overview'!$G$4/12 -> 0 | F88: ='Project Overview'!$G$5/12 -> 238714.63 | G88: 75000 | H88: =G88*($H$2-$F$2) -> 1678509.9 | I88: ='Project Overview'!$G$12/12 -> 0 | J88: ='Project Overview'!$G$13/12 -> 119251.3 | K88: 75000 | L88: =K88*($L$2-$J$2) -> 1678509.9 | M88: ='Project Overview'!$G$12/12 -> 0 | N88: ='Project Overview'!$G$13/12 -> 119251.3 | O88: 75000 | P88: =O88*($P$2-$N$2) -> 1678509.9 | Q88: ='Project Overview'!$G$12/12 -> 0 | R88: ='Project Overview'!$G$13/12 -> 119251.3 | S88: 75000 | T88: =S88*($T$2-$R$2) -> 1678509.9 | U88: ='Project Overview'!$G$12/12 -> 0 | V88: ='Project Overview'!$G$13/12 -> 119251.3 | W88: 75000 | X88: =W88*($X$2-$V$2) -> 1678509.9 | Y88: ='Project Overview'!$G$12/12 -> 0 | Z88: ='Project Overview'!$G$13/12 -> 119251.3 | AA88: 75000 | AB88: =AA88*($AB$2-$Z$2) -> 1678509.9 | AC88: =('Project Overview'!$E$12/12)*6 -> 0 | AD88: =('Project Overview'!$E$13/12)*6 -> 622180.7 | AE88: =75000*6 -> 450000 | AF88: =AE88*($AF$2-$AD$2) -> 10071059
A89: 80 | B89: =E89+F89+I89+J89+M89+N89+Q89+R89+U89+V89+Y89+Z89+AC89+AD89 -> 1457151.8 | C89: =G89+K89+O89+S89+W89+AA89+AE89 -> 900000 | D89: =(H89+L89+P89+T89+X89+AB89+AF89)-B89 -> 18684967 | E89: ='Project Overview'!$G$4/12 -> 0 | F89: ='Project Overview'!$G$5/12 -> 238714.63 | G89: 75000 | H89: =G89*($H$2-$F$2) -> 1678509.9 | I89: ='Project Overview'!$G$12/12 -> 0 | J89: ='Project Overview'!$G$13/12 -> 119251.3 | K89: 75000 | L89: =K89*($L$2-$J$2) -> 1678509.9 | M89: ='Project Overview'!$G$12/12 -> 0 | N89: ='Project Overview'!$G$13/12 -> 119251.3 | O89: 75000 | P89: =O89*($P$2-$N$2) -> 1678509.9 | Q89: ='Project Overview'!$G$12/12 -> 0 | R89: ='Project Overview'!$G$13/12 -> 119251.3 | S89: 75000 | T89: =S89*($T$2-$R$2) -> 1678509.9 | U89: ='Project Overview'!$G$12/12 -> 0 | V89: ='Project Overview'!$G$13/12 -> 119251.3 | W89: 75000 | X89: =W89*($X$2-$V$2) -> 1678509.9 | Y89: ='Project Overview'!$G$12/12 -> 0 | Z89: ='Project Overview'!$G$13/12 -> 119251.3 | AA89: 75000 | AB89: =AA89*($AB$2-$Z$2) -> 1678509.9 | AC89: =('Project Overview'!$E$12/12)*6 -> 0 | AD89: =('Project Overview'!$E$13/12)*6 -> 622180.7 | AE89: =75000*6 -> 450000 | AF89: =AE89*($AF$2-$AD$2) -> 10071059
A90: 81 | B90: =E90+F90+I90+J90+M90+N90+Q90+R90+U90+V90+Y90+Z90+AC90+AD90 -> 1457151.8 | C90: =G90+K90+O90+S90+W90+AA90+AE90 -> 900000 | D90: =(H90+L90+P90+T90+X90+AB90+AF90)-B90 -> 18684967 | E90: ='Project Overview'!$G$4/12 -> 0 | F90: ='Project Overview'!$G$5/12 -> 238714.63 | G90: 75000 | H90: =G90*($H$2-$F$2) -> 1678509.9 | I90: ='Project Overview'!$G$12/12 -> 0 | J90: ='Project Overview'!$G$13/12 -> 119251.3 | K90: 75000 | L90: =K90*($L$2-$J$2) -> 1678509.9 | M90: ='Project Overview'!$G$12/12 -> 0 | N90: ='Project Overview'!$G$13/12 -> 119251.3 | O90: 75000 | P90: =O90*($P$2-$N$2) -> 1678509.9 | Q90: ='Project Overview'!$G$12/12 -> 0 | R90: ='Project Overview'!$G$13/12 -> 119251.3 | S90: 75000 | T90: =S90*($T$2-$R$2) -> 1678509.9 | U90: ='Project Overview'!$G$12/12 -> 0 | V90: ='Project Overview'!$G$13/12 -> 119251.3 | W90: 75000 | X90: =W90*($X$2-$V$2) -> 1678509.9 | Y90: ='Project Overview'!$G$12/12 -> 0 | Z90: ='Project Overview'!$G$13/12 -> 119251.3 | AA90: 75000 | AB90: =AA90*($AB$2-$Z$2) -> 1678509.9 | AC90: =('Project Overview'!$E$12/12)*6 -> 0 | AD90: =('Project Overview'!$E$13/12)*6 -> 622180.7 | AE90: =75000*6 -> 450000 | AF90: =AE90*($AF$2-$AD$2) -> 10071059
A91: 82 | B91: =E91+F91+I91+J91+M91+N91+Q91+R91+U91+V91+Y91+Z91+AC91+AD91 -> 1457151.8 | C91: =G91+K91+O91+S91+W91+AA91+AE91 -> 900000 | D91: =(H91+L91+P91+T91+X91+AB91+AF91)-B91 -> 18684967 | E91: ='Project Overview'!$G$4/12 -> 0 | F91: ='Project Overview'!$G$5/12 -> 238714.63 | G91: 75000 | H91: =G91*($H$2-$F$2) -> 1678509.9 | I91: ='Project Overview'!$G$12/12 -> 0 | J91: ='Project Overview'!$G$13/12 -> 119251.3 | K91: 75000 | L91: =K91*($L$2-$J$2) -> 1678509.9 | M91: ='Project Overview'!$G$12/12 -> 0 | N91: ='Project Overview'!$G$13/12 -> 119251.3 | O91: 75000 | P91: =O91*($P$2-$N$2) -> 1678509.9 | Q91: ='Project Overview'!$G$12/12 -> 0 | R91: ='Project Overview'!$G$13/12 -> 119251.3 | S91: 75000 | T91: =S91*($T$2-$R$2) -> 1678509.9 | U91: ='Project Overview'!$G$12/12 -> 0 | V91: ='Project Overview'!$G$13/12 -> 119251.3 | W91: 75000 | X91: =W91*($X$2-$V$2) -> 1678509.9 | Y91: ='Project Overview'!$G$12/12 -> 0 | Z91: ='Project Overview'!$G$13/12 -> 119251.3 | AA91: 75000 | AB91: =AA91*($AB$2-$Z$2) -> 1678509.9 | AC91: =('Project Overview'!$E$12/12)*6 -> 0 | AD91: =('Project Overview'!$E$13/12)*6 -> 622180.7 | AE91: =75000*6 -> 450000 | AF91: =AE91*($AF$2-$AD$2) -> 10071059
A92: 83 | B92: =E92+F92+I92+J92+M92+N92+Q92+R92+U92+V92+Y92+Z92+AC92+AD92 -> 1457151.8 | C92: =G92+K92+O92+S92+W92+AA92+AE92 -> 900000 | D92: =(H92+L92+P92+T92+X92+AB92+AF92)-B92 -> 18684967 | E92: ='Project Overview'!$G$4/12 -> 0 | F92: ='Project Overview'!$G$5/12 -> 238714.63 | G92: 75000 | H92: =G92*($H$2-$F$2) -> 1678509.9 | I92: ='Project Overview'!$G$12/12 -> 0 | J92: ='Project Overview'!$G$13/12 -> 119251.3 | K92: 75000 | L92: =K92*($L$2-$J$2) -> 1678509.9 | M92: ='Project Overview'!$G$12/12 -> 0 | N92: ='Project Overview'!$G$13/12 -> 119251.3 | O92: 75000 | P92: =O92*($P$2-$N$2) -> 1678509.9 | Q92: ='Project Overview'!$G$12/12 -> 0 | R92: ='Project Overview'!$G$13/12 -> 119251.3 | S92: 75000 | T92: =S92*($T$2-$R$2) -> 1678509.9 | U92: ='Project Overview'!$G$12/12 -> 0 | V92: ='Project Overview'!$G$13/12 -> 119251.3 | W92: 75000 | X92: =W92*($X$2-$V$2) -> 1678509.9 | Y92: ='Project Overview'!$G$12/12 -> 0 | Z92: ='Project Overview'!$G$13/12 -> 119251.3 | AA92: 75000 | AB92: =AA92*($AB$2-$Z$2) -> 1678509.9 | AC92: =('Project Overview'!$E$12/12)*6 -> 0 | AD92: =('Project Overview'!$E$13/12)*6 -> 622180.7 | AE92: =75000*6 -> 450000 | AF92: =AE92*($AF$2-$AD$2) -> 10071059
A93: 84 | B93: =E93+F93+I93+J93+M93+N93+Q93+R93+U93+V93+Y93+Z93+AC93+AD93 -> 1457151.8 | C93: =G93+K93+O93+S93+W93+AA93+AE93 -> 900000 | D93: =(H93+L93+P93+T93+X93+AB93+AF93)-B93 -> 18684967 | E93: ='Project Overview'!$G$4/12 -> 0 | F93: ='Project Overview'!$G$5/12 -> 238714.63 | G93: 75000 | H93: =G93*($H$2-$F$2) -> 1678509.9 | I93: ='Project Overview'!$G$12/12 -> 0 | J93: ='Project Overview'!$G$13/12 -> 119251.3 | K93: 75000 | L93: =K93*($L$2-$J$2) -> 1678509.9 | M93: ='Project Overview'!$G$12/12 -> 0 | N93: ='Project Overview'!$G$13/12 -> 119251.3 | O93: 75000 | P93: =O93*($P$2-$N$2) -> 1678509.9 | Q93: ='Project Overview'!$G$12/12 -> 0 | R93: ='Project Overview'!$G$13/12 -> 119251.3 | S93: 75000 | T93: =S93*($T$2-$R$2) -> 1678509.9 | U93: ='Project Overview'!$G$12/12 -> 0 | V93: ='Project Overview'!$G$13/12 -> 119251.3 | W93: 75000 | X93: =W93*($X$2-$V$2) -> 1678509.9 | Y93: ='Project Overview'!$G$12/12 -> 0 | Z93: ='Project Overview'!$G$13/12 -> 119251.3 | AA93: 75000 | AB93: =AA93*($AB$2-$Z$2) -> 1678509.9 | AC93: =('Project Overview'!$E$12/12)*6 -> 0 | AD93: =('Project Overview'!$E$13/12)*6 -> 622180.7 | AE93: =75000*6 -> 450000 | AF93: =AE93*($AF$2-$AD$2) -> 10071059
A94: Total | B94: =SUM(B82:B93) -> 17485822 | C94: =SUM(C82:C93) -> 10800000 | D94: =SUM(D82:D93) -> 2.242196e+08 | E94: =SUM(E82:E93) -> 0 | F94: =SUM(F82:F93) -> 2864575.5 | G94: =SUM(G82:G93) -> 900000 | H94: =SUM(H82:H93) -> 20142118 | I94: =SUM(I82:I93) -> 0 | ... AF94: =SUM(AF82:AF93) -> 1.2085271e+08
H97: =(F94+G94)/H94 -> 0.18690068

Sheet Financials
B1: Year Counter | E1: 1 | F1: 1 | G1: 1 | H1: 1 | I1: 1 | J1: 1 | K1: 1 | L1: 1 | M1: 1 | N1: 1 | O1: 1 | P1: 1 | Q1: 2 | R1: 2 | S1: 2 | T1: 2 | U1: 2 | V1: 2 | W1: 2 | X1: 2 | Y1: 2 | Z1: 2 | AA1: 2 | AB1: 2 | AC1: 3 | AD1: 3 | AE1: 3 | AF1: 3 | AG1: 3 | AH1: 3 | AI1: 3 | AJ1: 3 | AK1: 3 | AL1: 3 | AM1: 3 | AN1: 3 | AO1: 4 | AP1: 4 | AQ1: 4 | AR1: 4 | AS1: 4 | AT1: 4 | AU1: 4 | AV1: 4 | AW1: 4 | AX1: 4 | AY1: 4 | AZ1: 4 | BA1: 5 | BB1: 5 | BC1: 5 | BD1: 5 | BE1: 5 | BF1: 5 | BG1: 5 | BH1: 5 | BI1: 5 | BJ1: 5 | BK1: 5 | BL1: 5 | BM1: 6 | BN1: 6 | BO1: 6 | BP1: 6 | BQ1: 6 | BR1: 6 | BS1: 6 | BT1: 6 | BU1: 6 | BV1: 6 | BW1: 6 | BX1: 6 | BY1: 7 | BZ1: 7 | CA1: 7 | CB1: 7 | CC1: 7 | CD1: 7 | CE1: 7 | CF1: 7 | CG1: 7 | CH1: 7 | CI1: 7 | CJ1: 7
B2: Year | E2: =2024+E1 -> 2025 | F2: =2024+F1 -> 2025 | G2: =2024+G1 -> 2025 | H2: =2024+H1 -> 2025 | I2: =2024+I1 -> 2025 | J2: =2024+J1 -> 2025 | K2: =2024+K1 -> 2025 | L2: =2024+L1 -> 2025 | ... CJ2: =2024+CJ1 -> 2031
B3: Month Counter | E3: 1 | F3: 2 | G3: 3 | H3: 4 | I3: 5 | J3: 6 | K3: 7 | L3: 8 | M3: 9 | N3: 10 | O3: 11 | P3: 12 | Q3: 13 | R3: 14 | S3: 15 | T3: 16 | U3: 17 | V3: 18 | W3: 19 | X3: 20 | Y3: 21 | Z3: 22 | AA3: 23 | AB3: 24 | AC3: 25 | AD3: 26 | AE3: 27 | AF3: 28 | AG3: 29 | AH3: 30 | AI3: 31 | AJ3: 32 | AK3: 33 | AL3: 34 | AM3: 35 | AN3: 36 | AO3: 37 | AP3: 38 | AQ3: 39 | AR3: 40 | AS3: 41 | AT3: 42 | AU3: 43 | AV3: 44 | AW3: 45 | AX3: 46 | AY3: 47 | AZ3: 48 | BA3: 49 | BB3: 50 | BC3: 51 | BD3: 52 | BE3: 53 | BF3: 54 | BG3: 55 | BH3: 56 | BI3: 57 | BJ3: 58 | BK3: 59 | BL3: 60 | BM3: 61 | BN3: 62 | BO3: 63 | BP3: 64 | BQ3: 65 | BR3: 66 | BS3: 67 | BT3: 68 | BU3: 69 | BV3: 70 | BW3: 71 | BX3: 72 | BY3: 73 | BZ3: 74 | CA3: 75 | CB3: 76 | CC3: 77 | CD3: 78 | CE3: 79 | CF3: 80 | CG3: 81 | CH3: 82 | CI3: 83 | CJ3: 84
B4: Date | E4: 45839 | F4: 45870 | G4: 45901 | H4: 45931 | I4: 45962 | J4: 45992 | K4: 46023 | L4: 46054 | M4: 46082 | N4: 46113 | O4: 46143 | P4: 46174 | Q4: 46204 | R4: 8/1/0202 | S4: 46266 | T4: 46204 | U4: 8/1/0202 | V4: 46266 | W4: 46204 | X4: 8/1/0202 | Y4: 46266 | Z4: 46204 | AA4: 8/1/0202 | AB4: 46266 | AC4: 46569 | AD4: 46600 | AE4: 46631 | AF4: 46661 | AG4: 46692 | AH4: 46722 | AI4: 46753 | AJ4: 46784 | AK4: 46813 | AL4: 46844 | AM4: 46874 | AN4: 46905 | AO4: 46935 | AP4: 46966 | AQ4: 46997 | AR4: 47027 | AS4: 47058 | AT4: 47088 | AU4: 47119 | AV4: 47150 | AW4: 47178 | AX4: 47209 | AY4: 47239 | AZ4: 47270 | BA4: 47300 | BB4: 47331 | BC4: 47362 | BD4: 47392 | BE4: 47423 | BF4: 47453 | BG4: 47484 | BH4: 47515 | BI4: 47543 | BJ4: 47574 | BK4: 47604 | BL4: 47635 | BM4: 47665 | BN4: 47696 | BO4: 47727 | BP4: 47757 | BQ4: 47788 | BR4: 47818 | BS4: 47849 | BT4: 47880 | BU4: 47908 | BV4: 47939 | BW4: 47969 | BX4: 48000 | BY4: 48030 | BZ4: 48061 | CA4: 48092 | CB4: 48122 | CC4: 48153 | CD4: 48183 | CE4: 48214 | CF4: 48245 | CG4: 48274 | CH4: 48305 | CI4: 48335 | CJ4: 48366
B6: Income Statement
B8: Revenue | E8: =SUM(E9:E15) -> 0 | F8: =SUM(F9:F15) -> 0 | G8: =SUM(G9:G15) -> 0 | H8: =SUM(H9:H15) -> 0 | I8: =SUM(I9:I15) -> 0 | J8: =SUM(J9:J15) -> 0 | K8: =SUM(K9:K15) -> 0 | L8: =SUM(L9:L15) -> 0 | ... CJ8: =SUM(CJ9:CJ15) -> 22500000
B9: GH2x - OKC | E9: ='Model Assumptions'!G15 -> 0 | F9: ='Model Assumptions'!H15 -> 0 | G9: ='Model Assumptions'!I15 -> 0 | H9: ='Model Assumptions'!J15 -> 0 | I9: ='Model Assumptions'!K15 -> 0 | J9: ='Model Assumptions'!L15 -> 0 | K9: ='Model Assumptions'!M15 -> 0 | L9: ='Model Assumptions'!N15 -> 0 | ... CJ9: ='Model Assumptions'!CL15 -> 1875000
B10: GH2x2 - Tulsa | E10: ='Model Assumptions'!G23 -> 0 | F10: ='Model Assumptions'!H23 -> 0 | G10: ='Model Assumptions'!I23 -> 0 | H10: ='Model Assumptions'!J23 -> 0 | I10: ='Model Assumptions'!K23 -> 0 | J10: ='Model Assumptions'!L23 -> 0 | K10: ='Model Assumptions'!M23 -> 0 | L10: ='Model Assumptions'!N23 -> 0 | ... CJ10: ='Model Assumptions'!CL23 -> 1875000
B11: GH2x3 - Seattle | E11: ='Model Assumptions'!G31 -> 0 | F11: ='Model Assumptions'!H31 -> 0 | G11: ='Model Assumptions'!I31 -> 0 | H11: ='Model Assumptions'!J31 -> 0 | I11: ='Model Assumptions'!K31 -> 0 | J11: ='Model Assumptions'!L31 -> 0 | K11: ='Model Assumptions'!M31 -> 0 | L11: ='Model Assumptions'!N31 -> 0 | ... CJ11: ='Model Assumptions'!CL31 -> 1875000
B12: GH2x4 - Spokane | E12: ='Model Assumptions'!G39 -> 0 | F12: ='Model Assumptions'!H39 -> 0 | G12: ='Model Assumptions'!I39 -> 0 | H12: ='Model Assumptions'!J39 -> 0 | I12: ='Model Assumptions'!K39 -> 0 | J12: ='Model Assumptions'!L39 -> 0 | K12: ='Model Assumptions'!M39 -> 0 | L12: ='Model Assumptions'!N39 -> 0 | ... CJ12: ='Model Assumptions'!CL39 -> 1875000
B13: GH2x5 - Albuquerque | E13: ='Model Assumptions'!G47 -> 0 | F13: ='Model Assumptions'!H47 -> 0 | G13: ='Model Assumptions'!I47 -> 0 | H13: ='Model Assumptions'!J47 -> 0 | I13: ='Model Assumptions'!K47 -> 0 | J13: ='Model Assumptions'!L47 -> 0 | K13: ='Model Assumptions'!M47 -> 0 | L13: ='Model Assumptions'!N47 -> 0 | ... CJ13: ='Model Assumptions'!CL47 -> 1875000
B14: GH2x6 - Des Moines | E14: ='Model Assumptions'!G55 -> 0 | F14: ='Model Assumptions'!H55 -> 0 | G14: ='Model Assumptions'!I55 -> 0 | H14: ='Model Assumptions'!J55 -> 0 | I14: ='Model Assumptions'!K55 -> 0 | J14: ='Model Assumptions'!L55 -> 0 | K14: ='Model Assumptions'!M55 -> 0 | L14: ='Model Assumptions'!N55 -> 0 | ... CJ14: ='Model Assumptions'!CL55 -> 1875000
B15: GH2x7-12 | E15: ='Model Assumptions'!G63 -> 0 | F15: ='Model Assumptions'!H63 -> 0 | G15: ='Model Assumptions'!I63 -> 0 | H15: ='Model Assumptions'!J63 -> 0 | I15: ='Model Assumptions'!K63 -> 0 | J15: ='Model Assumptions'!L63 -> 0 | K15: ='Model Assumptions'!M63 -> 0 | L15: ='Model Assumptions'!N63 -> 0 | ... CJ15: ='Model Assumptions'!CL63 -> 11250000
B17: COGS | E17: ='Model Assumptions'!G32+'Model Assumptions'!G40+'Model Assumptions'!G48+'Model Assumptions'!G56+'Model Assumptions'!G64 -> 0 | F17: ='Model Assumptions'!H32+'Model Assumptions'!H40+'Model Assumptions'!H48+'Model Assumptions'!H56+'Model Assumptions'!H64 -> 0 | G17: ='Model Assumptions'!I32+'Model Assumptions'!I40+'Model Assumptions'!I48+'Model Assumptions'!I56+'Model Assumptions'!I64 -> 0 | H17: ='Model Assumptions'!J32+'Model Assumptions'!J40+'Model Assumptions'!J48+'Model Assumptions'!J56+'Model Assumptions'!J64 -> 0 | I17: ='Model Assumptions'!K32+'Model Assumptions'!K40+'Model Assumptions'!K48+'Model Assumptions'!K56+'Model Assumptions'!K64 -> 0 | J17: ='Model Assumptions'!L32+'Model Assumptions'!L40+'Model Assumptions'!L48+'Model Assumptions'!L56+'Model Assumptions'!L64 -> 0 | K17: ='Model Assumptions'!M32+'Model Assumptions'!M40+'Model Assumptions'!M48+'Model Assumptions'!M56+'Model Assumptions'!M64 -> 0 | L17: ='Model Assumptions'!N32+'Model Assumptions'!N40+'Model Assumptions'!N48+'Model Assumptions'!N56+'Model Assumptions'!N64 -> 0 | ... CJ17: ='Model Assumptions'!CL32+'Model Assumptions'!CL40+'Model Assumptions'!CL48+'Model Assumptions'!CL56+'Model Assumptions'!CL64 -> 1964901.3
B19: Gross Profit | E19: ='Model Assumptions'!G17+'Model Assumptions'!G25+'Model Assumptions'!G33+'Model Assumptions'!G41+'Model Assumptions'!G49+'Model Assumptions'!G57+'Model Assumptions'!G65 -> 0 | F19: ='Model Assumptions'!H17+'Model Assumptions'!H25+'Model Assumptions'!H33+'Model Assumptions'!H41+'Model Assumptions'!H49+'Model Assumptions'!H57+'Model Assumptions'!H65 -> 0 | G19: ='Model Assumptions'!I17+'Model Assumptions'!I25+'Model Assumptions'!I33+'Model Assumptions'!I41+'Model Assumptions'!I49+'Model Assumptions'!I57+'Model Assumptions'!I65 -> 0 | H19: ='Model Assumptions'!J17+'Model Assumptions'!J25+'Model Assumptions'!J33+'Model Assumptions'!J41+'Model Assumptions'!J49+'Model Assumptions'!J57+'Model Assumptions'!J65 -> 0 | I19: ='Model Assumptions'!K17+'Model Assumptions'!K25+'Model Assumptions'!K33+'Model Assumptions'!K41+'Model Assumptions'!K49+'Model Assumptions'!K57+'Model Assumptions'!K65 -> 0 | J19: ='Model Assumptions'!L17+'Model Assumptions'!L25+'Model Assumptions'!L33+'Model Assumptions'!L41+'Model Assumptions'!L49+'Model Assumptions'!L57+'Model Assumptions'!L65 -> 0 | K19: ='Model Assumptions'!M17+'Model Assumptions'!M25+'Model Assumptions'!M33+'Model Assumptions'!M41+'Model Assumptions'!M49+'Model Assumptions'!M57+'Model Assumptions'!M65 -> 0 | L19: ='Model Assumptions'!N17+'Model Assumptions'!N25+'Model Assumptions'!N33+'Model Assumptions'!N41+'Model Assumptions'!N49+'Model Assumptions'!N57+'Model Assumptions'!N65 -> 0 | ... CJ19: ='Model Assumptions'!CL17+'Model Assumptions'!CL25+'Model Assumptions'!CL33+'Model Assumptions'!CL41+'Model Assumptions'!CL49+'Model Assumptions'!CL57+'Model Assumptions'!CL65 -> 20142118
B20: Gross Margin | E20: =E19/E8 -> #DIV/0! | F20: =F19/F8 -> #DIV/0! | G20: =G19/G8 -> #DIV/0! | H20: =H19/H8 -> #DIV/0! | I20: =I19/I8 -> #DIV/0! | J20: =J19/J8 -> #DIV/0! | K20: =K19/K8 -> #DIV/0! | L20: =L19/L8 -> #DIV/0! | ... CJ20: =CJ19/CJ8 -> 0.89520526
B22: Operating Expenses
B23: Salaries & Benefits | E23: =('Model Assumptions'!G13+'Model Assumptions'!G21+'Model Assumptions'!G29+'Model Assumptions'!G37+'Model Assumptions'!G53+'Model Assumptions'!G61)/(1+0.3736) -> 75834.789 | F23: =('Model Assumptions'!H13+'Model Assumptions'!H21+'Model Assumptions'!H29+'Model Assumptions'!H37+'Model Assumptions'!H53+'Model Assumptions'!H61)/(1+0.3736) -> 75834.789 | G23: =('Model Assumptions'!I13+'Model Assumptions'!I21+'Model Assumptions'!I29+'Model Assumptions'!I37+'Model Assumptions'!I53+'Model Assumptions'!I61)/(1+0.3736) -> 75834.789 | H23: =('Model Assumptions'!J13+'Model Assumptions'!J21+'Model Assumptions'!J29+'Model Assumptions'!J37+'Model Assumptions'!J53+'Model Assumptions'!J61)/(1+0.3736) -> 75834.789 | I23: =('Model Assumptions'!K13+'Model Assumptions'!K21+'Model Assumptions'!K29+'Model Assumptions'!K37+'Model Assumptions'!K53+'Model Assumptions'!K61)/(1+0.3736) -> 75834.789 | J23: =('Model Assumptions'!L13+'Model Assumptions'!L21+'Model Assumptions'!L29+'Model Assumptions'!L37+'Model Assumptions'!L53+'Model Assumptions'!L61)/(1+0.3736) -> 75834.789 | K23: =('Model Assumptions'!M13+'Model Assumptions'!M21+'Model Assumptions'!M29+'Model Assumptions'!M37+'Model Assumptions'!M53+'Model Assumptions'!M61)/(1+0.3736) -> 75834.789 | L23: =('Model Assumptions'!N13+'Model Assumptions'!N21+'Model Assumptions'!N29+'Model Assumptions'!N37+'Model Assumptions'!N53+'Model Assumptions'!N61)/(1+0.3736) -> 75834.789 | ... CJ23: =('Model Assumptions'!CL13+'Model Assumptions'!CL21+'Model Assumptions'!CL29+'Model Assumptions'!CL37+'Model Assumptions'!CL53+'Model Assumptions'!CL61)/(1+0.3736) -> 974010.3
B24: General & Admin | E24: =('Model Assumptions'!G13+'Model Assumptions'!G21+'Model Assumptions'!G29+'Model Assumptions'!G37+'Model Assumptions'!G53+'Model Assumptions'!G61)-E23 -> 28331.877 | F24: =('Model Assumptions'!H13+'Model Assumptions'!H21+'Model Assumptions'!H29+'Model Assumptions'!H37+'Model Assumptions'!H53+'Model Assumptions'!H61)-F23 -> 28331.877 | G24: =('Model Assumptions'!I13+'Model Assumptions'!I21+'Model Assumptions'!I29+'Model Assumptions'!I37+'Model Assumptions'!I53+'Model Assumptions'!I61)-G23 -> 28331.877 | H24: =('Model Assumptions'!J13+'Model Assumptions'!J21+'Model Assumptions'!J29+'Model Assumptions'!J37+'Model Assumptions'!J53+'Model Assumptions'!J61)-H23 -> 28331.877 | I24: =('Model Assumptions'!K13+'Model Assumptions'!K21+'Model Assumptions'!K29+'Model Assumptions'!K37+'Model Assumptions'!K53+'Model Assumptions'!K61)-I23 -> 28331.877 | J24: =('Model Assumptions'!L13+'Model Assumptions'!L21+'Model Assumptions'!L29+'Model Assumptions'!L37+'Model Assumptions'!L53+'Model Assumptions'!L61)-J23 -> 28331.877 | K24: =('Model Assumptions'!M13+'Model Assumptions'!M21+'Model Assumptions'!M29+'Model Assumptions'!M37+'Model Assumptions'!M53+'Model Assumptions'!M61)-K23 -> 28331.877 | L24: =('Model Assumptions'!N13+'Model Assumptions'!N21+'Model Assumptions'!N29+'Model Assumptions'!N37+'Model Assumptions'!N53+'Model Assumptions'!N61)-L23 -> 28331.877 | ... CJ24: =('Model Assumptions'!CL13+'Model Assumptions'!CL21+'Model Assumptions'!CL29+'Model Assumptions'!CL37+'Model Assumptions'!CL53+'Model Assumptions'!CL61)-CJ23 -> 363890.25
B25: Facility Lease | E25: 8750 | F25: 8750 | G25: 8750 | H25: 8750 | I25: 8750 | J25: 8750 | K25: 8750 | L25: 8750 | M25: 8750 | N25: 8750 | O25: 8750 | P25: 8750 | Q25: =8750*2 -> 17500 | R25: =8750*2 -> 17500 | S25: =8750*2 -> 17500 | T25: =8750*2 -> 17500 | U25: =8750*2 -> 17500 | V25: =8750*2 -> 17500 | W25: =8750*2 -> 17500 | X25: =8750*2 -> 17500 | ... AB25: =8750*2 -> 17500 | AC25: =8750*4 -> 35000 | AD25: =8750*4 -> 35000 | AE25: =8750*4 -> 35000 | AF25: =8750*4 -> 35000 | AG25: =8750*4 -> 35000 | AH25: =8750*4 -> 35000 | AI25: =8750*4 -> 35000 | AJ25: =8750*4 -> 35000 | ... AN25: =8750*4 -> 35000 | AO25: =8750*6 -> 52500 | AP25: =8750*6 -> 52500 | AQ25: =8750*6 -> 52500 | AR25: =8750*6 -> 52500 | AS25: =8750*6 -> 52500 | AT25: =8750*6 -> 52500 | AU25: =8750*6 -> 52500 | AV25: =8750*6 -> 52500 | ... AZ25: =8750*6 -> 52500 | BA25: =8750*12 -> 105000 | BB25: =8750*12 -> 105000 | BC25: =8750*12 -> 105000 | BD25: =8750*12 -> 105000 | BE25: =8750*12 -> 105000 | BF25: =8750*12 -> 105000 | BG25: =8750*12 -> 105000 | BH25: =8750*12 -> 105000 | ... CJ25: =8750*12 -> 105000
B26: Professional Fees + Sales & Marketing | E26: =E19*0.03 -> 0 | F26: =F19*0.03 -> 0 | G26: =G19*0.03 -> 0 | H26: =H19*0.03 -> 0 | I26: =I19*0.03 -> 0 | J26: =J19*0.03 -> 0 | K26: =K19*0.03 -> 0 | L26: =L19*0.03 -> 0 | ... CJ26: =CJ19*0.03 -> 604263.55
B27: Other | E27: =E19*0.02 -> 0 | F27: =F19*0.02 -> 0 | G27: =G19*0.02 -> 0 | H27: =H19*0.02 -> 0 | I27: =I19*0.02 -> 0 | J27: =J19*0.02 -> 0 | K27: =K19*0.02 -> 0 | L27: =L19*0.02 -> 0 | ... CJ27: =CJ19*0.02 -> 402842.37
B28: Total Operating Expenses | E28: =SUM(E23:E27) -> 112916.67 | F28: =SUM(F23:F27) -> 112916.67 | G28: =SUM(G23:G27) -> 112916.67 | H28: =SUM(H23:H27) -> 112916.67 | I28: =SUM(I23:I27) -> 112916.67 | J28: =SUM(J23:J27) -> 112916.67 | K28: =SUM(K23:K27) -> 112916.67 | L28: =SUM(L23:L27) -> 112916.67 | ... CJ28: =SUM(CJ23:CJ27) -> 2450006.5
B30: EBITDA | E30: =E19-E28 -> -112916.67 | F30: =F19-F28 -> -112916.67 | G30: =G19-G28 -> -112916.67 | H30: =H19-H28 -> -112916.67 | I30: =I19-I28 -> -112916.67 | J30: =J19-J28 -> -112916.67 | K30: =K19-K28 -> -112916.67 | L30: =L19-L28 -> -112916.67 | ... CJ30: =CJ19-CJ28 -> 17692112
B31: Depreciation | E31: =SUM('Model Assumptions'!G95:G109)-SUM('Model Assumptions'!F95:F109) -> 29629.63 | F31: =SUM('Model Assumptions'!H95:H109)-SUM('Model Assumptions'!G95:G109) -> 29629.63 | G31: =SUM('Model Assumptions'!I95:I109)-SUM('Model Assumptions'!H95:H109) -> 29629.63 | H31: =SUM('Model Assumptions'!J95:J109)-SUM('Model Assumptions'!I95:I109) -> 29629.63 | I31: =SUM('Model Assumptions'!K95:K109)-SUM('Model Assumptions'!J95:J109) -> 29629.63 | J31: =SUM('Model Assumptions'!L95:L109)-SUM('Model Assumptions'!K95:K109) -> 29629.63 | K31: =SUM('Model Assumptions'!M95:M109)-SUM('Model Assumptions'!L95:L109) -> 29629.63 | L31: =SUM('Model Assumptions'!N95:N109)-SUM('Model Assumptions'!M95:M109) -> 29629.63 | ... CJ31: =SUM('Model Assumptions'!CL95:CL109)-SUM('Model Assumptions'!CK95:CK109) -> 535555.56
B32: EBIT | E32: =E30-E31 -> -142546.3 | F32: =F30-F31 -> -142546.3 | G32: =G30-G31 -> -142546.3 | H32: =H30-H31 -> -142546.3 | I32: =I30-I31 -> -142546.3 | J32: =J30-J31 -> -142546.3 | K32: =K30-K31 -> -142546.3 | L32: =L30-L31 -> -142546.3 | ... CJ32: =CJ30-CJ31 -> 17156556
B33: Taxes | E33: =IF(E32>0,E32*'Model Assumptions'!$C$67,0) -> 0 | F33: =IF(F32>0,F32*'Model Assumptions'!$C$67,0) -> 0 | G33: =IF(G32>0,G32*'Model Assumptions'!$C$67,0) -> 0 | H33: =IF(H32>0,H32*'Model Assumptions'!$C$67,0) -> 0 | I33: =IF(I32>0,I32*'Model Assumptions'!$C$67,0) -> 0 | J33: =IF(J32>0,J32*'Model Assumptions'!$C$67,0) -> 0 | K33: =IF(K32>0,K32*'Model Assumptions'!$C$67,0) -> 0 | L33: =IF(L32>0,L32*'Model Assumptions'!$C$67,0) -> 0 | ... CJ33: =IF(CJ32>0,CJ32*'Model Assumptions'!$C$67,0) -> 4632270.2
B34: Net Income | E34: =E32-E33 -> -142546.3 | F34: =F32-F33 -> -142546.3 | G34: =G32-G33 -> -142546.3 | H34: =H32-H33 -> -142546.3 | I34: =I32-I33 -> -142546.3 | J34: =J32-J33 -> -142546.3 | K34: =K32-K33 -> -142546.3 | L34: =L32-L33 -> -142546.3 | ... CJ34: =CJ32-CJ33 -> 12524286
B35: Net Margin | E35: =E34/E8 -> #DIV/0! | F35: =F34/F8 -> #DIV/0! | G35: =G34/G8 -> #DIV/0! | H35: =H34/H8 -> #DIV/0! | I35: =I34/I8 -> #DIV/0! | J35: =J34/J8 -> #DIV/0! | K35: =K34/K8 -> #DIV/0! | L35: =L34/L8 -> #DIV/0! | ... CJ35: =CJ34/CJ8 -> 0.55663494
B37: Balance Sheet:
B39: Assets
B40: Current Assets
B41: Cash | E41: =E84 -> 1251458.3 | F41: =F84 -> 1138541.7 | G41: =G84 -> 1025625 | H41: =H84 -> 912708.33 | I41: =I84 -> 799791.67 | J41: =J84 -> 686875 | K41: =K84 -> 573958.33 | L41: =L84 -> 461041.67 | ... CJ41: =CJ84 -> 3.3638071e+08
B42: Accounts Receivable | E42: ='Model Assumptions'!G75 -> 0 | F42: ='Model Assumptions'!H75 -> 0 | G42: ='Model Assumptions'!I75 -> 0 | H42: ='Model Assumptions'!J75 -> 0 | I42: ='Model Assumptions'!K75 -> 0 | J42: ='Model Assumptions'!L75 -> 0 | K42: ='Model Assumptions'!M75 -> 0 | L42: ='Model Assumptions'!N75 -> 0 | ... CJ42: ='Model Assumptions'!CL75 -> 9375000
B43: Total Current Assets | E43: =SUM(E41:E42) -> 1251458.3 | F43: =SUM(F41:F42) -> 1138541.7 | G43: =SUM(G41:G42) -> 1025625 | H43: =SUM(H41:H42) -> 912708.33 | I43: =SUM(I41:I42) -> 799791.67 | J43: =SUM(J41:J42) -> 686875 | K43: =SUM(K41:K42) -> 573958.33 | L43: =SUM(L41:L42) -> 461041.67 | ... CJ43: =SUM(CJ41:CJ42) -> 3.4575571e+08
B45: Fixed Assets | E45: ='Model Assumptions'!$F$18 -> 3200000 | F45: ='Model Assumptions'!$F$18 -> 3200000 | G45: ='Model Assumptions'!$F$18 -> 3200000 | H45: ='Model Assumptions'!$F$18 -> 3200000 | I45: ='Model Assumptions'!$F$18 -> 3200000 | J45: ='Model Assumptions'!$F$18 -> 3200000 | K45: ='Model Assumptions'!$F$18 -> 3200000 | L45: ='Model Assumptions'!$F$18 -> 3200000 | ... P45: ='Model Assumptions'!$F$18 -> 3200000 | Q45: =$P$45+'Model Assumptions'!$S$27 -> 7440000 | R45: =$P$45+'Model Assumptions'!$S$27 -> 7440000 | S45: =$P$45+'Model Assumptions'!$S$27 -> 7440000 | T45: =$P$45+'Model Assumptions'!$S$27 -> 7440000 | U45: =$P$45+'Model Assumptions'!$S$27 -> 7440000 | V45: =$P$45+'Model Assumptions'!$S$27 -> 7440000 | W45: =$P$45+'Model Assumptions'!$S$27 -> 7440000 | X45: =$P$45+'Model Assumptions'!$S$27 -> 7440000 | ... AB45: =$P$45+'Model Assumptions'!$S$27 -> 7440000 | AC45: =$AB$45+'Model Assumptions'!$AE$35 -> 16920000 | AD45: =$AB$45+'Model Assumptions'!$AE$35 -> 16920000 | AE45: =$AB$45+'Model Assumptions'!$AE$35 -> 16920000 | AF45: =$AB$45+'Model Assumptions'!$AE$35 -> 16920000 | AG45: =$AB$45+'Model Assumptions'!$AE$35 -> 16920000 | AH45: =$AB$45+'Model Assumptions'!$AE$35 -> 16920000 | AI45: =$AB$45+'Model Assumptions'!$AE$35 -> 16920000 | AJ45: =$AB$45+'Model Assumptions'!$AE$35 -> 16920000 | ... AN45: =$AB$45+'Model Assumptions'!$AE$35 -> 16920000 | AO45: =$AN$45+'Model Assumptions'!$AQ$43 -> 26400000 | AP45: =$AN$45+'Model Assumptions'!$AQ$43 -> 26400000 | AQ45: =$AN$45+'Model Assumptions'!$AQ$43 -> 26400000 | AR45: =$AN$45+'Model Assumptions'!$AQ$43 -> 26400000 | AS45: =$AN$45+'Model Assumptions'!$AQ$43 -> 26400000 | AT45: =$AN$45+'Model Assumptions'!$AQ$43 -> 26400000 | AU45: =$AN$45+'Model Assumptions'!$AQ$43 -> 26400000 | AV45: =$AN$45+'Model Assumptions'!$AQ$43 -> 26400000 | ... AZ45: =$AN$45+'Model Assumptions'!$AQ$43 -> 26400000 | BA45: =$AZ$45+'Model Assumptions'!$BC$59 -> 48840000 | BB45: =$AZ$45+'Model Assumptions'!$BC$59 -> 48840000 | BC45: =$AZ$45+'Model Assumptions'!$BC$59 -> 48840000 | BD45: =$AZ$45+'Model Assumptions'!$BC$59 -> 48840000 | BE45: =$AZ$45+'Model Assumptions'!$BC$59 -> 48840000 | BF45: =$AZ$45+'Model Assumptions'!$BC$59 -> 48840000 | BG45: =$AZ$45+'Model Assumptions'!$BC$59 -> 48840000 | BH45: =$AZ$45+'Model Assumptions'!$BC$59 -> 48840000 | ... BL45: =$AZ$45+'Model Assumptions'!$BC$59 -> 48840000 | BM45: =$BL$45+'Model Assumptions'!$BO$59 -> 57840000 | BN45: =$BL$45+'Model Assumptions'!$BO$59 -> 57840000 | BO45: =$BL$45+'Model Assumptions'!$BO$59 -> 57840000 | BP45: =$BL$45+'Model Assumptions'!$BO$59 -> 57840000 | BQ45: =$BL$45+'Model Assumptions'!$BO$59 -> 57840000 | BR45: =$BL$45+'Model Assumptions'!$BO$59 -> 57840000 | BS45: =$BL$45+'Model Assumptions'!$BO$59 -> 57840000 | BT45: =$BL$45+'Model Assumptions'!$BO$59 -> 57840000 | ... CJ45: =$BL$45+'Model Assumptions'!$BO$59 -> 57840000
B46: Accumulated Depreciation | E46: =-SUM('Model Assumptions'!G95:G109) -> -29629.63 | F46: =-SUM('Model Assumptions'!H95:H109) -> -59259.259 | G46: =-SUM('Model Assumptions'!I95:I109) -> -88888.889 | H46: =-SUM('Model Assumptions'!J95:J109) -> -118518.52 | I46: =-SUM('Model Assumptions'!K95:K109) -> -148148.15 | J46: =-SUM('Model Assumptions'!L95:L109) -> -177777.78 | K46: =-SUM('Model Assumptions'!M95:M109) -> -207407.41 | L46: =-SUM('Model Assumptions'!N95:N109) -> -237037.04 | ... CJ46: =-SUM('Model Assumptions'!CL95:CL109) -> -24275556
B47: Total Assets | E47: =SUM(E43:E46) -> 4421828.7 | F47: =SUM(F43:F46) -> 4279282.4 | G47: =SUM(G43:G46) -> 4136736.1 | H47: =SUM(H43:H46) -> 3994189.8 | I47: =SUM(I43:I46) -> 3851643.5 | J47: =SUM(J43:J46) -> 3709097.2 | K47: =SUM(K43:K46) -> 3566550.9 | L47: =SUM(L43:L46) -> 3424004.6 | ... CJ47: =SUM(CJ43:CJ46) -> 3.7932015e+08
B49: Liabilities & Owner's Equity
B50: Liabilities
B51: Accounts payable | E51: ='Model Assumptions'!G114 -> 4375 | F51: ='Model Assumptions'!H114 -> 4375 | G51: ='Model Assumptions'!I114 -> 4375 | H51: ='Model Assumptions'!J114 -> 4375 | I51: ='Model Assumptions'!K114 -> 4375 | J51: ='Model Assumptions'!L114 -> 4375 | K51: ='Model Assumptions'!M114 -> 4375 | L51: ='Model Assumptions'!N114 -> 4375 | ... CJ51: ='Model Assumptions'!CL114 -> 1734993.8
B52: Total Liabilities | E52: =SUM(E50:E51) -> 4375 | F52: =SUM(F50:F51) -> 4375 | G52: =SUM(G50:G51) -> 4375 | H52: =SUM(H50:H51) -> 4375 | I52: =SUM(I50:I51) -> 4375 | J52: =SUM(J50:J51) -> 4375 | K52: =SUM(K50:K51) -> 4375 | L52: =SUM(L50:L51) -> 4375 | ... CJ52: =SUM(CJ50:CJ51) -> 1734993.8
B54: Equity
B55: Paid In Capital | D55: 60000 | E55: =$D$55+'Model Assumptions'!G128 -> 4560000 | F55: =$D$55+'Model Assumptions'!H128 -> 4560000 | G55: =$D$55+'Model Assumptions'!I128 -> 4560000 | H55: =$D$55+'Model Assumptions'!J128 -> 4560000 | I55: =$D$55+'Model Assumptions'!K128 -> 4560000 | J55: =$D$55+'Model Assumptions'!L128 -> 4560000 | K55: =$D$55+'Model Assumptions'!M128 -> 4560000 | L55: =$D$55+'Model Assumptions'!N128 -> 4560000 | ... CJ55: =$D$55+'Model Assumptions'!CL128 -> 16560000
B56: Accumulated Retained Earnings | E56: =E34+D56 -> -142546.3 | F56: =F34+E56 -> -285092.59 | G56: =G34+F56 -> -427638.89 | H56: =H34+G56 -> -570185.19 | I56: =I34+H56 -> -712731.48 | J56: =J34+I56 -> -855277.78 | K56: =K34+J56 -> -997824.07 | L56: =L34+K56 -> -1140370.4 | ... CJ56: =CJ34+CI56 -> 3.6102516e+08
B57: Total Equity | E57: =SUM(E55:E56) -> 4417453.7 | F57: =SUM(F55:F56) -> 4274907.4 | G57: =SUM(G55:G56) -> 4132361.1 | H57: =SUM(H55:H56) -> 3989814.8 | I57: =SUM(I55:I56) -> 3847268.5 | J57: =SUM(J55:J56) -> 3704722.2 | K57: =SUM(K55:K56) -> 3562175.9 | L57: =SUM(L55:L56) -> 3419629.6 | ... CJ57: =SUM(CJ55:CJ56) -> 3.7758516e+08
B59: Total Liabilities & Owner's Equity | E59: =E57+E52 -> 4421828.7 | F59: =F57+F52 -> 4279282.4 | G59: =G57+G52 -> 4136736.1 | H59: =H57+H52 -> 3994189.8 | I59: =I57+I52 -> 3851643.5 | J59: =J57+J52 -> 3709097.2 | K59: =K57+K52 -> 3566550.9 | L59: =L57+L52 -> 3424004.6 | ... CJ59: =CJ57+CJ52 -> 3.7932015e+08
Q60: =Q47-Q59 -> 0
B61: Balance Check | E61: =IF(ABS(E59-E47)>0.001,"ERROR","OK") -> OK | F61: =IF(ABS(F59-F47)>0.001,"ERROR","OK") -> OK | G61: =IF(ABS(G59-G47)>0.001,"ERROR","OK") -> OK | H61: =IF(ABS(H59-H47)>0.001,"ERROR","OK") -> OK | I61: =IF(ABS(I59-I47)>0.001,"ERROR","OK") -> OK | J61: =IF(ABS(J59-J47)>0.001,"ERROR","OK") -> OK | K61: =IF(ABS(K59-K47)>0.001,"ERROR","OK") -> OK | L61: =IF(ABS(L59-L47)>0.001,"ERROR","OK") -> OK | ... CJ61: =IF(ABS(CJ59-CJ47)>0.001,"ERROR","OK") -> OK
B63: Statement of Cash Flows:
B65: Operating Cash Flows
B66: Net Income | E66: =E56-D56 -> -142546.3 | F66: =F56-E56 -> -142546.3 | G66: =G56-F56 -> -142546.3 | H66: =H56-G56 -> -142546.3 | I66: =I56-H56 -> -142546.3 | J66: =J56-I56 -> -142546.3 | K66: =K56-J56 -> -142546.3 | L66: =L56-K56 -> -142546.3 | ... CJ66: =CJ56-CI56 -> 12524286
B67: Depreciation | E67: =D46-E46 -> 29629.63 | F67: =E46-F46 -> 29629.63 | G67: =F46-G46 -> 29629.63 | H67: =G46-H46 -> 29629.63 | I67: =H46-I46 -> 29629.63 | J67: =I46-J46 -> 29629.63 | K67: =J46-K46 -> 29629.63 | L67: =K46-L46 -> 29629.63 | ... CJ67: =CI46-CJ46 -> 535555.56
B68: Change in Accounts Receivable | E68: =D42-E42 -> 0 | F68: =E42-F42 -> 0 | G68: =F42-G42 -> 0 | H68: =G42-H42 -> 0 | I68: =H42-I42 -> 0 | J68: =I42-J42 -> 0 | K68: =J42-K42 -> 0 | L68: =K42-L42 -> 0 | ... CJ68: =CI42-CJ42 -> 0
B69: Change in Accounts Payable | E69: =E51-D51 -> 4375 | F69: =F51-E51 -> 0 | G69: =G51-F51 -> 0 | H69: =H51-G51 -> 0 | I69: =I51-H51 -> 0 | J69: =J51-I51 -> 0 | K69: =K51-J51 -> 0 | L69: =L51-K51 -> 0 | ... CJ69: =CJ51-CI51 -> 0
B70: Total Operating Cash Flows | E70: =SUM(E66:E69) -> -108541.67 | F70: =SUM(F66:F69) -> -112916.67 | G70: =SUM(G66:G69) -> -112916.67 | H70: =SUM(H66:H69) -> -112916.67 | I70: =SUM(I66:I69) -> -112916.67 | J70: =SUM(J66:J69) -> -112916.67 | K70: =SUM(K66:K69) -> -112916.67 | L70: =SUM(L66:L69) -> -112916.67 | ... CJ70: =SUM(CJ66:CJ69) -> 13059842
B72: Investing Cash Flows
B73: Changes in Fixed Assets | E73: =D45-E45 -> -3200000 | F73: =E45-F45 -> 0 | G73: =F45-G45 -> 0 | H73: =G45-H45 -> 0 | I73: =H45-I45 -> 0 | J73: =I45-J45 -> 0 | K73: =J45-K45 -> 0 | L73: =K45-L45 -> 0 | ... CJ73: =CI45-CJ45 -> 0
B74: Total Investing Cash Flows | E74: =E73 -> -3200000 | F74: =F73 -> 0 | G74: =G73 -> 0 | H74: =H73 -> 0 | I74: =I73 -> 0 | J74: =J73 -> 0 | K74: =K73 -> 0 | L74: =L73 -> 0 | ... CJ74: =CJ73 -> 0
B76: Financing Cash Flows
B77: Changes in Paid in Capital | E77: =E55-D55 -> 4500000 | F77: =F55-E55 -> 0 | G77: =G55-F55 -> 0 | H77: =H55-G55 -> 0 | I77: =I55-H55 -> 0 | J77: =J55-I55 -> 0 | K77: =K55-J55 -> 0 | L77: =L55-K55 -> 0 | ... CJ77: =CJ55-CI55 -> 0
B78: Total Financing Cash Flows | E78: =E77 -> 4500000 | F78: =F77 -> 0 | G78: =G77 -> 0 | H78: =H77 -> 0 | I78: =I77 -> 0 | J78: =J77 -> 0 | K78: =K77 -> 0 | L78: =L77 -> 0 | ... CJ78: =CJ77 -> 0
B80: Beginning Cash | E80: ='Model Assumptions'!C73 -> 60000 | F80: =E84 -> 1251458.3 | G80: =F84 -> 1138541.7 | H80: =G84 -> 1025625 | I80: =H84 -> 912708.33 | J80: =I84 -> 799791.67 | K80: =J84 -> 686875 | L80: =K84 -> 573958.33 | M80: =L84 -> 461041.67 | ... CJ80: =CI84 -> 3.2332087e+08
B82: Change in Cash | E82: =E78+E74+E70 -> 1191458.3 | F82: =F78+F74+F70 -> -112916.67 | G82: =G78+G74+G70 -> -112916.67 | H82: =H78+H74+H70 -> -112916.67 | I82: =I78+I74+I70 -> -112916.67 | J82: =J78+J74+J70 -> -112916.67 | K82: =K78+K74+K70 -> -112916.67 | L82: =L78+L74+L70 -> -112916.67 | M82: =SUM(M78,M74,M70) -> -112916.67 | N82: =SUM(N78,N74,N70) -> -112916.67 | O82: =SUM(O78,O74,O70) -> -112916.67 | P82: =SUM(P78,P74,P70) -> -112916.67 | Q82: =SUM(Q78,Q74,Q70) -> 7610667.9 | R82: =SUM(R78,R74,R70) -> -73977.896 | S82: =SUM(S78,S74,S70) -> -73977.896 | T82: =SUM(T78,T74,T70) -> -73977.896 | ... CJ82: =SUM(CJ78,CJ74,CJ70) -> 13059842
B84: Ending Cash | E84: =E82+E80 -> 1251458.3 | F84: =F82+F80 -> 1138541.7 | G84: =G82+G80 -> 1025625 | H84: =H82+H80 -> 912708.33 | I84: =I82+I80 -> 799791.67 | J84: =J82+J80 -> 686875 | K84: =K82+K80 -> 573958.33 | L84: =L82+L80 -> 461041.67 | ... CJ84: =CJ82+CJ80 -> 3.3638071e+08

Sheet Project Overview
B3: Pilot Facility Summary | C3: Year 0 | D3: Year 1 | E3: Year 2 | F3: Year 3 | G3: Year 4+
B4: Project Cost | C4: ='Facility AFE'!C29 -> 3200000 | D4: ='Facility AFE'!C90 -> 1000000 | E4: ='Facility AFE'!C91 -> 1500000 | F4: 0 | G4: 0
B5: Personnel Cost | C5: =Personnel!E15 -> 1250000 | D5: =Personnel!E34 -> 1773944 | E5: =Personnel!E55 -> 2281903.8 | F5: =Personnel!E78 -> 2864575.5 | G5: =Personnel!E78 -> 2864575.5
B6: Profit | C6: 0 | D6: ='H2 Production Costs'!C54*12 -> 2014211.8 | E6: ='H2 Production Costs'!C56*6+'H2 Production Costs'!C55*6 -> 15106589 | F6: ='H2 Production Costs'!C56*12 -> 20142118 | G6: ='H2 Production Costs'!C56*12 -> 20142118
B7: Total | C7: =-C4-C5 -> -4450000 | D7: =-D4-D5+D6 -> -759732.16 | E7: =-E4-E5+E6 -> 11324685 | F7: =-F4-F5+F6 -> 17277543 | G7: =-G4-G5+G6 -> 17277543
B11: Additional Facility Summary | C11: Year 0 | D11: Year 1 | E11: Year 2 | F11: Year 3 | G11: Year 4+
B12: Project Cost | C12: ='Facility AFE'!C53 -> 3240000 | D12: ='Facility AFE'!C92 -> 1500000 | E12: 0 | F12: 0 | G12: 0
B13: Personnel Cost | C13: =Personnel!E91 -> 817292 | D13: =Personnel!E104 -> 1082053.4 | E13: =Personnel!E117 -> 1244361.4 | F13: =Personnel!E130 -> 1431015.6 | G13: =Personnel!E130 -> 1431015.6
B14: Profit | C14: 0 | D14: ='H2 Production Costs'!C66*12 -> 10071059 | E14: ='H2 Production Costs'!C67*12 -> 20142118 | F14: ='H2 Production Costs'!C67*12 -> 20142118 | G14: ='H2 Production Costs'!C67*12 -> 20142118
B15: Total | C15: =-C12-C13 -> -4057292 | D15: =-D12-D13+D14 -> 7489005.8 | E15: =-E12-E13+E14 -> 18897757 | F15: =-F12-F13+F14 -> 18711103 | G15: =-G12-G13+G14 -> 18711103
B19: Phase | C19: Monthly H₂ Output | D19: Peak Power | E19: Service Type
B20: Initial (2025) | C20: ~7,500 kg | D20: ~0.6 MW | E20: Standard 1-2 MVA 480V service
B21: Intermediate | C21: ~37,500 kg | D21: ~2.65 MW | E21: 3–4 MVA primary service
B22: Full Build-Out | C22: ~75,000 kg | D22: ~5.2 MW | E22: Dedicated substation (6–8 MVA)
B26: Scenario | C26: Price per kg (30% margin)
B27: Delivered (within 50 miles, ~200 bar) | C27: 7.05
B28: At-the-gate | C28: 6.15
B29: At-the-gate (no R&D costs) | C29: 4.36
B120: Anticipated Funding | C120: Item | D120: Amount (USD) | E120: Notes
B121: Year 0 Sources of Funds | C121: Equity (VC) | D121: 3000000 | E121: Equity financing from venture capital
B122: Year 0 Sources of Funds | C122: Non-Dilutive (OCAST) | D122: 500000 | E122: Grant funding
B123: Year 0 Sources of Funds | C123: Non-Dilutive (ITC/IRA) | D123: 1000000 | E123: Federal Inflation Reduction Act credit
B124: Year 0 Sources of Funds | C124: Total | D124: =SUM(D121:D123) -> 4500000 | E124: Sum of all funding sources
B126: Additional Years Funding | C126: Item | D126: Amount (USD) | E126: Notes
B127: Year 1 Source of Funds | C127: Year 0 Profit | D127: =D218 -> 38000 | E127: Leftover Funds from Seed
B128: Year 1 Source of Funds | C128: Series A Equity | D128: 7500000 | E128: Raising $7.5M at $45M
B129: Year 2 Source of Funds | C129: Year 1 Profit | D129: =D227 -> 613000
B130: Year 2 Source of Funds | C130: Debt Financing | D130: 4000000 | E130: Debt Financed
B131: Year 3 Source of Funds | C131: Year 2 Profit | D131: =D239 -> 1050500
B132: Year 4 Source of Funds | C132: Year 3 Profit | D132: =D252 -> 3691125
B133: Year 5 Source of Funds | C133: Year 4 Profit | D133: =D264 -> 39534875
B135: Cost of Facility Construction | C135: Item | D135: Amount (USD) | E135: Notes
B136: Uses of Funds, Pilot Plant | C136: Equipment Costs | D136: 1105000 | E136: Electrolyzers, compressors, storage tanks, etc. | G136: compressors
B137: Uses of Funds, Pilot Plant | C137: Labor (Salaries + Contracted Construction) | D137: 325000 | E137: Site prep and installation
B138: Uses of Funds, Pilot Plant | C138: Material Costs | D138: 225000 | E138: Steel piping, wiring, etc.
B139: Uses of Funds, Pilot Plant | C139: Construction Costs | D139: 400000 | E139: Facility build-out civil works | F139: civil works
B140: Uses of Funds, Pilot Plant | C140: Contingency (10%) | D140: 182000 | E140: Safety net for overruns
B141: Uses of Funds, Pilot Plant | C141: Subtotal (Direct Project Costs) | D141: =SUM(D136:D140) -> 2237000 | E141: Sum of above FEED study line items
B143: Year 0 Manufacturing, R&D, & Personnel | C143: Item | D143: Amount (USD) | E143: Notes
B144: Uses of Funds, Operating Capital | C144: Manufacturing Equipment for in-House Electrolyzer Production | D144: 350000 | E144: Setting up in-house line, cnc winder, 3d printing, ect.
B145: Uses of Funds, Operating Capital | C145: Continued R&D on scale up sizing | D145: 375000 | E145: Prototype improvements, new tech dev, scale up | G145: new tech dev
B146: Uses of Funds, Operating Capital | C146: Personnel | D146: =F289 -> 1250000 | E146: Salaries, benefits, G&A
B147: Uses of Funds, Operating Capital | C147: Subtotal (Manufacturing, R&D, & Personnel) | D147: =SUM(D144:D146) -> 1975000
B149: Year 0 Misc. Costs | C149: Item | D149: Amount (USD) | E149: Notes
B150: Use of Funds, Misc. | C150: Facility Overheads; Insurance, minor repairs, utilities buffer | D150: 50000 | E150: Facility coverage, unexpected overhead
B151: Use of Funds, Misc. | C151: Consumables & Spare Parts; Filters, membranes, sensors | D151: 25000 | E151: Regular replacements to ensure uptime
B152: Use of Funds, Misc. | C152: Administrative & Professional Services; Legal, accounting, consulting | D152: 60000 | E152: Basic corporate and compliance needs
B153: Use of Funds, Misc. | C153: Biz Dev & Marketing; Conferences, advertising, travel | D153: 30000 | E153: Customer acquisition, partnership development
B154: Use of Funds, Misc. | C154: Licensing & Certification; Annual fees, safety certs | D154: 15000 | E154: Renewal fees, specialized certs
B155: Use of Funds, Misc. | C155: IT & Software; Engineering/SCADA licenses, cloud storage | D155: 20000 | E155: Essential digital infrastructure
B156: Use of Funds, Misc. | C156: Contingency; General buffer for unforeseen costs | D156: 50000 | E156: At least 10% of total operating expenses
B157: Use of Funds, Misc. | C157: Subtotal (Misc.) | D157: =SUM(D150:D156) -> 250000
C158: Facility / Materials (Non-Personnel) | D158: =D159-D146 -> 3212000
B159: Year 0, Total Use of Funds | C159: Facility Construction + Year 0 Mfg, R&D, & Personnel + Misc. Costs | D159: =SUM(D141,D147,D157) -> 4462000
B161: Year 1 Manufacturing, R&D, & Personnel | C161: Item | D161: Amount (USD) | E161: Notes
B162: Year 1 Uses of Funds, Operating Capital | C162: Continued R&D on scale up sizing | D162: 875000 | E162: Prototype improvements, new tech dev, scale up | G162: new tech dev
B163: Year 1 Uses of Funds, Operating Capital | C163: Personnel (50% Growth Year 1) | D163: =F289*1.5 -> 1875000 | E163: Salaries, benefits, G&A
B164: Year 1 Use of Funds, Misc. | C164: Use of Funds (50% Growth) | D164: =D157*1.5 -> 375000
B165: Year 1 Total | D165: =SUM(D162:D164) -> 3125000
B167: Year 2 Manufacturing, R&D, & Personnel | C167: Item | D167: Amount (USD) | E167: Notes
B168: Year 2 Uses of Funds, Operating Capital | C168: Continued R&D on scale up sizing | D168: 875000 | E168: Prototype improvements, new tech dev, scale up | G168: new tech dev
B169: Year 2 Uses of Funds, Operating Capital | C169: Personnel (25% Growth Year 2) | D169: =D163*1.25 -> 2343750 | E169: Salaries, benefits, G&A
B170: Year 2 Use of Funds, Misc. | C170: Use of Funds (50% Growth) | D170: =D164*1.5 -> 562500
B171: Total Year 2 | D171: =SUM(D168:D170) -> 3781250
B173: Year 3+ Manufacturing, R&D, & Personnel | C173: Item | D173: Amount (USD) | E173: Notes
B174: Year 3+ Uses of Funds, Operating Capital | C174: Continued R&D on scale up sizing | D174: 875000 | E174: Prototype improvements, new tech dev, scale up
B175: Year 3+ Uses of Funds, Operating Capital | C175: Personnel (25% Growth Year 2) | D175: =D169*1.25 -> 2929687.5 | E175: Salaries, benefits, G&A
B176: Year 3+ Use of Funds, Misc. | C176: Use of Funds (50% Growth) | D176: =D170*1.5 -> 843750
B177: Total Year 3+ | D177: =SUM(D174:D176) -> 4648437.5
B179: Per site example economics
B180: Profitability | C180: Market Price of H₂ ($/kg) | D180: 25 | E180: Cost of Delivered Hydrogen, Conservatively Low
B181: Profitability | C181: Production Cost of H₂ ($/kg) | D181: 5 | E181: Includes electricity and overhead
B182: Profitability | C182: Gross Margin ($/kg) | D182: 20 | E182: (Price - Cost)
B183: Profitability | C183: Initial Scale Monthly Output | D183: 5000 | E183: Months 1-12
B184: Profitability | C184: Intermediate Scale Monthly Output | D184: 25000 | E184: Months 13-18
B185: Profitability | C185: Full-Scale Monthly Output (kg) | D185: 50000 | E185: After Month 18
B186: Profitability | C186: Initial Scale Monthly Gross Profit | D186: =D183*D182 -> 100000 | E186: Months 1-12
B187: Profitability | C187: Intermediate Scale Monthly Gross Profit | D187: =D184*D182 -> 500000 | E187: Months 13-18 | F187: *First Year for Subsequent Facilities
B188: Profitability | C188: Full-Scale Monthly Gross Profit | D188: =D185*D182 -> 1000000 | E188: After Month 18 | F188: *Second year for subsequent facilities
B189: Profitability | C189: Year 0 Annual Gross Profit | D189: 0
B190: Profitability | C190: Year 1 Annual Gross Profit | D190: =D186*12 -> 1200000
B191: Profitability | C191: Year 1 Electrical Infrastructure Upgrades | D191: -1000000 | E191: At Month 12 only for OKC
B192: Profitability | C192: Year 2 Annual Gross Profit | D192: =D187*6+D188*6 -> 9000000 | E192: *Year 1 for subsequent facilities
B193: Profitability | C193: Year 2 Electrical Infrastructure Upgrades | D193: -1500000 | E193: At Month 24 for OKC At Month 12 for all other Sites
B194: Profitability | C194: Year 3+ Annual Gross Profit | D194: =D188*12 -> 12000000 | E194: Year 2 for subsequent facilities
B196: Production Metrics
B197: Monthly Year 0 H2 Production | C197: No Facilities Operating, Building OKC Facility | D197: 0 | E197: kg/month
B198: Monthly Year 1 H2 Production | C198: OKC Facility Operating, Constructing Tulsa Facility | D198: 5000 | E198: kg/month
B199: Monthly Year 2 H2 Production | C199: OKC Facility Operating avg. 37.5k Tulsa Facility Operating at 25k | D199: 62500 | E199: kg/month
B200: Monthly Year 3 H2 Production | C200: OKC 50k, Tulsa 50k, Washington 2 sites at 25k | D200: 100000 | E200: kg/month
B201: Monthly Year 4 H2 Production | C201: OKC 50k, Tulsa 50k, Washington 2 sites at 50k, Iowa 2 sites at 25k | D201: 250000 | E201: kg/month
B202: Monthly Year 5 H2 Production | C202: 6 Facilities at 50k each, building 12 facilites | D202: 300000 | E202: kg/month
B203: Monthly Year 6 H2 Production | C203: 6 Facilities at 50k each, 6 facilities at 25k each | D203: 450000 | E203: kg/month
B204: Yearly production Year 0 | C204: Total Production for year 0 | D204: =D197*12 -> 0 | E204: kg/year
B205: Yearly production Year 1 | C205: Total Production for year 1 | D205: =D198*12 -> 60000 | E205: kg/year
B206: Yearly production Year 2 | C206: Total Production for year 2 | D206: =D199*12 -> 750000 | E206: kg/year
B207: Yearly production Year 3 | C207: Total Production for year 3 | D207: =D200*12 -> 1200000 | E207: kg/year
B208: Yearly production Year 4 | C208: Total Production for year 4 | D208: =D201*12 -> 3000000 | E208: kg/year
B209: Yearly production Year 5 | C209: Total Production for year 5 | D209: =D202*12 -> 3600000 | E209: kg/year
B210: Yealy production Year 6 | C210: Total Production for year 6 | D210: =D203*12 -> 5400000 | E210: kg/year
...

Sheet H2 Cost Assumptions
A1: Category | B1: Purchase Type | C1: Volume (kg) | D1: Price per kg (USD) | E1: Notes
A2: Bulk Purchase | B2: Large Contract (>3x per week deliveries) | C2: Varies | D2: 15 | E2: Multi-year contract, high volume, near facility
A3: Bulk Purchase | B3: Industrial (1,000 kg quote) | C3: 1000 | D3: 32 | E3: Quote received in Oklahoma
A4: Bulk Purchase | B4: Industrial (Other Companies) | C4: 1000 | D4: 20 | E4: General range (LOW) of industrial quotes
A5: Bulk Purchase | B5: Industrial (Other Companies) | C5: 1000 | D5: 27 | E5: General range (HIGH) of industrial quotes
A6: Mid-Scale Purchase | B6: Hydrogen Pump (California) | C6: 6kg | D6: 30 | E6: Public hydrogen fueling stations (LOW)
A7: Mid-Scale Purchase | B7: Hydrogen Pump (California) | C7: 6kg | D7: 50 | E7: Public hydrogen fueling stations (HIGH)
A8: Mid-Scale Purchase | B8: 15-Pack Cylinders | C8: 19 kg | D8: 40 | E8: Typical cost per kg based on $760 per 15-pack
A9: Small-Scale Purchase | B9: Single CGA 350 Cylinder | C9: 1 kg | D9: 120 | E9: Highest price scenario for specialty applications
A10: Low (Best Case) | B10: Bulk industrial contract (large volume long-term) | D10: 15
A11: Average (Most Likely) | B11: Industrial & public hydrogen blend (typical real-world prices) | D11: 25
A12: High (Worst Case) | B12: Retail or small-batch industrial purchase | D12: 40

Sheet H2 Production Costs
B2: Category | C2: Basis / Assumptions | D2: Cost ($/kg H₂) | E2: Note
B3: Electrical Cost | C3: Industrial Rate in OK | D3: 0.035 | E3: $ / kWh
B4: Water Cost per Liter | C4: Industrial Rate in OK | D4: 0.0055555556 | E4: $ / Liter
B5: Electricity for H₂ production | C5: 42 | D5: =(C5*D3)/0.95 -> 1.5473684 | E5: 42 kWh/kg (95% sys eff.)
B6: Compression & purification | C6: 3.5 | D6: =C6*D3 -> 0.1225 | E6: ~3 kWh/kg for 200 bar
B7: Transport (50-mile tube trailer) | C7: 0.9 | D7: 0.9 | E7: ~0.9–1.0/kg for ~50 miles
B8: RO water (consumable) | C8: 9 | D8: =D4*C8 -> 0.05 | E8: ~9 liters water per kg H₂
B9: Total (Direct OpEx, excl. labor/maintenance/CAPEX) | D9: =SUM(D5:D8) -> 2.6198684
B10: Year 1 Sale Price | C10: Annualized Capex + Personnel | D10: =D19 -> 19.042091 | E10: *No Profit Margin
B11: Year 2 Sale Price | C11: Annualized Capex + Personnel + Profit Margin | D11: =D23*(1+C14) -> 9.4811623
B12: Year 3 Sale Price | C12: Annualized Capex + Personnel + Profit Margin | D12: =D27*(1+C14) -> 7.1205789
B13: Yera 4+ Sale Price | C13: Annualized Capex + Personnel + Profit Margin | D13: =D27*1.3 -> 7.1205789
B14: Profit Margin | C14: 0.3
B15: Annualized CAPEX (25 years) | D15: =(3200000+2500000)/(12*25) -> 19000 | E15: Total Facility Costs + Upgrades over 25 years of operations
B16: Year 1 Personnel Costs | D16: 1250000
B17: Year 1 Facility Costs | D17: =D15*12 -> 228000
B18: Year 1 Production Volume / Personnel & Facility Costs per kg | C18: =7500*12 -> 90000 | D18: =(D16+D17)/C18 -> 16.422222
B19: Year 1 Total Costs | D19: =D18+D9 -> 19.042091
B20: Year 2 Personnel Costs | D20: =D16*1.5 -> 1875000
B21: Year 2 Facility Costs | D21: =D15*12 -> 228000
B22: Year 2 Production Volume / Personnel & Facility Costs per kg | C22: =37500*12 -> 450000 | D22: =(D20+D21)/C22 -> 4.6733333
B23: Year 2 Total Costs | D23: =D9+D22 -> 7.2932018
B24: Year 3 Personnel Costs | D24: =D20*1.25 -> 2343750
B25: Year 3 Facility Costs | D25: =D15*12 -> 228000
B26: Year 3 Production Volume / Personnel & Facility Costs per kg | C26: =75000*12 -> 900000 | D26: =(D24+D25)/C26 -> 2.8575
B27: Year 3 Total Costs | D27: =D26+D9 -> 5.4773684
B29: Item | C29: Basis | D29: Value | E29: Note
B30: Additional Facility Total CAPEX | D30: =3240000+1500000 -> 4740000 | E30: $ / additional facility for 2,500 kg / day
B31: Annualized CAPEX per additional facility ($/month) | D31: =D30/(25*12) -> 15800 | E31: $ / month
B32: Annualized CAPEX per additional facility (annually) | D32: =D31*12 -> 189600 | E32: $ / year
B33: Personnel Salary Requirements for Additional Facility (includes misc. costs and overhead) | D33: =817292 -> 817292 | E33: $ / year
B34: Cost per kg of H2 of Annualized CAPEX + Personnel | C34: 900000 | D34: =(D32+D33)/C34 -> 1.1187689 | E34: $ / kg
B35: Total Cost of H2 + 30% margin and delivery at additional facilities | D35: =(D9+D34)*1.3 -> 4.8602285 | E35: $ / kg sale price
B36: Total Cost without Delivery | D36: =D35-D7 -> 3.9602285 | E36: $ / kg sale price
B39: Initial Pilot Facility | C39: Amount | D39: Unit
B40: Initial Operations | C40: 250 | D40: kg / day
B41: Monthly Operations Months 1 - 6 | C41: =C40*30 -> 7500 | D41: kg / month
B42: Intermediate Operations | C42: 1250 | D42: kg / day
B43: Monthly Operations Months 7 - 12 | C43: =C42*30 -> 37500 | D43: kg / month
B44: Final Operations | C44: 2500 | D44: kd /day
B45: Final Operations Monthly Months 13+ | C45: =C44*30 -> 75000 | D45: kg / month
B46: Second Facility
B47: Initial Operations | C47: 1250 | D47: kg / day
B48: Monthly Operations Months 1-12 | C48: =C47*30 -> 37500 | D48: kg / month
B49: Final Operations | C49: 2500 | D49: kd /day
B50: Final Monthly Operations Months 13+ | C50: =C49*30 -> 75000 | D50: kg / month
B53: Pilot Facility Profit | C53: AMOUNT USD | E53: Pilot Facility Operating Cost (Included in Profit already) | F53: AMOUNT USD
B54: Average Case, Months 1-6 | C54: =$C$41*('H2 Cost Assumptions'!D11-$D$9) -> 167850.99 | E54: Opex, Months 1-6 | F54: =C41*D9 -> 19649.013
B55: Average Case, Months 7-12 | C55: =$C$43*('H2 Cost Assumptions'!D11-$D$9) -> 839254.93 | E55: Opex, Months 7-12 | F55: =C43*D9 -> 98245.066
B56: Average Case, Months 13+ | C56: =$C$45*('H2 Cost Assumptions'!D11-$D$9) -> 1678509.9 | E56: Opex, Months 13+ | F56: =C45*D9 -> 196490.13
B57: High Case, Months 1-6 | C57: =$C$41*('H2 Cost Assumptions'!D12-$D$9) -> 280350.99
B58: High Case, Months 7-12 | C58: =$C$43*('H2 Cost Assumptions'!D12-$D$9) -> 1401754.9
B59: High Case, Months 13+ | C59: =$C$45*('H2 Cost Assumptions'!D12-$D$9) -> 2803509.9 | E59: Second Facility Operating Cost (Included in Profit Already) | F59: AMOUNT USD
B60: Low Case, Months 1-6 | C60: =$C$41*('H2 Cost Assumptions'!D10-$D$9) -> 92850.987 | E60: Opex, Months 1-12 | F60: =C48*D9 -> 98245.066
B61: Low Case, Months 7-12 | C61: =$C$43*('H2 Cost Assumptions'!D10-$D$9) -> 464254.93 | E61: Opex, Months 13+ | F61: =C50*D9 -> 196490.13
B62: Low Case, Months 13+ | C62: =$C$45*('H2 Cost Assumptions'!D10-$D$9) -> 928509.87
B65: Additional Facility Profit | C65: AMOUNT USD
B66: Average Case, Months 1-12 | C66: =$C$48*('H2 Cost Assumptions'!D11-$D$9) -> 839254.93
B67: Average Case, Months 13+ | C67: =$C$50*('H2 Cost Assumptions'!D11-$D$9) -> 1678509.9
B68: High Case, Months 1-12 | C68: =$C$48*('H2 Cost Assumptions'!D12-$D$9) -> 1401754.9
B69: High Case, Months 13+ | C69: =$C$50*('H2 Cost Assumptions'!D12-$D$9) -> 2803509.9
B70: Low Case, Months 1-12 | C70: =$C$48*('H2 Cost Assumptions'!D10-$D$9) -> 464254.93
B71: Low Case, Months 13+ | C71: =$C$50*('H2 Cost Assumptions'!D10-$D$9) -> 928509.87
B74: Item | C74: Cost ($/kg)
B75: Electricity (42 kWh/kg at $0.06/kWh) | C75: 2.65
B76: Compression & Purification (3.5 kWh/kg at $0.06/kWh) | C76: 0.21
B77: Transportation (50-mile delivery) | C77: 0.9
B78: RO Water (9 liters/kg at $0.01/liter) | C78: 0.05
B79: Direct OpEx (excluding CAPEX & labor) | C79: 3.81
B80: Annualized CAPEX & Personnel Costs (Year 3, 900,000 kg/year) | C80: 2.86
B81: Total Breakeven Cost (Year 3) | C81: 6.67
B82: Indicative Selling Price (30% profit margin) | C82: 8.67

Sheet Personnel
A1: Year 0 Salaries for Initial / R&D Facility
A3: Category | B3: Role | C3: Headcount | D3: Base Salary (USD) Subtotal | E3: Subtotal Base (USD) | F3: Base (USD) Notes
A4: Management | B4: CEO / Facility Director | C4: 1 | D4: 150000 | E4: =C4*D4 -> 150000 | F4: Oversees strategy & daily ops
A5: Engineering | B5: Senior Engineer | C5: 1 | D5: 130000 | E5: =C5*D5 -> 130000 | F5: Leads design, R&D, troubleshooting
A6: Engineering | B6: Engineer / Technician (Existing) | C6: 2 | D6: 90000 | E6: =C6*D6 -> 180000 | F6: Build/maintain systems, R&D tasks
A7: Production | B7: Operator / Maintenance (Day, Existing) | C7: 1 | D7: 70000 | E7: =C7*D7 -> 70000 | F7: Daytime production, maintenance
A8: Production | B8: Operator / Maintenance (Night, Existing) | C8: 1 | D8: 65000 | E8: =C8*D8 -> 65000 | F8: Night operation
A9: Business | B9: Biz Dev / Marketing | C9: 1 | D9: 90000 | E9: =C9*D9 -> 90000 | F9: Partnerships, sales/marketing
A10: Admin | B10: Office Administrator | C10: 1 | D10: 60000 | E10: =C10*D10 -> 60000 | F10: Purchasing, scheduling, documentation
A11: Manufacturing / R&D | B11: Assembly Lead / Tech | C11: 1 | D11: 85000 | E11: =C11*D11 -> 85000 | F11: In-house electrolyzer assembly
A12: Engineering / R&D | B12: Junior Engineer | C12: 1 | D12: 80000 | E12: =C12*D12 -> 80000 | F12: R&D support
A13: TOTAL BASE SALARIES | E13: =SUM(E4:E12) -> 910000
A14: Overhead & Benefits (~X%) | D14: 0.37362637 | E14: =E13*D14 -> 340000
A15: GRAND TOTAL (Personnel Budget) | E15: =SUM(E13:E14) -> 1250000
A17: Year 1 Salaries for Initial / R&D Facility
A19: Category | B19: Role | C19: Headcount | D19: Year-1 Base Salary (USD) | E19: Subtotal Base (USD) | F19: Notes
A20: Management | B20: CEO / Facility Director | C20: 1 | D20: 172500 | E20: =C20*D20 -> 172500 | F20: 15% raise from 150k (Yr0)
A21: Engineering | B21: Senior Engineer | C21: 1 | D21: 149500 | E21: =C21*D21 -> 149500 | F21: 15% raise from 130k
A22: Engineering | B22: Engineer / Technician (Existing) | C22: 2 | D22: 103500 | E22: =C22*D22 -> 207000 | F22: 2 staff, each up 15% from 90k
A23: Production | B23: Operator / Maintenance (Day, Existing) | C23: 1 | D23: 80500 | E23: =C23*D23 -> 80500 | F23: 15% raise from 70k
A24: Production | B24: Operator / Maintenance (Night, Existing) | C24: 1 | D24: 74750 | E24: =C24*D24 -> 74750 | F24: 15% raise from 65k
A25: Business | B25: Biz Dev / Marketing | C25: 1 | D25: 103500 | E25: =C25*D25 -> 103500 | F25: 15% raise from 90k
A26: Admin | B26: Office Administrator | C26: 1 | D26: 69000 | E26: =C26*D26 -> 69000 | F26: 15% raise from 60k
A27: Manufacturing / R&D | B27: Assembly Lead / Tech | C27: 1 | D27: 97750 | E27: =C27*D27 -> 97750 | F27: 15% raise from 85k
A28: Engineering / R&D | B28: Junior Engineer | C28: 1 | D28: 92000 | E28: =C28*D28 -> 92000 | F28: 15% raise from 80k
A29: Engineering | B29: Engineer / Technician (New) | C29: 1 | D29: 90000 | E29: =C29*D29 -> 90000 | F29: New hire at original base (Yr0 rate)
A30: Production | B30: Operator / Maintenance (Day, New) | C30: 1 | D30: 70000 | E30: =C30*D30 -> 70000 | F30: New day operator, Yr0 base
A31: Quality / Safety | B31: Quality & Safety Manager (New) | C31: 1 | D31: 85000 | E31: =C31*D31 -> 85000 | F31: New role for QA & safety
A32: TOTAL BASE SALARIES | E32: 1291500
A33: Overhead & Benefits (~37.36%) | E33: 482444
A34: GRAND TOTAL (Personnel Budget) | E34: 1773944
A36: Year 2 Salaries
A38: Category | B38: Role | C38: Headcount | D38: Year-2 Base Salary (USD) | E38: Subtotal Base (USD) | F38: Notes
A39: Management | B39: CEO / Facility Director | C39: 1 | D39: 198375 | E39: 198375 | F39: 15% raise from Year 1
A40: Engineering | B40: Senior Engineer | C40: 1 | D40: 172925 | E40: 172925
A41: Engineering | B41: Engineer / Technician (Existing) | C41: 2 | D41: 119025 | E41: 238050 | F41: 2 staff
A42: Production | B42: Operator / Maintenance (Day, Existing) | C42: 1 | D42: 92575 | E42: 92575
A43: Production | B43: Operator / Maintenance (Night, Existing) | C43: 1 | D43: 85963 | E43: 85963
A44: Business | B44: Biz Dev / Marketing | C44: 1 | D44: 119025 | E44: 119025
A45: Admin | B45: Office Administrator | C45: 1 | D45: 79350 | E45: 79350
A46: Manufacturing / R&D | B46: Assembly Lead / Tech | C46: 1 | D46: 112413 | E46: 112413
A47: Engineering / R&D | B47: Junior Engineer | C47: 1 | D47: 105800 | E47: 105800
A48: Engineering | B48: Engineer / Technician (Added in Y1) | C48: 1 | D48: 103500 | E48: 103500 | F48: 15% raise from 90k (Y1)
A49: Production | B49: Operator / Maintenance (Day, Added in Y1) | C49: 1 | D49: 80500 | E49: 80500 | F49: 15% raise from 70k (Y1)
A50: Quality / Safety | B50: Quality & Safety Manager (Added in Y1) | C50: 1 | D50: 97750 | E50: 97750 | F50: 15% raise from 85k (Y1)
A51: Procurement | B51: Procurement / Logistics Manager (New in Y2) | C51: 1 | D51: 80000 | E51: 80000 | F51: New hire
A52: Engineering | B52: Process Engineer (New in Y2) | C52: 1 | D52: 95000 | E52: 95000 | F52: New hire
A53: TOTAL BASE SALARIES | E53: =SUM(E39:E52) -> 1661226
A54: Overhead & Benefits (~37.36%) | D54: 0.37362637 | E54: =E53*D54 -> 620677.85
A55: GRAND TOTAL (Personnel Budget) | E55: =SUM(E53:E54) -> 2281903.8
A57: Year 3 Salaries for Initial / R&D Facility
A59: Category | B59: Role | C59: Headcount | D59: Year-3 Base Salary (USD) | E59: Subtotal Base (USD) | F59: Notes
A60: Management | B60: CEO / Facility Director | C60: 1 | D60: 228131 | E60: =C60*D60 -> 228131 | F60: 15% raise from Y2
A61: Engineering | B61: Senior Engineer | C61: 1 | D61: 198864 | E61: =C61*D61 -> 198864
A62: Engineering | B62: Engineer / Technician (Existing) | C62: 2 | D62: 136879 | E62: =C62*D62 -> 273758 | F62: (2 staff)
A63: Production | B63: Operator / Maintenance (Day, Existing) | C63: 1 | D63: 106461 | E63: =C63*D63 -> 106461
A64: Production | B64: Operator / Maintenance (Night, Existing) | C64: 1 | D64: 98857 | E64: =C64*D64 -> 98857
A65: Business | B65: Biz Dev / Marketing | C65: 1 | D65: 136879 | E65: =C65*D65 -> 136879
A66: Admin | B66: Office Administrator | C66: 1 | D66: 91253 | E66: =C66*D66 -> 91253
A67: Manufacturing / R&D | B67: Assembly Lead / Tech | C67: 1 | D67: 129275 | E67: =C67*D67 -> 129275
A68: Engineering / R&D | B68: Junior Engineer | C68: 1 | D68: 121670 | E68: =C68*D68 -> 121670
