Workbook

Sheet Summary
A1: TOBE ENERGY CORP.
A2: CAP TABLE SUMMARY
A3: As of March 9, 2026
A5: CURRENT EQUITY STRUCTURE
A6: Class | B6: Authorized | C6: Outstanding | D6: Current % | E6: Fully Diluted | F6: FD %
A7: Common Stock | B7: 15000000 | C7: 10000000 | D7: =C7/C7 -> 1 | E7: 10000000 | F7: =E7/(E7+E9) -> 0.89999928
A8: Option Pool (2025 EIP) - Reserved | B8: 1111120 | C8: 0 | D8: =C8/C7 -> 0 | E8: 0
A9: Option Pool (2025 EIP) - Available | E9: 1111120 | F9: =E9/(E7+E9) -> 0.10000072
A10: TOTAL FULLY DILUTED | E10: =E7+E9 -> 11111120 | F10: =F7+F9 -> 1
A12: OUTSTANDING CONVERTIBLE SECURITIES
A13: Investor | B13: Type | C13: Amount | D13: Cap | E13: Discount | F13: Date | G13: Pro Forma Shares | H13: Pro Forma %
A14: Techstars Accelerator 2024, L.P. | B14: Fixed % Equity | C14: 20000 | F14: 45688 | G14: 666667 | H14: 6.00% FD
A15: Techstars Accelerator 2024, L.P. | B15: Conv. Note | C15: 100000 | D15: 3000000 | E15: 0.2 | F15: 45730 | G15: 370370 | H15: (at $3M cap)
A16: Techstars Ventures 2022, L.P. | B16: SAFE | C16: 500000 | D16: 10000000 | E16: 0.2 | F16: 45856 | G16: 555556 | H16: =G16/('Pro Forma Cap Table'!B19) -> 0.03926702
A17: Wave Function Ventures Fund I, LP | B17: SAFE | C17: 350000 | D17: 10000000 | E17: 0.2 | F17: 45856 | G17: 388889 | H17: =G17/('Pro Forma Cap Table'!B19) -> 0.0274869
A18: Cortado Ventures Fund II, LP | B18: SAFE | C18: 400000 | D18: 10000000 | E18: 0.2 | F18: 45854 | G18: 444444 | H18: =G18/('Pro Forma Cap Table'!B19) -> 0.031413559
A19: Cortado Ventures Fund II SSBCI, LP | B19: SAFE | C19: 200000 | D19: 10000000 | E19: 0.2 | F19: 45854 | G19: 222222 | H19: =G19/('Pro Forma Cap Table'!B19) -> 0.01570678
A20: Scissortail Ventures Flight Fund I, LP | B20: SAFE | C20: 150000 | D20: 10000000 | E20: 0.2 | F20: 45862 | G20: 166667 | H20: =G20/('Pro Forma Cap Table'!B19) -> 0.01178012
A21: Hurricane Ventures, LP-C1 | B21: SAFE | C21: 150000 | D21: 10000000 | E21: 0.2 | F21: 45862 | G21: 166667 | H21: =G21/('Pro Forma Cap Table'!B19) -> 0.01178012
A22: Ryan Fathi | B22: SAFE | C22: 20000 | D22: 10000000 | E22: 0.2 | F22: 45849 | G22: 22222 | H22: =G22/('Pro Forma Cap Table'!B19) -> 0.0015706638
A23: David Velasquez | B23: SAFE | C23: 15000 | D23: 10000000 | E23: 0.2 | F23: 45884 | G23: 16667 | H23: =G23/('Pro Forma Cap Table'!B19) -> 0.0011780332
A24: Tianyi Cai | B24: SAFE | C24: 10000 | D24: 10000000 | E24: 0.2 | F24: 45849 | G24: 11111 | H24: =G24/('Pro Forma Cap Table'!B19) -> 0.00078533191
A25: Beck Kloss | B25: SAFE | C25: 5000 | D25: 10000000 | E25: 0.2 | F25: 45854 | G25: 5556 | H25: =G25/('Pro Forma Cap Table'!B19) -> 0.0003927013
A26: TOTAL CONVERTIBLES | C26: =SUM(C14:C25) -> 1920000 | G26: =SUM(G14:G25) -> 3037038

Sheet SAFE Detail
A1: SAFE AGREEMENTS - DETAIL
A2: All SAFEs are Post-Money YC SAFE Format
A3: Investor | B3: Amount | C3: Post-Money Cap | D3: Discount | E3: Date Signed | F3: Conversion Price | G3: Shares at Cap
A4: Techstars Ventures 2022, L.P. | B4: 500000 | C4: 10000000 | D4: 0.2 | E4: 45856 | F4: =C4/11111120 -> 0.89999928 | G4: =ROUND(B4/F4,0) -> 555556
A5: Wave Function Ventures Fund I, LP | B5: 350000 | C5: 10000000 | D5: 0.2 | E5: 45856 | F5: =C5/11111120 -> 0.89999928 | G5: =ROUND(B5/F5,0) -> 388889
A6: Cortado Ventures Fund II, LP | B6: 400000 | C6: 10000000 | D6: 0.2 | E6: 45854 | F6: =C6/11111120 -> 0.89999928 | G6: =ROUND(B6/F6,0) -> 444445
A7: Cortado Ventures Fund II SSBCI, LP | B7: 200000 | C7: 10000000 | D7: 0.2 | E7: 45854 | F7: =C7/11111120 -> 0.89999928 | G7: =ROUND(B7/F7,0) -> 222222
A8: Scissortail Ventures Flight Fund I, LP | B8: 150000 | C8: 10000000 | D8: 0.2 | E8: 45862 | F8: =C8/11111120 -> 0.89999928 | G8: =ROUND(B8/F8,0) -> 166667
A9: Hurricane Ventures, LP-C1 | B9: 150000 | C9: 10000000 | D9: 0.2 | E9: 45862 | F9: =C9/11111120 -> 0.89999928 | G9: =ROUND(B9/F9,0) -> 166667
A10: Ryan Fathi | B10: 20000 | C10: 10000000 | D10: 0.2 | E10: 45849 | F10: =C10/11111120 -> 0.89999928 | G10: =ROUND(B10/F10,0) -> 22222
A11: David Velasquez | B11: 15000 | C11: 10000000 | D11: 0.2 | E11: 45884 | F11: =C11/11111120 -> 0.89999928 | G11: =ROUND(B11/F11,0) -> 16667
A12: Tianyi Cai | B12: 10000 | C12: 10000000 | D12: 0.2 | E12: 45849 | F12: =C12/11111120 -> 0.89999928 | G12: =ROUND(B12/F12,0) -> 11111
A13: Beck Kloss | B13: 5000 | C13: 10000000 | D13: 0.2 | E13: 45854 | F13: =C13/11111120 -> 0.89999928 | G13: =ROUND(B13/F13,0) -> 5556
A14: TOTAL SAFEs | B14: =SUM(B4:B13) -> 1800000 | G14: =SUM(G4:G13) -> 2000002
A16: Conversion Price = Post-Money Cap / Company Capitalization (11,111,120 FD shares)
A17: Shares at Cap = Investment Amount / Conversion Price (rounded to nearest whole share)

Sheet Techstars
A1: TECHSTARS CONVERTIBLE INSTRUMENTS
A3: 1. FIXED PERCENTAGE CONVERTIBLE EQUITY
A4: Investor: | B4: Techstars Accelerator 2024, L.P.
A5: Amount: | B5: 20000
A6: Ownership: | B6: 6% Fully Diluted
A7: Date: | B7: January 31, 2025
A8: Shares (at current 11.1M FD): | B8: 666667
A10: 2. CONVERTIBLE PROMISSORY NOTE
A11: Investor: | B11: Techstars Accelerator 2024, L.P.
A12: Principal: | B12: 100000
A13: Interest Rate: | B13: 5% per annum (simple interest)
A14: Valuation Cap: | B14: 3000000
A15: Discount: | B15: 20% (80% Discount Rate)
A16: Date: | B16: March 14, 2025
A17: Maturity: | B17: March 14, 2027 (2 years)
A18: Interest Basis: | B18: Actual/365 day count
A19: Accrued Interest (as of 3/9/26): | B19: =100000*0.05*360/365 -> 4931.5068

Sheet Pro Forma Cap Table
A1: PRO FORMA CAP TABLE (Post-Conversion)
A2: Assumes conversion at $10M post-money for SAFEs, Techstars at their respective terms
A4: Shareholder | B4: Shares | C4: Ownership % | D4: Type
A5: Founders (Common) | B5: 10000000 | C5: =B5/B$19 -> 0.70680579 | D5: Common
A6: Option Pool (available) | B6: 1111120 | C6: =B6/B$19 -> 0.078534605 | D6: Options
A7: Techstars Accelerator (6% equity) | B7: 666667 | C7: =B7/B$19 -> 0.04712041 | D7: Preferred
A8: Techstars Accelerator (conv note) | B8: 370370 | C8: =B8/B$19 -> 0.026177966 | D8: Preferred
A9: Techstars Ventures (SAFE) | B9: 555556 | C9: =B9/B$19 -> 0.03926702 | D9: Preferred
A10: Wave Function Ventures (SAFE) | B10: 388889 | C10: =B10/B$19 -> 0.0274869 | D10: Preferred
A11: Cortado Ventures Fund II (SAFE) | B11: 444444 | C11: =B11/B$19 -> 0.031413559 | D11: Preferred
A12: Cortado Ventures SSBCI (SAFE) | B12: 222222 | C12: =B12/B$19 -> 0.01570678 | D12: Preferred
A13: Scissortail Ventures (SAFE) | B13: 166667 | C13: =B13/B$19 -> 0.01178012 | D13: Preferred
A14: Hurricane Ventures (SAFE) | B14: 166667 | C14: =B14/B$19 -> 0.01178012 | D14: Preferred
A15: Ryan Fathi (SAFE) | B15: 22222 | C15: =B15/B$19 -> 0.0015706638 | D15: Preferred
A16: David Velasquez (SAFE) | B16: 16667 | C16: =B16/B$19 -> 0.0011780332 | D16: Preferred
... A18: Beck Kloss (SAFE) | B18: 5556 | C18: =B18/B$19 -> 0.0003927013 | D18: Preferred
A19: TOTAL | B19: =SUM(B5:B18) -> 14148158 | C19: =SUM(C5:C18) -> 1
A38: NOTES
A39: 1. POST-MONEY SAFE CONVERSION MECHANICS:
A40: All SAFEs use the standard YC post-money SAFE format. The post-money valuation cap of $10,000,000
A41: includes the value of all shares issued upon conversion of all SAFEs. The conversion price is calculated
A42: as: Post-Money Cap / Company Capitalization, where Company Capitalization includes all outstanding
A43: shares, option pool, and SAFE conversion shares. PPS = $10M / 11,111,120 = ~$0.9000.
A45: 2. TECHSTARS 6% EQUITY:
A46: Techstars Accelerator 2024, L.P. holds a Fixed Percentage Convertible Equity Agreement granting 6%
A47: ownership on a Fully Diluted Basis. 'Fully Diluted Basis' includes: (i) all outstanding common stock,
A48: (ii) all outstanding preferred stock on an as-converted basis, (iii) all outstanding options/warrants,
A49: and (iv) the reserved option pool. It EXCLUDES other convertible instruments (SAFEs, notes) issued
A50: for capital raising purposes. At the current 11,111,120 FD share count, this equals 666,667 shares.
... A57: the cap conversion price is ~$0.2700/share, yielding ~370,370 shares (principal only, before interest).
