Workbook
Name BenefitsLoading: 'Base Case Inputs'!$B$75
Name CostInflation: 'Base Case Inputs'!$B$88
Name DebtRate: 'Base Case Inputs'!$B$62
Name H2_Price: 'Base Case Inputs'!$B$18
Name OtherOpExRate: 'Base Case Inputs'!$B$77
Name PF_Rate: 'Base Case Inputs'!$B$67
Name ProfFeesRate: 'Base Case Inputs'!$B$76
Name ServiceAttachRate: 'Base Case Inputs'!$B$129
Name ServiceEscalator: 'Base Case Inputs'!$B$132
Name T125_ASP: 'Base Case Inputs'!$B$33
Name T25_ASP: 'Base Case Inputs'!$B$27
Name T2500_ASP: 'Base Case Inputs'!$B$232
Name TaxRate: 'Base Case Inputs'!$B$71

Sheet Overview
B2: ● CONFIDENTIAL · SEED ROUND
B3: Tobe Energy — Financial Model
B4: $10M Seed Round · Green Hydrogen Electrolyzers · 92% System Efficiency · v8.5.2 · March 2026
B7: FY7 REVENUE | E7: FY7 EBITDA | H7: FY7 NET INCOME | K7: FY7 CASH
B8: $467M | E8: $278M | H8: $202M | K8: $921M
B9: 12 facilities · H₂ + Equip + Svc | E9: 59.4% margin · EBITDA+ from Y2 | H9: 43.3% net margin | K9: Self-funding by FY5
B11: ① | C11: REVENUE GROWTH — 7-YEAR PROJECTION ($M)
C12: FY1 | D12: FY2 | E12: FY3 | F12: FY4 | G12: FY5 | H12: FY6 | I12: FY7
B13: H₂ Production | C13: 0 | D13: 11.81 | E13: 77.81 | F13: 141.56 | G13: 210.94 | H13: 264.38 | I13: 270
B14: Equipment Sales | C14: 0.88 | D14: 4.3 | E14: 10.26 | F14: 33.77 | G14: 73.95 | H14: 129.13 | I14: 186.06
B15: Services | C15: 0 | D15: 0.02 | E15: 0.25 | F15: 0.85 | G15: 2.43 | H15: 5.87 | I15: 10.86
B16: EBITDA | C16: -2.65 | D16: 3.75 | E16: 54.91 | F16: 110.52 | G16: 177.64 | H16: 243.1 | I16: 277.57
B17: Net Income | C17: -2.78 | D17: 3.36 | E17: 44.78 | F17: 85.56 | G17: 132.66 | H17: 178.25 | I17: 202.22
B18: Cash | C18: 1.31 | D18: 49.63 | E18: 139.5 | F18: 227.79 | G18: 494.44 | H18: 728.15 | I18: 921.02
B19: EBITDA Margin % | C19: -3 | D19: 23.3 | E19: 62.2 | F19: 62.7 | G19: 61.8 | H19: 60.9 | I19: 59.4
B66: ② | C66: FUNDRAISING WATERFALL — $510M EQUITY · $734M TOTAL CAPITAL
B67: Round | C67: Timing | D67: Pre-Money | E67: Equity | F67: Debt/PF | G67: Total | H67: Post-Money | I67: Step-Up
B68: Pre-Seed | C68: Oct 2025 | D68: $8M | E68: $2.1M | F68: — | G68: $2.1M | H68: $10.1M | I68: —
B69: Seed ★ | C69: May 2026 | D69: $40M | E69: $7.5M | F69: $2.5M | G69: $10M | H69: $47.5M | I69: 4.0x
B70: Series A | C70: Jun 2027 | D70: $210M | E70: $40M | F70: $17M | G70: $57M | H70: $250M | I70: 4.4x | L70: Stream | M70: $M
B71: Series B | C71: Q1 2029 | D71: $500M | E71: $60M | F71: $30M | G71: $90M | H71: $560M | I71: 2.0x | L71: H₂ Production | M71: 270
B72: Series C | C72: Q1 2031 | D72: $1.5B | E72: $150M | F72: $75M | G72: $225M | H72: $1.65B | I72: 2.7x | L72: Equipment | M72: 186.06
B73: Series D | C73: Q1 2033 | D73: $3.5B | E73: $250M | F73: $100M | G73: $350M | H73: $3.75B | I73: 2.1x | L73: Services | M73: 10.86
B76: ③ | C76: INVESTMENT HIGHLIGHTS
B78: ⚡ 92% System Efficiency | E78: Proprietary membrane-free electrolysis. Structural cost moat vs. grey H₂ and PEM competitors.
B79: 📈 EBITDA Positive from Year 2 | E79: Tiered facility ramps (Pilot → Mastered) drive operational mastery and rapid margin expansion.
B80: 🏭 12 Facilities by FY7 | E80: 4 tiers: Pilot 24mo, Early 18mo, Mature 15mo, Mastered 13mo. Each 900K kg/yr nameplate.
B81: 💰 45V PTC: $27M per Facility | E81: $3/kg × 900K kg/yr × 10 years. Must begin construction by Dec 2027 to qualify.
B82: 🔧 3-Engine Revenue Model | E82: H₂ production + equipment sales (T-25 / T-125) + recurring services (75% attach).
B83: 🎯 Single Source of Truth | E83: 15,400+ formulas trace to Base Case Inputs. One cell changes the entire 84-month engine.
B85: v8.5.2 · March 2026 · Prepared for Investor Diligence | H85: ● All integrity checks passing · 0 formula errors · BS balanced 84/84 months

Sheet P&L Summary
B1: P&L SUMMARY
B2: Annual income statement with integrated services and equipment revenue. T-25 and T-125 product lines drive equipment sales; services revenue begins 12 months after first equipment sale with 75% attach rate. Blue cells are adjustable. All figures pull directly from the Financials tab.
B4: REVENUE | C4: FY1 Apr '26 – Mar '27 | D4: FY2 Apr '27 – Mar '28 | E4: FY3 Apr '28 – Mar '29 | F4: FY4 Apr '29 – Mar '30 | G4: FY5 Apr '30 – Mar '31 | H4: FY6 Apr '31 – Mar '32 | I4: FY7 Apr '32 – Mar '33
B5: H₂ Production Revenue | C5: =SUM(Financials!E9:P15) -> 0 | D5: =SUM(Financials!Q9:AB15) -> 11812500 | E5: =SUM(Financials!AC9:AN15) -> 77812500 | F5: =SUM(Financials!AO9:AZ15) -> 141562500 | G5: =SUM(Financials!BA9:BL15) -> 210937500 | H5: =SUM(Financials!BM9:BX15) -> 264375000 | I5: =SUM(Financials!BY9:CJ15) -> 270000000
B6: Equipment Sales Revenue | C6: =SUM(Financials!E16:P16) -> 807692.31 | D6: =SUM(Financials!Q16:AB16) -> 4295000 | E6: =SUM(Financials!AC16:AN16) -> 10260000 | F6: =SUM(Financials!AO16:AZ16) -> 18770000 | G6: =SUM(Financials!BA16:BL16) -> 28950000 | H6: =SUM(Financials!BM16:BX16) -> 39130000 | I6: =SUM(Financials!BY16:CJ16) -> 51060000
B7: Equipment Services Revenue | C7: =SUM(Financials!E17:P17) -> 0 | D7: =SUM(Financials!Q17:AB17) -> 32812.5 | E7: =SUM(Financials!AC17:AN17) -> 242113.14 | F7: =SUM(Financials!AO17:AZ17) -> 848204.85 | G7: =SUM(Financials!BA17:BL17) -> 2092280.6 | H7: =SUM(Financials!BM17:BX17) -> 4204952.3 | I7: =SUM(Financials!BY17:CJ17) -> 6594846.3
B8: 45V Production Tax Credit (non-operating, excluded from Operating Revenue) | C8: =SUM('Model Assumptions'!G69:R69) -> 0 | D8: =SUM('Model Assumptions'!S69:AD69) -> 1417500 | E8: =SUM('Model Assumptions'!AE69:AP69) -> 8887500 | F8: =SUM('Model Assumptions'!AQ69:BB69) -> 10800000 | G8: =SUM('Model Assumptions'!BC69:BN69) -> 10800000 | H8: =SUM('Model Assumptions'!BO69:BZ69) -> 10800000 | I8: =SUM('Model Assumptions'!CA69:CL69) -> 10800000
B9: OPERATING REVENUE (ex-PTC) | C9: =C5+C6+C7 -> 807692.31 | D9: =D5+D6+D7 -> 16140312 | E9: =E5+E6+E7 -> 88314613 | F9: =F5+F6+F7 -> 1.611807e+08 | G9: =G5+G6+G7 -> 2.4197978e+08 | H9: =H5+H6+H7 -> 3.0770995e+08 | I9: =I5+I6+I7 -> 3.2765485e+08
B10: H₂ Revenue % | C10: =IFERROR(C5/C9,0) -> 0 | D10: =IFERROR(D5/D9,0) -> 0.73186315 | E10: =IFERROR(E5/E9,0) -> 0.88108295 | F10: =IFERROR(F5/F9,0) -> 0.87828441 | G10: =IFERROR(G5/G9,0) -> 0.87171539 | H10: =IFERROR(H5/H9,0) -> 0.85916948 | I10: =IFERROR(I5/I9,0) -> 0.82403786
B11: Equipment Revenue % | C11: =IFERROR(C6/C9,0) -> 1 | D11: =IFERROR(D6/D9,0) -> 0.26610389 | E11: =IFERROR(E6/E9,0) -> 0.11617556 | F11: =IFERROR(F6/F9,0) -> 0.11645315 | G11: =IFERROR(G6/G9,0) -> 0.1196381 | H11: =IFERROR(H6/H9,0) -> 0.12716521 | I11: =IFERROR(I6/I9,0) -> 0.15583472
B12: Services Revenue % | C12: =IFERROR(C7/C9,0) -> 0 | D12: =IFERROR(D7/D9,0) -> 0.0020329532 | E12: =IFERROR(E7/E9,0) -> 0.0027414844 | F12: =IFERROR(F7/F9,0) -> 0.0052624466 | G12: =IFERROR(G7/G9,0) -> 0.0086465102 | H12: =IFERROR(H7/H9,0) -> 0.013665311 | I12: =IFERROR(I7/I9,0) -> 0.020127419
B13: PTC % of Operating Revenue | C13: =IFERROR(C8/C9,0) -> 0 | D13: =IFERROR(D8/D9,0) -> 0.087823578 | E13: =IFERROR(E8/E9,0) -> 0.10063453 | F13: =IFERROR(F8/F9,0) -> 0.067005539 | G13: =IFERROR(G8/G9,0) -> 0.044631828 | H13: =IFERROR(H8/H9,0) -> 0.035097987 | I13: =IFERROR(I8/I9,0) -> 0.032961515 | J13: PTC (45V Production Tax Credit) is not included in Operating Revenue. This percentage shows PTC relative to Operating Revenue for comparability.
B14: COST OF GOODS SOLD
B15: H₂ Production COGS | C15: =SUM(Financials!E18:P18) -> 0 | D15: =SUM(Financials!Q18:AB18) -> 1268854.4 | E15: =SUM(Financials!AC18:AN18) -> 9728387.9 | F15: =SUM(Financials!AO18:AZ18) -> 18937473 | G15: =SUM(Financials!BA18:BL18) -> 28621619 | H15: =SUM(Financials!BM18:BX18) -> 36584628 | I15: =SUM(Financials!BY18:CJ18) -> 38281207
B16: Equipment COGS | C16: =SUM(Financials!E19:P19) -> 484615.38 | D16: =SUM(Financials!Q19:AB19) -> 2512000 | E16: =SUM(Financials!AC19:AN19) -> 5793750 | F16: =SUM(Financials!AO19:AZ19) -> 10143750 | G16: =SUM(Financials!BA19:BL19) -> 14813750 | H16: =SUM(Financials!BM19:BX19) -> 19110000 | I16: =SUM(Financials!BY19:CJ19) -> 24030000
B17: Services COGS | C17: =SUM(Financials!E20:P20) -> 0 | D17: =SUM(Financials!Q20:AB20) -> 6562.5 | E17: =SUM(Financials!AC20:AN20) -> 48422.627 | F17: =SUM(Financials!AO20:AZ20) -> 169640.97 | G17: =SUM(Financials!BA20:BL20) -> 418456.13 | H17: =SUM(Financials!BM20:BX20) -> 840990.46 | I17: =SUM(Financials!BY20:CJ20) -> 1318969.3
B18: TOTAL COGS | C18: =C15+C16+C17 -> 484615.38 | D18: =D15+D16+D17 -> 3787416.9 | E18: =E15+E16+E17 -> 15570561 | F18: =F15+F16+F17 -> 29250863 | G18: =G15+G16+G17 -> 43853825 | H18: =H15+H16+H17 -> 56535618 | I18: =I15+I16+I17 -> 63630177
B20: GROSS PROFIT | C20: =C9-C18 -> 323076.92 | D20: =D9-D18 -> 12352896 | E20: =E9-E18 -> 72744053 | F20: =F9-F18 -> 1.3192984e+08 | G20: =G9-G18 -> 1.9812596e+08 | H20: =H9-H18 -> 2.5117433e+08 | I20: =I9-I18 -> 2.6402467e+08
B21: Gross Margin | C21: =IFERROR(C20/C9,0) -> 0.4 | D21: =IFERROR(D20/D9,0) -> 0.76534426 | E21: =IFERROR(E20/E9,0) -> 0.82369214 | F21: =IFERROR(F20/F9,0) -> 0.81852131 | G21: =IFERROR(G20/G9,0) -> 0.8187707 | H21: =IFERROR(H20/H9,0) -> 0.81626978 | I21: =IFERROR(I20/I9,0) -> 0.8058012
B23: OPERATING EXPENSES
B24: Base Salaries | C24: =SUM(Financials!E26:P26) -> 1263500 | D24: =SUM(Financials!Q26:AB26) -> 3509147.2 | E24: =SUM(Financials!AC26:AN26) -> 7590438.4 | F24: =SUM(Financials!AO26:AZ26) -> 12122426 | G24: =SUM(Financials!BA26:BL26) -> 16827031 | H24: =SUM(Financials!BM26:BX26) -> 19624011 | I24: =SUM(Financials!BY26:CJ26) -> 20817306
B25: Benefits & Payroll Taxes | C25: =SUM(Financials!E27:P27) -> 472043.6 | D25: =SUM(Financials!Q27:AB27) -> 1311017.4 | E25: =SUM(Financials!AC27:AN27) -> 2835787.8 | F25: =SUM(Financials!AO27:AZ27) -> 4528938.4 | G25: =SUM(Financials!BA27:BL27) -> 6286578.8 | H25: =SUM(Financials!BM27:BX27) -> 7331530.4 | I25: =SUM(Financials!BY27:CJ27) -> 7777345.5
B26: HQ & Production Facility Leases | C26: =SUM(Financials!E28:P29) -> 262500 | D26: =SUM(Financials!Q28:AB29) -> 580662.5 | E26: =SUM(Financials!AC28:AN29) -> 848642.34 | F26: =SUM(Financials!AO28:AZ29) -> 1027353.7 | G26: =SUM(Financials!BA28:BL29) -> 1450410.1 | H26: =SUM(Financials!BM28:BX29) -> 1758208.4 | I26: =SUM(Financials!BY28:CJ29) -> 1802163.6
B27: Professional Fees + Sales & Mktg | C27: =SUM(Financials!E30:P30) -> 24230.769 | D27: =SUM(Financials!Q30:AB30) -> 484209.38 | E27: =SUM(Financials!AC30:AN30) -> 2649438.4 | F27: =SUM(Financials!AO30:AZ30) -> 4835421.1 | G27: =SUM(Financials!BA30:BL30) -> 7259393.4 | H27: =SUM(Financials!BM30:BX30) -> 9231298.6 | I27: =SUM(Financials!BY30:CJ30) -> 9829645.4
B28: R&D + Other | C28: =SUM(Financials!E31:P31)+SUM(Financials!E32:P32) -> 978903.85 | D28: =SUM(Financials!Q31:AB31)+SUM(Financials!Q32:AB32) -> 2709806.3 | E28: =SUM(Financials!AC31:AN31)+SUM(Financials!AC32:AN32) -> 3916292.3 | F28: =SUM(Financials!AO31:AZ31)+SUM(Financials!AO32:AZ32) -> 3823614.1 | G28: =SUM(Financials!BA31:BL31)+SUM(Financials!BA32:BL32) -> 5589595.6 | H28: =SUM(Financials!BM31:BX31)+SUM(Financials!BM32:BX32) -> 7154199 | I28: =SUM(Financials!BY31:CJ31)+SUM(Financials!BY32:CJ32) -> 7803097
B29: TOTAL OPERATING EXPENSES | C29: =C24+C25+C26+C27+C28 -> 3001178.2 | D29: =D24+D25+D26+D27+D28 -> 8594842.7 | E29: =E24+E25+E26+E27+E28 -> 17840599 | F29: =F24+F25+F26+F27+F28 -> 26337754 | G29: =G24+G25+G26+G27+G28 -> 37413009 | H29: =H24+H25+H26+H27+H28 -> 45099247 | I29: =I24+I25+I26+I27+I28 -> 48029557
B30: OpEx % of Revenue | C30: =IFERROR(C29/C9,0) -> 3.7157445 | D30: =IFERROR(D29/D9,0) -> 0.53250782 | E30: =IFERROR(E29/E9,0) -> 0.20201186 | F30: =IFERROR(F29/F9,0) -> 0.16340513 | G30: =IFERROR(G29/G9,0) -> 0.15461213 | H30: =IFERROR(H29/H9,0) -> 0.14656415 | I30: =IFERROR(I29/I9,0) -> 0.14658583
B31: Headcount (FTEs) | C31: =Personnel!B152 -> 15 | D31: =Personnel!C152 -> 50 | E31: =Personnel!D152 -> 89 | F31: =Personnel!E152 -> 135 | G31: =Personnel!F152 -> 182 | H31: =Personnel!G152 -> 205 | I31: =Personnel!H152 -> 224
B32: EBITDA | C32: =C20-C29 -> -2678101.3 | D32: =D20-D29 -> 3758052.9 | E32: =E20-E29 -> 54903453 | F32: =F20-F29 -> 1.0559209e+08 | G32: =G20-G29 -> 1.6071295e+08 | H32: =H20-H29 -> 2.0607509e+08 | I32: =I20-I29 -> 2.1599511e+08
B33: EBITDA Margin | C33: =IFERROR(C32/C9,0) -> -3.3157445 | D33: =IFERROR(D32/D9,0) -> 0.23283644 | E33: =IFERROR(E32/E9,0) -> 0.62168028 | F33: =IFERROR(F32/F9,0) -> 0.65511618 | G33: =IFERROR(G32/G9,0) -> 0.66415858 | H33: =IFERROR(H32/H9,0) -> 0.66970563 | I33: =IFERROR(I32/I9,0) -> 0.65921537
B35: Non-Operating Items
B36: Depreciation & Amortization | C36: =-SUM(Financials!E36:P36) -> 0 | D36: =-SUM(Financials!Q36:AB36) -> -706250 | E36: =-SUM(Financials!AC36:AN36) -> -1581944.4 | F36: =-SUM(Financials!AO36:AZ36) -> -2598611.1 | G36: =-SUM(Financials!BA36:BL36) -> -4640277.8 | H36: =-SUM(Financials!BM36:BX36) -> -5986111.1 | I36: =-SUM(Financials!BY36:CJ36) -> -6236111.1
B37: 45V PTC (applied in EBIT) | C37: =C8 -> 0 | D37: =D8 -> 1417500 | E37: =E8 -> 8887500 | F37: =F8 -> 10800000 | G37: =G8 -> 10800000 | H37: =H8 -> 10800000 | I37: =I8 -> 10800000
B38: EBIT | C38: =C32+C8+C36 -> -2678101.3 | D38: =D32+D8+D36 -> 4469302.9 | E38: =E32+E8+E36 -> 62209009 | F38: =F32+F8+F36 -> 1.1379348e+08 | G38: =G32+G8+G36 -> 1.6687267e+08 | H38: =H32+H8+H36 -> 2.1088898e+08 | I38: =I32+I8+I36 -> 2.20559e+08
B39: Interest Expense | C39: =SUM(Financials!E38:P38) -> -129908.71 | D39: =SUM(Financials!Q38:AB38) -> -855453.13 | E39: =SUM(Financials!AC38:AN38) -> -906767.09 | F39: =SUM(Financials!AO38:AZ38) -> -1515308.7 | G39: =SUM(Financials!BA38:BL38) -> -2062445.6 | H39: =SUM(Financials!BM38:BX38) -> -3737518.2 | I39: =SUM(Financials!BY38:CJ38) -> -5124499.7
B40: Earnings Before Tax | C40: =C38+C39 -> -2808010 | D40: =D38+D39 -> 3613849.8 | E40: =E38+E39 -> 61302242 | F40: =F38+F39 -> 1.1227817e+08 | G40: =G38+G39 -> 1.6481022e+08 | H40: =H38+H39 -> 2.0715146e+08 | I40: =I38+I39 -> 2.154345e+08
B41: Taxes | C41: =-SUM(Financials!E40:P40) -> 0 | D41: =-SUM(Financials!Q40:AB40) -> -245318.56 | E41: =-SUM(Financials!AC40:AN40) -> -16523863 | F41: =-SUM(Financials!AO40:AZ40) -> -30315105 | G41: =-SUM(Financials!BA40:BL40) -> -44498760 | H41: =-SUM(Financials!BM40:BX40) -> -55930894 | I41: =-SUM(Financials!BY40:CJ40) -> -58167315
B42: NET INCOME | C42: =C40+C41 -> -2808010 | D42: =D40+D41 -> 3368531.2 | E42: =E40+E41 -> 44778378 | F42: =F40+F41 -> 81963063 | G42: =G40+G41 -> 1.2031146e+08 | H42: =H40+H41 -> 1.5122056e+08 | I42: =I40+I41 -> 1.5726719e+08
B43: Net Margin | C43: =IFERROR(C42/C9,0) -> -3.4765838 | D43: =IFERROR(D42/D9,0) -> 0.20870297 | E43: =IFERROR(E42/E9,0) -> 0.50703249 | F43: =IFERROR(F42/F9,0) -> 0.50851659 | G43: =IFERROR(G42/G9,0) -> 0.49719635 | H43: =IFERROR(H42/H9,0) -> 0.49143865 | I43: =IFERROR(I42/I9,0) -> 0.47997821
B45: CASH POSITION
B46: Year-End Cash Balance | C46: =Financials!P101 -> 1289092.1 | D46: =Financials!AB101 -> 49613513 | E46: =Financials!AN101 -> 1.3948772e+08 | F46: =Financials!AZ101 -> 2.241518e+08 | G46: =Financials!BL101 -> 4.7838468e+08 | H46: =Financials!BX101 -> 6.8495995e+08 | I46: =Financials!CJ101 -> 8.3278198e+08
B51: DEBT & FINANCING SCHEDULE
B52: Annual debt balance waterfall — all values pulled directly from Financials. Seed debt ($2.5M) drawn at close (May 2026) at 7%, 6-month I/O then 30-month P&I, retired by end of Year 4. Project financing tranches drawn per facility milestones. No Series A venture debt.
B55: VENTURE / GROWTH DEBT | C55: FY1 Apr '26 – Mar '27 | D55: FY2 Apr '27 – Mar '28 | E55: FY3 Apr '28 – Mar '29 | F55: FY4 Apr '29 – Mar '30 | G55: FY5 Apr '30 – Mar '31 | H55: FY6 Apr '31 – Mar '32 | I55: FY7 Apr '32 – Mar '33
B56: Beginning Balance | C56: =0 -> 0 | D56: =Financials!P58 -> 2269169.4 | E56: =Financials!AB58 -> 1304494.1 | F56: =Financials!AN58 -> 270082.24 | G56: =Financials!AZ58 -> 0 | H56: =Financials!BL58 -> 0 | I56: =Financials!BX58 -> 0
B57: (+) New Draws | C57: =SUM(Financials!E86:P86) -> 2500000 | D57: =SUM(Financials!Q86:AB86) -> 0 | E57: =SUM(Financials!AC86:AN86) -> 0 | F57: =SUM(Financials!AO86:AZ86) -> 0 | G57: =SUM(Financials!BA86:BL86) -> 0 | H57: =SUM(Financials!BM86:BX86) -> 0 | I57: =SUM(Financials!BY86:CJ86) -> 0
B58: (−) Principal Repayment | C58: =-SUM(Financials!E89:P89) -> -230830.59 | D58: =-SUM(Financials!Q89:AB89) -> -964675.35 | E58: =-SUM(Financials!AC89:AN89) -> -1034411.8 | F58: =-SUM(Financials!AO89:AZ89) -> -270082.24 | G58: =-SUM(Financials!BA89:BL89) -> 0 | H58: =-SUM(Financials!BM89:BX89) -> 0 | I58: =-SUM(Financials!BY89:CJ89) -> 0
B59: Ending Balance | C59: =Financials!P58 -> 2269169.4 | D59: =Financials!AB58 -> 1304494.1 | E59: =Financials!AN58 -> 270082.24 | F59: =Financials!AZ58 -> 0 | G59: =Financials!BL58 -> 0 | H59: =Financials!BX58 -> 0 | I59: =Financials!CJ58 -> 0
B60: Interest Expense | C60: =SUM(Financials!E88:P88) -> -129908.71 | D60: =SUM(Financials!Q88:AB88) -> -128281.86 | E60: =SUM(Financials!AC88:AN88) -> -58545.403 | F60: =SUM(Financials!AO88:AZ88) -> -3157.0684 | G60: =SUM(Financials!BA88:BL88) -> 0 | H60: =SUM(Financials!BM88:BX88) -> 0 | I60: =SUM(Financials!BY88:CJ88) -> 0
B61: Total Debt Service (P+I) | C61: =C60+C58 -> -360739.3 | D61: =D60+D58 -> -1092957.2 | E61: =E60+E58 -> -1092957.2 | F61: =F60+F58 -> -273239.3 | G61: =G60+G58 -> 0 | H61: =H60+H58 -> 0 | I61: =I60+I58 -> 0
B63: PROJECT FINANCING
B64: Beginning Balance | C64: =0 -> 0 | D64: =Financials!P59 -> 0 | E64: =Financials!AB59 -> 13878096 | F64: =Financials!AN59 -> 10236497 | G64: =Financials!AZ59 -> 31244502 | H64: =Financials!BL59 -> 24889976 | I64: =Financials!BX59 -> 77594001
B65: (+) New Draws | C65: =SUM(Financials!E90:P90) -> 0 | D65: =SUM(Financials!Q90:AB90) -> 17000000 | E65: =SUM(Financials!AC90:AN90) -> 0 | F65: =SUM(Financials!AO90:AZ90) -> 27500000 | G65: =SUM(Financials!BA90:BL90) -> 2500000 | H65: =SUM(Financials!BM90:BX90) -> 68750000 | I65: =SUM(Financials!BY90:CJ90) -> 6250000
B66: (−) Principal Repayment | C66: =-SUM(Financials!E93:P93) -> 0 | D66: =-SUM(Financials!Q93:AB93) -> -3121903.8 | E66: =-SUM(Financials!AC93:AN93) -> -3641599.4 | F66: =-SUM(Financials!AO93:AZ93) -> -6491994.7 | G66: =-SUM(Financials!BA93:BL93) -> -8854525.7 | H66: =-SUM(Financials!BM93:BX93) -> -16045975 | I66: =-SUM(Financials!BY93:CJ93) -> -22000587
B67: Ending Balance | C67: =Financials!P59 -> 0 | D67: =Financials!AB59 -> 13878096 | E67: =Financials!AN59 -> 10236497 | F67: =Financials!AZ59 -> 31244502 | G67: =Financials!BL59 -> 24889976 | H67: =Financials!BX59 -> 77594001 | I67: =Financials!CJ59 -> 61843414
B68: Interest Expense | C68: =SUM(Financials!E92:P92) -> 0 | D68: =SUM(Financials!Q92:AB92) -> -727171.27 | E68: =SUM(Financials!AC92:AN92) -> -848221.69 | F68: =SUM(Financials!AO92:AZ92) -> -1512151.7 | G68: =SUM(Financials!BA92:BL92) -> -2062445.6 | H68: =SUM(Financials!BM92:BX92) -> -3737518.2 | I68: =SUM(Financials!BY92:CJ92) -> -5124499.7
B69: Total Debt Service (P+I) | C69: =C68+C66 -> 0 | D69: =D68+D66 -> -3849075 | E69: =E68+E66 -> -4489821.1 | F69: =F68+F66 -> -8004146.3 | G69: =G68+G66 -> -10916971 | H69: =H68+H66 -> -19783493 | I69: =I68+I66 -> -27125087
B71: COMBINED DEBT SUMMARY
B72: Total Debt Outstanding (EOY) | C72: =IF(ABS(C59+C67)<5,0,C59+C67) -> 2269169.4 | D72: =IF(ABS(D59+D67)<5,0,D59+D67) -> 15182590 | E72: =IF(ABS(E59+E67)<5,0,E59+E67) -> 10506579 | F72: =IF(ABS(F59+F67)<5,0,F59+F67) -> 31244502 | G72: =IF(ABS(G59+G67)<5,0,G59+G67) -> 24889976 | H72: =IF(ABS(H59+H67)<5,0,H59+H67) -> 77594001 | I72: =IF(ABS(I59+I67)<5,0,I59+I67) -> 61843414
B73: Total Interest Expense | C73: =C60+C68 -> -129908.71 | D73: =D60+D68 -> -855453.13 | E73: =E60+E68 -> -906767.09 | F73: =F60+F68 -> -1515308.7 | G73: =G60+G68 -> -2062445.6 | H73: =H60+H68 -> -3737518.2 | I73: =I60+I68 -> -5124499.7
B74: Total Debt Service | C74: =C61+C69 -> -360739.3 | D74: =D61+D69 -> -4942032.3 | E74: =E61+E69 -> -5582778.4 | F74: =F61+F69 -> -8277385.6 | G74: =G61+G69 -> -10916971 | H74: =H61+H69 -> -19783493 | I74: =I61+I69 -> -27125087
B76: Debt Terms Reference
B77: Tranche | C77: Amount | D77: Rate | E77: Term | F77: Notes
B78: Seed Debt | C78: ='Base Case Inputs'!B43 -> 2500000 | D78: ='Base Case Inputs'!$B$62 -> 0.07 | E78: 36 mo. (6 I/O) | F78: Drawn at seed close (May 2026)
B79: Series A Debt | C79: ='Base Case Inputs'!B48 -> 0 | D79: N/A | E79: N/A
B80: Seed Project Financing | C80: ='Base Case Inputs'!B44 -> 0 | D80: N/A | E80: N/A | F80: No separate PF at Seed. $2.5M venture debt (above) covers all project costs.
B81: Series B Project Financing | C81: ='Base Case Inputs'!B53 -> 30000000 | D81: 7% | E81: 36 months | F81: Drawn at Series B (Mar 2029)
B82: Series C Project Financing | C82: ='Base Case Inputs'!B57 -> 75000000 | D82: 7% | E82: 36 months | F82: Drawn at Series C (Mar 2031)
B84: HQ Lease: $105K/year ($8,750/mo) headquarters only. Production Facility Leases: per-facility site leases in BCI B142-B147. Additional facility operating costs (utilities, per-facility personnel) flow through COGS via per-facility cost blocks in Model Assumptions.
B85: Note: All fiscal years run April–March (e.g., FY1 = Apr 2026 – Mar 2027). Each year represents a full 12-month period.

Sheet Unit Economics
B1: UNIT ECONOMICS: Structural Cost Advantage → Margin Expansion
B4: 1. PRODUCTION COST BUILDUP ($/kg H₂) — vs. Delivered Grey H₂ (SMR)
B5: Direct variable costs at Oklahoma industrial rates. Compared against delivered grey H₂ (centralized SMR).
B7: Cost Component | C7: Tobe ($/kg) | D7: Grey H₂ Delivered ($/kg) | E7: Tobe Advantage | F7: Source / Note
B8: Production Cost | C8: ='Base Case Inputs'!B90 -> 1.5473684 | D8: 1.25 | E8: =D8-C8 -> -0.29736842 | F8: Tobe: 42 kWh/kg × $0.035/kWh (OK rate). Grey SMR: $1.00-$1.50/kg production. Source: NREL ATB 2025
B9: Compression & Purification | C9: ='Base Case Inputs'!B83*'Base Case Inputs'!B11 -> 0.1225 | D9: 0.75 | E9: =D9-C9 -> 0.6275 | F9: Tobe: 3.5 kWh/kg × $0.035. Grey: $0.50-$1.00/kg at centralized facility. Source: DOE H2A-Lite v1.01
B10: Transportation (50-mile tube trailer / 500-mile liquefied) | C10: ='Base Case Inputs'!B82 -> 0.9 | D10: 8.25 | E10: =D10-C10 -> 7.35 | F10: Tobe: $0.90/kg 50-mi tube trailer. Grey: $2.50-$4.00/kg 150-300+ mi from centralized SMR. Source: NREL ATB 2025 delivery module; Brattle Group Feb 2024
B11: RO Water | C11: ='Base Case Inputs'!B84*'Base Case Inputs'!B85 -> 0.05004 | D11: 0.05 | E11: =D11-C11 -> -4e-05 | F11: 9 L/kg × $0.00556/L; industry ~$0.05/kg (comparable)
B12: TOTAL DIRECT OPEX | C12: =SUM(C8:C11) -> 2.6199084 | D12: =SUM(D8:D11) -> 10.3 | E12: =D12-C12 -> 7.6800916 | F12: Sum of variable production costs
B13: Overhead Absorption (at nameplate: 900,000 kg/year per facility)
B14: Allocated Facility Labor | C14: =Personnel!E15/900000 -> 1.3888622 | D14: N/A (absorbed)¹ | E14: N/A | F14: Tobe: allocated overhead (rent, insurance, admin) spread across production volume. At full capacity (900,000 kg/yr), overhead per kg is minimal.
B15: Allocated Facility CapEx (annualized) | C15: ='Model Assumptions'!$C$79/'Base Case Inputs'!$B$12/'Base Case Inputs'!$B$8 -> 0.40740741 | D15: N/A (absorbed)¹ | E15: N/A | F15: Tobe: capex allocated at $3.3M / 9yr useful life = $367K/yr; divided by annual production volume. Drops rapidly with scale.
B16: Maintenance & Consumables | C16: 0.42 | D16: N/A (absorbed)¹ | E16: N/A | F16: Tobe: $0.42/kg maintenance based on detailed cost analysis. Includes preventive maintenance and consumables.
B17: ALL-IN PRODUCTION COST ($/kg) | C17: =C12+C14+C15+C16 -> 4.8361781 | D17: ='Base Case Inputs'!B160 -> 5.25 | E17: =1-C17/D17 -> 0.078823228 | F17: Tobe all-in: production + overhead. Grey all-in: delivered price (.50-.50/kg). Source: NREL ATB 2025
B18: Base Case Sale Price ($/kg) | C18: ='Base Case Inputs'!B18 -> 25
B19: GROSS MARGIN PER KG | C19: =C18-C17 -> 20.163822
B20: ¹ Grey H₂ overhead note: Centralized SMR producers (Air Liquide, Air Products, Linde) quote all-in delivered prices that embed production cost, overhead, profit margin, and transportation. Their overhead is not shown separately because it's already baked into the $1.00-$1.50/kg production cost. Tobe's model shows overhead as a separate line because we build the full cost stack bottom-up for investor transparency. The comparison is apples-to-apples: both "all-in" numbers include overhead.
B22: 2. COST-DOWN CURVE BY YEAR
B23: Cost per kg decreases as production ramps and overhead absorption improves
C25: Year 2 (2027) | D25: Year 3 (2028) | E25: Year 4 (2029) | F25: Year 5 (2030)
B26: Annual H₂ Production (kg) | C26: =SUM(Financials!Q9:AB15)/'Base Case Inputs'!B18 -> 472500 | D26: ='Base Case Inputs'!$B$8 -> 900000 | E26: ='Base Case Inputs'!$B$8 -> 900000 | F26: ='Base Case Inputs'!$B$8 -> 900000 | G26: Ramp schedule from Model Assumptions
B27: Facility Utilization | C27: =C26/900000 -> 0.525 | D27: =D26/900000 -> 1 | E27: =E26/900000 -> 1 | F27: =F26/900000 -> 1 | G27: Volume ÷ 900K nameplate
B28: Direct OpEx ($/kg) | C28: =C12 -> 2.6199084 | D28: =C12 -> 2.6199084 | E28: =C12 -> 2.6199084 | F28: =C12 -> 2.6199084 | G28: Constant — variable cost per kg
B29: Allocated Labor ($/kg) | C29: =1250000/C26 -> 2.6455026 | D29: =1250000/D26 -> 1.3888889 | E29: =1250000/E26 -> 1.3888889 | F29: =1250000/F26 -> 1.3888889 | G29: $1.25M personnel ÷ actual volume
B30: Allocated CapEx ($/kg) | C30: ='Model Assumptions'!$C$79/'Base Case Inputs'!$B$12/C26 -> 0.77601411 | D30: ='Model Assumptions'!$C$79/'Base Case Inputs'!$B$12/D26 -> 0.40740741 | E30: ='Model Assumptions'!$C$79/'Base Case Inputs'!$B$12/E26 -> 0.40740741 | F30: ='Model Assumptions'!$C$79/'Base Case Inputs'!$B$12/F26 -> 0.40740741 | G30: $3.3M facility ÷ 9yr ÷ actual volume
B31: Maintenance ($/kg) | C31: 0.43 | D31: 0.42 | E31: 0.4 | F31: 0.4 | G31: Declines with operational maturity - Operational learning reduces unplanned maintenance by ~5% per year through Year 4, then stabilizes
B32: ALL-IN COST ($/kg) | C32: =C28+C29+C30+C31 -> 6.4714252 | D32: =D28+D29+D30+D31 -> 4.8362047 | E32: =E28+E29+E30+E31 -> 4.8162047 | F32: =F28+F29+F30+F31 -> 4.8162047
B33: Gross Margin ($/kg) | C33: ='Base Case Inputs'!$B$18-C32 -> 18.528575 | D33: ='Base Case Inputs'!$B$18-D32 -> 20.163795 | E33: ='Base Case Inputs'!$B$18-E32 -> 20.183795 | F33: ='Base Case Inputs'!$B$18-F32 -> 20.183795
B34: Gross Margin % | C34: =1-C32/'Base Case Inputs'!$B$18 -> 0.74114299 | D34: =1-D32/'Base Case Inputs'!$B$18 -> 0.80655181 | E34: =1-E32/'Base Case Inputs'!$B$18 -> 0.80735181 | F34: =1-F32/'Base Case Inputs'!$B$18 -> 0.80735181
B35: YoY Cost Improvement (from Year 2) | C35: =0 -> 0 | D35: =1-D32/C32 -> 0.25268321 | E35: =1-E32/D32 -> 0.0041354742 | F35: =1-F32/E32 -> 0
B37: FY1 shows N/A — no production during ramp-up phase. Meaningful unit economics begin FY2 at ~17.5% of nameplate capacity (157,500 kg). All-in cost drops significantly as production scales toward 900,000 kg/yr.
B39: 3. MARGIN SENSITIVITY ACROSS PRICE ENVIRONMENTS
B40: At full production (Year 3+), showing margin at various H₂ sale prices
B42: H₂ Sale Price | C42: Tobe Cost | D42: Tobe Margin
B43: ='Base Case Inputs'!B19 -> 15 | C43: =C17 -> 4.8361781 | D43: =1-C43/B43 -> 0.67758813
B44: ='Base Case Inputs'!B20 -> 20 | C44: =C17 -> 4.8361781 | D44: =1-C44/B44 -> 0.7581911
B45: ='Base Case Inputs'!B18 -> 25 | C45: =C17 -> 4.8361781 | D45: =1-C45/B45 -> 0.80655288
B46: ='Base Case Inputs'!B21 -> 30 | C46: =C17 -> 4.8361781 | D46: =1-C46/B46 -> 0.83879406
B47: ='Base Case Inputs'!B22 -> 35 | C47: =C17 -> 4.8361781 | D47: =1-C47/B47 -> 0.86182348
B49: Tobe is profitable at every price point.
B51: 4. EQUIPMENT SALES: Electrolyzer Product Line Unit Economics (T-25 · T-125)
B52: Two manufactured products sold to third-party operators. T-25 (25 kg/day) and T-125 (125 kg/day) share the same membrane-less, rare-earth-free stack design. T-25/T-125 validated in Pulse Holdings Quote TE-PH-ELX-88-51 (Jan 9, 2026). All EXW Oklahoma City.
B53: Product Spec | C53: T-25 | D53: T-125 | F53: Source / Note
B54: H₂ Production Capacity | C54: 25 kg/day | D54: 125 kg/day | F54: Pulse Holdings Quote TE-PH-ELX-88-51, Jan 2026
B55: Nameplate Power | C55: 50 kW | D55: 250 kW | F55: Pulse Holdings Quote · Part A (T-25) / Part B (T-125)
B56: Base Unit Price ($/unit) | C56: ='Base Case Inputs'!B27 -> 35000 | D56: ='Base Case Inputs'!B33 -> 167000 | F56: T-25: $25K base ($500/kW, Quote Sec A). T-125: $167K optioned ($120K base + $47K options). Source: Pulse Holdings Quote TE-PH-ELX-88-51.
B57: Manufacturing COGS ($/unit) | C57: ='Learning Curve'!C74 -> 21000 | D57: ='Base Case Inputs'!B33*'Base Case Inputs'!B34 -> 100000 | F57: T-125 COGS declines per Learning Curve ($100K→$77.5K). 40% starting margin benchmarked to Bloom Q4 2024.
C58: Year 2 (2027) | D58: Year 3 (2028) | E58: Year 4 (2029) | F58: Year 5 (2030) | G58: Year 6+ (2031+)
B59: T-25 Units Sold | C59: ='Base Case Inputs'!G30 -> 75 | D59: ='Base Case Inputs'!H30 -> 150 | E59: ='Base Case Inputs'!I30 -> 250 | F59: ='Base Case Inputs'!J30 -> 350 | G59: ='Base Case Inputs'!K30+'Base Case Inputs'!L30 -> 1050
B60: T-125 Units Sold | C60: ='Base Case Inputs'!G36 -> 10 | D60: ='Base Case Inputs'!H36 -> 30 | E60: ='Base Case Inputs'!I36 -> 60 | F60: ='Base Case Inputs'!J36 -> 100 | G60: ='Base Case Inputs'!K36+'Base Case Inputs'!L36 -> 320
B61: (Reserved)
B62: Total Units Sold | C62: =C61+C59+C60 -> 85 | D62: =D61+D59+D60 -> 180 | E62: =E61+E59+E60 -> 310 | F62: =F61+F59+F60 -> 450 | G62: =G61+G59+G60 -> 1370
B63: Equipment Revenue | C63: =C59*'Base Case Inputs'!B$27+C60*'Base Case Inputs'!B$33+C61*'Base Case Inputs'!B$232 -> 4295000 | D63: =D59*'Base Case Inputs'!B$27+D60*'Base Case Inputs'!B$33+D61*'Base Case Inputs'!B$232 -> 10260000 | E63: =E59*'Base Case Inputs'!B$27+E60*'Base Case Inputs'!B$33+E61*'Base Case Inputs'!B$232 -> 18770000 | F63: =F59*'Base Case Inputs'!B$27+F60*'Base Case Inputs'!B$33+F61*'Base Case Inputs'!B$232 -> 28950000 | G63: =G59*'Base Case Inputs'!B$27+G60*'Base Case Inputs'!B$33+G61*'Base Case Inputs'!B$232 -> 90190000
B64: Equipment COGS | C64: =C59*'Learning Curve'!C74+C60*'Learning Curve'!C75+C61*'Learning Curve'!C76 -> 2575000 | D64: =D59*'Learning Curve'!D74+D60*'Learning Curve'!D75+D61*'Learning Curve'!D76 -> 5904000 | E64: =E59*'Learning Curve'!E74+E60*'Learning Curve'!E75+E61*'Learning Curve'!E76 -> 10406250 | F64: =F59*'Learning Curve'!F74+F60*'Learning Curve'!F75+F61*'Learning Curve'!F76 -> 15181250 | G64: =G59*('Learning Curve'!G74+'Learning Curve'!H74)/2+G60*('Learning Curve'!G75+'Learning Curve'!H75)/2+G61*('Learning Curve'!G76+'Learning Curve'!H76)/2 -> 43515625
B65: Equipment Gross Profit | C65: =C63-C64 -> 1720000 | D65: =D63-D64 -> 4356000 | E65: =E63-E64 -> 8363750 | F65: =F63-F64 -> 13768750 | G65: =G63-G64 -> 46674375
B67: Manufacturing Cost-Down (Learning Curve — Wright’s Law). T-25 and T-125 follow proportional trajectories. All products share membrane-less, PGM-free stack design. Source: Tobe BOM analysis; Bloom Energy Q4 2024 benchmarked at 40% product margin.
B68: BOM Cost per Unit | C68: ='Learning Curve'!C75 -> 100000 | D68: ='Learning Curve'!D75 -> 96000 | E68: ='Learning Curve'!E75 -> 92500 | F68: ='Learning Curve'!F75 -> 87500 | G68: ='Learning Curve'!G75 -> 82500
B69: Mfg Learning Curve Savings | C69: — | D69: =1-D68/C68 -> 0.04 | E69: =1-E68/D68 -> 0.036458333 | F69: =1-F68/E68 -> 0.054054054 | G69: =1-G68/F68 -> 0.057142857
B70: Implied Equipment Margin (at cost-down) | C70: =1-C68/'Base Case Inputs'!B33 -> 0.4011976 | D70: =1-D68/'Base Case Inputs'!B33 -> 0.4251497 | E70: =1-E68/'Base Case Inputs'!B33 -> 0.44610778 | F70: =1-F68/'Base Case Inputs'!B33 -> 0.4760479 | G70: =1-G68/'Base Case Inputs'!B33 -> 0.50598802
B72: 5. BLENDED UNIT ECONOMICS: H₂ + Equipment
B73: Two revenue streams: high-margin H₂ production + equipment sales create a diversified technology business
C75: FY1 Apr '26 – Mar '27 | D75: FY2 Apr '27 – Mar '28 | E75: FY3 Apr '28 – Mar '29 | F75: FY4 Apr '29 – Mar '30 | G75: FY5 Apr '30 – Mar '31
B76: H₂ Production Revenue | C76: ='P&L Summary'!C5 -> 0 | D76: ='P&L Summary'!D5 -> 11812500 | E76: ='P&L Summary'!E5 -> 77812500 | F76: ='P&L Summary'!F5 -> 141562500 | G76: ='P&L Summary'!G5 -> 210937500
B77: Equipment Sales Revenue | C77: ='P&L Summary'!C6 -> 807692.31 | D77: ='P&L Summary'!D6 -> 4295000 | E77: ='P&L Summary'!E6 -> 10260000 | F77: ='P&L Summary'!F6 -> 18770000 | G77: ='P&L Summary'!G6 -> 28950000
B78: Production + Equipment Revenue | C78: =C76+C77 -> 807692.31 | D78: =D76+D77 -> 16107500 | E78: =E76+E77 -> 88072500 | F78: =F76+F77 -> 160332500 | G78: =G76+G77 -> 239887500
B79: Equipment Revenue Mix | C79: =IFERROR(C77/C78,0) -> 1 | D79: =IFERROR(D77/D78,0) -> 0.26664597 | E79: =IFERROR(E77/E78,0) -> 0.11649493 | F79: =IFERROR(F77/F78,0) -> 0.11706922 | G79: =IFERROR(G77/G78,0) -> 0.12068157
B81: H₂ Gross Profit | C81: ='P&L Summary'!C5-'P&L Summary'!C15 -> 0 | D81: ='P&L Summary'!D5-'P&L Summary'!D15 -> 10543646 | E81: ='P&L Summary'!E5-'P&L Summary'!E15 -> 68084112 | F81: ='P&L Summary'!F5-'P&L Summary'!F15 -> 1.2262503e+08 | G81: ='P&L Summary'!G5-'P&L Summary'!G15 -> 1.8231588e+08
B82: Equipment Gross Profit | C82: ='P&L Summary'!C6-'P&L Summary'!C16 -> 323076.92 | D82: ='P&L Summary'!D6-'P&L Summary'!D16 -> 1783000 | E82: ='P&L Summary'!E6-'P&L Summary'!E16 -> 4466250 | F82: ='P&L Summary'!F6-'P&L Summary'!F16 -> 8626250 | G82: ='P&L Summary'!G6-'P&L Summary'!G16 -> 14136250
B83: Total Gross Profit | C83: =C81+C82 -> 323076.92 | D83: =D81+D82 -> 12326646 | E83: =E81+E82 -> 72550362 | F83: =F81+F82 -> 1.3125128e+08 | G83: =G81+G82 -> 1.9645213e+08
B84: BLENDED GROSS MARGIN | C84: =IFERROR(C83/C78,0) -> 0.4 | D84: =IFERROR(D83/D78,0) -> 0.76527367 | E84: =IFERROR(E83/E78,0) -> 0.82375727 | F84: =IFERROR(F83/F78,0) -> 0.81861929 | G84: =IFERROR(G83/G78,0) -> 0.81893442
B86: Blended margins improve as equipment BOM declines via learning curve ($100K→$77.5K) on fixed $167K sale price. H₂ production maintains 75%+ margins. Equipment margin starts at 40% and expands to ~50%+ at scale. Key narrative: Tobe's structural moat is distributed production. On-site production within 50 miles eliminates the $2-$4/kg transportation premium that centralized SMR producers pay. Grey H₂ all-in delivered: $4.50-$6.50/kg. Tobe all-in: $4.40/kg. Source: NREL ATB 2025; Brattle Group Feb 2024.

Sheet Fundraising
B1: TOBE ENERGY — FUNDRAISING STORY
B2: $510M equity across 5 rounds · $734M total capital · Seed → Series D → IPO / Strategic Exit
F3: ⚠ ILLUSTRATIVE — NOT MODELED. Series D capital is NOT included in the Financials, Balance Sheet, or Cash Flow projections. The 7-year model covers Seed through Series C only.
B4: 1 · FUNDRAISING WATERFALL
C5: Pre-Seed | D5: Seed ★ | E5: Series A | F5: Series B | G5: Series C | H5: Series D / Growth
B6: Timing | C6: Oct 2025 | D6: May 2026 | E6: Jun 2027 | F6: Q1 2029 | G6: Q1 2031 | H6: Q1 2033
B7: Pre-Money Valuation | C7: 8000000 | D7: 40000000 | E7: 210000000 | F7: 500000000 | G7: 1500000000 | H7: 3500000000 | I7: Series D NOT MODELED - shown for illustrative purposes only
B8: Equity Raised | C8: ='Base Case Inputs'!B86 -> 2050000 | D8: ='Base Case Inputs'!B42 -> 7500000 | E8: ='Base Case Inputs'!B47 -> 40000000 | F8: ='Base Case Inputs'!B52 -> 60000000 | G8: ='Base Case Inputs'!B56 -> 150000000 | H8: 250000000
B9: Debt / Project Finance | C9: 0 | D9: ='Base Case Inputs'!B43+'Base Case Inputs'!B44 -> 2500000 | E9: ='Base Case Inputs'!B49+'Base Case Inputs'!B48 -> 17000000 | F9: ='Base Case Inputs'!B53 -> 30000000 | G9: ='Base Case Inputs'!B57 -> 75000000 | H9: 100000000
B10: Total Capital This Round | C10: =C8+C9 -> 2050000 | D10: =D8+D9 -> 10000000 | E10: =E8+E9 -> 57000000 | F10: =F8+F9 -> 90000000 | G10: =G8+G9 -> 225000000 | H10: =H8+H9 -> 350000000
B11: Post-Money Valuation | C11: =C7+C8 -> 10050000 | D11: =D7+D8 -> 47500000 | E11: =E7+E8 -> 250000000 | F11: =F7+F8 -> 560000000 | G11: =G7+G8 -> 1650000000 | H11: =H7+H8 -> 3750000000
B12: Valuation Step-Up | C12: — | D12: 4.0x | E12: 4.4x | F12: =IFERROR(TEXT(F7/E11,"0.0x"),"—") -> 2.0x | G12: =IFERROR(TEXT(G7/F11,"0.0x"),"—") -> 2.7x | H12: 2.1x
B14: 2 · USE OF CAPITAL — WHAT EACH ROUND FUNDS
B15: Pre-Seed | C15: 45931 | D15: SAFEs — bridge to Seed. Technology validation, patent filings, initial team.
B16: Seed ★ | C16: 46143 | D16: Facility 1 (Tulsa) buildout · Manufacturing pilot · First T-125 units · Core team of 20
B17: Series A | C17: 46539 | D17: Facilities 2–3 · T-125 scale-up launch · Next-gen R&D kickoff · Manufacturing scale to 150+ T-25 units/yr · Team → 66
B18: Series B | C18: Q1 2029 | D18: Facilities 4–7 · T-125 commercial scale · Regional expansion · Team → 109
B19: Series C | C19: Q1 2031 | D19: Facilities 8–12 · T-125 at commercial scale · National footprint · Revenue run-rate $280M+ · Team → 223
B20: Series D / Growth | C20: Q1 2033 | D20: Pre-IPO acceleration · International expansion · $397M+ revenue · 326 FTEs
B23: 3 · IMPLIED EXIT — IPO / STRATEGIC ACQUISITION
C24: Bear (8x Rev) | D24: Base (10x Rev) | E24: Bull (12x Rev) | G24: Bear (15x EBITDA) | H24: Base (20x EBITDA) | I24: Bull (25x EBITDA)
B25: Y7 Revenue / EBITDA Basis | C25: ='P&L Summary'!I9 -> 3.2765485e+08 | D25: ='P&L Summary'!I9 -> 3.2765485e+08 | E25: ='P&L Summary'!I9 -> 3.2765485e+08 | G25: ='P&L Summary'!I32 -> 2.1599511e+08 | H25: ='P&L Summary'!I32 -> 2.1599511e+08 | I25: ='P&L Summary'!I32 -> 2.1599511e+08
B26: Implied Enterprise Value | C26: =C25*8 -> 2.6212388e+09 | D26: =D25*10 -> 3.2765485e+09 | E26: =E25*12 -> 3.9318582e+09 | G26: =G25*15 -> 3.2399267e+09 | H26: =H25*20 -> 4.3199022e+09 | I26: =I25*25 -> 5.3998778e+09
B27: vs. Series D Pre-Money ($3.5B) | C27: =IFERROR(TEXT(C26/H7,"0.0x"),"—") -> 0.7x | D27: =IFERROR(TEXT(D26/H7,"0.0x"),"—") -> 0.9x | E27: =IFERROR(TEXT(E26/H7,"0.0x"),"—") -> 1.1x | G27: =IFERROR(TEXT(G26/H7,"0.0x"),"—") -> 0.9x | H27: =IFERROR(TEXT(H26/H7,"0.0x"),"—") -> 1.2x | I27: =IFERROR(TEXT(I26/H7,"0.0x"),"—") -> 1.5x
B29: ★ Current round · Seed investor ownership at exit ~10.8% (post-Series C dilution) · Trajectory benchmarked to Fervo Energy: Pre-Seed → Seed → A → B → C → IPO / Strategic Exit | G29: Seed ownership calc (post-Series C) | H29: =D8/D11*E7/E11*F7/(F7+F8)*G7/G11 -> 0.1076555

Sheet Use of Funds
B1: 1. SEED ROUND — CAPITAL STRUCTURE
C2: Amount ($) | D2: % of Total | F2: Notes
B3: Equity Financing | C3: ='Base Case Inputs'!B42 -> 7500000 | D3: =C3/C5 -> 0.75 | F3: Priced equity round (Seed)
B4: Debt Financing | C4: ='Base Case Inputs'!B43 -> 2500000 | D4: =C4/C5 -> 0.25 | F4: Venture debt / revenue-based financing; secured by project assets
B5: TOTAL SEED CAPITAL | C5: =C3+C4 -> 10000000 | D5: =C5/C5 -> 1
B7: 2. EQUITY USE OF FUNDS
B8: Category | C8: Budget ($) | D8: % of Equity | E8: Hire Mo | F8: Notes / Milestone
B9: R&D: T-125 System Validation
B10: Stack design, materials, & prototype iteration | C10: 450000 | F10: Cell/stack architecture for commercial-scale 125 kg/day
B11: System integration & BOP engineering | C11: 300000 | F11: Power electronics, thermal management, water/gas handling
B12: Testing & commissioning (at Zeeco facility) | C12: 200000 | F12: $1.1M total R&D — $1.875M saved vs. standalone facility electrical upgrades
B13: Certification test specimens & destructive testing | C13: 150000 | F13: ASME, DOT test articles
B14: Subtotal: R&D | C14: =SUM(C10:C13) -> 1100000 | D14: =C14/C3 -> 0.14666667
B16: Manufacturing Equipment & Automation
B17: 5-Axis CNC Machine (#2) | C17: 140000 | F17: Second unit for production throughput
B18: CNC Lathe (precision electrode/manifold work) | C18: 95000 | F18: Turning operations for cylindrical components
B19: CNC Transformer Winder (#2) | C19: 90000 | F19: Coil winding for power electronics
B20: Laser Cutter / Waterjet | C20: 120000 | F20: Plate cutting for bipolar plates, gaskets, enclosures
B21: Welding Automation (TIG/MIG cell) | C21: 150000 | F21: Automated TIG/MIG cell + orbital welding for pressure circuits
B22: Assembly fixtures, jigs, & tooling | C22: 110000 | F22: Custom production tooling & work-holding fixtures
B23: 3D Printer (Industrial — metal/polymer) | C23: 85000 | F23: Rapid prototyping, custom fittings, test fixtures
B24: Electronics test & lab equipment | C24: 80000 | F24: Oscilloscopes, power analyzers, impedance spectroscopy, DAQ
B25: CAD/CAM/PLM Software Licenses | C25: 100000 | F25: SolidWorks, Mastercam, Arena PLM
B26: Spares & replacement parts inventory | C26: 100000 | F26: Critical spares for production uptime: electrodes, membranes, seals, gaskets
B27: Safety equipment & infrastructure | C27: 50000 | F27: H₂ leak detection, ventilation, fire suppression, PPE, safety signage
B28: Subtotal: Manufacturing Equipment | C28: =SUM(C17:C27) -> 1120000 | D28: =C28/C3 -> 0.14933333
B30: Personnel (15-Month Seed Period)
B31: Benefits Loading % | C31: ='Base Case Inputs'!$B$75 -> 0.3736 | F31: From Base Case Inputs B75 (benefits loading)
B32: Role | C32: Annual Base ($) | D32: Monthly Loaded | E32: Hire Mo | F32: Seed Period Cost (to Mo 15)
B33: Existing Team (7 FTEs) | C33: 665000 | D33: =C33*(1+$C$31)/12 -> 76120.333 | E33: Existing | F33: =D33*15 -> 1141805
B34: Sales Representative | C34: 95000 | D34: =C34*(1+$C$31)/12 -> 10874.333 | E34: Mo 2 | F34: =D34*14 -> 152240.67
B35: Electrical Engineer | C35: 110000 | D35: =C35*(1+$C$31)/12 -> 12591.333 | E35: Mo 3 | F35: =D35*13 -> 163687.33
B36: Mechanical Engineer | C36: 110000 | D36: =C36*(1+$C$31)/12 -> 12591.333 | E36: Mo 3 | F36: =D36*13 -> 163687.33
B37: Chemical Engineer | C37: 110000 | D37: =C37*(1+$C$31)/12 -> 12591.333 | E37: Mo 4 | F37: =D37*12 -> 151096
B38: Electrical Technician | C38: 85000 | D38: =C38*(1+$C$31)/12 -> 9729.6667 | E38: Mo 4 | F38: =D38*12 -> 116756
B39: Mechanical Technician | C39: 85000 | D39: =C39*(1+$C$31)/12 -> 9729.6667 | E39: Mo 5 | F39: =D39*11 -> 107026.33
B40: Chemical Technician | C40: 80000 | D40: =C40*(1+$C$31)/12 -> 9157.3333 | E40: Mo 6 | F40: =D40*10 -> 91573.333
B41: Field Service Install Technician | C41: 90000 | D41: =C41*(1+$C$31)/12 -> 10302 | E41: Mo 4 | F41: =D41*12 -> 123624
B42: Subtotal: Personnel | D42: =F42/C3 -> 0.29486613 | F42: =SUM(F33:F41) -> 2211496
B44: Certifications & Compliance
B45: ASME Hydrogen Equipment Certification | C45: 125000 | F45: Mo 2–8: Pressure vessel stamps, piping code compliance
B46: DOT Transport Certification | C46: 125000 | F46: Mo 3–10: Tube trailer & cylinder certification
B47: State/Local Permitting & Environmental | C47: 100000 | F47: Mo 1–4: Zoning, air quality, fire marshal, SPCC plan
B48: ISO 9001 / Quality System Setup | C48: 75000 | F48: Quality management system for manufacturing
B49: Third-party Testing / Independent Validation | C49: 50000 | F49: Independent performance & safety validation by accredited test lab
B50: Subtotal: Certifications | C50: =SUM(C45:C49) -> 475000 | D50: =C50/C3 -> 0.063333333
B52: Working Capital & G&A
B53: Operating runway buffer (~3.6 months based on FY1 avg OpEx) | C53: 900000 | F53: Bridge to Series A close at Mo 15 (Jun 2027)
B54: Insurance (GL, product liability, D&O, P&E, WC) | C54: 150000 | F54: GL, product liability, property & equipment coverage, workers' comp, D&O
B55: Legal & Professional Fees | C55: 230000 | F55: IP filings, patent prosecution, FTO analysis, employment law, investor counsel, accounting/audit
B56: HQ / Mfg Facility Lease | C56: 131250 | F56: $8,750/mo × 15 months
B57: Sales, Marketing & Business Development | C57: 200000 | F57: Customer site visits, conferences, trade shows, pilot demos, market development
B58: Software & IT Infrastructure | C58: 110000 | F58: Cloud hosting, SaaS, ERP/MRP, cybersecurity tools
B59: Recruiting & HR | C59: 110000 | F59: Recruiting fees, onboarding, HRIS, safety & skills training
B60: Fundraising & Investor Relations | C60: 80000 | F60: Executive & investor relations travel
B61: Subtotal: Working Capital & G&A | C61: =SUM(C53:C60) -> 1911250 | D61: =C61/C3 -> 0.25483333
B62: Contingency & Reserve
B63: Contingency | C63: =0.10007031649463*(C14+C28+F42+C50+C61) -> 682254 | D63: =C63/C3 -> 0.0909672 | F63: Standard 10% contingency on all equity-funded line items
B66: TOTAL EQUITY USE OF FUNDS | C66: =C14+C28+F42+C50+C61+C63 -> 7500000 | D66: =C66/C3 -> 1
B67: Equity Surplus / (Deficit) | C67: =C3-C66 -> 0
B70: 3. DEBT USE OF FUNDS — ZEECO FACILITY PROJECT
B71: Category | C71: Budget ($) | D71: % of Debt | F71: Notes
B72: Electrical Utility Float (Zeeco)
B73: Ramp-up period (Mo 1-6, avg 50% load) | C73: 16538 | F73: ~$2,756/mo avg; 62.5 kg/day × 42 kWh/kg × 30d × $0.035
B74: Full production (Mo 7-15, 125 kg/day) | C74: 49613 | F74: $5,513/mo × 9 months; 125 kg/day × 42 kWh/kg × 30d × $0.035
B75: Facility HVAC, lighting, & aux loads (15 mo) | C75: 45000 | F75: ~$3,000/mo for shop/office HVAC, compressors, ventilation
B76: Subtotal: Electrical Utility Float | C76: =SUM(C73:C75) -> 111151 | D76: =C76/C4 -> 0.0444604
B78: Water & Consumables (Zeeco)
B79: DI water system consumables & supply | C79: 18000 | F79: ~$1,200/mo; RO membrane replacement, resin, municipal water
B80: KOH / electrolyte chemicals | C80: 12000 | F80: ~$800/mo; alkaline electrolyte replenishment
B81: Waste treatment & discharge permits | C81: 8000 | F81: Wastewater neutralization, monitoring, discharge compliance
B82: Subtotal: Water & Consumables | C82: =SUM(C79:C81) -> 38000 | D82: =C82/C4 -> 0.0152
B84: Zeeco Project CAPEX (Debt-Secured)
B85: Electrolyzer system installation (125 kg/day) | C85: 700000 | F85: T-125 system placed at Zeeco; secured asset for lender
B86: H₂ compression & storage skid | C86: 417000 | F86: Compressor ($250K) + cascade storage ($167K)
B87: BOP: piping, valves, safety systems, dispensing | C87: 280000 | F87: Dispensing ($150K) + water treatment ($50K) + safety ($30K) + piping ($50K)
B88: Electrical installation & interconnect | C88: 100000 | F88: Power wiring, switchgear, controls — savings vs standalone facility
B89: Mechanical installation & commissioning | C89: 200000 | F89: Piping install ($150K) + commissioning/startup ($50K)
B90: Contingency (15%) | C90: =0.15*SUM(C85:C89) -> 254550 | F90: Standard project contingency on hard costs
B91: Subtotal: Zeeco Project CAPEX | C91: =SUM(C85:C90) -> 1951550 | D91: =C91/C4 -> 0.78062
B93: Debt Service & Reserve
B94: Interest reserve (6 mo I/O @ 7%) | C94: =C4*'Base Case Inputs'!$B$62/12*'Base Case Inputs'!$B$64 -> 87500 | F94: Per Base Case Inputs: 7% rate, 6 months interest-only
B95: Loan origination & legal fees | C95: 50000 | F95: ~2% origination + counsel
B96: Subtotal: Debt Service & Reserve | C96: =SUM(C94:C95) -> 137500 | D96: =C96/C4 -> 0.055
B98: Debt Working Capital Reserve | F98: Buffer for project cost overruns and schedule variance
B99: Project working capital reserve | C99: 261799 | F99: Covers schedule delays, change orders
B100: Subtotal: Debt Working Capital Reserve | C100: =C99 -> 261799 | D100: =C100/C4 -> 0.1047196
B102: TOTAL DEBT USE OF FUNDS | C102: =C76+C82+C91+C96+C100 -> 2500000 | D102: =C102/C4 -> 1
B103: Debt Surplus / (Deficit) | C103: =C4-C102 -> 0
B105: 4. COMBINED SEED ROUND SUMMARY
C106: Equity ($) | D106: Debt ($) | E106: Total ($) | F106: % of Total Raise
B107: R&D: 125 kg/day System | C107: =C14 -> 1100000 | D107: 0 | E107: =C107+D107 -> 1100000 | F107: =E107/C5 -> 0.11
B108: Manufacturing Equipment | C108: =C28 -> 1120000 | D108: 0 | E108: =C108+D108 -> 1120000 | F108: =E108/C5 -> 0.112
B109: Personnel (15-month) | C109: =F42 -> 2211496 | D109: 0 | E109: =C109+D109 -> 2211496 | F109: =E109/C5 -> 0.2211496
B110: Certifications & Compliance | C110: =C50 -> 475000 | D110: 0 | E110: =C110+D110 -> 475000 | F110: =E110/C5 -> 0.0475
B111: Working Capital & G&A | C111: =C61 -> 1911250 | D111: 0 | E111: =C111+D111 -> 1911250 | F111: =E111/C5 -> 0.191125
B112: Contingency & Reserve | C112: =C63 -> 682254 | D112: 0 | E112: =C112+D112 -> 682254 | F112: =E112/C5 -> 0.0682254
B113: Debt Working Capital Reserve | C113: 0 | D113: =C100 -> 261799 | E113: =C113+D113 -> 261799 | F113: =E113/C5 -> 0.0261799
B114: Zeeco Electrical Utility Float | C114: 0 | D114: =C76 -> 111151 | E114: =C114+D114 -> 111151 | F114: =E114/C5 -> 0.0111151
B115: Zeeco Water & Consumables | C115: 0 | D115: =C82 -> 38000 | E115: =C115+D115 -> 38000 | F115: =E115/C5 -> 0.0038
...

Sheet Tax Credits
B1: TAX CREDITS & SENSITIVITY ANALYSIS
B2: 45V Production Tax Credit · H₂ price sensitivity · facility ramp speed · facility buildout pace · combined scenario tables. Scenario B (premium geography) parked — review with Lou. Scenario C (tube trailer fleet) parked to Notes tab.
B5: SCENARIO A: 45V PRODUCTION TAX CREDIT
B6: $3/kg federal credit for qualifying green H₂ (IRA §45V). 10-year credit per facility. Begin-construction deadline Dec 2027. Toggle: Base Case Inputs.
C7: FY1 Apr '26 – Mar '27 | D7: FY2 Apr '27 – Mar '28 | E7: FY3 Apr '28 – Mar '29 | F7: FY4 Apr '29 – Mar '30 | G7: FY5 Apr '30 – Mar '31
B8: PTC Revenue ($3/kg) | C8: =SUM('Model Assumptions'!G69:R69) -> 0 | D8: =SUM('Model Assumptions'!S69:AD69) -> 1417500 | E8: =SUM('Model Assumptions'!AE69:AP69) -> 8887500 | F8: =SUM('Model Assumptions'!AQ69:BB69) -> 10800000 | G8: =SUM('Model Assumptions'!BC69:BN69) -> 10800000
B9: Total H₂ Production (kg) | C9: =SUM('Model Assumptions'!G15:R15)+SUM('Model Assumptions'!G23:R23)+SUM('Model Assumptions'!G31:R31)+SUM('Model Assumptions'!G39:R39)+SUM('Model Assumptions'!G47:R47)+SUM('Model Assumptions'!G55:R55)+SUM('Model Assumptions'!G63:R63) -> 0 | D9: =SUM('Model Assumptions'!S15:AD15)+SUM('Model Assumptions'!S23:AD23)+SUM('Model Assumptions'!S31:AD31)+SUM('Model Assumptions'!S39:AD39)+SUM('Model Assumptions'!S47:AD47)+SUM('Model Assumptions'!S55:AD55)+SUM('Model Assumptions'!S63:AD63) -> 472500 | E9: =SUM('Model Assumptions'!AE15:AP15)+SUM('Model Assumptions'!AE23:AP23)+SUM('Model Assumptions'!AE31:AP31)+SUM('Model Assumptions'!AE39:AP39)+SUM('Model Assumptions'!AE47:AP47)+SUM('Model Assumptions'!AE55:AP55)+SUM('Model Assumptions'!AE63:AP63) -> 3112500 | F9: =SUM('Model Assumptions'!AQ15:BB15)+SUM('Model Assumptions'!AQ23:BB23)+SUM('Model Assumptions'!AQ31:BB31)+SUM('Model Assumptions'!AQ39:BB39)+SUM('Model Assumptions'!AQ47:BB47)+SUM('Model Assumptions'!AQ55:BB55)+SUM('Model Assumptions'!AQ63:BB63) -> 5662500 | G9: =SUM('Model Assumptions'!BC15:BN15)+SUM('Model Assumptions'!BC23:BN23)+SUM('Model Assumptions'!BC31:BN31)+SUM('Model Assumptions'!BC39:BN39)+SUM('Model Assumptions'!BC47:BN47)+SUM('Model Assumptions'!BC55:BN55)+SUM('Model Assumptions'!BC63:BN63) -> 8437500
B10: Incremental EBITDA from PTC | C10: =C8 -> 0 | D10: =D8 -> 1417500 | E10: =E8 -> 8887500 | F10: =F8 -> 10800000 | G10: =G8 -> 10800000
B11: Cumulative PTC Cash | C11: =C8 -> 0 | D11: =C11+D8 -> 1417500 | E11: =D11+E8 -> 10305000 | F11: =E11+F8 -> 21105000 | G11: =F11+G8 -> 31905000
B13: The PTC is pure margin — no incremental COGS. Adds $3/kg to every qualifying kg produced. Toggle in Base Case Inputs.
B16: SCENARIO UPSIDE SUMMARY
C17: FY1 Apr '26 – Mar '27 | D17: FY2 Apr '27 – Mar '28 | E17: FY3 Apr '28 – Mar '29 | F17: FY4 Apr '29 – Mar '30 | G17: FY5 Apr '30 – Mar '31
B18: A: 45V PTC Revenue | C18: =C8 -> 0 | D18: =D8 -> 1417500 | E18: =E8 -> 8887500 | F18: =F8 -> 10800000 | G18: =G8 -> 10800000
B19: TOTAL UPSIDE vs. BASE | C19: =C8 -> 0 | D19: =D8 -> 1417500 | E19: =E8 -> 8887500 | F19: =F8 -> 10800000 | G19: =G8 -> 10800000
B21: Additional scenarios (e.g. premium geographies, fleet) may be added here once validated.
B23: BASE CASE ANNUAL SUMMARY (from Core Financials Engine)
B24: All figures sourced directly from P&L Summary / Financials. No parallel calculations — single source of truth.
C25: FY1 Apr '26 – Mar '27 | D25: FY2 Apr '27 – Mar '28 | E25: FY3 Apr '28 – Mar '29 | F25: FY4 Apr '29 – Mar '30 | G25: FY5 Apr '30 – Mar '31 | H25: Source
B26: Total Revenue | C26: ='P&L Summary'!C9 -> 807692.31 | D26: ='P&L Summary'!D9 -> 16140312 | E26: ='P&L Summary'!E9 -> 88314613 | F26: ='P&L Summary'!F9 -> 1.611807e+08 | G26: ='P&L Summary'!G9 -> 2.4197978e+08 | H26: P&L Summary row 10
B27: H₂ Revenue | C27: ='P&L Summary'!C5 -> 0 | D27: ='P&L Summary'!D5 -> 11812500 | E27: ='P&L Summary'!E5 -> 77812500 | F27: ='P&L Summary'!F5 -> 141562500 | G27: ='P&L Summary'!G5 -> 210937500 | H27: P&L Summary row 6
B28: Equipment + Services + 45V | C28: ='P&L Summary'!C6+'P&L Summary'!C7+'P&L Summary'!C8 -> 807692.31 | D28: ='P&L Summary'!D6+'P&L Summary'!D7+'P&L Summary'!D8 -> 5745312.5 | E28: ='P&L Summary'!E6+'P&L Summary'!E7+'P&L Summary'!E8 -> 19389613 | F28: ='P&L Summary'!F6+'P&L Summary'!F7+'P&L Summary'!F8 -> 30418205 | G28: ='P&L Summary'!G6+'P&L Summary'!G7+'P&L Summary'!G8 -> 41842281 | H28: P&L Summary rows 7+8+9
B29: Total COGS | C29: ='P&L Summary'!C18 -> 484615.38 | D29: ='P&L Summary'!D18 -> 3787416.9 | E29: ='P&L Summary'!E18 -> 15570561 | F29: ='P&L Summary'!F18 -> 29250863 | G29: ='P&L Summary'!G18 -> 43853825 | H29: P&L Summary row 18
B30: Total OpEx | C30: ='P&L Summary'!C29 -> 3001178.2 | D30: ='P&L Summary'!D29 -> 8594842.7 | E30: ='P&L Summary'!E29 -> 17840599 | F30: ='P&L Summary'!F29 -> 26337754 | G30: ='P&L Summary'!G29 -> 37413009 | H30: P&L Summary row 29 (incl R&D, Site Occ)
B31: EBITDA | C31: ='P&L Summary'!C32 -> -2678101.3 | D31: ='P&L Summary'!D32 -> 3758052.9 | E31: ='P&L Summary'!E32 -> 54903453 | F31: ='P&L Summary'!F32 -> 1.0559209e+08 | G31: ='P&L Summary'!G32 -> 1.6071295e+08 | H31: P&L Summary row 32
B32: EBITDA Margin | C32: =IFERROR(C31/C26,0) -> -3.3157445 | D32: =IFERROR(D31/D26,0) -> 0.23283644 | E32: =IFERROR(E31/E26,0) -> 0.62168028 | F32: =IFERROR(F31/F26,0) -> 0.65511618 | G32: =IFERROR(G31/G26,0) -> 0.66415858 | H32: EBITDA / Revenue
B33: Net Income | C33: ='P&L Summary'!C42 -> -2808010 | D33: ='P&L Summary'!D42 -> 3368531.2 | E33: ='P&L Summary'!E42 -> 44778378 | F33: ='P&L Summary'!F42 -> 81963063 | G33: ='P&L Summary'!G42 -> 1.2031146e+08 | H33: P&L Summary row 41
B34: Year-End Cash | C34: =Financials!P101 -> 1289092.1 | D34: =Financials!AB101 -> 49613513 | E34: =Financials!AN101 -> 1.3948772e+08 | F34: =Financials!AZ101 -> 2.241518e+08 | G34: =Financials!BL101 -> 4.7838468e+08 | H34: Financials row 97
B35: H₂ Production Vol (kg) | C35: =IFERROR(C27/'Base Case Inputs'!$B$18,0) -> 0 | D35: =IFERROR(D27/'Base Case Inputs'!$B$18,0) -> 472500 | E35: =IFERROR(E27/'Base Case Inputs'!$B$18,0) -> 3112500 | F35: =IFERROR(F27/'Base Case Inputs'!$B$18,0) -> 5662500 | G35: =IFERROR(G27/'Base Case Inputs'!$B$18,0) -> 8437500 | H35: H₂ Rev ÷ base price
B36: R&D | C36: ='Base Case Inputs'!B135 -> 962750 | D36: ='Base Case Inputs'!B136 -> 2387000 | E36: ='Base Case Inputs'!B137 -> 2150000 | F36: ='Base Case Inputs'!B138 -> 600000 | G36: ='Base Case Inputs'!B139 -> 750000 | H36: BCI rows 117-121
B37: Blended Variable Cost Rate | C37: =IFERROR('Base Case Inputs'!$B$76+'Base Case Inputs'!$B$77+C36/C26,0) -> 1.2419762 | D37: =IFERROR('Base Case Inputs'!$B$76+'Base Case Inputs'!$B$77+D36/D26,0) -> 0.19789057 | E37: =IFERROR('Base Case Inputs'!$B$76+'Base Case Inputs'!$B$77+E36/E26,0) -> 0.074344782 | F37: =IFERROR('Base Case Inputs'!$B$76+'Base Case Inputs'!$B$77+F36/F26,0) -> 0.05372253 | G37: =IFERROR('Base Case Inputs'!$B$76+'Base Case Inputs'!$B$77+G36/G26,0) -> 0.053099433 | H37: 3% + 2% + R&D/Revenue
B39: SENSITIVITY 1: H₂ SALE PRICE (Engine-Referenced)
B40: EBITDA = Core EBITDA + (SensPrice/BasePrice − 1) × H₂ Rev × (1 − VarCostRate). Exact match at $25/kg. Revenue & EBITDA shown per scenario.
C41: FY1 Apr '26 – Mar '27 | D41: FY2 Apr '27 – Mar '28 | E41: FY3 Apr '28 – Mar '29 | F41: FY4 Apr '29 – Mar '30 | G41: FY5 Apr '30 – Mar '31
B42: $15/kg (Bear)
B43: Revenue | C43: =IFERROR(C27*('Base Case Inputs'!$B$19/'Base Case Inputs'!$B$18)+C28,0) -> 807692.31 | D43: =IFERROR(D27*('Base Case Inputs'!$B$19/'Base Case Inputs'!$B$18)+D28,0) -> 12832812 | E43: =IFERROR(E27*('Base Case Inputs'!$B$19/'Base Case Inputs'!$B$18)+E28,0) -> 66077113 | F43: =IFERROR(F27*('Base Case Inputs'!$B$19/'Base Case Inputs'!$B$18)+F28,0) -> 1.153557e+08 | G43: =IFERROR(G27*('Base Case Inputs'!$B$19/'Base Case Inputs'!$B$18)+G28,0) -> 1.6840478e+08 | H43: H₂ repriced + Equip+Svc+45V
B44: EBITDA | C44: =IFERROR(C31+('Base Case Inputs'!$B$19/'Base Case Inputs'!$B$18-1)*C27*(1-C37),0) -> -2678101.3 | D44: =IFERROR(D31+('Base Case Inputs'!$B$19/'Base Case Inputs'!$B$18-1)*D27*(1-D37),0) -> -31914.137 | E44: =IFERROR(E31+('Base Case Inputs'!$B$19/'Base Case Inputs'!$B$18-1)*E27*(1-E37),0) -> 26092435 | F44: =IFERROR(F31+('Base Case Inputs'!$B$19/'Base Case Inputs'!$B$18-1)*F27*(1-F37),0) -> 52009126 | G44: =IFERROR(G31+('Base Case Inputs'!$B$19/'Base Case Inputs'!$B$18-1)*G27*(1-G37),0) -> 80818211 | H44: Core EBITDA + Δ adjustment
B45: $20/kg
B46: Revenue | C46: =IFERROR(C27*('Base Case Inputs'!$B$20/'Base Case Inputs'!$B$18)+C28,0) -> 807692.31 | D46: =IFERROR(D27*('Base Case Inputs'!$B$20/'Base Case Inputs'!$B$18)+D28,0) -> 15195312 | E46: =IFERROR(E27*('Base Case Inputs'!$B$20/'Base Case Inputs'!$B$18)+E28,0) -> 81639613 | F46: =IFERROR(F27*('Base Case Inputs'!$B$20/'Base Case Inputs'!$B$18)+F28,0) -> 1.436682e+08 | G46: =IFERROR(G27*('Base Case Inputs'!$B$20/'Base Case Inputs'!$B$18)+G28,0) -> 2.1059228e+08
B47: EBITDA | C47: =IFERROR(C31+('Base Case Inputs'!$B$20/'Base Case Inputs'!$B$18-1)*C27*(1-C37),0) -> -2678101.3 | D47: =IFERROR(D31+('Base Case Inputs'!$B$20/'Base Case Inputs'!$B$18-1)*D27*(1-D37),0) -> 1863069.4 | E47: =IFERROR(E31+('Base Case Inputs'!$B$20/'Base Case Inputs'!$B$18-1)*E27*(1-E37),0) -> 40497944 | F47: =IFERROR(F31+('Base Case Inputs'!$B$20/'Base Case Inputs'!$B$18-1)*F27*(1-F37),0) -> 78800607 | G47: =IFERROR(G31+('Base Case Inputs'!$B$20/'Base Case Inputs'!$B$18-1)*G27*(1-G37),0) -> 1.2076558e+08
B48: $25/kg (Base Case)
B49: Revenue | C49: =C26 -> 807692.31 | D49: =D26 -> 16140312 | E49: =E26 -> 88314613 | F49: =F26 -> 1.611807e+08 | G49: =G26 -> 2.4197978e+08 | H49: Zero delta = base case
B50: EBITDA | C50: =C31 -> -2678101.3 | D50: =D31 -> 3758052.9 | E50: =E31 -> 54903453 | F50: =F31 -> 1.0559209e+08 | G50: =G31 -> 1.6071295e+08 | H50: Exact match to core engine
B51: $30/kg
B52: Revenue | C52: =IFERROR(C27*('Base Case Inputs'!$B$21/'Base Case Inputs'!$B$18)+C28,0) -> 807692.31 | D52: =IFERROR(D27*('Base Case Inputs'!$B$21/'Base Case Inputs'!$B$18)+D28,0) -> 19920312 | E52: =IFERROR(E27*('Base Case Inputs'!$B$21/'Base Case Inputs'!$B$18)+E28,0) -> 1.1276461e+08 | F52: =IFERROR(F27*('Base Case Inputs'!$B$21/'Base Case Inputs'!$B$18)+F28,0) -> 2.002932e+08 | G52: =IFERROR(G27*('Base Case Inputs'!$B$21/'Base Case Inputs'!$B$18)+G28,0) -> 2.9496728e+08
B53: EBITDA | C53: =IFERROR(C31+('Base Case Inputs'!$B$21/'Base Case Inputs'!$B$18-1)*C27*(1-C37),0) -> -2678101.3 | D53: =IFERROR(D31+('Base Case Inputs'!$B$21/'Base Case Inputs'!$B$18-1)*D27*(1-D37),0) -> 5653036.5 | E53: =IFERROR(E31+('Base Case Inputs'!$B$21/'Base Case Inputs'!$B$18-1)*E27*(1-E37),0) -> 69308963 | F53: =IFERROR(F31+('Base Case Inputs'!$B$21/'Base Case Inputs'!$B$18-1)*F27*(1-F37),0) -> 1.3238357e+08 | G53: =IFERROR(G31+('Base Case Inputs'!$B$21/'Base Case Inputs'!$B$18-1)*G27*(1-G37),0) -> 2.0066031e+08
B54: $35/kg (Bull)
B55: Revenue | C55: =IFERROR(C27*('Base Case Inputs'!$B$22/'Base Case Inputs'!$B$18)+C28,0) -> 807692.31 | D55: =IFERROR(D27*('Base Case Inputs'!$B$22/'Base Case Inputs'!$B$18)+D28,0) -> 22282812 | E55: =IFERROR(E27*('Base Case Inputs'!$B$22/'Base Case Inputs'!$B$18)+E28,0) -> 1.2832711e+08 | F55: =IFERROR(F27*('Base Case Inputs'!$B$22/'Base Case Inputs'!$B$18)+F28,0) -> 2.286057e+08 | G55: =IFERROR(G27*('Base Case Inputs'!$B$22/'Base Case Inputs'!$B$18)+G28,0) -> 3.3715478e+08
B56: EBITDA | C56: =IFERROR(C31+('Base Case Inputs'!$B$22/'Base Case Inputs'!$B$18-1)*C27*(1-C37),0) -> -2678101.3 | D56: =IFERROR(D31+('Base Case Inputs'!$B$22/'Base Case Inputs'!$B$18-1)*D27*(1-D37),0) -> 7548020 | E56: =IFERROR(E31+('Base Case Inputs'!$B$22/'Base Case Inputs'!$B$18-1)*E27*(1-E37),0) -> 83714472 | F56: =IFERROR(F31+('Base Case Inputs'!$B$22/'Base Case Inputs'!$B$18-1)*F27*(1-F37),0) -> 1.5917505e+08 | G56: =IFERROR(G31+('Base Case Inputs'!$B$22/'Base Case Inputs'!$B$18-1)*G27*(1-G37),0) -> 2.4060768e+08
B57: All EBITDA figures reference core engine. Formula: EBITDA(P) = Core EBITDA + (P/BasePrice - 1) x H2 Rev x (1 - VarCostRate). VarCostRate = 3% ProfFees + 2% Other + R&D rate.
B58: SENSITIVITY 2: FACILITY RAMP SPEED (Engine-Referenced)
B59: Ramp speed affects H2 production volume. EBITDA delta = volume change x (H2 margin - variable cost rate). Equipment sales are independent of ramp timing.
C60: FY1 Apr '26 – Mar '27 | D60: FY2 Apr '27 – Mar '28 | E60: FY3 Apr '28 – Mar '29 | F60: FY4 Apr '29 – Mar '30 | G60: FY5 Apr '30 – Mar '31
B61: 6-Month Delay (0.7x→0.9x graduated vol)
B62: Prod Multiplier | C62: 1 | D62: 0.7 | E62: 0.8 | F62: 0.85 | G62: 0.9
B63: EBITDA | C63: =IFERROR(C31+(C62-1)*C27*(1-'Base Case Inputs'!$B$15/'Base Case Inputs'!$B$18-C37),0) -> -2678101.3 | D63: =IFERROR(D31+(D62-1)*D27*(1-'Base Case Inputs'!$B$15/'Base Case Inputs'!$B$18-D37),0) -> 1286962.6 | E63: =IFERROR(E31+(E62-1)*E27*(1-'Base Case Inputs'!$B$15/'Base Case Inputs'!$B$18-E37),0) -> 42128894 | F63: =IFERROR(F31+(F62-1)*F27*(1-'Base Case Inputs'!$B$15/'Base Case Inputs'!$B$18-F37),0) -> 87723840 | G63: =IFERROR(G31+(G62-1)*G27*(1-'Base Case Inputs'!$B$15/'Base Case Inputs'!$B$18-G37),0) -> 1.4294989e+08
B64: On-Time (Base Case)
B65: Prod Multiplier | C65: 1 | D65: 1 | E65: 1 | F65: 1 | G65: 1
B66: EBITDA | C66: =C31 -> -2678101.3 | D66: =D31 -> 3758052.9 | E66: =E31 -> 54903453 | F66: =F31 -> 1.0559209e+08 | G66: =G31 -> 1.6071295e+08
B67: 3-Month Acceleration (1.15x→1.05x graduated vol)
B68: Prod Multiplier | C68: 1 | D68: 1.15 | E68: 1.1 | F68: 1.08 | G68: 1.05
B69: EBITDA | C69: =IFERROR(C31+(C68-1)*C27*(1-'Base Case Inputs'!$B$15/'Base Case Inputs'!$B$18-C37),0) -> -2678101.3 | D69: =IFERROR(D31+(D68-1)*D27*(1-'Base Case Inputs'!$B$15/'Base Case Inputs'!$B$18-D37),0) -> 4993598.1 | E69: =IFERROR(E31+(E68-1)*E27*(1-'Base Case Inputs'!$B$15/'Base Case Inputs'!$B$18-E37),0) -> 61290733 | F69: =IFERROR(F31+(F68-1)*F27*(1-'Base Case Inputs'!$B$15/'Base Case Inputs'!$B$18-F37),0) -> 1.1512182e+08 | G69: =IFERROR(G31+(G68-1)*G27*(1-'Base Case Inputs'!$B$15/'Base Case Inputs'!$B$18-G37),0) -> 1.6959448e+08
B70: Volume multipliers are graduated, not flat. Delay scenario: ramp shortfall is largest in FY2 (0.7x) and recovers toward nameplate by FY5 (0.9x) as delayed facilities catch up. Acceleration scenario: early advantage is largest in FY2 (1.15x) and tapers as all facilities converge to nameplate (1.05x by FY5). Equipment/services/45V are independent of ramp timing.
B72: SENSITIVITY 3: FACILITY BUILDOUT PACE (Engine-Referenced)
B73: Fewer/more facilities scale H2 revenue proportionally vs base. Equipment sales independent. Uses core engine EBITDA as anchor.
C74: FY1 Apr '26 – Mar '27 | D74: FY2 Apr '27 – Mar '28 | E74: FY3 Apr '28 – Mar '29 | F74: FY4 Apr '29 – Mar '30 | G74: FY5 Apr '30 – Mar '31
B75: Conservative (5 facilities by Y5)
B76: Facility Multiplier | C76: =IF(C79=0,1,0/C79) -> 1 | D76: =IF(D79=0,1,1/D79) -> 0.5 | E76: =IF(E79=0,1,2/E79) -> 0.4 | F76: =IF(F79=0,1,4/F79) -> 0.5 | G76: =IF(G79=0,1,5/G79) -> 0.45454545
B77: EBITDA | C77: =C31 -> -2678101.3 | D77: =D31 -> 3758052.9 | E77: =IFERROR(E31+(E76-1)*E27*(1-'Base Case Inputs'!$B$15/'Base Case Inputs'!$B$18-E37),0) -> 16579775 | F77: =IFERROR(F31+(F76-1)*F27*(1-'Base Case Inputs'!$B$15/'Base Case Inputs'!$B$18-F37),0) -> 46031261 | G77: =IFERROR(G31+(G76-1)*G27*(1-'Base Case Inputs'!$B$15/'Base Case Inputs'!$B$18-G37),0) -> 63823535
B78: Base Case (11 facilities by Y5)
B79: Facilities | C79: =_xlfn.MAXIFS('Model Assumptions'!$G$5:$CL$5,'Model Assumptions'!$G$1:$CL$1,1) -> 0 | D79: =_xlfn.MAXIFS('Model Assumptions'!$G$5:$CL$5,'Model Assumptions'!$G$1:$CL$1,2) -> 2 | E79: =_xlfn.MAXIFS('Model Assumptions'!$G$5:$CL$5,'Model Assumptions'!$G$1:$CL$1,3) -> 5 | F79: =_xlfn.MAXIFS('Model Assumptions'!$G$5:$CL$5,'Model Assumptions'!$G$1:$CL$1,4) -> 8 | G79: =_xlfn.MAXIFS('Model Assumptions'!$G$5:$CL$5,'Model Assumptions'!$G$1:$CL$1,5) -> 11
B80: EBITDA | C80: =C31 -> -2678101.3 | D80: =D31 -> 3758052.9 | E80: =E31 -> 54903453 | F80: =F31 -> 1.0559209e+08 | G80: =G31 -> 1.6071295e+08
B81: Aggressive (13 facilities by Y5)
B82: Facility Multiplier | C82: =IF(C79=0,1,0/C79) -> 1 | D82: =IF(D79=0,1,2/D79) -> 1 | E82: =IF(E79=0,1,6/E79) -> 1.2 | F82: =IF(F79=0,1,10/F79) -> 1.25 | G82: =IF(G79=0,1,13/G79) -> 1.1818182
B83: EBITDA | C83: =C31 -> -2678101.3 | D83: =D31 -> 3758052.9 | E83: =IFERROR(E31+(E82-1)*E27*(1-'Base Case Inputs'!$B$15/'Base Case Inputs'!$B$18-E37),0) -> 67678013 | F83: =IFERROR(F31+(F82-1)*F27*(1-'Base Case Inputs'!$B$15/'Base Case Inputs'!$B$18-F37),0) -> 1.353725e+08 | G83: =IFERROR(G31+(G82-1)*G27*(1-'Base Case Inputs'!$B$15/'Base Case Inputs'!$B$18-G37),0) -> 1.9300942e+08
B84: Facility buildout scales H2 production only. Equipment and services revenue are independent. Conservative = 3 facilities (Y5), Aggressive = 12 (Y5).
B86: SENSITIVITY 4: 45V PRODUCTION TAX CREDIT IMPACT (Engine-Referenced)
B87: Incremental EBITDA when 45V PTC ($3/kg) is enabled. 10-year credit per facility from in-service date. Begin-construction deadline Dec 2027.
C88: FY1 Apr '26 – Mar '27 | D88: FY2 Apr '27 – Mar '28 | E88: FY3 Apr '28 – Mar '29 | F88: FY4 Apr '29 – Mar '30 | G88: FY5 Apr '30 – Mar '31
B89: 45V PTC Revenue ($3/kg) | C89: ='P&L Summary'!C8 -> 0 | D89: ='P&L Summary'!D8 -> 1417500 | E89: ='P&L Summary'!E8 -> 8887500 | F89: ='P&L Summary'!F8 -> 10800000 | G89: ='P&L Summary'!G8 -> 10800000
B90: Base EBITDA (PTC OFF) | C90: =C31-'P&L Summary'!C8*(1-C37) -> -2678101.3 | D90: =D31-'P&L Summary'!D8*(1-D37) -> 2621062.8 | E90: =E31-'P&L Summary'!E8*(1-E37) -> 46676693 | F90: =F31-'P&L Summary'!F8*(1-F37) -> 95372291 | G90: =G31-'P&L Summary'!G8*(1-G37) -> 1.5048642e+08
B91: EBITDA with PTC (current model) | C91: =C31 -> -2678101.3 | D91: =D31 -> 3758052.9 | E91: =E31 -> 54903453 | F91: =F31 -> 1.0559209e+08 | G91: =G31 -> 1.6071295e+08
B92: Incremental EBITDA from PTC | C92: =C91-C90 -> 0 | D92: =D91-D90 -> 1136990.1 | E92: =E91-E90 -> 8226760.7 | F92: =F91-F90 -> 10219797 | G92: =G91-G90 -> 10226526
B93: Cumulative PTC Cash Impact | C93: =C89 -> 0 | D93: =C93+D89 -> 1417500 | E93: =D93+E89 -> 10305000 | F93: =E93+F89 -> 21105000 | G93: =F93+G89 -> 31905000
B94: The 45V PTC adds $3/kg to every qualifying green H2 produced. At full ramp, worth ~$2.7M/year per facility. Toggle in Base Case Inputs.
B96: COMBINED SENSITIVITY: Year 5 Revenue ($M) — H₂ Price x Facility Count
B97: Uses engine revenue at base facility count, scaled proportionally for alternative facility counts. Equipment revenue is facility-count independent.
C98: 3 Facilities | D98: 5 Facilities | E98: 7 (Base) | F98: 10 Facilities | G98: 12 Facilities
B99: $15/kg | C99: =IFERROR((G27*3/7*('Base Case Inputs'!$B$19/'Base Case Inputs'!$B$18)+G28)/1000000,0) -> 96.083352 | D99: =IFERROR((G27*5/7*('Base Case Inputs'!$B$19/'Base Case Inputs'!$B$18)+G28)/1000000,0) -> 132.24407 | E99: =IFERROR((G27*('Base Case Inputs'!$B$19/'Base Case Inputs'!$B$18)+G28)/1000000,0) -> 168.40478 | F99: =IFERROR((G27*10/7*('Base Case Inputs'!$B$19/'Base Case Inputs'!$B$18)+G28)/1000000,0) -> 222.64585 | G99: =IFERROR((G27*12/7*('Base Case Inputs'!$B$19/'Base Case Inputs'!$B$18)+G28)/1000000,0) -> 258.80657
B100: $25/kg (Base) | C100: =IFERROR((G27*3/7+G28)/1000000,0) -> 132.24407 | D100: =IFERROR((G27*5/7+G28)/1000000,0) -> 192.51192 | E100: =IFERROR(G26/1000000,0) -> 241.97978 | F100: =IFERROR((G27*10/7+G28)/1000000,0) -> 343.18157 | G100: =IFERROR((G27*12/7+G28)/1000000,0) -> 403.44942
B101: $35/kg | C101: =IFERROR((G27*3/7*('Base Case Inputs'!$B$22/'Base Case Inputs'!$B$18)+G28)/1000000,0) -> 168.40478 | D101: =IFERROR((G27*5/7*('Base Case Inputs'!$B$22/'Base Case Inputs'!$B$18)+G28)/1000000,0) -> 252.77978 | E101: =IFERROR((G27*('Base Case Inputs'!$B$22/'Base Case Inputs'!$B$18)+G28)/1000000,0) -> 337.15478 | F101: =IFERROR((G27*10/7*('Base Case Inputs'!$B$22/'Base Case Inputs'!$B$18)+G28)/1000000,0) -> 463.71728 | G101: =IFERROR((G27*12/7*('Base Case Inputs'!$B$22/'Base Case Inputs'!$B$18)+G28)/1000000,0) -> 548.09228
B102: Highlighted cell = base case. Equipment revenue independent of H2 price and facility count.
B104: COMBINED SENSITIVITY: Year 5 EBITDA ($M) — H₂ Price x Facility Count
B105: EBITDA = Core EBITDA + price delta + volume delta. All scenarios EBITDA-positive by Y5.
C106: 3 Facilities | D106: 5 Facilities | E106: 7 (Base) | F106: 10 Facilities | G106: 12 Facilities
B107: $15/kg | C107: =IFERROR((G31+('Base Case Inputs'!$B$19/'Base Case Inputs'!$B$18-1)*G27*(1-G37)+(3/7-1)*G27*(1-'Base Case Inputs'!$B$15/'Base Case Inputs'!$B$18-G37))/1000000,0) -> -20.684982 | D107: =IFERROR((G31+('Base Case Inputs'!$B$19/'Base Case Inputs'!$B$18-1)*G27*(1-G37)+(5/7-1)*G27*(1-'Base Case Inputs'!$B$15/'Base Case Inputs'!$B$18-G37))/1000000,0) -> 30.066614 | E107: =IFERROR((G31+('Base Case Inputs'!$B$19/'Base Case Inputs'!$B$18-1)*G27*(1-G37))/1000000,0) -> 80.818211 | F107: =IFERROR((G31+('Base Case Inputs'!$B$19/'Base Case Inputs'!$B$18-1)*G27*(1-G37)+(10/7-1)*G27*(1-'Base Case Inputs'!$B$15/'Base Case Inputs'!$B$18-G37))/1000000,0) -> 156.94561 | G107: =IFERROR((G31+('Base Case Inputs'!$B$19/'Base Case Inputs'!$B$18-1)*G27*(1-G37)+(12/7-1)*G27*(1-'Base Case Inputs'!$B$15/'Base Case Inputs'!$B$18-G37))/1000000,0) -> 207.6972
B108: $25/kg (Base) | C108: =IFERROR((G31+(3/7-1)*G27*(1-'Base Case Inputs'!$B$15/'Base Case Inputs'!$B$18-G37))/1000000,0) -> 59.209753 | D108: =IFERROR((G31+(5/7-1)*G27*(1-'Base Case Inputs'!$B$15/'Base Case Inputs'!$B$18-G37))/1000000,0) -> 109.96135 | E108: =IFERROR(G31/1000000,0) -> 160.71295 | F108: =IFERROR((G31+(10/7-1)*G27*(1-'Base Case Inputs'!$B$15/'Base Case Inputs'!$B$18-G37))/1000000,0) -> 236.84034 | G108: =IFERROR((G31+(12/7-1)*G27*(1-'Base Case Inputs'!$B$15/'Base Case Inputs'!$B$18-G37))/1000000,0) -> 287.59194
B109: $35/kg | C109: =IFERROR((G31+('Base Case Inputs'!$B$22/'Base Case Inputs'!$B$18-1)*G27*(1-G37)+(3/7-1)*G27*(1-'Base Case Inputs'!$B$15/'Base Case Inputs'!$B$18-G37))/1000000,0) -> 139.10449 | D109: =IFERROR((G31+('Base Case Inputs'!$B$22/'Base Case Inputs'!$B$18-1)*G27*(1-G37)+(5/7-1)*G27*(1-'Base Case Inputs'!$B$15/'Base Case Inputs'!$B$18-G37))/1000000,0) -> 189.85609 | E109: =IFERROR((G31+('Base Case Inputs'!$B$22/'Base Case Inputs'!$B$18-1)*G27*(1-G37))/1000000,0) -> 240.60768 | F109: =IFERROR((G31+('Base Case Inputs'!$B$22/'Base Case Inputs'!$B$18-1)*G27*(1-G37)+(10/7-1)*G27*(1-'Base Case Inputs'!$B$15/'Base Case Inputs'!$B$18-G37))/1000000,0) -> 316.73508 | G109: =IFERROR((G31+('Base Case Inputs'!$B$22/'Base Case Inputs'!$B$18-1)*G27*(1-G37)+(12/7-1)*G27*(1-'Base Case Inputs'!$B$15/'Base Case Inputs'!$B$18-G37))/1000000,0) -> 367.48667
B110: All EBITDA-positive across scenarios. Equipment revenue provides resilient floor. EBITDA formula anchored to core Financials engine.
B113: 45V PTC ELIGIBILITY BY FACILITY
B114: 45V PTC requires construction to BEGIN before Dec 31, 2027 (BCI!B124). Eligibility set by formula: Model Assumptions col F = IF(Begin Construction ≤ Deadline, 1, 0).
...

Sheet Learning Curve
B1: MANUFACTURING COST ANALYSIS
B2: Blended cost reduction across T-25 and T-125 product lines. ~15% average learning rate (Wright’s Law). Blended BOM declines as mix shifts toward higher-value units and cumulative production drives manufacturing efficiency.
B4: 1. BLENDED ELECTROLYZER COST (T-25 + T-125 — includes mix effect)
C5: Launch Year 2 | D5: First Scale Year 3 | E5: Multi-Line Year 4 | F5: Volume Mfg Year 5 | G5: At Scale Year 6+ | H5: At Scale Year 7
B6: Cumulative Units Produced | C6: ='Unit Economics'!C62 -> 85 | D6: =C6+'Unit Economics'!D62 -> 265 | E6: =D6+'Unit Economics'!E62 -> 575 | F6: =E6+'Unit Economics'!F62 -> 1025 | G6: =F6+'Unit Economics'!G62 -> 2395 | H6: =G6+SUM('Model Assumptions'!CA133:CL133)+SUM('Model Assumptions'!CA67:CL67)+SUM('Model Assumptions'!CA136:CL136) -> 3175
B7: Total Units Sold in Period | C7: ='Unit Economics'!C62 -> 85 | D7: ='Unit Economics'!D62 -> 180 | E7: ='Unit Economics'!E62 -> 310 | F7: ='Unit Economics'!F62 -> 450 | G7: ='Unit Economics'!G62 -> 1370 | H7: =SUM('Model Assumptions'!CA133:CL133)+SUM('Model Assumptions'!CA67:CL67)+SUM('Model Assumptions'!CA136:CL136) -> 780
B8: Blended Avg BOM ($/unit) | C8: =IFERROR(('Unit Economics'!C59*$C$74+'Unit Economics'!C60*$C$75+'Unit Economics'!C61*$C$76)/('Unit Economics'!C62),0) -> 30294.118 | D8: =IFERROR(('Unit Economics'!D59*$D$74+'Unit Economics'!D60*$D$75+'Unit Economics'!D61*$D$76)/('Unit Economics'!D62),0) -> 32800 | E8: =IFERROR(('Unit Economics'!E59*$E$74+'Unit Economics'!E60*$E$75+'Unit Economics'!E61*$E$76)/('Unit Economics'!E62),0) -> 33568.548 | F8: =IFERROR(('Unit Economics'!F59*$F$74+'Unit Economics'!F60*$F$75+'Unit Economics'!F61*$F$76)/('Unit Economics'!F62),0) -> 33736.111 | G8: =IFERROR(('Unit Economics'!G59*$G$74+'Unit Economics'!G60*$G$75+'Unit Economics'!G61*$G$76)/('Unit Economics'!G62),0) -> 32548.358 | H8: =IFERROR((SUM('Model Assumptions'!CA67:CL67)*$H$74+SUM('Model Assumptions'!CA133:CL133)*$H$75+SUM('Model Assumptions'!CA136:CL136)*$H$76)/(SUM('Model Assumptions'!CA67:CL67)+SUM('Model Assumptions'!CA133:CL133)+SUM('Model Assumptions'!CA136:CL136)),0) -> 30807.692 | I8: Blended BOM reflects both per-unit cost-down (learning curve) AND product mix shift. T-125 share grows from 44%→62% in Y2-Y4, which increases the blend even though per-unit costs decline. See R71-R72 for per-product trends.
B9: Blended BOM Change vs. Launch (includes mix effect) | C9: =1-C8/C8 -> 0 | D9: =1-D8/C8 -> -0.082718447 | E9: =1-E8/C8 -> -0.10808801 | F9: =1-F8/C8 -> -0.1136192 | G9: =1-G8/C8 -> -0.074411806 | H9: =1-H8/C8 -> -0.01695295
B11: T-25 Cost Reduction vs. Launch | C11: =1-C74/$C$74 -> 0 | D11: =1-D74/$C$74 -> 0.04 | E11: =1-E74/$C$74 -> 0.075 | F11: =1-F74/$C$74 -> 0.125 | G11: =1-G74/$C$74 -> 0.175 | H11: =1-H74/$C$74 -> 0.2
B12: T-125 Cost Reduction vs. Launch | C12: =1-C75/$C$75 -> 0 | D12: =1-D75/$C$75 -> 0.04 | E12: =1-E75/$C$75 -> 0.075 | F12: =1-F75/$C$75 -> 0.125 | G12: =1-G75/$C$75 -> 0.175 | H12: =1-H75/$C$75 -> 0.225
B14: Blended ASP ($/unit) | C14: =IFERROR('Unit Economics'!C63/'Unit Economics'!C62,0) -> 50529.412 | D14: =IFERROR('Unit Economics'!D63/'Unit Economics'!D62,0) -> 57000 | E14: =IFERROR('Unit Economics'!E63/'Unit Economics'!E62,0) -> 60548.387 | F14: =IFERROR('Unit Economics'!F63/'Unit Economics'!F62,0) -> 64333.333 | G14: =IFERROR('Unit Economics'!G63/'Unit Economics'!G62,0) -> 65832.117 | H14: =IFERROR((SUM('Model Assumptions'!CA67:CL67)*35000+SUM('Model Assumptions'!CA133:CL133)*167000+SUM('Model Assumptions'!CA136:CL136)*3000000)/(SUM('Model Assumptions'!CA67:CL67)+SUM('Model Assumptions'!CA133:CL133)+SUM('Model Assumptions'!CA136:CL136)),0) -> 65461.538
B15: Blended Gross Margin | C15: =IFERROR(1-C8/C14,0) -> 0.40046566 | D15: =IFERROR(1-D8/D14,0) -> 0.4245614 | E15: =IFERROR(1-E8/E14,0) -> 0.44559137 | F15: =IFERROR(1-F8/F14,0) -> 0.47560449 | G15: =IFERROR(1-G8/G14,0) -> 0.50558543 | H15: =IFERROR(1-H8/H14,0) -> 0.5293772
B16: Blended Gross Profit per Unit | C16: =IFERROR(C14-C8,0) -> 20235.294 | D16: =IFERROR(D14-D8,0) -> 24200 | E16: =IFERROR(E14-E8,0) -> 26979.839 | F16: =IFERROR(F14-F8,0) -> 30597.222 | G16: =IFERROR(G14-G8,0) -> 33283.759 | H16: =IFERROR(H14-H8,0) -> 34653.846
B17: Install Cost per Unit (with inflation) | C17: =75000*(1+'Base Case Inputs'!$B$88)^1 -> 76875 | D17: =75000*(1+'Base Case Inputs'!$B$88)^2 -> 78796.875 | E17: =75000*(1+'Base Case Inputs'!$B$88)^3 -> 80766.797 | F17: =75000*(1+'Base Case Inputs'!$B$88)^4 -> 82785.967 | G17: =75000*(1+'Base Case Inputs'!$B$88)^5 -> 84855.616 | H17: =75000*(1+'Base Case Inputs'!$B$88)^6 -> 86977.006 | I17: $75k calculated in Y1 with detailed engineering analysis; annual inflation added thereafter
B18: 2. COST-DOWN DRIVER DECOMPOSITION — What Actually Moves the BOM
B19: Cost reductions modeled per $100K of equipment BOM (T-125 base). T-25 follows the same proportional trajectory at its ~$15K base. Costs shown as absolute $ on T-125 equivalent unit.
B20: Phase 1: Standardization (SN 1→20) | C20: Cost Δ: $100K → $82K (−18%)
B21: Design-for-Manufacturability (DFM) redesign | C21: −$6,000 | D21: Eliminate hand-fitted parts; tolerance stack analysis; reduce unique fasteners from ~120 to ~40
B22: First CNC automation (5-axis mill + transformer winder) | C22: −$4,000 | D22: Replace hand-machined manifolds & plates with CNC-cut parts; 60% labor reduction on machined components
B23: Standardized BOP packaging | C23: −$3,000 | D23: Common piping/valve/sensor kits; eliminate one-off field-fit assemblies
B24: Initial bulk procurement (stainless, copper, seals) | C24: −$3,000 | D24: 10-unit MOQ pricing vs. single-unit spot buys; ~15% materials discount
B25: Assembly sequence optimization | C25: −$2,000 | D25: Documented build procedures; fixture-based alignment; reduced rework from ~15% to ~3%
B26: Phase 2: Automation Ramp (SN 20→130) | C26: Cost Δ: $82K → $76K (−7.3%)
B27: AI-powered QA/QC automation | C27: −$2,000 | D27: Computer vision for weld inspection, dimensional verification; replaces 2 manual QC steps per unit
B28: Automated stack testing & conditioning | C28: −$1,500 | D28: AI-controlled break-in protocol; reduces test time from 72hr to 24hr; catches defects earlier
B29: Volume purchasing agreements (25+ unit MOQ) | C29: −$1,500 | D29: Locked pricing on SS316L plate, Viton seals, power electronics modules
B30: Laser cutter / waterjet integration | C30: −$1,000 | D30: Bipolar plate & gasket cutting automated; replaces outsourced waterjet job shop
B31: Phase 3: Mature Optimization (SN 130→535) | C31: Cost Δ: $76K → $73K (−3.9%)
B32: AI engineering tools (FEA/CFD/thermal, human-approved) | C32: −$1,000 | D32: Automated design iteration; senior engineer reviews & approves. Reduces eng. hours per design change by ~60%
B33: Robotic sub-assembly (first station) | C33: −$800 | D33: Automated cell stacking or electrode assembly; first commercially available cobot deployment
B34: Supply chain optimization (dual-sourcing, JIT) | C34: −$700 | D34: Reduced inventory carrying cost; competitive bidding on long-lead items
B35: Continuous improvement (kaizen) + workforce learning | C35: −$500 | D35: Technician experience curve; reduced scrap rate from ~3% to <1%
B36: Phase 4: Plateau → Inflation (SN 535→1560) | C36: Cost Δ: $73K → $73.5K (+0.7%) — Materials inflation begins to dominate
B37: Raw materials inflation (+2.5%/yr on ~60% of BOM) | C37: 1100 | D37: SS316L, nickel, copper — long-run 2-3% annual commodity inflation is the historical norm
B38: AI-driven predictive maintenance & process control | C38: −$400 | D38: Reduce unplanned downtime; optimize power electronics burn-in; ML on production data
B39: Additional robotic stations (welding, material handling) | C39: −$400 | D39: As cobot costs decline ~15%/yr, ROI threshold drops; deploy 2nd and 3rd stations
B40: Net: slight increase | C40: 300 | D40: The uncomfortable truth — at this point, further optimization cannot fully offset commodity inflation
B41: Phase 5+: Scale Production (SN 1560→6000+) | C41: Cost Δ: $73.5K → $74.5K (+1.4%) — Net annual creep ~1%/yr
B42: Materials inflation continues (+2.5%/yr) | C42: 1800 | D42: Stainless steel historically inflates 2-4%/yr; copper 3-5%/yr. Every financial model that ignores this is wrong.
B43: Full AI engineering pipeline (design → test → cert) | C43: −$500 | D43: AI generates design variants, runs simulations, drafts certification packages. Senior engineer approves.
B44: Expanded robotics (assembly line, not job shop) | C44: −$500 | D44: Lights-out sub-assembly cells for repetitive tasks; human oversight for final integration
B45: Net: ~1% annual cost creep | C45: 800 | D45: Realistic steady-state. Offset by price increases and margin structure.
B47: 3. AI & AUTOMATION INTEGRATION ROADMAP
B48: Initiative | C48: Timeline | D48: Area | E48: BOM Saving | F48: Human Approval? | G48: Tech / Approach | H48: Status
B49: QA/QC: Computer Vision Weld Inspection | C49: Y1 Q3 | D49: Production | E49: −$1,200 | F49: No — autonomous | G49: CNN + structured light scanning | H49: Build in Y1
B50: QA/QC: Dimensional Verification (CMM + vision) | C50: Y1 Q4 | D50: Production | E50: −$800 | F50: No — autonomous | G50: Point cloud comparison to CAD | H50: Build in Y1
A51: 131.25 | B51: Automated Stack Test & Conditioning | C51: Y2 Q1 | D51: Production | E51: −$1,500 | F51: No — protocol-based | G51: ML-optimized break-in curves | H51: Build in Y2
B52: T-25 / T-125 COGS Tracking (live BOM vs. actuals) | C52: Y2 Q2 | D52: Finance / Ops | E52: Model input | F52: Yes — Finance lead | G52: ERP/MES → Base Case Inputs B25/B26/B30/B31 | H52: Plan Y2
B53: Engineering: Automated Test Report Generation | C53: Y2 Q3 | D53: Engineering | E53: −$600 | F53: Yes — Sr. Engineer | G53: LLM + structured data templates | H53: Build in Y2
B54: Predictive Maintenance (production equipment) | C54: Y3 Q1 | D54: Operations | E54: −$400 | F54: No — alerts only | G54: Vibration/current ML models | H54: Deploy Y3
B55: Engineering: Certification Package Drafting | C55: Y3 Q2 | D55: Engineering | E55: −$500 | F55: Yes — Sr. Engineer | G55: AI drafts UL/ASME submissions | H55: Deploy Y3
B56: Robotic Sub-Assembly (first cobot station) | C56: Y3 Q3 | D56: Production | E56: −$800 | F56: No — programmed | G56: UR/FANUC cobot, fixed routine | H56: Deploy Y3
B57: AI Process Optimization (real-time tuning) | C57: Y4 Q1 | D57: Production | E57: −$500 | F57: No — within bounds | G57: Reinforcement learning on process params | H57: Deploy Y4
B58: Full Robotic Assembly Line (3+ stations) | C58: Y5+ | D58: Production | E58: −$1,500 | F58: No — programmed | G58: Multi-cobot cell, human oversight | H58: Plan Y5
B59: AI Engineering Pipeline (design → sim → cert) | C59: Y5+ | D59: Engineering | E59: −$2,000 | F59: Yes — Sr. Engineer | G59: End-to-end AI with human gate | H59: Vision Y5+
B61: PRINCIPLE: AI tools generate, humans approve. Every automated engineering output (FEA results, design changes, certification docs) is first built by hand the old-school way, then replicated by AI, then approved by a senior engineer. Trust is earned through demonstrated accuracy on the training set.
B63: 4. MATERIALS INFLATION — The Cost Reality Most Models Ignore
B64: Material | C64: % of BOM | D64: 10-yr Avg Inflation | E64: Stress Case | F64: Modeled Rate | G64: Source | H64: Annual Impact on $100K BOM
B65: Stainless Steel 316L (plate, tube, fittings) | C65: 0.35 | D65: 0.028 | E65: 0.041 | F65: 0.025 | G65: MEPS Intl / LME Ni | H65: $35K of BOM; +$875/yr
B66: Copper (bus bars, windings, power electronics) | C66: 0.12 | D66: 0.032 | E66: 0.058 | F66: 0.03 | G66: LME Cu Forward | H66: $12K of BOM; +$360/yr
B67: Nickel (alloy content in SS + catalyst) | C67: 0.08 | D67: 0.025 | E67: 0.039 | F67: 0.025 | G67: LME Ni Forward | H67: $8K of BOM; +$200/yr
B68: Power Electronics (IGBTs, rectifiers, controls) | C68: 0.15 | D68: −1.5% | E68: −2.1% | F68: −1.0% | G68: IHS Markit / Yole | H68: DEFLATING — $15K, saves $150/yr
B69: Seals, Gaskets, Polymers (Viton, PTFE) | C69: 0.05 | D69: 0.018 | E69: 0.025 | F69: 0.02 | G69: ICIS Chemicals | H69: $5K of BOM; +$100/yr
B70: Fasteners, Hardware, Misc. | C70: 0.1 | D70: 0.02 | E70: 0.028 | F70: 0.02 | G70: Industrial PPI | H70: $10K of BOM; +$200/yr
B71: Labor (assembly, test, pack) | C71: 0.15 | D71: 0.035 | E71: 0.042 | F71: 0.025 | G71: BLS OES Oklahoma | H71: $15K of BOM; +$375/yr
B72: WEIGHTED NET ANNUAL INFLATION: ~2.1% on total BOM (after power electronics deflation). Modeled: 2.5% gross / 1.5% AI offset = 1.0% net annual cost creep from Phase 4 onward. Most learning curve models assume infinite cost decline — empirically wrong for any manufactured good past 2-3 doublings.
B73: 5. PRODUCT-SPECIFIC BOM SCHEDULES (Referenced by Financials COGS)
B74: T-25 BOM per Unit (by year) | C74: 21000 | D74: 20160 | E74: 19425 | F74: 18375 | G74: 17325 | H74: 16800
B75: T-125 BOM per Unit (by year) | C75: 100000 | D75: 96000 | E75: 92500 | F75: 87500 | G75: 82500 | H75: 77500

Sheet Error Dashboard
A1: MODEL INTEGRITY DASHBOARD
A3: Balance Sheet Check (EOY)
B4: FY1 | C4: FY2 | D4: FY3 | E4: FY4 | F4: FY5 | G4: FY6 | H4: FY7
B5: =IF(Financials!P70="OK","OK","FAIL") -> OK | C5: =IF(Financials!AB70="OK","OK","FAIL") -> OK | D5: =IF(Financials!AN70="OK","OK","FAIL") -> OK | E5: =IF(Financials!AZ70="OK","OK","FAIL") -> OK | F5: =IF(Financials!BL70="OK","OK","FAIL") -> OK | G5: =IF(Financials!BX70="OK","OK","FAIL") -> OK | H5: =IF(Financials!CJ70="OK","OK","FAIL") -> OK
A7: Minimum Ending Cash (>= 0) | B7: =MIN(Financials!E101:CJ101) -> 273110.92 | C7: =IF(B7>=0,"OK","FAIL") -> OK
A8: Minimum Debt Outstanding (>= 0) | B8: =MIN(Financials!E58:CJ58) -> 0 | C8: =IF(B8>=0,"OK","FAIL") -> OK
A9: Minimum Total Revenue (>= 0) | B9: =MIN(Financials!E8:CJ8) -> 67307.692 | C9: =IF(B9>=0,"OK","FAIL") -> OK
A10: Max COGS - Revenue (<= 0) | B10: =SUMPRODUCT((Financials!E21:CJ21-Financials!E8:CJ8)*(Financials!E21:CJ21>Financials!E8:CJ8)) -> 0 | C10: =IF(B10<=0,"OK","FAIL") -> OK
A11: Formula Error Count (Financials + Model Assumptions) | B11: =SUMPRODUCT(--ISERROR(Financials!E1:CJ200))+SUMPRODUCT(--ISERROR('Model Assumptions'!G1:CL200)) -> 0 | C11: =IF(B11=0,"OK","FAIL") -> OK
A13: P&L Summary Operating Revenue Tie-Out (ex-PTC)
B14: FY1 | C14: FY2 | D14: FY3 | E14: FY4 | F14: FY5 | G14: FY6 | H14: FY7
B15: =IF(ABS('P&L Summary'!C9-SUM(Financials!E8:P8))<1,"OK","FAIL") -> OK | C15: =IF(ABS('P&L Summary'!D9-SUM(Financials!Q8:AB8))<1,"OK","FAIL") -> OK | D15: =IF(ABS('P&L Summary'!E9-SUM(Financials!AC8:AN8))<1,"OK","FAIL") -> OK | E15: =IF(ABS('P&L Summary'!F9-SUM(Financials!AO8:AZ8))<1,"OK","FAIL") -> OK | F15: =IF(ABS('P&L Summary'!G9-SUM(Financials!BA8:BL8))<1,"OK","FAIL") -> OK | G15: =IF(ABS('P&L Summary'!H9-SUM(Financials!BM8:BX8))<1,"OK","FAIL") -> OK | H15: =IF(ABS('P&L Summary'!I9-SUM(Financials!BY8:CJ8))<1,"OK","FAIL") -> OK
A17: Last verified: 2026-03-04 | B17: =Financials!AQ58 -> 0 | C17: =IF(B17=0,"OK","FAIL") -> OK

Sheet Change Log
A1: Version | B1: Date | C1: Author | D1: Summary
A2: v7.x | B2: 2024 | C2: Original | D2: Original model build (pre-Techstars).
A3: v8.0 | B3: 2025 | C3: Team | D3: Techstars restructure and metric overhaul.
A4: v8.1–v8.2 | B4: 2026-02 | C4: Claude | D4: Audit remediation, fiscal year labels, and sensitivity rebuild.
A5: v8.3 | B5: 2026-02 | C5: Claude | D5: T-2500 integration across inputs, schedules, and outputs.
A6: v8.4 | B6: 2026-03 | C6: Claude | D6: Text audit and investor-facing polish.
A7: v8.5 | B7: 2026-03-04 | C7: Codex | D7: Comprehensive remediation: debt terms docs, error dashboard, archive link break, tab order/colors, and final verification.
A8: v8.5.1 | B8: 2026-03-04 | C8: Codex | D8: Final audit remediation: Error Dashboard fixes, PTC presentation clarity, internal tab organization, verification pass complete.
A9: v8.5.2 | B9: 2026-03-04 | C9: Claude | D9: Final investor-readiness remediation: 39 false-positive error codes escaped in Claude Log/Notes text, Fundraising rows 10-11 converted from hardcodes to formulas (=X8+X9, =X7+X8), green font applied to cross-sheet links, end-to-end verification of 3 months, debt schedule, BS integrity (84/84 OK), Error Dashboard all-pass confirmed.
A10: v8.5.3 | B10: 2026-03-16 | C10: Remove T-2500 product line | D10: Removed T-2500 from all formulas (Financials rows 16/17/19), BCI inputs (rows 231-238), Model Assumptions schedules (rows 136-138), Learning Curve BOM (row 76), Personnel EU calc (row 146), and all text references across Overview, P&L Summary, Unit Economics, Fundraising, Use of Funds. Two-product model: T-25 + T-125.

Sheet Base Case Inputs
A1: TIMELINE | B1: Value | C1: Unit | D1: Note
A2: Start Month | B2: 46113 | D2: Month 1
A5: Facility Expansion Base Date | B5: =EDATE(B2,3) -> 46204 | D5: Base date for facility expansion schedule
A7: FACILITY / PRODUCTION | B7: Value | C7: Unit | D7: Note
A8: Nameplate H2 Production Per Facility | B8: 900000 | C8: kg / year | E8: Engineering design target
A10: kWh/kg | B10: 42 | D10: From H2 Production Costs | E10: Lab-validated at stack level; commercial system TBD
A11: Electricity Price | B11: =B98 -> 0.035 | C11: $ / kWh | D11: Shown for reference - determined in cell B97 | E11: Published OK industrial rate
A12: Asset Useful Life | B12: 9 | C12: years | D12: Straight-line depreciation period | E12: Engineering estimate
A13: Pilot Facility CapEx | B13: ='Facility AFE'!C29 -> 3300000 | C13: $ | D13: Capex drawn as straight-line over construction period. Actual draws will be milestone-based per EPC contract.
A14: Construction Duration (months) | B14: 12 | C14: months | D14: Months over which facility capex is drawn down during construction and commissioning
A15: H₂ Production Cost ($/kg) | B15: =ROUND(B94,2) -> 2.62 | D15: ROUND(B94, 2). B94 = Direct OpEx total (electricity + compression + transport + water). See B90:B93 for component breakdown.
A16: DO NOT ENTER H2 PRICE ANYWHERE ELSE IN THE WORKBOOK
A17: HYDROGEN SALE ASSUMPTIONS | B17: Value | C17: Unit | D17: Note
A18: Hydrogen Sale Price (Base) | B18: 25 | C18: $ / kg | D18: Base Case | Flat 7yr — no escalator. Conservative vs. cost inflation at 2.5%/yr. | E18: On-site small-volume pricing — validated by Airgas cylinder quote ($121/kg) and Platts specialty data ($15–$36/kg delivered)
A19: Hydrogen Sale Price (Sens 1) | B19: 15 | C19: $ / kg | D19: Sensitivity 1 | E19: Bear scenario — bulk industrial pricing near grey H₂ parity
A20: Hydrogen Sale Price (Sens 2) | B20: 20 | C20: $ / kg | D20: Sensitivity 2 | E20: Sensitivity scenario — mid-market delivered pricing
A21: Hydrogen Sale Price (Sens 3) | B21: 30 | C21: $ / kg | D21: Sensitivity 3 | E21: Sensitivity scenario — premium specialty applications
A22: Hydrogen Sale Price (Sens 4) | B22: 35 | C22: $ / kg | D22: Sensitivity 4 | E22: Bull scenario — cylinder-replacement pricing (incumbent $30–$121/kg)
A26: EQUIPMENT SALES ASSUMPTIONS | B26: Value | C26: Unit | D26: Note
A27: Unit Sale Price Per T-25 (25 kg/day) | B27: 35000 | C27: $ | D27: $35K blended ASP: $25K base + 50% options attach (~$10K avg). Source: Pulse Holdings Quote TE-PH-ELX-88-51 Jan 2026. Options: remote monitoring HW $3K, consumables $3K, extended warranty $6K = $12K at 50% attach = ~$6K avg uplift.
A28: T-25 Equipment COGS Rate | B28: ='Learning Curve'!C74/B27 -> 0.6 | D28: T-25 launch COGS rate. References LC R74 (T-25 BOM $15K) / B27 ($35K ASP). Starting at 42.9% — margin improves as BOM declines per learning curve (85% Wright's Law). Matches T-125 methodology in B34. Prior value: flat 60% hardcode (overestimated COGS by ~$6K/unit at launch). | E28: Starting rate — actual COGS decline per Learning Curve tab
A29: Annual T-25 Equipment Sales Schedule | D29: T-25 targets: Y1:25, Y2:75, Y3:150, Y4:250, Y5:350, Y6:450, Y7:600. Modular entry-level unit — lower price point drives higher volume. Door-opener product converting to T-125 upsell. | F29: Y1 | G29: Y2 | H29: Y3 | I29: Y4 | J29: Y5 | K29: Y6 | L29: Y7
A30: T-25 Total 7yr Units | B30: =SUM(F30:L30) -> 1900 | D30: Total T-25 units over 7 years. | F30: 25 | G30: 75 | H30: 150 | I30: 250 | J30: 350 | K30: 450 | L30: 600
A31: T-25 Annual Service Price ($/yr) | B31: 3500 | C31: $ | D31: ~10% of $35K T-25 sale price. Separated from B29 (unit total) to eliminate dual-purpose ambiguity. | E31: Validated — industry benchmark OEM service contracts avg 10%/yr of equipment capex. | F31: Y1 assumption: 25 units based on initial channel partner commitments (nexAir, Norco).
A33: Unit Sale Price Per T-125 (125 kg/day) | B33: 167000 | C33: $ | D33: $167K standard optioned ASP. Validated: Pulse Holdings Quote base $120K + options ($3K remote HW + $7.5K subscription + $30K SCADA + $4K consumables + $7.5K warranty = $52K at ~90% attach) ≈ $167K. | E33: Validated: $120K base + ~$47K options at standard attach = $167K. Source: Pulse Holdings Quote TE-PH-ELX-88-51.
A34: T-125 Equipment COGS Rate | B34: ='Learning Curve'!C75/B33 -> 0.5988024 | D34: T-125 launch COGS rate. References LC!C75 / B33 ($167K ASP). Starting at 59.9% — margin improves as BOM declines per learning curve. REFERENCE ONLY — not used in Financials engine. Actual COGS pulled directly from Learning Curve tab. | E34: Starting rate — actual COGS decline per Learning Curve tab
A35: Annual T-125 Equipment Sales Schedule | D35: T-125 targets: Y1:0, Y2:10, Y3:30, Y4:60, Y5:100, Y6:140, Y7:180. Commercial-scale unit at $167K — lower price than legacy T-500 ($750K) drives higher accessible volume. Introduced Y2 as early adopters emerge. | F35: Y1 | G35: Y2 | H35: Y3 | I35: Y4 | J35: Y5 | K35: Y6 | L35: Y7
A36: T-125 Total 7yr Units | B36: =SUM(F36:L36) -> 520 | D36: SUM(F35:L35) formula. Auto-calculated from annual schedule. Prior value (16,700) was a stale service price — fixed to 520 actual units. | F36: 0 | G36: 10 | H36: 30 | I36: 60 | J36: 100 | K36: 140 | L36: 180
A37: T-125 Annual Service Price ($/yr) | B37: 16700 | C37: $ | D37: ~10% of $167K T-125 sale price. Separated from B35 (unit total) to eliminate dual-purpose ambiguity. | E37: Validated — industry benchmark OEM service contracts avg 10%/yr of equipment capex. | F37: T-125 launches Y2. 10 units = early adopter estimate based on LOI pipeline. Scales with facility capacity addition.
A39: Services COGS Rate | B39: 0.2 | D39: 20% COGS = 80% gross margin on services | E39: Assumed: standard services margin for monitoring + maintenance. Service prices set at ~10% of unit capex per industry benchmark (OEM service contracts avg 10%/yr of equipment value).
A40: FINANCING | B40: Value | C40: Unit | D40: Note
A41: Seed Close Date | B41: 46143 | D41: In progress — fundraise launched Feb 2026; targeting May close
A42: Seed Equity | B42: 7500000 | D42: Target
A43: Seed Debt | B43: 2500000 | D43: Target
A44: Seed Project Financing | B44: 0 | D44: No separate project financing at Seed. The $2.5M venture debt (B43) covers all facility project costs including Zeeco CAPEX.
A46: Series A Close Date | B46: 46539 | D46: Manually set. Assumed: Series A timing dependent on seed milestones
A47: Series A Equity | B47: 40000000 | D47: Series A equity — funds R&D + manufacturing scale. Equity-heavy; tech proving stage
A48: Series A Debt | B48: 0
A49: Series A Project Financing | B49: 17000000 | D49: Sized to facility pipeline + inventory
A51: Series B Close Date | B51: =DATE(2029,3,1) -> 47178 | D51: Manually set. Assumed: Series B timing dependent on Series A milestones
A52: Series B Equity | B52: 60000000
A53: Series B Project Financing | B53: 30000000 | D53: Sized for facility pipeline
A55: Series C Close Date | B55: =DATE(2031,3,1) -> 47908 | D55: Manually set. Assumed: Series C timing dependent on Series B milestones
A56: Series C Equity | B56: 150000000 | D56: Modeled after Fervo trajectory — equity funds business, PF funds assets
A57: Series C Project Financing | B57: 75000000 | D57: Sized for facility pipeline
A59: PF Draw Period (months) | B59: 12 | D59: Series B/C PF drawn evenly over this window post-close; models milestone-based draws
F60: DEBT TERMS
F61: Tranche | G61: Amount | H61: Rate | I61: Term (mo) | J61: I/O (mo) | K61: Notes
A62: Debt Interest Rate | B62: 0.07 | D62: Market rate — equipment-collateralized. Source: FRED SOFR + MicroVentures 2025 | F62: Seed Debt | G62: =B43 -> 2500000 | H62: =B62 -> 0.07 | I62: =B63 -> 36 | J62: =B64 -> 6 | K62: Venture debt
A63: Debt Term | B63: 36 | C63: Months | D63: Standard venture debt terms | F63: Series A PF | G63: =B49 -> 17000000 | H63: =B67 -> 0.07 | I63: =B69 -> 36 | J63: =0 -> 0 | K63: Project financing
A64: Interest-only months | B64: 6 | D64: Standard venture debt terms | F64: Series B PF | G64: =B53 -> 30000000 | H64: =B67 -> 0.07 | I64: =B69 -> 36 | J64: =0 -> 0 | K64: Project financing
F65: Series C PF | G65: =B57 -> 75000000 | H65: =B67 -> 0.07 | I65: =B69 -> 36 | J65: =0 -> 0 | K65: Project financing
A67: Project Financing Rate | B67: 0.07 | D67: Based on CSC Leasing Lease Schedule Terms
A68: PF Monthly Pmt Factor (per $1 outstanding) | B68: =PMT(B67/12,B69,-1) -> 0.030877097 | D68: Based on CSC Leasing Lease Schedule Terms
A69: Project Financing Term | B69: 36 | C69: Months | D69: Based on CSC Leasing Lease Schedule Terms
A71: Income Tax Rate | B71: 0.27 | D71: Published — federal 21% + OK state ~6%
A74: OPERATING ASSUMPTIONS | B74: Value | C74: Unit | D74: Note
A75: Benefits Loading % | B75: 0.3736 | D75: Payroll benefits ratio applied to base salaries | E75: Current payroll benefits ratio
A76: Professional Fees % of Revenue | B76: 0.03 | D76: Sales, marketing, professional services | E76: Industry benchmark — 2–5% typical for early-stage
A77: Other OpEx % of Revenue | B77: 0.02 | D77: Miscellaneous operating expenses | E77: Industry benchmark — placeholder
A78: HQ Facility Lease (Monthly) | B78: 8750 | C78: $ / month | D78: Per-facility monthly lease cost | E78: Contracted — current facility lease
A79: Starting Cash Balance | B79: 682500 | D79: Pre-funding cash on hand | E79: Known — pre-seed cash on hand as of April 2026
A80: Days Receivable | B80: 15 | C80: days | D80: Customer payment terms | E80: Estimated — standard industrial terms; customer-dependent
A81: Days Payable | B81: 15 | C81: days | D81: Vendor payment terms | E81: Estimated — standard industrial terms; vendor-dependent
A82: Transport Cost | B82: 0.9 | C82: $ / kg | D82: 50-mile tube trailer delivery | E82: Quoted — tube trailer delivery estimate for 50-mile radius
A83: Compression kWh/kg | B83: 3.5 | C83: kWh / kg | D83: ~3.5 kWh/kg for 200 bar | E83: Engineering spec — well-established for 200 bar compression
A84: Water Usage | B84: 9 | C84: liters / kg | D84: RO water consumption per kg H2 | E84: Chemistry — stoichiometric with RO system losses
A85: Water Cost | B85: 0.00556 | C85: $ / liter | D85: Industrial rate in OK | E85: Quoted — OK municipal/industrial water rate
A86: Pre-Seed Equity Raised | B86: 2050000 | E86: Known — matches B58 starting cash
A87: Opening Accumulated Deficit | B87: =B79-B86 -> -1367500 | D87: Starting Cash ($682,500) minus total Paid-in Capital ($2,050,000). | E87: Known — current cap table
A88: Annual Cost Inflation Rate | B88: 0.025 | C88: % / year | D88: Applied to: H₂ direct opex (electricity, compression, transport, water), HQ lease (Financials row 25), and site occupancy
A89: H₂ COST BUILDUP (REFERENCE) | B89: Cost ($/kg) | C89: Unit | E89: Confidence
A90: Electricity | B90: =B10*B11/0.95 -> 1.5473684 | D90: 42 kWh/kg at $0.035/kWh, derated by 95% BOP Efficiency Factor for balance-of-plant parasitic loads | E90: Derived
A91: Compression & Purification | B91: =B83*B11 -> 0.1225 | D91: 3.5 kWh/kg at $0.035/kWh | E91: Derived
A92: Transportation | B92: =B82 -> 0.9 | D92: 50-mile delivery | E92: Estimated — tube trailer quote
A93: RO Water | B93: =B84*B85 -> 0.05004 | D93: 9 liters/kg at $0.00556/liter | E93: Derived — stoichiometric
A94: Direct OpEx | B94: =SUM(B90:B93) -> 2.6199084 | D94: excluding CAPEX & labor | E94: Derived — sum of above
A95: Annualized CAPEX & Personnel Costs | B95: =(B119+'Model Assumptions'!$C$79/B12)/B8 -> 1.7962696 | D95: Year 3, 900,000 kg/yr | E95: Derived — Year 3 at nameplate
A96: Total Breakeven Cost | B96: =B94+B95 -> 4.4161781 | D96: Year 3, at nameplate | E96: Derived — Year 3 at nameplate
A97: PER-FACILITY ELECTRICITY RATES & OPEX | C97: Unit
A98: Facility 1 — Tulsa, OK | B98: 0.035 | C98: $ / kWh | D98: OK industrial rate
A99: Facility 2 — OKC, OK | B99: 0.035 | C99: $ / kWh | D99: OK industrial rate
A100: Facility 3 — Seattle, WA | B100: 0.0595 | C100: $ / kWh | D100: Seattle City Light avg industrial rate
A101: Facility 4 — Spokane, WA | B101: 0.0413 | C101: $ / kWh | D101: Avista Utilities avg industrial rate
A102: Facility 5 — Albuquerque, NM | B102: 0.0587 | C102: $ / kWh | D102: PNM avg industrial rate
A103: Facility 6 — Des Moines, IA | B103: 0.0429 | C103: $ / kWh | D103: MidAmerican Energy avg industrial rate - used as proxy value for facilities 7-12
A105: Per-Facility Direct OpEx ($/kg) | B105: $/kg
A106: Facility 1 Direct OpEx | B106: =B98*($B$10/0.95+$B$83)+$B$82+$B$84*$B$85 -> 2.6199084
A107: Facility 2 Direct OpEx | B107: =B99*($B$10/0.95+$B$83)+$B$82+$B$84*$B$85 -> 2.6199084
A108: Facility 3 Direct OpEx | B108: =B100*($B$10/0.95+$B$83)+$B$82+$B$84*$B$85 -> 3.7888163
A109: Facility 4 Direct OpEx | B109: =B101*($B$10/0.95+$B$83)+$B$82+$B$84*$B$85 -> 2.9204847
A110: Facility 5 Direct OpEx | B110: =B102*($B$10/0.95+$B$83)+$B$82+$B$84*$B$85 -> 3.7506479
A111: Facility 6 Direct OpEx | B111: =B103*($B$10/0.95+$B$83)+$B$82+$B$84*$B$85 -> 2.9968216
A115: Pilot Initial Production (kg/day) | B115: 250 | C115: kg/day | D115: Months 1-6 | E115: Engineering design — single-stack pilot capacity
A116: Pilot Intermediate Production (kg/day) | B116: 1250 | C116: kg/day | D116: Months 7-12 | E116: Engineering design — multi-stack intermediate
A117: Pilot/Addtl Full Production (kg/day) | B117: 2500 | C117: kg/day | D117: Months 13+ | E117: Engineering design — full facility nameplate
A118: Addtl Facility Personnel Year 0 | B118: =Personnel!E91 -> 817292 | C118: $/year | D118: Grand total from Personnel sheet | E118: Formula — from Personnel tab
A119: Pilot Personnel Year 0 | B119: =Personnel!E15 -> 1249976 | C119: $/year | D119: Grand total from Personnel sheet | E119: Formula — from Personnel tab
A121: 45V Production Tax Credit (Sensitivity Toggle)
A122: 45V PTC Enabled (0=OFF, 1=ON) | B122: 1 | C122: ← Toggle: 0=Base Case (no PTC), 1=With 45V PTC
...

Sheet Financials
B1: Year Counter | E1: 1 | F1: 1 | G1: 1 | H1: 1 | I1: 1 | J1: 1 | K1: 1 | L1: 1 | M1: 1 | N1: 1 | O1: 1 | P1: 1 | Q1: 2 | R1: 2 | S1: 2 | T1: 2 | U1: 2 | V1: 2 | W1: 2 | X1: 2 | Y1: 2 | Z1: 2 | AA1: 2 | AB1: 2 | AC1: 3 | AD1: 3 | AE1: 3 | AF1: 3 | AG1: 3 | AH1: 3 | AI1: 3 | AJ1: 3 | AK1: 3 | AL1: 3 | AM1: 3 | AN1: 3 | AO1: 4 | AP1: 4 | AQ1: 4 | AR1: 4 | AS1: 4 | AT1: 4 | AU1: 4 | AV1: 4 | AW1: 4 | AX1: 4 | AY1: 4 | AZ1: 4 | BA1: 5 | BB1: 5 | BC1: 5 | BD1: 5 | BE1: 5 | BF1: 5 | BG1: 5 | BH1: 5 | BI1: 5 | BJ1: 5 | BK1: 5 | BL1: 5 | BM1: 6 | BN1: 6 | BO1: 6 | BP1: 6 | BQ1: 6 | BR1: 6 | BS1: 6 | BT1: 6 | BU1: 6 | BV1: 6 | BW1: 6 | BX1: 6 | BY1: 7 | BZ1: 7 | CA1: 7 | CB1: 7 | CC1: 7 | CD1: 7 | CE1: 7 | CF1: 7 | CG1: 7 | CH1: 7 | CI1: 7 | CJ1: 7
B2: Year | E2: =YEAR(E4) -> 2026 | F2: =YEAR(F4) -> 2026 | G2: =YEAR(G4) -> 2026 | H2: =YEAR(H4) -> 2026 | I2: =YEAR(I4) -> 2026 | J2: =YEAR(J4) -> 2026 | K2: =YEAR(K4) -> 2026 | L2: =YEAR(L4) -> 2026 | ... CJ2: =YEAR(CJ4) -> 2033
B3: Month Counter | E3: 1 | F3: 2 | G3: 3 | H3: 4 | I3: 5 | J3: 6 | K3: 7 | L3: 8 | M3: 9 | N3: 10 | O3: 11 | P3: 12 | Q3: 13 | R3: 14 | S3: 15 | T3: 16 | U3: 17 | V3: 18 | W3: 19 | X3: 20 | Y3: 21 | Z3: 22 | AA3: 23 | AB3: 24 | AC3: 25 | AD3: 26 | AE3: 27 | AF3: 28 | AG3: 29 | AH3: 30 | AI3: 31 | AJ3: 32 | AK3: 33 | AL3: 34 | AM3: 35 | AN3: 36 | AO3: 37 | AP3: 38 | AQ3: 39 | AR3: 40 | AS3: 41 | AT3: 42 | AU3: 43 | AV3: 44 | AW3: 45 | AX3: 46 | AY3: 47 | AZ3: 48 | BA3: 49 | BB3: 50 | BC3: 51 | BD3: 52 | BE3: 53 | BF3: 54 | BG3: 55 | BH3: 56 | BI3: 57 | BJ3: 58 | BK3: 59 | BL3: 60 | BM3: 61 | BN3: 62 | BO3: 63 | BP3: 64 | BQ3: 65 | BR3: 66 | BS3: 67 | BT3: 68 | BU3: 69 | BV3: 70 | BW3: 71 | BX3: 72 | BY3: 73 | BZ3: 74 | CA3: 75 | CB3: 76 | CC3: 77 | CD3: 78 | CE3: 79 | CF3: 80 | CG3: 81 | CH3: 82 | CI3: 83 | CJ3: 84
B4: Date | E4: ='Base Case Inputs'!$B$2 -> 46113 | F4: =EDATE(E4,1) -> 46143 | G4: =EDATE(F4,1) -> 46174 | H4: =EDATE(G4,1) -> 46204 | I4: =EDATE(H4,1) -> 46235 | J4: =EDATE(I4,1) -> 46266 | K4: =EDATE(J4,1) -> 46296 | L4: =EDATE(K4,1) -> 46327 | M4: =EDATE(L4,1) -> 46357 | ... CJ4: =EDATE(CI4,1) -> 48639
B6: Income Statement
B8: Revenue | E8: =SUM(E9:E17) -> 67307.692 | F8: =SUM(F9:F17) -> 67307.692 | G8: =SUM(G9:G17) -> 67307.692 | H8: =SUM(H9:H17) -> 67307.692 | I8: =SUM(I9:I17) -> 67307.692 | J8: =SUM(J9:J17) -> 67307.692 | K8: =SUM(K9:K17) -> 67307.692 | L8: =SUM(L9:L17) -> 67307.692 | ... CJ8: =SUM(CJ9:CJ17) -> 27421520
B9: GH2x - Tulsa | E9: ='Model Assumptions'!G16 -> 0 | F9: ='Model Assumptions'!H16 -> 0 | G9: ='Model Assumptions'!I16 -> 0 | H9: ='Model Assumptions'!J16 -> 0 | I9: ='Model Assumptions'!K16 -> 0 | J9: ='Model Assumptions'!L16 -> 0 | K9: ='Model Assumptions'!M16 -> 0 | L9: ='Model Assumptions'!N16 -> 0 | ... CJ9: ='Model Assumptions'!CL16 -> 1875000
B10: GH2x2 - OKC | E10: ='Model Assumptions'!G24 -> 0 | F10: ='Model Assumptions'!H24 -> 0 | G10: ='Model Assumptions'!I24 -> 0 | H10: ='Model Assumptions'!J24 -> 0 | I10: ='Model Assumptions'!K24 -> 0 | J10: ='Model Assumptions'!L24 -> 0 | K10: ='Model Assumptions'!M24 -> 0 | L10: ='Model Assumptions'!N24 -> 0 | ... CJ10: ='Model Assumptions'!CL24 -> 1875000
B11: GH2x3 - Seattle | E11: ='Model Assumptions'!G32 -> 0 | F11: ='Model Assumptions'!H32 -> 0 | G11: ='Model Assumptions'!I32 -> 0 | H11: ='Model Assumptions'!J32 -> 0 | I11: ='Model Assumptions'!K32 -> 0 | J11: ='Model Assumptions'!L32 -> 0 | K11: ='Model Assumptions'!M32 -> 0 | L11: ='Model Assumptions'!N32 -> 0 | ... CJ11: ='Model Assumptions'!CL32 -> 1875000
B12: GH2x4 - Spokane | E12: ='Model Assumptions'!G40 -> 0 | F12: ='Model Assumptions'!H40 -> 0 | G12: ='Model Assumptions'!I40 -> 0 | H12: ='Model Assumptions'!J40 -> 0 | I12: ='Model Assumptions'!K40 -> 0 | J12: ='Model Assumptions'!L40 -> 0 | K12: ='Model Assumptions'!M40 -> 0 | L12: ='Model Assumptions'!N40 -> 0 | ... CJ12: ='Model Assumptions'!CL40 -> 1875000
B13: GH2x5 - Albuquerque | E13: ='Model Assumptions'!G48 -> 0 | F13: ='Model Assumptions'!H48 -> 0 | G13: ='Model Assumptions'!I48 -> 0 | H13: ='Model Assumptions'!J48 -> 0 | I13: ='Model Assumptions'!K48 -> 0 | J13: ='Model Assumptions'!L48 -> 0 | K13: ='Model Assumptions'!M48 -> 0 | L13: ='Model Assumptions'!N48 -> 0 | ... CJ13: ='Model Assumptions'!CL48 -> 1875000
B14: GH2x6 - Des Moines | E14: ='Model Assumptions'!G56 -> 0 | F14: ='Model Assumptions'!H56 -> 0 | G14: ='Model Assumptions'!I56 -> 0 | H14: ='Model Assumptions'!J56 -> 0 | I14: ='Model Assumptions'!K56 -> 0 | J14: ='Model Assumptions'!L56 -> 0 | K14: ='Model Assumptions'!M56 -> 0 | L14: ='Model Assumptions'!N56 -> 0 | ... CJ14: ='Model Assumptions'!CL56 -> 1875000
B15: GH2x7-12 | E15: ='Model Assumptions'!G64 -> 0 | F15: ='Model Assumptions'!H64 -> 0 | G15: ='Model Assumptions'!I64 -> 0 | H15: ='Model Assumptions'!J64 -> 0 | I15: ='Model Assumptions'!K64 -> 0 | J15: ='Model Assumptions'!L64 -> 0 | K15: ='Model Assumptions'!M64 -> 0 | L15: ='Model Assumptions'!N64 -> 0 | ... CJ15: ='Model Assumptions'!CL64 -> 11250000
B16: Equipment Sales | E16: ='Model Assumptions'!G67*'Base Case Inputs'!$B$27+'Model Assumptions'!G133*'Base Case Inputs'!$B$33 -> 67307.692 | F16: ='Model Assumptions'!H67*'Base Case Inputs'!$B$27+'Model Assumptions'!H133*'Base Case Inputs'!$B$33 -> 67307.692 | G16: ='Model Assumptions'!I67*'Base Case Inputs'!$B$27+'Model Assumptions'!I133*'Base Case Inputs'!$B$33 -> 67307.692 | H16: ='Model Assumptions'!J67*'Base Case Inputs'!$B$27+'Model Assumptions'!J133*'Base Case Inputs'!$B$33 -> 67307.692 | I16: ='Model Assumptions'!K67*'Base Case Inputs'!$B$27+'Model Assumptions'!K133*'Base Case Inputs'!$B$33 -> 67307.692 | J16: ='Model Assumptions'!L67*'Base Case Inputs'!$B$27+'Model Assumptions'!L133*'Base Case Inputs'!$B$33 -> 67307.692 | K16: ='Model Assumptions'!M67*'Base Case Inputs'!$B$27+'Model Assumptions'!M133*'Base Case Inputs'!$B$33 -> 67307.692 | L16: ='Model Assumptions'!N67*'Base Case Inputs'!$B$27+'Model Assumptions'!N133*'Base Case Inputs'!$B$33 -> 67307.692 | ... CJ16: ='Model Assumptions'!CL67*'Base Case Inputs'!$B$27+'Model Assumptions'!CL133*'Base Case Inputs'!$B$33 -> 4255000
B17: Services Revenue | E17: ='Model Assumptions'!G132*'Base Case Inputs'!$B$31/12*(1+'Base Case Inputs'!$B$132)^MAX(E$1-2,0)+'Model Assumptions'!G135*'Base Case Inputs'!$B$37/12*(1+'Base Case Inputs'!$B$132)^MAX(E$1-2,0) -> 0 | F17: ='Model Assumptions'!H132*'Base Case Inputs'!$B$31/12*(1+'Base Case Inputs'!$B$132)^MAX(F$1-2,0)+'Model Assumptions'!H135*'Base Case Inputs'!$B$37/12*(1+'Base Case Inputs'!$B$132)^MAX(F$1-2,0) -> 0 | G17: ='Model Assumptions'!I132*'Base Case Inputs'!$B$31/12*(1+'Base Case Inputs'!$B$132)^MAX(G$1-2,0)+'Model Assumptions'!I135*'Base Case Inputs'!$B$37/12*(1+'Base Case Inputs'!$B$132)^MAX(G$1-2,0) -> 0 | H17: ='Model Assumptions'!J132*'Base Case Inputs'!$B$31/12*(1+'Base Case Inputs'!$B$132)^MAX(H$1-2,0)+'Model Assumptions'!J135*'Base Case Inputs'!$B$37/12*(1+'Base Case Inputs'!$B$132)^MAX(H$1-2,0) -> 0 | I17: ='Model Assumptions'!K132*'Base Case Inputs'!$B$31/12*(1+'Base Case Inputs'!$B$132)^MAX(I$1-2,0)+'Model Assumptions'!K135*'Base Case Inputs'!$B$37/12*(1+'Base Case Inputs'!$B$132)^MAX(I$1-2,0) -> 0 | J17: ='Model Assumptions'!L132*'Base Case Inputs'!$B$31/12*(1+'Base Case Inputs'!$B$132)^MAX(J$1-2,0)+'Model Assumptions'!L135*'Base Case Inputs'!$B$37/12*(1+'Base Case Inputs'!$B$132)^MAX(J$1-2,0) -> 0 | K17: ='Model Assumptions'!M132*'Base Case Inputs'!$B$31/12*(1+'Base Case Inputs'!$B$132)^MAX(K$1-2,0)+'Model Assumptions'!M135*'Base Case Inputs'!$B$37/12*(1+'Base Case Inputs'!$B$132)^MAX(K$1-2,0) -> 0 | L17: ='Model Assumptions'!N132*'Base Case Inputs'!$B$31/12*(1+'Base Case Inputs'!$B$132)^MAX(L$1-2,0)+'Model Assumptions'!N135*'Base Case Inputs'!$B$37/12*(1+'Base Case Inputs'!$B$132)^MAX(L$1-2,0) -> 0 | ... CJ17: ='Model Assumptions'!CL132*'Base Case Inputs'!$B$31/12*(1+'Base Case Inputs'!$B$132)^MAX(CJ$1-2,0)+'Model Assumptions'!CL135*'Base Case Inputs'!$B$37/12*(1+'Base Case Inputs'!$B$132)^MAX(CJ$1-2,0) -> 666520.45
B18: H₂ Production COGS | E18: ='Model Assumptions'!G17+'Model Assumptions'!G25+'Model Assumptions'!G33+'Model Assumptions'!G41+'Model Assumptions'!G49+'Model Assumptions'!G57+'Model Assumptions'!G65 -> 0 | F18: ='Model Assumptions'!H17+'Model Assumptions'!H25+'Model Assumptions'!H33+'Model Assumptions'!H41+'Model Assumptions'!H49+'Model Assumptions'!H57+'Model Assumptions'!H65 -> 0 | G18: ='Model Assumptions'!I17+'Model Assumptions'!I25+'Model Assumptions'!I33+'Model Assumptions'!I41+'Model Assumptions'!I49+'Model Assumptions'!I57+'Model Assumptions'!I65 -> 0 | H18: ='Model Assumptions'!J17+'Model Assumptions'!J25+'Model Assumptions'!J33+'Model Assumptions'!J41+'Model Assumptions'!J49+'Model Assumptions'!J57+'Model Assumptions'!J65 -> 0 | I18: ='Model Assumptions'!K17+'Model Assumptions'!K25+'Model Assumptions'!K33+'Model Assumptions'!K41+'Model Assumptions'!K49+'Model Assumptions'!K57+'Model Assumptions'!K65 -> 0 | J18: ='Model Assumptions'!L17+'Model Assumptions'!L25+'Model Assumptions'!L33+'Model Assumptions'!L41+'Model Assumptions'!L49+'Model Assumptions'!L57+'Model Assumptions'!L65 -> 0 | K18: ='Model Assumptions'!M17+'Model Assumptions'!M25+'Model Assumptions'!M33+'Model Assumptions'!M41+'Model Assumptions'!M49+'Model Assumptions'!M57+'Model Assumptions'!M65 -> 0 | L18: ='Model Assumptions'!N17+'Model Assumptions'!N25+'Model Assumptions'!N33+'Model Assumptions'!N41+'Model Assumptions'!N49+'Model Assumptions'!N57+'Model Assumptions'!N65 -> 0 | ... CJ18: ='Model Assumptions'!CL17+'Model Assumptions'!CL25+'Model Assumptions'!CL33+'Model Assumptions'!CL41+'Model Assumptions'!CL49+'Model Assumptions'!CL57+'Model Assumptions'!CL65 -> 3190100.6
B19: Equipment COGS | E19: ='Model Assumptions'!G67*IF(E$1<=1,'Learning Curve'!$C$74,IF(E$1<=2,'Learning Curve'!$D$74,IF(E$1<=3,'Learning Curve'!$E$74,IF(E$1<=4,'Learning Curve'!$F$74,IF(E$1<=5,'Learning Curve'!$G$74,'Learning Curve'!$H$74)))))+'Model Assumptions'!G133*IF(E$1<=2,'Learning Curve'!$C$75,IF(E$1<=3,'Learning Curve'!$D$75,IF(E$1<=4,'Learning Curve'!$E$75,IF(E$1<=5,'Learning Curve'!$F$75,IF(E$1<=6,'Learning Curve'!$G$75,'Learning Curve'!$H$75))))) -> 40384.615 | F19: ='Model Assumptions'!H67*IF(F$1<=1,'Learning Curve'!$C$74,IF(F$1<=2,'Learning Curve'!$D$74,IF(F$1<=3,'Learning Curve'!$E$74,IF(F$1<=4,'Learning Curve'!$F$74,IF(F$1<=5,'Learning Curve'!$G$74,'Learning Curve'!$H$74)))))+'Model Assumptions'!H133*IF(F$1<=2,'Learning Curve'!$C$75,IF(F$1<=3,'Learning Curve'!$D$75,IF(F$1<=4,'Learning Curve'!$E$75,IF(F$1<=5,'Learning Curve'!$F$75,IF(F$1<=6,'Learning Curve'!$G$75,'Learning Curve'!$H$75))))) -> 40384.615 | G19: ='Model Assumptions'!I67*IF(G$1<=1,'Learning Curve'!$C$74,IF(G$1<=2,'Learning Curve'!$D$74,IF(G$1<=3,'Learning Curve'!$E$74,IF(G$1<=4,'Learning Curve'!$F$74,IF(G$1<=5,'Learning Curve'!$G$74,'Learning Curve'!$H$74)))))+'Model Assumptions'!I133*IF(G$1<=2,'Learning Curve'!$C$75,IF(G$1<=3,'Learning Curve'!$D$75,IF(G$1<=4,'Learning Curve'!$E$75,IF(G$1<=5,'Learning Curve'!$F$75,IF(G$1<=6,'Learning Curve'!$G$75,'Learning Curve'!$H$75))))) -> 40384.615 | H19: ='Model Assumptions'!J67*IF(H$1<=1,'Learning Curve'!$C$74,IF(H$1<=2,'Learning Curve'!$D$74,IF(H$1<=3,'Learning Curve'!$E$74,IF(H$1<=4,'Learning Curve'!$F$74,IF(H$1<=5,'Learning Curve'!$G$74,'Learning Curve'!$H$74)))))+'Model Assumptions'!J133*IF(H$1<=2,'Learning Curve'!$C$75,IF(H$1<=3,'Learning Curve'!$D$75,IF(H$1<=4,'Learning Curve'!$E$75,IF(H$1<=5,'Learning Curve'!$F$75,IF(H$1<=6,'Learning Curve'!$G$75,'Learning Curve'!$H$75))))) -> 40384.615 | I19: ='Model Assumptions'!K67*IF(I$1<=1,'Learning Curve'!$C$74,IF(I$1<=2,'Learning Curve'!$D$74,IF(I$1<=3,'Learning Curve'!$E$74,IF(I$1<=4,'Learning Curve'!$F$74,IF(I$1<=5,'Learning Curve'!$G$74,'Learning Curve'!$H$74)))))+'Model Assumptions'!K133*IF(I$1<=2,'Learning Curve'!$C$75,IF(I$1<=3,'Learning Curve'!$D$75,IF(I$1<=4,'Learning Curve'!$E$75,IF(I$1<=5,'Learning Curve'!$F$75,IF(I$1<=6,'Learning Curve'!$G$75,'Learning Curve'!$H$75))))) -> 40384.615 | J19: ='Model Assumptions'!L67*IF(J$1<=1,'Learning Curve'!$C$74,IF(J$1<=2,'Learning Curve'!$D$74,IF(J$1<=3,'Learning Curve'!$E$74,IF(J$1<=4,'Learning Curve'!$F$74,IF(J$1<=5,'Learning Curve'!$G$74,'Learning Curve'!$H$74)))))+'Model Assumptions'!L133*IF(J$1<=2,'Learning Curve'!$C$75,IF(J$1<=3,'Learning Curve'!$D$75,IF(J$1<=4,'Learning Curve'!$E$75,IF(J$1<=5,'Learning Curve'!$F$75,IF(J$1<=6,'Learning Curve'!$G$75,'Learning Curve'!$H$75))))) -> 40384.615 | K19: ='Model Assumptions'!M67*IF(K$1<=1,'Learning Curve'!$C$74,IF(K$1<=2,'Learning Curve'!$D$74,IF(K$1<=3,'Learning Curve'!$E$74,IF(K$1<=4,'Learning Curve'!$F$74,IF(K$1<=5,'Learning Curve'!$G$74,'Learning Curve'!$H$74)))))+'Model Assumptions'!M133*IF(K$1<=2,'Learning Curve'!$C$75,IF(K$1<=3,'Learning Curve'!$D$75,IF(K$1<=4,'Learning Curve'!$E$75,IF(K$1<=5,'Learning Curve'!$F$75,IF(K$1<=6,'Learning Curve'!$G$75,'Learning Curve'!$H$75))))) -> 40384.615 | L19: ='Model Assumptions'!N67*IF(L$1<=1,'Learning Curve'!$C$74,IF(L$1<=2,'Learning Curve'!$D$74,IF(L$1<=3,'Learning Curve'!$E$74,IF(L$1<=4,'Learning Curve'!$F$74,IF(L$1<=5,'Learning Curve'!$G$74,'Learning Curve'!$H$74)))))+'Model Assumptions'!N133*IF(L$1<=2,'Learning Curve'!$C$75,IF(L$1<=3,'Learning Curve'!$D$75,IF(L$1<=4,'Learning Curve'!$E$75,IF(L$1<=5,'Learning Curve'!$F$75,IF(L$1<=6,'Learning Curve'!$G$75,'Learning Curve'!$H$75))))) -> 40384.615 | ... CJ19: ='Model Assumptions'!CL67*IF(CJ$1<=1,'Learning Curve'!$C$74,IF(CJ$1<=2,'Learning Curve'!$D$74,IF(CJ$1<=3,'Learning Curve'!$E$74,IF(CJ$1<=4,'Learning Curve'!$F$74,IF(CJ$1<=5,'Learning Curve'!$G$74,'Learning Curve'!$H$74)))))+'Model Assumptions'!CL133*IF(CJ$1<=2,'Learning Curve'!$C$75,IF(CJ$1<=3,'Learning Curve'!$D$75,IF(CJ$1<=4,'Learning Curve'!$E$75,IF(CJ$1<=5,'Learning Curve'!$F$75,IF(CJ$1<=6,'Learning Curve'!$G$75,'Learning Curve'!$H$75))))) -> 2002500
B20: Services COGS | E20: =E17*'Base Case Inputs'!$B$39 -> 0 | F20: =F17*'Base Case Inputs'!$B$39 -> 0 | G20: =G17*'Base Case Inputs'!$B$39 -> 0 | H20: =H17*'Base Case Inputs'!$B$39 -> 0 | I20: =I17*'Base Case Inputs'!$B$39 -> 0 | J20: =J17*'Base Case Inputs'!$B$39 -> 0 | K20: =K17*'Base Case Inputs'!$B$39 -> 0 | L20: =L17*'Base Case Inputs'!$B$39 -> 0 | ... CJ20: =CJ17*'Base Case Inputs'!$B$39 -> 133304.09
B21: TOTAL COGS | E21: =E18+E19+E20 -> 40384.615 | F21: =F18+F19+F20 -> 40384.615 | G21: =G18+G19+G20 -> 40384.615 | H21: =H18+H19+H20 -> 40384.615 | I21: =I18+I19+I20 -> 40384.615 | J21: =J18+J19+J20 -> 40384.615 | K21: =K18+K19+K20 -> 40384.615 | L21: =L18+L19+L20 -> 40384.615 | ... CJ21: =CJ18+CJ19+CJ20 -> 5325904.7
B22: Gross Profit | E22: =E8-E21 -> 26923.077 | F22: =F8-F21 -> 26923.077 | G22: =G8-G21 -> 26923.077 | H22: =H8-H21 -> 26923.077 | I22: =I8-I21 -> 26923.077 | J22: =J8-J21 -> 26923.077 | K22: =K8-K21 -> 26923.077 | L22: =L8-L21 -> 26923.077 | ... CJ22: =CJ8-CJ21 -> 22095616
B23: Gross Margin | E23: =IFERROR(E22/E8,0) -> 0.4 | F23: =IFERROR(F22/F8,0) -> 0.4 | G23: =IFERROR(G22/G8,0) -> 0.4 | H23: =IFERROR(H22/H8,0) -> 0.4 | I23: =IFERROR(I22/I8,0) -> 0.4 | J23: =IFERROR(J22/J8,0) -> 0.4 | K23: =IFERROR(K22/K8,0) -> 0.4 | L23: =IFERROR(L22/L8,0) -> 0.4 | ... CJ23: =IFERROR(CJ22/CJ8,0) -> 0.80577646
B25: Operating Expenses
B26: Base Salaries | E26: =('Model Assumptions'!G14+'Model Assumptions'!G22+'Model Assumptions'!G30+'Model Assumptions'!G38+'Model Assumptions'!G46+'Model Assumptions'!G54+'Model Assumptions'!G62)/(1+'Base Case Inputs'!$B$75) -> 56333.333 | F26: =('Model Assumptions'!H14+'Model Assumptions'!H22+'Model Assumptions'!H30+'Model Assumptions'!H38+'Model Assumptions'!H46+'Model Assumptions'!H54+'Model Assumptions'!H62)/(1+'Base Case Inputs'!$B$75) -> 64250 | G26: =('Model Assumptions'!I14+'Model Assumptions'!I22+'Model Assumptions'!I30+'Model Assumptions'!I38+'Model Assumptions'!I46+'Model Assumptions'!I54+'Model Assumptions'!I62)/(1+'Base Case Inputs'!$B$75) -> 82583.333 | H26: =('Model Assumptions'!J14+'Model Assumptions'!J22+'Model Assumptions'!J30+'Model Assumptions'!J38+'Model Assumptions'!J46+'Model Assumptions'!J54+'Model Assumptions'!J62)/(1+'Base Case Inputs'!$B$75) -> 106333.33 | I26: =('Model Assumptions'!K14+'Model Assumptions'!K22+'Model Assumptions'!K30+'Model Assumptions'!K38+'Model Assumptions'!K46+'Model Assumptions'!K54+'Model Assumptions'!K62)/(1+'Base Case Inputs'!$B$75) -> 113416.67 | J26: =('Model Assumptions'!L14+'Model Assumptions'!L22+'Model Assumptions'!L30+'Model Assumptions'!L38+'Model Assumptions'!L46+'Model Assumptions'!L54+'Model Assumptions'!L62)/(1+'Base Case Inputs'!$B$75) -> 120083.33 | K26: =('Model Assumptions'!M14+'Model Assumptions'!M22+'Model Assumptions'!M30+'Model Assumptions'!M38+'Model Assumptions'!M46+'Model Assumptions'!M54+'Model Assumptions'!M62)/(1+'Base Case Inputs'!$B$75) -> 120083.33 | L26: =('Model Assumptions'!N14+'Model Assumptions'!N22+'Model Assumptions'!N30+'Model Assumptions'!N38+'Model Assumptions'!N46+'Model Assumptions'!N54+'Model Assumptions'!N62)/(1+'Base Case Inputs'!$B$75) -> 120083.33 | ... CJ26: =('Model Assumptions'!CL14+'Model Assumptions'!CL22+'Model Assumptions'!CL30+'Model Assumptions'!CL38+'Model Assumptions'!CL46+'Model Assumptions'!CL54+'Model Assumptions'!CL62)/(1+'Base Case Inputs'!$B$75) -> 1734775.5
B27: Benefits & Payroll Taxes | E27: =('Model Assumptions'!G14+'Model Assumptions'!G22+'Model Assumptions'!G30+'Model Assumptions'!G38+'Model Assumptions'!G46+'Model Assumptions'!G54+'Model Assumptions'!G62)-E26 -> 21046.133 | F27: =('Model Assumptions'!H14+'Model Assumptions'!H22+'Model Assumptions'!H30+'Model Assumptions'!H38+'Model Assumptions'!H46+'Model Assumptions'!H54+'Model Assumptions'!H62)-F26 -> 24003.8 | G27: =('Model Assumptions'!I14+'Model Assumptions'!I22+'Model Assumptions'!I30+'Model Assumptions'!I38+'Model Assumptions'!I46+'Model Assumptions'!I54+'Model Assumptions'!I62)-G26 -> 30853.133 | H27: =('Model Assumptions'!J14+'Model Assumptions'!J22+'Model Assumptions'!J30+'Model Assumptions'!J38+'Model Assumptions'!J46+'Model Assumptions'!J54+'Model Assumptions'!J62)-H26 -> 39726.133 | I27: =('Model Assumptions'!K14+'Model Assumptions'!K22+'Model Assumptions'!K30+'Model Assumptions'!K38+'Model Assumptions'!K46+'Model Assumptions'!K54+'Model Assumptions'!K62)-I26 -> 42372.467 | J27: =('Model Assumptions'!L14+'Model Assumptions'!L22+'Model Assumptions'!L30+'Model Assumptions'!L38+'Model Assumptions'!L46+'Model Assumptions'!L54+'Model Assumptions'!L62)-J26 -> 44863.133 | K27: =('Model Assumptions'!M14+'Model Assumptions'!M22+'Model Assumptions'!M30+'Model Assumptions'!M38+'Model Assumptions'!M46+'Model Assumptions'!M54+'Model Assumptions'!M62)-K26 -> 44863.133 | L27: =('Model Assumptions'!N14+'Model Assumptions'!N22+'Model Assumptions'!N30+'Model Assumptions'!N38+'Model Assumptions'!N46+'Model Assumptions'!N54+'Model Assumptions'!N62)-L26 -> 44863.133 | ... CJ27: =('Model Assumptions'!CL14+'Model Assumptions'!CL22+'Model Assumptions'!CL30+'Model Assumptions'!CL38+'Model Assumptions'!CL46+'Model Assumptions'!CL54+'Model Assumptions'!CL62)-CJ26 -> 648112.13
B28: Headquarters Lease — $8,750/mo | E28: ='Base Case Inputs'!$B$78*(1+'Base Case Inputs'!$B$88)^(E$1-1) -> 8750 | F28: ='Base Case Inputs'!$B$78*(1+'Base Case Inputs'!$B$88)^(F$1-1) -> 8750 | G28: ='Base Case Inputs'!$B$78*(1+'Base Case Inputs'!$B$88)^(G$1-1) -> 8750 | H28: ='Base Case Inputs'!$B$78*(1+'Base Case Inputs'!$B$88)^(H$1-1) -> 8750 | I28: ='Base Case Inputs'!$B$78*(1+'Base Case Inputs'!$B$88)^(I$1-1) -> 8750 | J28: ='Base Case Inputs'!$B$78*(1+'Base Case Inputs'!$B$88)^(J$1-1) -> 8750 | K28: ='Base Case Inputs'!$B$78*(1+'Base Case Inputs'!$B$88)^(K$1-1) -> 8750 | L28: ='Base Case Inputs'!$B$78*(1+'Base Case Inputs'!$B$88)^(L$1-1) -> 8750 | ... CJ28: ='Base Case Inputs'!$B$78*(1+'Base Case Inputs'!$B$88)^(CJ$1-1) -> 10147.317
B29: Production Facility Leases | E29: =(IF(E$4>='Model Assumptions'!$D$12,'Base Case Inputs'!$B$142,0)+IF(E$4>='Model Assumptions'!$D$20,'Base Case Inputs'!$B$143,0)+IF(E$4>='Model Assumptions'!$D$28,'Base Case Inputs'!$B$144,0)+IF(E$4>='Model Assumptions'!$D$36,'Base Case Inputs'!$B$145,0)+IF(E$4>='Model Assumptions'!$D$44,'Base Case Inputs'!$B$146,0)+IF(E$4>='Model Assumptions'!$D$52,'Base Case Inputs'!$B$147,0)+IF(E$4>='Base Case Inputs'!$B$188,'Base Case Inputs'!$B$148,0)+IF(E$4>='Base Case Inputs'!$B$189,'Base Case Inputs'!$B$149,0)+IF(E$4>='Base Case Inputs'!$B$190,'Base Case Inputs'!$B$150,0)+IF(E$4>='Base Case Inputs'!$B$191,'Base Case Inputs'!$B$151,0)+IF(E$4>='Base Case Inputs'!$B$192,'Base Case Inputs'!$B$152,0)+IF(E$4>='Base Case Inputs'!$B$193,'Base Case Inputs'!$B$153,0))*(1+'Base Case Inputs'!$B$88)^(E$1-1) -> 8750 | F29: =(IF(F$4>='Model Assumptions'!$D$12,'Base Case Inputs'!$B$142,0)+IF(F$4>='Model Assumptions'!$D$20,'Base Case Inputs'!$B$143,0)+IF(F$4>='Model Assumptions'!$D$28,'Base Case Inputs'!$B$144,0)+IF(F$4>='Model Assumptions'!$D$36,'Base Case Inputs'!$B$145,0)+IF(F$4>='Model Assumptions'!$D$44,'Base Case Inputs'!$B$146,0)+IF(F$4>='Model Assumptions'!$D$52,'Base Case Inputs'!$B$147,0)+IF(F$4>='Base Case Inputs'!$B$188,'Base Case Inputs'!$B$148,0)+IF(F$4>='Base Case Inputs'!$B$189,'Base Case Inputs'!$B$149,0)+IF(F$4>='Base Case Inputs'!$B$190,'Base Case Inputs'!$B$150,0)+IF(F$4>='Base Case Inputs'!$B$191,'Base Case Inputs'!$B$151,0)+IF(F$4>='Base Case Inputs'!$B$192,'Base Case Inputs'!$B$152,0)+IF(F$4>='Base Case Inputs'!$B$193,'Base Case Inputs'!$B$153,0))*(1+'Base Case Inputs'!$B$88)^(F$1-1) -> 8750 | G29: =(IF(G$4>='Model Assumptions'!$D$12,'Base Case Inputs'!$B$142,0)+IF(G$4>='Model Assumptions'!$D$20,'Base Case Inputs'!$B$143,0)+IF(G$4>='Model Assumptions'!$D$28,'Base Case Inputs'!$B$144,0)+IF(G$4>='Model Assumptions'!$D$36,'Base Case Inputs'!$B$145,0)+IF(G$4>='Model Assumptions'!$D$44,'Base Case Inputs'!$B$146,0)+IF(G$4>='Model Assumptions'!$D$52,'Base Case Inputs'!$B$147,0)+IF(G$4>='Base Case Inputs'!$B$188,'Base Case Inputs'!$B$148,0)+IF(G$4>='Base Case Inputs'!$B$189,'Base Case Inputs'!$B$149,0)+IF(G$4>='Base Case Inputs'!$B$190,'Base Case Inputs'!$B$150,0)+IF(G$4>='Base Case Inputs'!$B$191,'Base Case Inputs'!$B$151,0)+IF(G$4>='Base Case Inputs'!$B$192,'Base Case Inputs'!$B$152,0)+IF(G$4>='Base Case Inputs'!$B$193,'Base Case Inputs'!$B$153,0))*(1+'Base Case Inputs'!$B$88)^(G$1-1) -> 8750 | H29: =(IF(H$4>='Model Assumptions'!$D$12,'Base Case Inputs'!$B$142,0)+IF(H$4>='Model Assumptions'!$D$20,'Base Case Inputs'!$B$143,0)+IF(H$4>='Model Assumptions'!$D$28,'Base Case Inputs'!$B$144,0)+IF(H$4>='Model Assumptions'!$D$36,'Base Case Inputs'!$B$145,0)+IF(H$4>='Model Assumptions'!$D$44,'Base Case Inputs'!$B$146,0)+IF(H$4>='Model Assumptions'!$D$52,'Base Case Inputs'!$B$147,0)+IF(H$4>='Base Case Inputs'!$B$188,'Base Case Inputs'!$B$148,0)+IF(H$4>='Base Case Inputs'!$B$189,'Base Case Inputs'!$B$149,0)+IF(H$4>='Base Case Inputs'!$B$190,'Base Case Inputs'!$B$150,0)+IF(H$4>='Base Case Inputs'!$B$191,'Base Case Inputs'!$B$151,0)+IF(H$4>='Base Case Inputs'!$B$192,'Base Case Inputs'!$B$152,0)+IF(H$4>='Base Case Inputs'!$B$193,'Base Case Inputs'!$B$153,0))*(1+'Base Case Inputs'!$B$88)^(H$1-1) -> 8750 | I29: =(IF(I$4>='Model Assumptions'!$D$12,'Base Case Inputs'!$B$142,0)+IF(I$4>='Model Assumptions'!$D$20,'Base Case Inputs'!$B$143,0)+IF(I$4>='Model Assumptions'!$D$28,'Base Case Inputs'!$B$144,0)+IF(I$4>='Model Assumptions'!$D$36,'Base Case Inputs'!$B$145,0)+IF(I$4>='Model Assumptions'!$D$44,'Base Case Inputs'!$B$146,0)+IF(I$4>='Model Assumptions'!$D$52,'Base Case Inputs'!$B$147,0)+IF(I$4>='Base Case Inputs'!$B$188,'Base Case Inputs'!$B$148,0)+IF(I$4>='Base Case Inputs'!$B$189,'Base Case Inputs'!$B$149,0)+IF(I$4>='Base Case Inputs'!$B$190,'Base Case Inputs'!$B$150,0)+IF(I$4>='Base Case Inputs'!$B$191,'Base Case Inputs'!$B$151,0)+IF(I$4>='Base Case Inputs'!$B$192,'Base Case Inputs'!$B$152,0)+IF(I$4>='Base Case Inputs'!$B$193,'Base Case Inputs'!$B$153,0))*(1+'Base Case Inputs'!$B$88)^(I$1-1) -> 8750 | J29: =(IF(J$4>='Model Assumptions'!$D$12,'Base Case Inputs'!$B$142,0)+IF(J$4>='Model Assumptions'!$D$20,'Base Case Inputs'!$B$143,0)+IF(J$4>='Model Assumptions'!$D$28,'Base Case Inputs'!$B$144,0)+IF(J$4>='Model Assumptions'!$D$36,'Base Case Inputs'!$B$145,0)+IF(J$4>='Model Assumptions'!$D$44,'Base Case Inputs'!$B$146,0)+IF(J$4>='Model Assumptions'!$D$52,'Base Case Inputs'!$B$147,0)+IF(J$4>='Base Case Inputs'!$B$188,'Base Case Inputs'!$B$148,0)+IF(J$4>='Base Case Inputs'!$B$189,'Base Case Inputs'!$B$149,0)+IF(J$4>='Base Case Inputs'!$B$190,'Base Case Inputs'!$B$150,0)+IF(J$4>='Base Case Inputs'!$B$191,'Base Case Inputs'!$B$151,0)+IF(J$4>='Base Case Inputs'!$B$192,'Base Case Inputs'!$B$152,0)+IF(J$4>='Base Case Inputs'!$B$193,'Base Case Inputs'!$B$153,0))*(1+'Base Case Inputs'!$B$88)^(J$1-1) -> 8750 | K29: =(IF(K$4>='Model Assumptions'!$D$12,'Base Case Inputs'!$B$142,0)+IF(K$4>='Model Assumptions'!$D$20,'Base Case Inputs'!$B$143,0)+IF(K$4>='Model Assumptions'!$D$28,'Base Case Inputs'!$B$144,0)+IF(K$4>='Model Assumptions'!$D$36,'Base Case Inputs'!$B$145,0)+IF(K$4>='Model Assumptions'!$D$44,'Base Case Inputs'!$B$146,0)+IF(K$4>='Model Assumptions'!$D$52,'Base Case Inputs'!$B$147,0)+IF(K$4>='Base Case Inputs'!$B$188,'Base Case Inputs'!$B$148,0)+IF(K$4>='Base Case Inputs'!$B$189,'Base Case Inputs'!$B$149,0)+IF(K$4>='Base Case Inputs'!$B$190,'Base Case Inputs'!$B$150,0)+IF(K$4>='Base Case Inputs'!$B$191,'Base Case Inputs'!$B$151,0)+IF(K$4>='Base Case Inputs'!$B$192,'Base Case Inputs'!$B$152,0)+IF(K$4>='Base Case Inputs'!$B$193,'Base Case Inputs'!$B$153,0))*(1+'Base Case Inputs'!$B$88)^(K$1-1) -> 17500 | L29: =(IF(L$4>='Model Assumptions'!$D$12,'Base Case Inputs'!$B$142,0)+IF(L$4>='Model Assumptions'!$D$20,'Base Case Inputs'!$B$143,0)+IF(L$4>='Model Assumptions'!$D$28,'Base Case Inputs'!$B$144,0)+IF(L$4>='Model Assumptions'!$D$36,'Base Case Inputs'!$B$145,0)+IF(L$4>='Model Assumptions'!$D$44,'Base Case Inputs'!$B$146,0)+IF(L$4>='Model Assumptions'!$D$52,'Base Case Inputs'!$B$147,0)+IF(L$4>='Base Case Inputs'!$B$188,'Base Case Inputs'!$B$148,0)+IF(L$4>='Base Case Inputs'!$B$189,'Base Case Inputs'!$B$149,0)+IF(L$4>='Base Case Inputs'!$B$190,'Base Case Inputs'!$B$150,0)+IF(L$4>='Base Case Inputs'!$B$191,'Base Case Inputs'!$B$151,0)+IF(L$4>='Base Case Inputs'!$B$192,'Base Case Inputs'!$B$152,0)+IF(L$4>='Base Case Inputs'!$B$193,'Base Case Inputs'!$B$153,0))*(1+'Base Case Inputs'!$B$88)^(L$1-1) -> 17500 | ... CJ29: =(IF(CJ$4>='Model Assumptions'!$D$12,'Base Case Inputs'!$B$142,0)+IF(CJ$4>='Model Assumptions'!$D$20,'Base Case Inputs'!$B$143,0)+IF(CJ$4>='Model Assumptions'!$D$28,'Base Case Inputs'!$B$144,0)+IF(CJ$4>='Model Assumptions'!$D$36,'Base Case Inputs'!$B$145,0)+IF(CJ$4>='Model Assumptions'!$D$44,'Base Case Inputs'!$B$146,0)+IF(CJ$4>='Model Assumptions'!$D$52,'Base Case Inputs'!$B$147,0)+IF(CJ$4>='Base Case Inputs'!$B$188,'Base Case Inputs'!$B$148,0)+IF(CJ$4>='Base Case Inputs'!$B$189,'Base Case Inputs'!$B$149,0)+IF(CJ$4>='Base Case Inputs'!$B$190,'Base Case Inputs'!$B$150,0)+IF(CJ$4>='Base Case Inputs'!$B$191,'Base Case Inputs'!$B$151,0)+IF(CJ$4>='Base Case Inputs'!$B$192,'Base Case Inputs'!$B$152,0)+IF(CJ$4>='Base Case Inputs'!$B$193,'Base Case Inputs'!$B$153,0))*(1+'Base Case Inputs'!$B$88)^(CJ$1-1) -> 140032.98
B30: Professional Fees + Sales & Marketing | E30: =E8*'Base Case Inputs'!$B$76 -> 2019.2308 | F30: =F8*'Base Case Inputs'!$B$76 -> 2019.2308 | G30: =G8*'Base Case Inputs'!$B$76 -> 2019.2308 | H30: =H8*'Base Case Inputs'!$B$76 -> 2019.2308 | I30: =I8*'Base Case Inputs'!$B$76 -> 2019.2308 | J30: =J8*'Base Case Inputs'!$B$76 -> 2019.2308 | K30: =K8*'Base Case Inputs'!$B$76 -> 2019.2308 | L30: =L8*'Base Case Inputs'!$B$76 -> 2019.2308 | ... CJ30: =CJ8*'Base Case Inputs'!$B$76 -> 822645.61
B31: Other | E31: =E8*'Base Case Inputs'!$B$77 -> 1346.1538 | F31: =F8*'Base Case Inputs'!$B$77 -> 1346.1538 | G31: =G8*'Base Case Inputs'!$B$77 -> 1346.1538 | H31: =H8*'Base Case Inputs'!$B$77 -> 1346.1538 | I31: =I8*'Base Case Inputs'!$B$77 -> 1346.1538 | J31: =J8*'Base Case Inputs'!$B$77 -> 1346.1538 | K31: =K8*'Base Case Inputs'!$B$77 -> 1346.1538 | L31: =L8*'Base Case Inputs'!$B$77 -> 1346.1538 | ... CJ31: =CJ8*'Base Case Inputs'!$B$77 -> 548430.41
B32: R&D | E32: ='Base Case Inputs'!B$216 -> 64750 | F32: ='Base Case Inputs'!C$216 -> 121000 | G32: ='Base Case Inputs'!D$216 -> 120000 | H32: ='Base Case Inputs'!E$216 -> 99000 | I32: ='Base Case Inputs'!F$216 -> 106000 | J32: ='Base Case Inputs'!G$216 -> 96000 | K32: ='Base Case Inputs'!H$216 -> 76000 | L32: ='Base Case Inputs'!I$216 -> 71000 | ... CJ32: ='Base Case Inputs'!CG$216 -> 104166.67
B33: Total Operating Expenses | E33: =SUM(E26:E32) -> 162994.85 | F33: =SUM(F26:F32) -> 230119.18 | G33: =SUM(G26:G32) -> 254301.85 | H33: =SUM(H26:H32) -> 265924.85 | I33: =SUM(I26:I32) -> 282654.52 | J33: =SUM(J26:J32) -> 281811.85 | K33: =SUM(K26:K32) -> 270561.85 | L33: =SUM(L26:L32) -> 265561.85 | ... CJ33: =SUM(CJ26:CJ32) -> 4008310.6
B34: EBITDA | E34: =E22-E33 -> -136071.77 | F34: =F22-F33 -> -203196.11 | G34: =G22-G33 -> -227378.77 | H34: =H22-H33 -> -239001.77 | I34: =I22-I33 -> -255731.44 | J34: =J22-J33 -> -254888.77 | K34: =K22-K33 -> -243638.77 | L34: =L22-L33 -> -238638.77 | ... CJ34: =CJ22-CJ33 -> 18087305
B35: 45V Production Tax Credit | E35: ='Model Assumptions'!G69 -> 0 | F35: ='Model Assumptions'!H69 -> 0 | G35: ='Model Assumptions'!I69 -> 0 | H35: ='Model Assumptions'!J69 -> 0 | I35: ='Model Assumptions'!K69 -> 0 | J35: ='Model Assumptions'!L69 -> 0 | K35: ='Model Assumptions'!M69 -> 0 | L35: ='Model Assumptions'!N69 -> 0 | ... CJ35: ='Model Assumptions'!CL69 -> 900000
B36: Depreciation | E36: =SUM('Model Assumptions'!G96:G110)-SUM('Model Assumptions'!F96:F110) -> 0 | F36: =SUM('Model Assumptions'!H96:H110)-SUM('Model Assumptions'!G96:G110) -> 0 | G36: =SUM('Model Assumptions'!I96:I110)-SUM('Model Assumptions'!H96:H110) -> 0 | H36: =SUM('Model Assumptions'!J96:J110)-SUM('Model Assumptions'!I96:I110) -> 0 | I36: =SUM('Model Assumptions'!K96:K110)-SUM('Model Assumptions'!J96:J110) -> 0 | J36: =SUM('Model Assumptions'!L96:L110)-SUM('Model Assumptions'!K96:K110) -> 0 | K36: =SUM('Model Assumptions'!M96:M110)-SUM('Model Assumptions'!L96:L110) -> 0 | L36: =SUM('Model Assumptions'!N96:N110)-SUM('Model Assumptions'!M96:M110) -> 0 | ... CJ36: =SUM('Model Assumptions'!CL96:CL110)-SUM('Model Assumptions'!CK96:CK110) -> 519675.93
B37: EBIT | E37: =E34+E35-E36 -> -136071.77 | F37: =F34+F35-F36 -> -203196.11 | G37: =G34+G35-G36 -> -227378.77 | H37: =H34+H35-H36 -> -239001.77 | I37: =I34+I35-I36 -> -255731.44 | J37: =J34+J35-J36 -> -254888.77 | K37: =K34+K35-K36 -> -243638.77 | L37: =L34+L35-L36 -> -238638.77 | ... CJ37: =CJ34+CJ35-CJ36 -> 18467629
B38: Interest Expense | E38: =E88+E92 -> 0 | F38: =F88+F92 -> 0 | G38: =G88+G92 -> 0 | H38: =H88+H92 -> -14583.333 | I38: =I88+I92 -> -14583.333 | J38: =J88+J92 -> -14583.333 | K38: =K88+K92 -> -14583.333 | L38: =L88+L92 -> -14583.333 | ... CJ38: =CJ88+CJ92 -> -370019.94
B39: EBT | E39: =E37+E38 -> -136071.77 | F39: =F37+F38 -> -203196.11 | G39: =G37+G38 -> -227378.77 | H39: =H37+H38 -> -253585.11 | I39: =I37+I38 -> -270314.77 | J39: =J37+J38 -> -269472.11 | K39: =K37+K38 -> -258222.11 | L39: =L37+L38 -> -253222.11 | ... CJ39: =CJ37+CJ38 -> 18097609
B40: Taxes | E40: =IF(E39<=0,0,E39*'Base Case Inputs'!$B$71) -> 0 | F40: =IF(F39<=0,0,(F39-MIN(F39*0.8,E43))*'Base Case Inputs'!$B$71) -> 0 | G40: =IF(G39<=0,0,(G39-MIN(G39*0.8,F43))*'Base Case Inputs'!$B$71) -> 0 | H40: =IF(H39<=0,0,(H39-MIN(H39*0.8,G43))*'Base Case Inputs'!$B$71) -> 0 | I40: =IF(I39<=0,0,(I39-MIN(I39*0.8,H43))*'Base Case Inputs'!$B$71) -> 0 | J40: =IF(J39<=0,0,(J39-MIN(J39*0.8,I43))*'Base Case Inputs'!$B$71) -> 0 | K40: =IF(K39<=0,0,(K39-MIN(K39*0.8,J43))*'Base Case Inputs'!$B$71) -> 0 | L40: =IF(L39<=0,0,(L39-MIN(L39*0.8,K43))*'Base Case Inputs'!$B$71) -> 0 | M40: =IF(M39<=0,0,(M39-MIN(M39*0.8,L43))*'Base Case Inputs'!$B$71) -> 0 | ... CJ40: =IF(CJ39<=0,0,(CJ39-MIN(CJ39*0.8,CI43))*'Base Case Inputs'!$B$71) -> 4886354.5
B41: Net Income | E41: =E39-E40 -> -136071.77 | F41: =F39-F40 -> -203196.11 | G41: =G39-G40 -> -227378.77 | H41: =H39-H40 -> -253585.11 | I41: =I39-I40 -> -270314.77 | J41: =J39-J40 -> -269472.11 | K41: =K39-K40 -> -258222.11 | L41: =L39-L40 -> -253222.11 | ... CJ41: =CJ39-CJ40 -> 13211255
B42: Net Margin | E42: =IFERROR(E41/E8,0) -> -2.0216378 | F42: =IFERROR(F41/F8,0) -> -3.0189136 | G42: =IFERROR(G41/G8,0) -> -3.3781989 | H42: =IFERROR(H41/H8,0) -> -3.7675502 | I42: =IFERROR(I41/I8,0) -> -4.0161052 | J42: =IFERROR(J41/J8,0) -> -4.0035856 | K42: =IFERROR(K41/K8,0) -> -3.8364427 | L42: =IFERROR(L41/L8,0) -> -3.762157 | ... CJ42: =IFERROR(CJ41/CJ8,0) -> 0.48178418
B43: NOL Balance | D43: 0 | E43: =IF(E39<0,ABS(E39),0) -> 136071.77 | F43: =IF(F39<0,E43+ABS(F39),MAX(E43-MIN(F39*0.8,E43),0)) -> 339267.88 | G43: =IF(G39<0,F43+ABS(G39),MAX(F43-MIN(G39*0.8,F43),0)) -> 566646.66 | H43: =IF(H39<0,G43+ABS(H39),MAX(G43-MIN(H39*0.8,G43),0)) -> 820231.76 | I43: =IF(I39<0,H43+ABS(I39),MAX(H43-MIN(I39*0.8,H43),0)) -> 1090546.5 | J43: =IF(J39<0,I43+ABS(J39),MAX(I43-MIN(J39*0.8,I43),0)) -> 1360018.6 | K43: =IF(K39<0,J43+ABS(K39),MAX(J43-MIN(K39*0.8,J43),0)) -> 1618240.8 | L43: =IF(L39<0,K43+ABS(L39),MAX(K43-MIN(L39*0.8,K43),0)) -> 1871462.9 | M43: =IF(M39<0,L43+ABS(M39),MAX(L43-MIN(M39*0.8,L43),0)) -> 2124685 | ... CJ43: =IF(CJ39<0,CI43+ABS(CJ39),MAX(CI43-MIN(CJ39*0.8,CI43),0)) -> 0
B44: Balance Sheet:
B46: Assets
B47: Current Assets
B48: Cash | E48: =E101 -> 273110.92 | F48: =F101 -> 7294914.8 | G48: =G101 -> 6792536 | H48: =H101 -> 8424367.6 | I48: =I101 -> 7539469.5 | J48: =J101 -> 6655414 | K48: =K101 -> 5782608.6 | L48: =L101 -> 4914803.2 | ... CJ48: =CJ101 -> 8.3278198e+08
B49: Accounts Receivable | E49: ='Model Assumptions'!G76 -> 0 | F49: ='Model Assumptions'!H76 -> 0 | G49: ='Model Assumptions'!I76 -> 0 | H49: ='Model Assumptions'!J76 -> 0 | I49: ='Model Assumptions'!K76 -> 0 | J49: ='Model Assumptions'!L76 -> 0 | K49: ='Model Assumptions'!M76 -> 0 | L49: ='Model Assumptions'!N76 -> 0 | ... CJ49: ='Model Assumptions'!CL76 -> 11250000
B50: Total Current Assets | E50: =SUM(E48:E49) -> 273110.92 | F50: =SUM(F48:F49) -> 7294914.8 | G50: =SUM(G48:G49) -> 6792536 | H50: =SUM(H48:H49) -> 8424367.6 | I50: =SUM(I48:I49) -> 7539469.5 | J50: =SUM(J48:J49) -> 6655414 | K50: =SUM(K48:K49) -> 5782608.6 | L50: =SUM(L48:L49) -> 4914803.2 | ... CJ50: =SUM(CJ48:CJ49) -> 8.4403198e+08
B52: Fixed Assets | E52: =SUM('Model Assumptions'!G79:G93) -> 275000 | F52: =SUM('Model Assumptions'!H79:H93) -> 550000 | G52: =SUM('Model Assumptions'!I79:I93) -> 825000 | H52: =SUM('Model Assumptions'!J79:J93) -> 1439583.3 | I52: =SUM('Model Assumptions'!K79:K93) -> 2054166.7 | J52: =SUM('Model Assumptions'!L79:L93) -> 2668750 | K52: =SUM('Model Assumptions'!M79:M93) -> 3283333.3 | L52: =SUM('Model Assumptions'!N79:N93) -> 3897916.7 | ... CJ52: =SUM('Model Assumptions'!CL79:CL93) -> 56125000
B53: Accumulated Depreciation | E53: =-SUM('Model Assumptions'!G96:G110) -> 0 | F53: =-SUM('Model Assumptions'!H96:H110) -> 0 | G53: =-SUM('Model Assumptions'!I96:I110) -> 0 | H53: =-SUM('Model Assumptions'!J96:J110) -> 0 | I53: =-SUM('Model Assumptions'!K96:K110) -> 0 | J53: =-SUM('Model Assumptions'!L96:L110) -> 0 | K53: =-SUM('Model Assumptions'!M96:M110) -> 0 | L53: =-SUM('Model Assumptions'!N96:N110) -> 0 | ... CJ53: =-SUM('Model Assumptions'!CL96:CL110) -> -21749306
B54: Total Assets | E54: =SUM(E50:E53) -> 548110.92 | F54: =SUM(F50:F53) -> 7844914.8 | G54: =SUM(G50:G53) -> 7617536 | H54: =SUM(H50:H53) -> 9863950.9 | I54: =SUM(I50:I53) -> 9593636.2 | J54: =SUM(J50:J53) -> 9324164 | K54: =SUM(K50:K53) -> 9065941.9 | L54: =SUM(L50:L53) -> 8812719.8 | ... CJ54: =SUM(CJ50:CJ53) -> 8.7840768e+08
B56: Liabilities & Owner's Equity
B57: Liabilities
B58: Debt Outstanding | D58: 0 | E58: =D58+E86-E89 -> 0 | F58: =E58+F86-F89 -> 0 | G58: =F58+G86-G89 -> 0 | H58: =G58+H86-H89 -> 2500000 | I58: =H58+I86-I89 -> 2500000 | J58: =I58+J86-J89 -> 2500000 | K58: =J58+K86-K89 -> 2500000 | L58: =K58+L86-L89 -> 2500000 | ... CJ58: =CI58+CJ86-CJ89 -> 0
B59: Project Financing Outstanding | D59: 0 | E59: =D59+E90-E93 -> 0 | F59: =E59+F90-F93 -> 0 | G59: =F59+G90-G93 -> 0 | H59: =G59+H90-H93 -> 0 | I59: =H59+I90-I93 -> 0 | J59: =I59+J90-J93 -> 0 | K59: =J59+K90-K93 -> 0 | L59: =K59+L90-L93 -> 0 | ... CJ59: =CI59+CJ90-CJ93 -> 61843414
B60: Accounts payable | E60: ='Model Assumptions'!G115 -> 1682.6923 | F60: ='Model Assumptions'!H115 -> 1682.6923 | G60: ='Model Assumptions'!I115 -> 1682.6923 | H60: ='Model Assumptions'!J115 -> 1682.6923 | I60: ='Model Assumptions'!K115 -> 1682.6923 | J60: ='Model Assumptions'!L115 -> 1682.6923 | K60: ='Model Assumptions'!M115 -> 1682.6923 | L60: ='Model Assumptions'!N115 -> 1682.6923 | ... CJ60: ='Model Assumptions'!CL115 -> 2280588.3
B61: Total Liabilities | E61: =SUM(E57:E60) -> 1682.6923 | F61: =SUM(F57:F60) -> 1682.6923 | G61: =SUM(G57:G60) -> 1682.6923 | H61: =SUM(H57:H60) -> 2501682.7 | I61: =SUM(I57:I60) -> 2501682.7 | J61: =SUM(J57:J60) -> 2501682.7 | K61: =SUM(K57:K60) -> 2501682.7 | L61: =SUM(L57:L60) -> 2501682.7 | ... CJ61: =SUM(CJ57:CJ60) -> 64124002
B63: Equity
B64: Paid In Capital | D64: ='Base Case Inputs'!$B$86 -> 2050000 | E64: =D64+'Model Assumptions'!G129 -> 2050000 | F64: =E64+'Model Assumptions'!H129 -> 9550000 | G64: =F64+'Model Assumptions'!I129 -> 9550000 | H64: =G64+'Model Assumptions'!J129 -> 9550000 | I64: =H64+'Model Assumptions'!K129 -> 9550000 | J64: =I64+'Model Assumptions'!L129 -> 9550000 | K64: =J64+'Model Assumptions'!M129 -> 9550000 | L64: =K64+'Model Assumptions'!N129 -> 9550000 | ... CJ64: =CI64+'Model Assumptions'!CL129 -> 259550000
B65: Accumulated Retained Earnings | D65: ='Base Case Inputs'!$B$87 -> -1367500 | E65: =E41+D65 -> -1503571.8 | F65: =F41+E65 -> -1706767.9 | G65: =G41+F65 -> -1934146.7 | H65: =H41+G65 -> -2187731.8 | I65: =I41+H65 -> -2458046.5 | J65: =J41+I65 -> -2727518.6 | K65: =K41+J65 -> -2985740.8 | L65: =L41+K65 -> -3238962.9 | ... CJ65: =CJ41+CI65 -> 5.5473368e+08
B66: Total Equity | E66: =SUM(E64:E65) -> 546428.23 | F66: =SUM(F64:F65) -> 7843232.1 | G66: =SUM(G64:G65) -> 7615853.3 | H66: =SUM(H64:H65) -> 7362268.2 | I66: =SUM(I64:I65) -> 7091953.5 | J66: =SUM(J64:J65) -> 6822481.4 | K66: =SUM(K64:K65) -> 6564259.2 | L66: =SUM(L64:L65) -> 6311037.1 | ... CJ66: =SUM(CJ64:CJ65) -> 8.1428368e+08
B68: Total Liabilities & Owner's Equity | E68: =E66+E61 -> 548110.92 | F68: =F66+F61 -> 7844914.8 | G68: =G66+G61 -> 7617536 | H68: =H66+H61 -> 9863950.9 | I68: =I66+I61 -> 9593636.2 | J68: =J66+J61 -> 9324164 | K68: =K66+K61 -> 9065941.9 | L68: =L66+L61 -> 8812719.8 | ... CJ68: =CJ66+CJ61 -> 8.7840768e+08
B70: Balance Check | E70: =IF(ABS(E68-E54)>0.001,"ERROR","OK") -> OK | F70: =IF(ABS(F68-F54)>0.001,"ERROR","OK") -> OK | G70: =IF(ABS(G68-G54)>0.001,"ERROR","OK") -> OK | H70: =IF(ABS(H68-H54)>0.001,"ERROR","OK") -> OK | I70: =IF(ABS(I68-I54)>0.001,"ERROR","OK") -> OK | J70: =IF(ABS(J68-J54)>0.001,"ERROR","OK") -> OK | K70: =IF(ABS(K68-K54)>0.001,"ERROR","OK") -> OK | L70: =IF(ABS(L68-L54)>0.001,"ERROR","OK") -> OK | ... CJ70: =IF(ABS(CJ68-CJ54)>0.001,"ERROR","OK") -> OK
B72: Statement of Cash Flows:
B74: Operating Cash Flows
B75: Net Income | E75: =E65-D65 -> -136071.77 | F75: =F65-E65 -> -203196.11 | G75: =G65-F65 -> -227378.77 | H75: =H65-G65 -> -253585.11 | I75: =I65-H65 -> -270314.77 | J75: =J65-I65 -> -269472.11 | K75: =K65-J65 -> -258222.11 | L75: =L65-K65 -> -253222.11 | ... CJ75: =CJ65-CI65 -> 13211255
B76: Depreciation | E76: =D53-E53 -> 0 | F76: =E53-F53 -> 0 | G76: =F53-G53 -> 0 | H76: =G53-H53 -> 0 | I76: =H53-I53 -> 0 | J76: =I53-J53 -> 0 | K76: =J53-K53 -> 0 | L76: =K53-L53 -> 0 | ... CJ76: =CI53-CJ53 -> 519675.93
B77: Change in Accounts Receivable | E77: =D49-E49 -> 0 | F77: =E49-F49 -> 0 | G77: =F49-G49 -> 0 | H77: =G49-H49 -> 0 | I77: =H49-I49 -> 0 | J77: =I49-J49 -> 0 | K77: =J49-K49 -> 0 | L77: =K49-L49 -> 0 | ... CJ77: =CI49-CJ49 -> 0
B78: Change in Accounts Payable | E78: =E60-D60 -> 1682.6923 | F78: =F60-E60 -> 0 | G78: =G60-F60 -> 0 | H78: =H60-G60 -> 0 | I78: =I60-H60 -> 0 | J78: =J60-I60 -> 0 | K78: =K60-J60 -> 0 | L78: =L60-K60 -> 0 | ... CJ78: =CJ60-CI60 -> 531.59056
B79: Total Operating Cash Flows | E79: =SUM(E75:E78) -> -134389.08 | F79: =SUM(F75:F78) -> -203196.11 | G79: =SUM(G75:G78) -> -227378.77 | H79: =SUM(H75:H78) -> -253585.11 | I79: =SUM(I75:I78) -> -270314.77 | J79: =SUM(J75:J78) -> -269472.11 | K79: =SUM(K75:K78) -> -258222.11 | L79: =SUM(L75:L78) -> -253222.11 | ... CJ79: =SUM(CJ75:CJ78) -> 13731462
B81: Investing Cash Flows
B82: Changes in Fixed Assets | E82: =D52-E52 -> -275000 | F82: =E52-F52 -> -275000 | G82: =F52-G52 -> -275000 | H82: =G52-H52 -> -614583.33 | I82: =H52-I52 -> -614583.33 | J82: =I52-J52 -> -614583.33 | K82: =J52-K52 -> -614583.33 | L82: =K52-L52 -> -614583.33 | ... CJ82: =CI52-CJ52 -> 0
B83: Total Investing Cash Flows | E83: =E82 -> -275000 | F83: =F82 -> -275000 | G83: =G82 -> -275000 | H83: =H82 -> -614583.33 | I83: =I82 -> -614583.33 | J83: =J82 -> -614583.33 | K83: =K82 -> -614583.33 | L83: =L82 -> -614583.33 | ... CJ83: =CJ82 -> 0
B85: Financing Cash Flows
B86: New Debt | E86: =IF(E$4=EDATE('Base Case Inputs'!$B$41,2),'Base Case Inputs'!$B$43,IF(E$4=EDATE('Base Case Inputs'!$B$46,2),'Base Case Inputs'!$B$48,0)) -> 0 | F86: =IF(F$4=EDATE('Base Case Inputs'!$B$41,2),'Base Case Inputs'!$B$43,IF(F$4=EDATE('Base Case Inputs'!$B$46,2),'Base Case Inputs'!$B$48,0)) -> 0 | G86: =IF(G$4=EDATE('Base Case Inputs'!$B$41,2),'Base Case Inputs'!$B$43,IF(G$4=EDATE('Base Case Inputs'!$B$46,2),'Base Case Inputs'!$B$48,0)) -> 0 | H86: =IF(H$4=EDATE('Base Case Inputs'!$B$41,2),'Base Case Inputs'!$B$43,IF(H$4=EDATE('Base Case Inputs'!$B$46,2),'Base Case Inputs'!$B$48,0)) -> 2500000 | I86: =IF(I$4=EDATE('Base Case Inputs'!$B$41,2),'Base Case Inputs'!$B$43,IF(I$4=EDATE('Base Case Inputs'!$B$46,2),'Base Case Inputs'!$B$48,0)) -> 0 | J86: =IF(J$4=EDATE('Base Case Inputs'!$B$41,2),'Base Case Inputs'!$B$43,IF(J$4=EDATE('Base Case Inputs'!$B$46,2),'Base Case Inputs'!$B$48,0)) -> 0 | K86: =IF(K$4=EDATE('Base Case Inputs'!$B$41,2),'Base Case Inputs'!$B$43,IF(K$4=EDATE('Base Case Inputs'!$B$46,2),'Base Case Inputs'!$B$48,0)) -> 0 | L86: =IF(L$4=EDATE('Base Case Inputs'!$B$41,2),'Base Case Inputs'!$B$43,IF(L$4=EDATE('Base Case Inputs'!$B$46,2),'Base Case Inputs'!$B$48,0)) -> 0 | ... CJ86: =IF(CJ$4=EDATE('Base Case Inputs'!$B$41,2),'Base Case Inputs'!$B$43,IF(CJ$4=EDATE('Base Case Inputs'!$B$46,2),'Base Case Inputs'!$B$48,0)) -> 0
B87: Debt Payment | E87: =0 -> 0 | F87: =0 -> 0 | G87: =0 -> 0 | H87: =IF((G58+H86)<=0,0,-(G58+H86)*('Base Case Inputs'!$B$62/12)) -> -14583.333 | I87: =IF((H58+I86)<=0,0,-(H58+I86)*('Base Case Inputs'!$B$62/12)) -> -14583.333 | J87: =IF((I58+J86)<=0,0,-(I58+J86)*('Base Case Inputs'!$B$62/12)) -> -14583.333 | K87: =IF((J58+K86)<=0,0,-(J58+K86)*('Base Case Inputs'!$B$62/12)) -> -14583.333 | L87: =IF((K58+L86)<=0,0,-(K58+L86)*('Base Case Inputs'!$B$62/12)) -> -14583.333 | M87: =IF((L58+M86)<=0,0,-(L58+M86)*('Base Case Inputs'!$B$62/12)) -> -14583.333 | N87: =IF((M58+N86)<=0,0,-PMT('Base Case Inputs'!$B$62/12,30,-(M58+N86))) -> -91079.768 | O87: =IF((N58+O86)<=0,0,-PMT('Base Case Inputs'!$B$62/12,29,-(N58+O86))) -> -91079.768 | P87: =IF((O58+P86)<=0,0,-PMT('Base Case Inputs'!$B$62/12,28,-(O58+P86))) -> -91079.768 | Q87: =IF((P58+Q86)<=0,0,-PMT('Base Case Inputs'!$B$62/12,27,-(P58+Q86))) -> -91079.768 | R87: =IF((Q58+R86)<=0,0,-PMT('Base Case Inputs'!$B$62/12,26,-(Q58+R86))) -> -91079.768 | S87: =IF((R58+S86)<=0,0,-PMT('Base Case Inputs'!$B$62/12,25,-(R58+S86))) -> -91079.768 | T87: =IF((S58+T86)<=0,0,-PMT('Base Case Inputs'!$B$62/12,24,-(S58+T86))) -> -91079.768 | U87: =IF((T58+U86)<=0,0,-PMT('Base Case Inputs'!$B$62/12,23,-(T58+U86))) -> -91079.768 | V87: =IF((U58+V86)<=0,0,-PMT('Base Case Inputs'!$B$62/12,22,-(U58+V86))) -> -91079.768 | W87: =IF((V58+W86)<=0,0,-PMT('Base Case Inputs'!$B$62/12,21,-(V58+W86))) -> -91079.768 | X87: =IF((W58+X86)<=0,0,-PMT('Base Case Inputs'!$B$62/12,20,-(W58+X86))) -> -91079.768 | Y87: =IF((X58+Y86)<=0,0,-PMT('Base Case Inputs'!$B$62/12,19,-(X58+Y86))) -> -91079.768 | Z87: =IF((Y58+Z86)<=0,0,-PMT('Base Case Inputs'!$B$62/12,18,-(Y58+Z86))) -> -91079.768 | AA87: =IF((Z58+AA86)<=0,0,-PMT('Base Case Inputs'!$B$62/12,17,-(Z58+AA86))) -> -91079.768 | AB87: =IF((AA58+AB86)<=0,0,-PMT('Base Case Inputs'!$B$62/12,16,-(AA58+AB86))) -> -91079.768 | AC87: =IF((AB58+AC86)<=0,0,-PMT('Base Case Inputs'!$B$62/12,15,-(AB58+AC86))) -> -91079.768 | AD87: =IF((AC58+AD86)<=0,0,-PMT('Base Case Inputs'!$B$62/12,14,-(AC58+AD86))) -> -91079.768 | AE87: =IF((AD58+AE86)<=0,0,-PMT('Base Case Inputs'!$B$62/12,13,-(AD58+AE86))) -> -91079.768 | AF87: =IF((AE58+AF86)<=0,0,-PMT('Base Case Inputs'!$B$62/12,12,-(AE58+AF86))) -> -91079.768 | AG87: =IF((AF58+AG86)<=0,0,-PMT('Base Case Inputs'!$B$62/12,11,-(AF58+AG86))) -> -91079.768 | AH87: =IF((AG58+AH86)<=0,0,-PMT('Base Case Inputs'!$B$62/12,10,-(AG58+AH86))) -> -91079.768 | AI87: =IF((AH58+AI86)<=0,0,-PMT('Base Case Inputs'!$B$62/12,9,-(AH58+AI86))) -> -91079.768 | AJ87: =IF((AI58+AJ86)<=0,0,-PMT('Base Case Inputs'!$B$62/12,8,-(AI58+AJ86))) -> -91079.768 | AK87: =IF((AJ58+AK86)<=0,0,-PMT('Base Case Inputs'!$B$62/12,7,-(AJ58+AK86))) -> -91079.768 | AL87: =IF((AK58+AL86)<=0,0,-PMT('Base Case Inputs'!$B$62/12,6,-(AK58+AL86))) -> -91079.768 | AM87: =IF((AL58+AM86)<=0,0,-PMT('Base Case Inputs'!$B$62/12,5,-(AL58+AM86))) -> -91079.768 | AN87: =IF((AM58+AN86)<=0,0,-PMT('Base Case Inputs'!$B$62/12,4,-(AM58+AN86))) -> -91079.768 | AO87: =IF((AN58+AO86)<=0,0,-PMT('Base Case Inputs'!$B$62/12,3,-(AN58+AO86))) -> -91079.768 | AP87: =IF((AO58+AP86)<=0,0,-PMT('Base Case Inputs'!$B$62/12,2,-(AO58+AP86))) -> -91079.768 | AQ87: =IF((AP58+AQ86)<=0,0,-PMT('Base Case Inputs'!$B$62/12,1,-(AP58+AQ86))) -> -91079.768 | AR87: =0 -> 0 | AS87: =0 -> 0 | AT87: =0 -> 0 | AU87: =0 -> 0 | AV87: =0 -> 0 | AW87: =0 -> 0 | AX87: =0 -> 0 | AY87: =0 -> 0 | ... CJ87: =0 -> 0
B88: Debt Interest | E88: =0 -> 0 | F88: =0 -> 0 | G88: =0 -> 0 | H88: =IF((G58+H86)<=0,0,-(G58+H86)*('Base Case Inputs'!$B$62/12)) -> -14583.333 | I88: =IF((H58+I86)<=0,0,-(H58+I86)*('Base Case Inputs'!$B$62/12)) -> -14583.333 | J88: =IF((I58+J86)<=0,0,-(I58+J86)*('Base Case Inputs'!$B$62/12)) -> -14583.333 | K88: =IF((J58+K86)<=0,0,-(J58+K86)*('Base Case Inputs'!$B$62/12)) -> -14583.333 | L88: =IF((K58+L86)<=0,0,-(K58+L86)*('Base Case Inputs'!$B$62/12)) -> -14583.333 | M88: =IF((L58+M86)<=0,0,-(L58+M86)*('Base Case Inputs'!$B$62/12)) -> -14583.333 | N88: =IF((M58+N86)<=0,0,-(M58+N86)*('Base Case Inputs'!$B$62/12)) -> -14583.333 | O88: =IF((N58+O86)<=0,0,-(N58+O86)*('Base Case Inputs'!$B$62/12)) -> -14137.104 | ... AQ88: =IF((AP58+AQ86)<=0,0,-(AP58+AQ86)*('Base Case Inputs'!$B$62/12)) -> -528.21738 | AR88: =0 -> 0 | AS88: =0 -> 0 | AT88: =0 -> 0 | AU88: =0 -> 0 | AV88: =0 -> 0 | AW88: =0 -> 0 | AX88: =0 -> 0 | AY88: =0 -> 0 | ... CJ88: =0 -> 0
B89: Debt Principal | E89: =-E87+E88 -> 0 | F89: =-F87+F88 -> 0 | G89: =-G87+G88 -> 0 | H89: =-H87+H88 -> 0 | I89: =-I87+I88 -> 0 | J89: =-J87+J88 -> 0 | K89: =-K87+K88 -> 0 | L89: =-L87+L88 -> 0 | ... CJ89: =-CJ87+CJ88 -> 0
B90: New Project Financing | E90: =IF(E$4='Base Case Inputs'!$B$41,'Base Case Inputs'!$B$44,IF(E$4=EDATE('Base Case Inputs'!$B$46,2),'Base Case Inputs'!$B$49,IF(AND(E$4>=EDATE('Base Case Inputs'!$B$51,2),E$4<EDATE('Base Case Inputs'!$B$51,2+'Base Case Inputs'!$B$59)),'Base Case Inputs'!$B$53/'Base Case Inputs'!$B$59,IF(AND(E$4>=EDATE('Base Case Inputs'!$B$55,2),E$4<EDATE('Base Case Inputs'!$B$55,2+'Base Case Inputs'!$B$59)),'Base Case Inputs'!$B$57/'Base Case Inputs'!$B$59,0)))) -> 0 | F90: =IF(F$4='Base Case Inputs'!$B$41,'Base Case Inputs'!$B$44,IF(F$4=EDATE('Base Case Inputs'!$B$46,2),'Base Case Inputs'!$B$49,IF(AND(F$4>=EDATE('Base Case Inputs'!$B$51,2),F$4<EDATE('Base Case Inputs'!$B$51,2+'Base Case Inputs'!$B$59)),'Base Case Inputs'!$B$53/'Base Case Inputs'!$B$59,IF(AND(F$4>=EDATE('Base Case Inputs'!$B$55,2),F$4<EDATE('Base Case Inputs'!$B$55,2+'Base Case Inputs'!$B$59)),'Base Case Inputs'!$B$57/'Base Case Inputs'!$B$59,0)))) -> 0 | G90: =IF(G$4='Base Case Inputs'!$B$41,'Base Case Inputs'!$B$44,IF(G$4=EDATE('Base Case Inputs'!$B$46,2),'Base Case Inputs'!$B$49,IF(AND(G$4>=EDATE('Base Case Inputs'!$B$51,2),G$4<EDATE('Base Case Inputs'!$B$51,2+'Base Case Inputs'!$B$59)),'Base Case Inputs'!$B$53/'Base Case Inputs'!$B$59,IF(AND(G$4>=EDATE('Base Case Inputs'!$B$55,2),G$4<EDATE('Base Case Inputs'!$B$55,2+'Base Case Inputs'!$B$59)),'Base Case Inputs'!$B$57/'Base Case Inputs'!$B$59,0)))) -> 0 | H90: =IF(H$4='Base Case Inputs'!$B$41,'Base Case Inputs'!$B$44,IF(H$4=EDATE('Base Case Inputs'!$B$46,2),'Base Case Inputs'!$B$49,IF(AND(H$4>=EDATE('Base Case Inputs'!$B$51,2),H$4<EDATE('Base Case Inputs'!$B$51,2+'Base Case Inputs'!$B$59)),'Base Case Inputs'!$B$53/'Base Case Inputs'!$B$59,IF(AND(H$4>=EDATE('Base Case Inputs'!$B$55,2),H$4<EDATE('Base Case Inputs'!$B$55,2+'Base Case Inputs'!$B$59)),'Base Case Inputs'!$B$57/'Base Case Inputs'!$B$59,0)))) -> 0 | I90: =IF(I$4='Base Case Inputs'!$B$41,'Base Case Inputs'!$B$44,IF(I$4=EDATE('Base Case Inputs'!$B$46,2),'Base Case Inputs'!$B$49,IF(AND(I$4>=EDATE('Base Case Inputs'!$B$51,2),I$4<EDATE('Base Case Inputs'!$B$51,2+'Base Case Inputs'!$B$59)),'Base Case Inputs'!$B$53/'Base Case Inputs'!$B$59,IF(AND(I$4>=EDATE('Base Case Inputs'!$B$55,2),I$4<EDATE('Base Case Inputs'!$B$55,2+'Base Case Inputs'!$B$59)),'Base Case Inputs'!$B$57/'Base Case Inputs'!$B$59,0)))) -> 0 | J90: =IF(J$4='Base Case Inputs'!$B$41,'Base Case Inputs'!$B$44,IF(J$4=EDATE('Base Case Inputs'!$B$46,2),'Base Case Inputs'!$B$49,IF(AND(J$4>=EDATE('Base Case Inputs'!$B$51,2),J$4<EDATE('Base Case Inputs'!$B$51,2+'Base Case Inputs'!$B$59)),'Base Case Inputs'!$B$53/'Base Case Inputs'!$B$59,IF(AND(J$4>=EDATE('Base Case Inputs'!$B$55,2),J$4<EDATE('Base Case Inputs'!$B$55,2+'Base Case Inputs'!$B$59)),'Base Case Inputs'!$B$57/'Base Case Inputs'!$B$59,0)))) -> 0 | K90: =IF(K$4='Base Case Inputs'!$B$41,'Base Case Inputs'!$B$44,IF(K$4=EDATE('Base Case Inputs'!$B$46,2),'Base Case Inputs'!$B$49,IF(AND(K$4>=EDATE('Base Case Inputs'!$B$51,2),K$4<EDATE('Base Case Inputs'!$B$51,2+'Base Case Inputs'!$B$59)),'Base Case Inputs'!$B$53/'Base Case Inputs'!$B$59,IF(AND(K$4>=EDATE('Base Case Inputs'!$B$55,2),K$4<EDATE('Base Case Inputs'!$B$55,2+'Base Case Inputs'!$B$59)),'Base Case Inputs'!$B$57/'Base Case Inputs'!$B$59,0)))) -> 0 | L90: =IF(L$4='Base Case Inputs'!$B$41,'Base Case Inputs'!$B$44,IF(L$4=EDATE('Base Case Inputs'!$B$46,2),'Base Case Inputs'!$B$49,IF(AND(L$4>=EDATE('Base Case Inputs'!$B$51,2),L$4<EDATE('Base Case Inputs'!$B$51,2+'Base Case Inputs'!$B$59)),'Base Case Inputs'!$B$53/'Base Case Inputs'!$B$59,IF(AND(L$4>=EDATE('Base Case Inputs'!$B$55,2),L$4<EDATE('Base Case Inputs'!$B$55,2+'Base Case Inputs'!$B$59)),'Base Case Inputs'!$B$57/'Base Case Inputs'!$B$59,0)))) -> 0 | ... CJ90: =IF(CJ$4='Base Case Inputs'!$B$41,'Base Case Inputs'!$B$44,IF(CJ$4=EDATE('Base Case Inputs'!$B$46,2),'Base Case Inputs'!$B$49,IF(AND(CJ$4>=EDATE('Base Case Inputs'!$B$51,2),CJ$4<EDATE('Base Case Inputs'!$B$51,2+'Base Case Inputs'!$B$59)),'Base Case Inputs'!$B$53/'Base Case Inputs'!$B$59,IF(AND(CJ$4>=EDATE('Base Case Inputs'!$B$55,2),CJ$4<EDATE('Base Case Inputs'!$B$55,2+'Base Case Inputs'!$B$59)),'Base Case Inputs'!$B$57/'Base Case Inputs'!$B$59,0)))) -> 0
B91: Project Financing Payment | E91: =IF((D59+E90)>0,-(D59+E90)*'Base Case Inputs'!$B$68,0) -> 0 | F91: =IF((E59+F90)>0,-(E59+F90)*'Base Case Inputs'!$B$68,0) -> 0 | G91: =IF((F59+G90)>0,-(F59+G90)*'Base Case Inputs'!$B$68,0) -> 0 | H91: =IF((G59+H90)>0,-(G59+H90)*'Base Case Inputs'!$B$68,0) -> 0 | I91: =IF((H59+I90)>0,-(H59+I90)*'Base Case Inputs'!$B$68,0) -> 0 | J91: =IF((I59+J90)>0,-(I59+J90)*'Base Case Inputs'!$B$68,0) -> 0 | K91: =IF((J59+K90)>0,-(J59+K90)*'Base Case Inputs'!$B$68,0) -> 0 | L91: =IF((K59+L90)>0,-(K59+L90)*'Base Case Inputs'!$B$68,0) -> 0 | ... CJ91: =IF((CI59+CJ90)>0,-(CI59+CJ90)*'Base Case Inputs'!$B$68,0) -> -1958595.7
B92: Project Financing Interest | E92: =IF((D59+E90)<=0,0,-(D59+E90)*('Base Case Inputs'!$B$67/12)) -> 0 | F92: =IF((E59+F90)<=0,0,-(E59+F90)*('Base Case Inputs'!$B$67/12)) -> 0 | G92: =IF((F59+G90)<=0,0,-(F59+G90)*('Base Case Inputs'!$B$67/12)) -> 0 | H92: =IF((G59+H90)<=0,0,-(G59+H90)*('Base Case Inputs'!$B$67/12)) -> 0 | I92: =IF((H59+I90)<=0,0,-(H59+I90)*('Base Case Inputs'!$B$67/12)) -> 0 | J92: =IF((I59+J90)<=0,0,-(I59+J90)*('Base Case Inputs'!$B$67/12)) -> 0 | K92: =IF((J59+K90)<=0,0,-(J59+K90)*('Base Case Inputs'!$B$67/12)) -> 0 | L92: =IF((K59+L90)<=0,0,-(K59+L90)*('Base Case Inputs'!$B$67/12)) -> 0 | ... CJ92: =IF((CI59+CJ90)<=0,0,-(CI59+CJ90)*('Base Case Inputs'!$B$67/12)) -> -370019.94
B93: Project Financing Principal | E93: =IF((D59+E90)<=0,0,MIN((D59+E90),MAX(0,ABS(E91)-ABS(E92)))) -> 0 | F93: =IF((E59+F90)<=0,0,MIN((E59+F90),MAX(0,ABS(F91)-ABS(F92)))) -> 0 | G93: =IF((F59+G90)<=0,0,MIN((F59+G90),MAX(0,ABS(G91)-ABS(G92)))) -> 0 | H93: =IF((G59+H90)<=0,0,MIN((G59+H90),MAX(0,ABS(H91)-ABS(H92)))) -> 0 | I93: =IF((H59+I90)<=0,0,MIN((H59+I90),MAX(0,ABS(I91)-ABS(I92)))) -> 0 | J93: =IF((I59+J90)<=0,0,MIN((I59+J90),MAX(0,ABS(J91)-ABS(J92)))) -> 0 | K93: =IF((J59+K90)<=0,0,MIN((J59+K90),MAX(0,ABS(K91)-ABS(K92)))) -> 0 | L93: =IF((K59+L90)<=0,0,MIN((K59+L90),MAX(0,ABS(L91)-ABS(L92)))) -> 0 | ... CJ93: =IF((CI59+CJ90)<=0,0,MIN((CI59+CJ90),MAX(0,ABS(CJ91)-ABS(CJ92)))) -> 1588575.7
B94: Changes in Paid in Capital | E94: =E64-D64 -> 0 | F94: =F64-E64 -> 7500000 | G94: =G64-F64 -> 0 | H94: =H64-G64 -> 0 | I94: =I64-H64 -> 0 | J94: =J64-I64 -> 0 | K94: =K64-J64 -> 0 | L94: =L64-K64 -> 0 | ... CJ94: =CJ64-CI64 -> 0
B95: Total Financing Cash Flows | E95: =E86-E89+E90-E93+E94 -> 0 | F95: =F86-F89+F90-F93+F94 -> 7500000 | G95: =G86-G89+G90-G93+G94 -> 0 | H95: =H86-H89+H90-H93+H94 -> 2500000 | I95: =I86-I89+I90-I93+I94 -> 0 | J95: =J86-J89+J90-J93+J94 -> 0 | K95: =K86-K89+K90-K93+K94 -> 0 | L95: =L86-L89+L90-L93+L94 -> 0 | ... CJ95: =CJ86-CJ89+CJ90-CJ93+CJ94 -> -1588575.7
B97: Beginning Cash | E97: ='Model Assumptions'!C74 -> 682500 | F97: =E101 -> 273110.92 | G97: =F101 -> 7294914.8 | H97: =G101 -> 6792536 | I97: =H101 -> 8424367.6 | J97: =I101 -> 7539469.5 | K97: =J101 -> 6655414 | L97: =K101 -> 5782608.6 | M97: =L101 -> 4914803.2 | ... CJ97: =CI101 -> 8.206391e+08
B99: Change in Cash | E99: =E95+E83+E79 -> -409389.08 | F99: =F95+F83+F79 -> 7021803.9 | G99: =G95+G83+G79 -> -502378.77 | H99: =H95+H83+H79 -> 1631831.6 | I99: =I95+I83+I79 -> -884898.11 | J99: =J95+J83+J79 -> -884055.44 | K99: =K95+K83+K79 -> -872805.44 | L99: =L95+L83+L79 -> -867805.44 | ... CJ99: =CJ95+CJ83+CJ79 -> 12142887
B101: Ending Cash | E101: =E99+E97 -> 273110.92 | F101: =F99+F97 -> 7294914.8 | G101: =G99+G97 -> 6792536 | H101: =H99+H97 -> 8424367.6 | I101: =I99+I97 -> 7539469.5 | J101: =J99+J97 -> 6655414 | K101: =K99+K97 -> 5782608.6 | L101: =L99+L97 -> 4914803.2 | ... CJ101: =CJ99+CJ97 -> 8.3278198e+08
B103: Depreciation Cross-Check
B104: Method: Straight-Line | Useful Life: 9 years | Source: BCI!B12
D105: Year → | E105: Year 1 | F105: Year 2 | G105: Year 3 | H105: Year 4 | I105: Year 5 | J105: Year 6 | K105: Year 7
B106: Annual Depr (Row 33 Sum) | E106: {=SUMPRODUCT(($E$1:$CJ$1=1)*$E$36:$CJ$36)} -> 0 | F106: {=SUMPRODUCT(($E$1:$CJ$1=2)*$E$36:$CJ$36)} -> 706250 | G106: {=SUMPRODUCT(($E$1:$CJ$1=3)*$E$36:$CJ$36)} -> 1581944.4 | H106: {=SUMPRODUCT(($E$1:$CJ$1=4)*$E$36:$CJ$36)} -> 2598611.1 | I106: {=SUMPRODUCT(($E$1:$CJ$1=5)*$E$36:$CJ$36)} -> 4640277.8 | J106: {=SUMPRODUCT(($E$1:$CJ$1=6)*$E$36:$CJ$36)} -> 5986111.1 | K106: {=SUMPRODUCT(($E$1:$CJ$1=7)*$E$36:$CJ$36)} -> 6236111.1
B107: Expected Annual Depr | E107: =SUM('Model Assumptions'!R96:R110)-SUM('Model Assumptions'!F96:F110) -> 0 | F107: =SUM('Model Assumptions'!AD96:AD110)-SUM('Model Assumptions'!R96:R110) -> 706250 | G107: =SUM('Model Assumptions'!AP96:AP110)-SUM('Model Assumptions'!AD96:AD110) -> 1581944.4 | H107: =SUM('Model Assumptions'!BB96:BB110)-SUM('Model Assumptions'!AP96:AP110) -> 2598611.1 | I107: =SUM('Model Assumptions'!BN96:BN110)-SUM('Model Assumptions'!BB96:BB110) -> 4640277.8 | J107: =SUM('Model Assumptions'!BZ96:BZ110)-SUM('Model Assumptions'!BN96:BN110) -> 5986111.1 | K107: =SUM('Model Assumptions'!CL96:CL110)-SUM('Model Assumptions'!BZ96:BZ110) -> 6236111.1
B108: Variance ($) | E108: =E106-E107 -> 0 | F108: =F106-F107 -> 0 | G108: =G106-G107 -> 0 | H108: =H106-H107 -> 0 | I108: =I106-I107 -> 0 | J108: =J106-J107 -> 0 | K108: =K106-K107 -> 0
B109: Variance (%) | E109: =IFERROR(E108/E107,0) -> 0 | F109: =IFERROR(F108/F107,0) -> 0 | G109: =IFERROR(G108/G107,0) -> 0 | H109: =IFERROR(H108/H107,0) -> 0 | I109: =IFERROR(I108/I107,0) -> 0 | J109: =IFERROR(J108/J107,0) -> 0 | K109: =IFERROR(K108/K107,0) -> 0
B110: Status | E110: =IF(ABS(E109)<=0.05,"✅ PASS","❌ FAIL") -> ✅ PASS | F110: =IF(ABS(F109)<=0.05,"✅ PASS","❌ FAIL") -> ✅ PASS | G110: =IF(ABS(G109)<=0.05,"✅ PASS","❌ FAIL") -> ✅ PASS | H110: =IF(ABS(H109)<=0.05,"✅ PASS","❌ FAIL") -> ✅ PASS | I110: =IF(ABS(I109)<=0.05,"✅ PASS","❌ FAIL") -> ✅ PASS | J110: =IF(ABS(J109)<=0.05,"✅ PASS","❌ FAIL") -> ✅ PASS | K110: =IF(ABS(K109)<=0.05,"✅ PASS","❌ FAIL") -> ✅ PASS
B112: Cumulative Fixed Assets (as of year-end) | E112: {=SUMPRODUCT(('Model Assumptions'!$D$79:$D$93<=P$4)*'Model Assumptions'!$C$79:$C$93)} -> 7375000 | F112: {=SUMPRODUCT(('Model Assumptions'!$D$79:$D$93<=AB$4)*'Model Assumptions'!$C$79:$C$93)} -> 16525000 | G112: {=SUMPRODUCT(('Model Assumptions'!$D$79:$D$93<=AN$4)*'Model Assumptions'!$C$79:$C$93)} -> 25675000 | H112: {=SUMPRODUCT(('Model Assumptions'!$D$79:$D$93<=AZ$4)*'Model Assumptions'!$C$79:$C$93)} -> 47125000 | I112: {=SUMPRODUCT(('Model Assumptions'!$D$79:$D$93<=BL$4)*'Model Assumptions'!$C$79:$C$93)} -> 56125000 | J112: {=SUMPRODUCT(('Model Assumptions'!$D$79:$D$93<=BX$4)*'Model Assumptions'!$C$79:$C$93)} -> 56125000 | K112: {=SUMPRODUCT(('Model Assumptions'!$D$79:$D$93<=CJ$4)*'Model Assumptions'!$C$79:$C$93)} -> 56125000
B113: Max Annual Depr at Steady-State | E113: =E112/'Base Case Inputs'!$B$12 -> 819444.44 | F113: =F112/'Base Case Inputs'!$B$12 -> 1836111.1 | G113: =G112/'Base Case Inputs'!$B$12 -> 2852777.8 | H113: =H112/'Base Case Inputs'!$B$12 -> 5236111.1 | I113: =I112/'Base Case Inputs'!$B$12 -> 6236111.1 | J113: =J112/'Base Case Inputs'!$B$12 -> 6236111.1 | K113: =K112/'Base Case Inputs'!$B$12 -> 6236111.1
B115: Cross-Check Notes:
B116: • Row 103: Sum of monthly depreciation (row 33 delta method) aggregated by year using Year Counter (row 1)
B117: • Row 104: Year-end accumulated depr minus year-start accumulated depr (Model Assumptions rows 95-109) — independent path
B118: • Row 109: SUMPRODUCT of asset costs (MA!C78:C92) where in-service date (MA!D78:D92) ≤ year-end date
B119: • Row 110: Cumulative assets / 9-year useful life (BCI!B12) = max annual depr if all assets depreciated full year
...

Sheet Model Assumptions
B1: Year Counter | G1: 1 | H1: 1 | I1: 1 | J1: 1 | K1: 1 | L1: 1 | M1: 1 | N1: 1 | O1: 1 | P1: 1 | Q1: 1 | R1: 1 | S1: 2 | T1: 2 | U1: 2 | V1: 2 | W1: 2 | X1: 2 | Y1: 2 | Z1: 2 | AA1: 2 | AB1: 2 | AC1: 2 | AD1: 2 | AE1: 3 | AF1: 3 | AG1: 3 | AH1: 3 | AI1: 3 | AJ1: 3 | AK1: 3 | AL1: 3 | AM1: 3 | AN1: 3 | AO1: 3 | AP1: 3 | AQ1: 4 | AR1: 4 | AS1: 4 | AT1: 4 | AU1: 4 | AV1: 4 | AW1: 4 | AX1: 4 | AY1: 4 | AZ1: 4 | BA1: 4 | BB1: 4 | BC1: 5 | BD1: 5 | BE1: 5 | BF1: 5 | BG1: 5 | BH1: 5 | BI1: 5 | BJ1: 5 | BK1: 5 | BL1: 5 | BM1: 5 | BN1: 5 | BO1: 6 | BP1: 6 | BQ1: 6 | BR1: 6 | BS1: 6 | BT1: 6 | BU1: 6 | BV1: 6 | BW1: 6 | BX1: 6 | BY1: 6 | BZ1: 6 | CA1: 7 | CB1: 7 | CC1: 7 | CD1: 7 | CE1: 7 | CF1: 7 | CG1: 7 | CH1: 7 | CI1: 7 | CJ1: 7 | CK1: 7 | CL1: 7
B2: Year | G2: =YEAR(G4) -> 2026 | H2: =YEAR(H4) -> 2026 | I2: =YEAR(I4) -> 2026 | J2: =YEAR(J4) -> 2026 | K2: =YEAR(K4) -> 2026 | L2: =YEAR(L4) -> 2026 | M2: =YEAR(M4) -> 2026 | N2: =YEAR(N4) -> 2026 | ... CL2: =YEAR(CL4) -> 2033
B3: Month Counter | G3: 1 | H3: 2 | I3: 3 | J3: 4 | K3: 5 | L3: 6 | M3: 7 | N3: 8 | O3: 9 | P3: 10 | Q3: 11 | R3: 12 | S3: 13 | T3: 14 | U3: 15 | V3: 16 | W3: 17 | X3: 18 | Y3: 19 | Z3: 20 | AA3: 21 | AB3: 22 | AC3: 23 | AD3: 24 | AE3: 25 | AF3: 26 | AG3: 27 | AH3: 28 | AI3: 29 | AJ3: 30 | AK3: 31 | AL3: 32 | AM3: 33 | AN3: 34 | AO3: 35 | AP3: 36 | AQ3: 37 | AR3: 38 | AS3: 39 | AT3: 40 | AU3: 41 | AV3: 42 | AW3: 43 | AX3: 44 | AY3: 45 | AZ3: 46 | BA3: 47 | BB3: 48 | BC3: 49 | BD3: 50 | BE3: 51 | BF3: 52 | BG3: 53 | BH3: 54 | BI3: 55 | BJ3: 56 | BK3: 57 | BL3: 58 | BM3: 59 | BN3: 60 | BO3: 61 | BP3: 62 | BQ3: 63 | BR3: 64 | BS3: 65 | BT3: 66 | BU3: 67 | BV3: 68 | BW3: 69 | BX3: 70 | BY3: 71 | BZ3: 72 | CA3: 73 | CB3: 74 | CC3: 75 | CD3: 76 | CE3: 77 | CF3: 78 | CG3: 79 | CH3: 80 | CI3: 81 | CJ3: 82 | CK3: 83 | CL3: 84
B4: Date | G4: ='Base Case Inputs'!$B$2 -> 46113 | H4: =EDATE(G4,1) -> 46143 | I4: =EDATE(H4,1) -> 46174 | J4: =EDATE(I4,1) -> 46204 | K4: =EDATE(J4,1) -> 46235 | L4: =EDATE(K4,1) -> 46266 | M4: =EDATE(L4,1) -> 46296 | N4: =EDATE(M4,1) -> 46327 | O4: =EDATE(N4,1) -> 46357 | ... CL4: =EDATE(CK4,1) -> 48639
B5: Facilities Operating | C5: Count | G5: =IF(G4>=$E$12,1,0)+IF(G4>=$E$20,1,0)+IF(G4>=$E$28,1,0)+IF(G4>=$E$36,1,0)+IF(G4>=$E$44,1,0)+IF(G4>=$E$52,1,0)+IF(G4>='Base Case Inputs'!$B$188,1,0)+IF(G4>='Base Case Inputs'!$B$189,1,0)+IF(G4>='Base Case Inputs'!$B$190,1,0)+IF(G4>='Base Case Inputs'!$B$191,1,0)+IF(G4>='Base Case Inputs'!$B$192,1,0)+IF(G4>='Base Case Inputs'!$B$193,1,0) -> 0 | H5: =IF(H4>=$E$12,1,0)+IF(H4>=$E$20,1,0)+IF(H4>=$E$28,1,0)+IF(H4>=$E$36,1,0)+IF(H4>=$E$44,1,0)+IF(H4>=$E$52,1,0)+IF(H4>='Base Case Inputs'!$B$188,1,0)+IF(H4>='Base Case Inputs'!$B$189,1,0)+IF(H4>='Base Case Inputs'!$B$190,1,0)+IF(H4>='Base Case Inputs'!$B$191,1,0)+IF(H4>='Base Case Inputs'!$B$192,1,0)+IF(H4>='Base Case Inputs'!$B$193,1,0) -> 0 | I5: =IF(I4>=$E$12,1,0)+IF(I4>=$E$20,1,0)+IF(I4>=$E$28,1,0)+IF(I4>=$E$36,1,0)+IF(I4>=$E$44,1,0)+IF(I4>=$E$52,1,0)+IF(I4>='Base Case Inputs'!$B$188,1,0)+IF(I4>='Base Case Inputs'!$B$189,1,0)+IF(I4>='Base Case Inputs'!$B$190,1,0)+IF(I4>='Base Case Inputs'!$B$191,1,0)+IF(I4>='Base Case Inputs'!$B$192,1,0)+IF(I4>='Base Case Inputs'!$B$193,1,0) -> 0 | J5: =IF(J4>=$E$12,1,0)+IF(J4>=$E$20,1,0)+IF(J4>=$E$28,1,0)+IF(J4>=$E$36,1,0)+IF(J4>=$E$44,1,0)+IF(J4>=$E$52,1,0)+IF(J4>='Base Case Inputs'!$B$188,1,0)+IF(J4>='Base Case Inputs'!$B$189,1,0)+IF(J4>='Base Case Inputs'!$B$190,1,0)+IF(J4>='Base Case Inputs'!$B$191,1,0)+IF(J4>='Base Case Inputs'!$B$192,1,0)+IF(J4>='Base Case Inputs'!$B$193,1,0) -> 0 | K5: =IF(K4>=$E$12,1,0)+IF(K4>=$E$20,1,0)+IF(K4>=$E$28,1,0)+IF(K4>=$E$36,1,0)+IF(K4>=$E$44,1,0)+IF(K4>=$E$52,1,0)+IF(K4>='Base Case Inputs'!$B$188,1,0)+IF(K4>='Base Case Inputs'!$B$189,1,0)+IF(K4>='Base Case Inputs'!$B$190,1,0)+IF(K4>='Base Case Inputs'!$B$191,1,0)+IF(K4>='Base Case Inputs'!$B$192,1,0)+IF(K4>='Base Case Inputs'!$B$193,1,0) -> 0 | L5: =IF(L4>=$E$12,1,0)+IF(L4>=$E$20,1,0)+IF(L4>=$E$28,1,0)+IF(L4>=$E$36,1,0)+IF(L4>=$E$44,1,0)+IF(L4>=$E$52,1,0)+IF(L4>='Base Case Inputs'!$B$188,1,0)+IF(L4>='Base Case Inputs'!$B$189,1,0)+IF(L4>='Base Case Inputs'!$B$190,1,0)+IF(L4>='Base Case Inputs'!$B$191,1,0)+IF(L4>='Base Case Inputs'!$B$192,1,0)+IF(L4>='Base Case Inputs'!$B$193,1,0) -> 0 | M5: =IF(M4>=$E$12,1,0)+IF(M4>=$E$20,1,0)+IF(M4>=$E$28,1,0)+IF(M4>=$E$36,1,0)+IF(M4>=$E$44,1,0)+IF(M4>=$E$52,1,0)+IF(M4>='Base Case Inputs'!$B$188,1,0)+IF(M4>='Base Case Inputs'!$B$189,1,0)+IF(M4>='Base Case Inputs'!$B$190,1,0)+IF(M4>='Base Case Inputs'!$B$191,1,0)+IF(M4>='Base Case Inputs'!$B$192,1,0)+IF(M4>='Base Case Inputs'!$B$193,1,0) -> 0 | N5: =IF(N4>=$E$12,1,0)+IF(N4>=$E$20,1,0)+IF(N4>=$E$28,1,0)+IF(N4>=$E$36,1,0)+IF(N4>=$E$44,1,0)+IF(N4>=$E$52,1,0)+IF(N4>='Base Case Inputs'!$B$188,1,0)+IF(N4>='Base Case Inputs'!$B$189,1,0)+IF(N4>='Base Case Inputs'!$B$190,1,0)+IF(N4>='Base Case Inputs'!$B$191,1,0)+IF(N4>='Base Case Inputs'!$B$192,1,0)+IF(N4>='Base Case Inputs'!$B$193,1,0) -> 0 | ... CL5: =IF(CL4>=$E$12,1,0)+IF(CL4>=$E$20,1,0)+IF(CL4>=$E$28,1,0)+IF(CL4>=$E$36,1,0)+IF(CL4>=$E$44,1,0)+IF(CL4>=$E$52,1,0)+IF(CL4>='Base Case Inputs'!$B$188,1,0)+IF(CL4>='Base Case Inputs'!$B$189,1,0)+IF(CL4>='Base Case Inputs'!$B$190,1,0)+IF(CL4>='Base Case Inputs'!$B$191,1,0)+IF(CL4>='Base Case Inputs'!$B$192,1,0)+IF(CL4>='Base Case Inputs'!$B$193,1,0) -> 12
B6: Tobe Energy Corp. Overall
C7: Total Cost | G7: =G13+G14+G21+G22+G29+G30+G37+G38+G45+G46+G53+G54+G61+G62 -> 77379.467 | H7: =H13+H14+H21+H22+H29+H30+H37+H38+H45+H46+H53+H54+H61+H62 -> 88253.8 | I7: =I13+I14+I21+I22+I29+I30+I37+I38+I45+I46+I53+I54+I61+I62 -> 113436.47 | J7: =J13+J14+J21+J22+J29+J30+J37+J38+J45+J46+J53+J54+J61+J62 -> 146059.47 | K7: =K13+K14+K21+K22+K29+K30+K37+K38+K45+K46+K53+K54+K61+K62 -> 155789.13 | L7: =L13+L14+L21+L22+L29+L30+L37+L38+L45+L46+L53+L54+L61+L62 -> 164946.47 | M7: =M13+M14+M21+M22+M29+M30+M37+M38+M45+M46+M53+M54+M61+M62 -> 164946.47 | N7: =N13+N14+N21+N22+N29+N30+N37+N38+N45+N46+N53+N54+N61+N62 -> 164946.47 | ... CL7: =CL13+CL14+CL21+CL22+CL29+CL30+CL37+CL38+CL45+CL46+CL53+CL54+CL61+CL62 -> 3257887.6
C8: Total Production | G8: =G15+G23+G31+G39+G47+G55+G63 -> 0 | H8: =H15+H23+H31+H39+H47+H55+H63 -> 0 | I8: =I15+I23+I31+I39+I47+I55+I63 -> 0 | J8: =J15+J23+J31+J39+J47+J55+J63 -> 0 | K8: =K15+K23+K31+K39+K47+K55+K63 -> 0 | L8: =L15+L23+L31+L39+L47+L55+L63 -> 0 | M8: =M15+M23+M31+M39+M47+M55+M63 -> 0 | N8: =N15+N23+N31+N39+N47+N55+N63 -> 0 | ... CL8: =CL15+CL23+CL31+CL39+CL47+CL55+CL63 -> 900000
C9: Total Profit | G9: =(G18+G26+G34+G42+G50+G58+G66)-G7 -> -77379.467 | H9: =(H18+H26+H34+H42+H50+H58+H66)-H7 -> -88253.8 | I9: =(I18+I26+I34+I42+I50+I58+I66)-I7 -> -113436.47 | J9: =(J18+J26+J34+J42+J50+J58+J66)-J7 -> -146059.47 | K9: =(K18+K26+K34+K42+K50+K58+K66)-K7 -> -155789.13 | L9: =(L18+L26+L34+L42+L50+L58+L66)-L7 -> -164946.47 | M9: =(M18+M26+M34+M42+M50+M58+M66)-M7 -> -164946.47 | N9: =(N18+N26+N34+N42+N50+N58+N66)-N7 -> -164946.47 | ... CL9: =(CL18+CL26+CL34+CL42+CL50+CL58+CL66)-CL7 -> 16052012
B10: Inflated $/kg Opex | C10: (incl. inflation) | G10: ='Base Case Inputs'!$B$94*(1+'Base Case Inputs'!$B$88)^(G$1-1) -> 2.6199084 | H10: ='Base Case Inputs'!$B$94*(1+'Base Case Inputs'!$B$88)^(H$1-1) -> 2.6199084 | I10: ='Base Case Inputs'!$B$94*(1+'Base Case Inputs'!$B$88)^(I$1-1) -> 2.6199084 | J10: ='Base Case Inputs'!$B$94*(1+'Base Case Inputs'!$B$88)^(J$1-1) -> 2.6199084 | K10: ='Base Case Inputs'!$B$94*(1+'Base Case Inputs'!$B$88)^(K$1-1) -> 2.6199084 | L10: ='Base Case Inputs'!$B$94*(1+'Base Case Inputs'!$B$88)^(L$1-1) -> 2.6199084 | M10: ='Base Case Inputs'!$B$94*(1+'Base Case Inputs'!$B$88)^(M$1-1) -> 2.6199084 | N10: ='Base Case Inputs'!$B$94*(1+'Base Case Inputs'!$B$88)^(N$1-1) -> 2.6199084 | ... CL10: ='Base Case Inputs'!$B$94*(1+'Base Case Inputs'!$B$88)^(CL$1-1) -> 3.0382906
D11: Begin Construction | E11: In-Service Date | F11: 45V Eligible?
B12: GH2x - Tulsa | D12: 46113 | E12: 46478 | F12: =IF(D12<='Base Case Inputs'!$B$124,1,0) -> 1
B13: kg Opex | C13: Capital Costs | G13: =IF(G$4 >= $E$12, ('Facility AFE'!$C$29/12),0) -> 0 | H13: =IF(H$4 >= $E$12, ('Facility AFE'!$C$29/12),0) -> 0 | I13: =IF(I$4 >= $E$12, ('Facility AFE'!$C$29/12),0) -> 0 | J13: =IF(J$4 >= $E$12, ('Facility AFE'!$C$29/12),0) -> 0 | K13: =IF(K$4 >= $E$12, ('Facility AFE'!$C$29/12),0) -> 0 | L13: =IF(L$4 >= $E$12, ('Facility AFE'!$C$29/12),0) -> 0 | M13: =IF(M$4 >= $E$12, ('Facility AFE'!$C$29/12),0) -> 0 | N13: =IF(N$4 >= $E$12, ('Facility AFE'!$C$29/12),0) -> 0 | ... R13: =IF(R$4 >= $E$12, ('Facility AFE'!$C$29/12),0) -> 0 | S13: ='Facility AFE'!$C$90/12 -> 83333.333 | T13: ='Facility AFE'!$C$90/12 -> 83333.333 | U13: ='Facility AFE'!$C$90/12 -> 83333.333 | V13: ='Facility AFE'!$C$90/12 -> 83333.333 | W13: ='Facility AFE'!$C$90/12 -> 83333.333 | X13: ='Facility AFE'!$C$90/12 -> 83333.333 | Y13: ='Facility AFE'!$C$90/12 -> 83333.333 | Z13: ='Facility AFE'!$C$90/12 -> 83333.333 | ... AD13: ='Facility AFE'!$C$90/12 -> 83333.333 | AE13: =('Facility AFE'!$C$91/12) -> 125000 | AF13: =('Facility AFE'!$C$91/12) -> 125000 | AG13: =('Facility AFE'!$C$91/12) -> 125000 | AH13: =('Facility AFE'!$C$91/12) -> 125000 | AI13: =('Facility AFE'!$C$91/12) -> 125000 | AJ13: =('Facility AFE'!$C$91/12) -> 125000 | AK13: =('Facility AFE'!$C$91/12) -> 125000 | AL13: =('Facility AFE'!$C$91/12) -> 125000 | ... AP13: =('Facility AFE'!$C$91/12) -> 125000 | AQ13: =0/12 -> 0 | AR13: =0/12 -> 0 | AS13: =0/12 -> 0 | AT13: =0/12 -> 0 | AU13: =0/12 -> 0 | AV13: =0/12 -> 0 | AW13: =0/12 -> 0 | AX13: =0/12 -> 0 | ... CL13: =0/12 -> 0
B14: ='Base Case Inputs'!$B$15 -> 2.62 | C14: Personnel | G14: {=IF(G$3<=14,IF(G$1<=1,SUMPRODUCT((Personnel!$F$172:$F$186<=G$3)*Personnel!$G$172:$G$186),SUMPRODUCT((Personnel!$F$172:$F$186<=G$3)*Personnel!$I$172:$I$186)),IF(G$1<=1,'Base Case Inputs'!$B$197/12,IF(G$1<=2,'Base Case Inputs'!$B$198/12,IF(G$1<=3,'Base Case Inputs'!$B$199/12,IF(G$1<=4,'Base Case Inputs'!$B$200/12,IF(G$1<=5,'Base Case Inputs'!$B$201/12,IF(G$1<=6,'Base Case Inputs'!$B$202/12,'Base Case Inputs'!$B$203/12)))))))} -> 77379.467 | H14: {=IF(H$3<=14,IF(H$1<=1,SUMPRODUCT((Personnel!$F$172:$F$186<=H$3)*Personnel!$G$172:$G$186),SUMPRODUCT((Personnel!$F$172:$F$186<=H$3)*Personnel!$I$172:$I$186)),IF(H$1<=1,'Base Case Inputs'!$B$197/12,IF(H$1<=2,'Base Case Inputs'!$B$198/12,IF(H$1<=3,'Base Case Inputs'!$B$199/12,IF(H$1<=4,'Base Case Inputs'!$B$200/12,IF(H$1<=5,'Base Case Inputs'!$B$201/12,IF(H$1<=6,'Base Case Inputs'!$B$202/12,'Base Case Inputs'!$B$203/12)))))))} -> 88253.8 | I14: {=IF(I$3<=14,IF(I$1<=1,SUMPRODUCT((Personnel!$F$172:$F$186<=I$3)*Personnel!$G$172:$G$186),SUMPRODUCT((Personnel!$F$172:$F$186<=I$3)*Personnel!$I$172:$I$186)),IF(I$1<=1,'Base Case Inputs'!$B$197/12,IF(I$1<=2,'Base Case Inputs'!$B$198/12,IF(I$1<=3,'Base Case Inputs'!$B$199/12,IF(I$1<=4,'Base Case Inputs'!$B$200/12,IF(I$1<=5,'Base Case Inputs'!$B$201/12,IF(I$1<=6,'Base Case Inputs'!$B$202/12,'Base Case Inputs'!$B$203/12)))))))} -> 113436.47 | J14: {=IF(J$3<=14,IF(J$1<=1,SUMPRODUCT((Personnel!$F$172:$F$186<=J$3)*Personnel!$G$172:$G$186),SUMPRODUCT((Personnel!$F$172:$F$186<=J$3)*Personnel!$I$172:$I$186)),IF(J$1<=1,'Base Case Inputs'!$B$197/12,IF(J$1<=2,'Base Case Inputs'!$B$198/12,IF(J$1<=3,'Base Case Inputs'!$B$199/12,IF(J$1<=4,'Base Case Inputs'!$B$200/12,IF(J$1<=5,'Base Case Inputs'!$B$201/12,IF(J$1<=6,'Base Case Inputs'!$B$202/12,'Base Case Inputs'!$B$203/12)))))))} -> 146059.47 | K14: {=IF(K$3<=14,IF(K$1<=1,SUMPRODUCT((Personnel!$F$172:$F$186<=K$3)*Personnel!$G$172:$G$186),SUMPRODUCT((Personnel!$F$172:$F$186<=K$3)*Personnel!$I$172:$I$186)),IF(K$1<=1,'Base Case Inputs'!$B$197/12,IF(K$1<=2,'Base Case Inputs'!$B$198/12,IF(K$1<=3,'Base Case Inputs'!$B$199/12,IF(K$1<=4,'Base Case Inputs'!$B$200/12,IF(K$1<=5,'Base Case Inputs'!$B$201/12,IF(K$1<=6,'Base Case Inputs'!$B$202/12,'Base Case Inputs'!$B$203/12)))))))} -> 155789.13 | L14: {=IF(L$3<=14,IF(L$1<=1,SUMPRODUCT((Personnel!$F$172:$F$186<=L$3)*Personnel!$G$172:$G$186),SUMPRODUCT((Personnel!$F$172:$F$186<=L$3)*Personnel!$I$172:$I$186)),IF(L$1<=1,'Base Case Inputs'!$B$197/12,IF(L$1<=2,'Base Case Inputs'!$B$198/12,IF(L$1<=3,'Base Case Inputs'!$B$199/12,IF(L$1<=4,'Base Case Inputs'!$B$200/12,IF(L$1<=5,'Base Case Inputs'!$B$201/12,IF(L$1<=6,'Base Case Inputs'!$B$202/12,'Base Case Inputs'!$B$203/12)))))))} -> 164946.47 | M14: {=IF(M$3<=14,IF(M$1<=1,SUMPRODUCT((Personnel!$F$172:$F$186<=M$3)*Personnel!$G$172:$G$186),SUMPRODUCT((Personnel!$F$172:$F$186<=M$3)*Personnel!$I$172:$I$186)),IF(M$1<=1,'Base Case Inputs'!$B$197/12,IF(M$1<=2,'Base Case Inputs'!$B$198/12,IF(M$1<=3,'Base Case Inputs'!$B$199/12,IF(M$1<=4,'Base Case Inputs'!$B$200/12,IF(M$1<=5,'Base Case Inputs'!$B$201/12,IF(M$1<=6,'Base Case Inputs'!$B$202/12,'Base Case Inputs'!$B$203/12)))))))} -> 164946.47 | N14: {=IF(N$3<=14,IF(N$1<=1,SUMPRODUCT((Personnel!$F$172:$F$186<=N$3)*Personnel!$G$172:$G$186),SUMPRODUCT((Personnel!$F$172:$F$186<=N$3)*Personnel!$I$172:$I$186)),IF(N$1<=1,'Base Case Inputs'!$B$197/12,IF(N$1<=2,'Base Case Inputs'!$B$198/12,IF(N$1<=3,'Base Case Inputs'!$B$199/12,IF(N$1<=4,'Base Case Inputs'!$B$200/12,IF(N$1<=5,'Base Case Inputs'!$B$201/12,IF(N$1<=6,'Base Case Inputs'!$B$202/12,'Base Case Inputs'!$B$203/12)))))))} -> 164946.47 | ... CL14: {=IF(CL$3<=14,IF(CL$1<=1,SUMPRODUCT((Personnel!$F$172:$F$186<=CL$3)*Personnel!$G$172:$G$186),SUMPRODUCT((Personnel!$F$172:$F$186<=CL$3)*Personnel!$I$172:$I$186)),IF(CL$1<=1,'Base Case Inputs'!$B$197/12,IF(CL$1<=2,'Base Case Inputs'!$B$198/12,IF(CL$1<=3,'Base Case Inputs'!$B$199/12,IF(CL$1<=4,'Base Case Inputs'!$B$200/12,IF(CL$1<=5,'Base Case Inputs'!$B$201/12,IF(CL$1<=6,'Base Case Inputs'!$B$202/12,'Base Case Inputs'!$B$203/12)))))))} -> 1270044.1
B15: kg Market | C15: Production | G15: =IF(G$4<$E$12,0,IF(G$4<EDATE($E$12,3),'Base Case Inputs'!$B$8/12*'Base Case Inputs'!$B$166,IF(G$4<EDATE($E$12,9),'Base Case Inputs'!$B$8/12*'Base Case Inputs'!$B$167,IF(G$4<EDATE($E$12,12),'Base Case Inputs'!$B$8/12*'Base Case Inputs'!$B$168,'Base Case Inputs'!$B$8/12*'Base Case Inputs'!$B$169)))) -> 0 | H15: =IF(H$4<$E$12,0,IF(H$4<EDATE($E$12,3),'Base Case Inputs'!$B$8/12*'Base Case Inputs'!$B$166,IF(H$4<EDATE($E$12,9),'Base Case Inputs'!$B$8/12*'Base Case Inputs'!$B$167,IF(H$4<EDATE($E$12,12),'Base Case Inputs'!$B$8/12*'Base Case Inputs'!$B$168,'Base Case Inputs'!$B$8/12*'Base Case Inputs'!$B$169)))) -> 0 | I15: =IF(I$4<$E$12,0,IF(I$4<EDATE($E$12,3),'Base Case Inputs'!$B$8/12*'Base Case Inputs'!$B$166,IF(I$4<EDATE($E$12,9),'Base Case Inputs'!$B$8/12*'Base Case Inputs'!$B$167,IF(I$4<EDATE($E$12,12),'Base Case Inputs'!$B$8/12*'Base Case Inputs'!$B$168,'Base Case Inputs'!$B$8/12*'Base Case Inputs'!$B$169)))) -> 0 | J15: =IF(J$4<$E$12,0,IF(J$4<EDATE($E$12,3),'Base Case Inputs'!$B$8/12*'Base Case Inputs'!$B$166,IF(J$4<EDATE($E$12,9),'Base Case Inputs'!$B$8/12*'Base Case Inputs'!$B$167,IF(J$4<EDATE($E$12,12),'Base Case Inputs'!$B$8/12*'Base Case Inputs'!$B$168,'Base Case Inputs'!$B$8/12*'Base Case Inputs'!$B$169)))) -> 0 | K15: =IF(K$4<$E$12,0,IF(K$4<EDATE($E$12,3),'Base Case Inputs'!$B$8/12*'Base Case Inputs'!$B$166,IF(K$4<EDATE($E$12,9),'Base Case Inputs'!$B$8/12*'Base Case Inputs'!$B$167,IF(K$4<EDATE($E$12,12),'Base Case Inputs'!$B$8/12*'Base Case Inputs'!$B$168,'Base Case Inputs'!$B$8/12*'Base Case Inputs'!$B$169)))) -> 0 | L15: =IF(L$4<$E$12,0,IF(L$4<EDATE($E$12,3),'Base Case Inputs'!$B$8/12*'Base Case Inputs'!$B$166,IF(L$4<EDATE($E$12,9),'Base Case Inputs'!$B$8/12*'Base Case Inputs'!$B$167,IF(L$4<EDATE($E$12,12),'Base Case Inputs'!$B$8/12*'Base Case Inputs'!$B$168,'Base Case Inputs'!$B$8/12*'Base Case Inputs'!$B$169)))) -> 0 | M15: =IF(M$4<$E$12,0,IF(M$4<EDATE($E$12,3),'Base Case Inputs'!$B$8/12*'Base Case Inputs'!$B$166,IF(M$4<EDATE($E$12,9),'Base Case Inputs'!$B$8/12*'Base Case Inputs'!$B$167,IF(M$4<EDATE($E$12,12),'Base Case Inputs'!$B$8/12*'Base Case Inputs'!$B$168,'Base Case Inputs'!$B$8/12*'Base Case Inputs'!$B$169)))) -> 0 | N15: =IF(N$4<$E$12,0,IF(N$4<EDATE($E$12,3),'Base Case Inputs'!$B$8/12*'Base Case Inputs'!$B$166,IF(N$4<EDATE($E$12,9),'Base Case Inputs'!$B$8/12*'Base Case Inputs'!$B$167,IF(N$4<EDATE($E$12,12),'Base Case Inputs'!$B$8/12*'Base Case Inputs'!$B$168,'Base Case Inputs'!$B$8/12*'Base Case Inputs'!$B$169)))) -> 0 | ... CL15: =IF(CL$4<$E$12,0,IF(CL$4<EDATE($E$12,3),'Base Case Inputs'!$B$8/12*'Base Case Inputs'!$B$166,IF(CL$4<EDATE($E$12,9),'Base Case Inputs'!$B$8/12*'Base Case Inputs'!$B$167,IF(CL$4<EDATE($E$12,12),'Base Case Inputs'!$B$8/12*'Base Case Inputs'!$B$168,'Base Case Inputs'!$B$8/12*'Base Case Inputs'!$B$169)))) -> 75000
B16: ='Base Case Inputs'!$B$18 -> 25 | C16: Revenue | G16: =G15*$B$16 -> 0 | H16: =H15*$B$16 -> 0 | I16: =I15*$B$16 -> 0 | J16: =J15*$B$16 -> 0 | K16: =K15*$B$16 -> 0 | L16: =L15*$B$16 -> 0 | M16: =M15*$B$16 -> 0 | N16: =N15*$B$16 -> 0 | ... CL16: =CL15*$B$16 -> 1875000
C17: COGS | G17: =G15*('Base Case Inputs'!$B$106*(1+'Base Case Inputs'!$B$88)^(G$1-1)) -> 0 | H17: =H15*('Base Case Inputs'!$B$106*(1+'Base Case Inputs'!$B$88)^(H$1-1)) -> 0 | I17: =I15*('Base Case Inputs'!$B$106*(1+'Base Case Inputs'!$B$88)^(I$1-1)) -> 0 | J17: =J15*('Base Case Inputs'!$B$106*(1+'Base Case Inputs'!$B$88)^(J$1-1)) -> 0 | K17: =K15*('Base Case Inputs'!$B$106*(1+'Base Case Inputs'!$B$88)^(K$1-1)) -> 0 | L17: =L15*('Base Case Inputs'!$B$106*(1+'Base Case Inputs'!$B$88)^(L$1-1)) -> 0 | M17: =M15*('Base Case Inputs'!$B$106*(1+'Base Case Inputs'!$B$88)^(M$1-1)) -> 0 | N17: =N15*('Base Case Inputs'!$B$106*(1+'Base Case Inputs'!$B$88)^(N$1-1)) -> 0 | ... CL17: =CL15*('Base Case Inputs'!$B$106*(1+'Base Case Inputs'!$B$88)^(CL$1-1)) -> 227871.79
C18: Gross Profit | G18: =G15*($B$16-('Base Case Inputs'!$B$106*(1+'Base Case Inputs'!$B$88)^(G$1-1))) -> 0 | H18: =H15*($B$16-('Base Case Inputs'!$B$106*(1+'Base Case Inputs'!$B$88)^(H$1-1))) -> 0 | I18: =I15*($B$16-('Base Case Inputs'!$B$106*(1+'Base Case Inputs'!$B$88)^(I$1-1))) -> 0 | J18: =J15*($B$16-('Base Case Inputs'!$B$106*(1+'Base Case Inputs'!$B$88)^(J$1-1))) -> 0 | K18: =K15*($B$16-('Base Case Inputs'!$B$106*(1+'Base Case Inputs'!$B$88)^(K$1-1))) -> 0 | L18: =L15*($B$16-('Base Case Inputs'!$B$106*(1+'Base Case Inputs'!$B$88)^(L$1-1))) -> 0 | M18: =M15*($B$16-('Base Case Inputs'!$B$106*(1+'Base Case Inputs'!$B$88)^(M$1-1))) -> 0 | N18: =N15*($B$16-('Base Case Inputs'!$B$106*(1+'Base Case Inputs'!$B$88)^(N$1-1))) -> 0 | ... CL18: =CL15*($B$16-('Base Case Inputs'!$B$106*(1+'Base Case Inputs'!$B$88)^(CL$1-1))) -> 1647128.2
B20: GH2x2 - OKC | D20: 46296 | E20: 46661 | F20: =IF(D20<='Base Case Inputs'!$B$124,1,0) -> 1
B21: kg Opex | C21: Capital Costs | P21: =('Facility AFE'!$C$53/12) -> 256250 | Q21: =('Facility AFE'!$C$53/12) -> 256250 | R21: =('Facility AFE'!$C$53/12) -> 256250 | S21: =('Facility AFE'!$C$53/12) -> 256250 | T21: =('Facility AFE'!$C$53/12) -> 256250 | U21: =('Facility AFE'!$C$53/12) -> 256250 | V21: =('Facility AFE'!$C$53/12) -> 256250 | W21: =('Facility AFE'!$C$53/12) -> 256250 | ... AA21: =('Facility AFE'!$C$53/12) -> 256250 | AB21: =('Facility AFE'!$C$92/12) -> 125000 | AC21: =('Facility AFE'!$C$92/12) -> 125000 | AD21: =('Facility AFE'!$C$92/12) -> 125000 | AE21: =('Facility AFE'!$C$92/12) -> 125000 | AF21: =('Facility AFE'!$C$92/12) -> 125000 | AG21: =('Facility AFE'!$C$92/12) -> 125000 | AH21: =('Facility AFE'!$C$92/12) -> 125000 | AI21: =('Facility AFE'!$C$92/12) -> 125000 | ... BW21: =('Facility AFE'!$C$92/12) -> 125000
B22: ='Base Case Inputs'!$B$15 -> 2.62 | C22: Personnel | G22: =IF(G$4<$E$20,0,'Base Case Inputs'!$B$205/12) -> 0 | H22: =IF(H$4<$E$20,0,'Base Case Inputs'!$B$205/12) -> 0 | I22: =IF(I$4<$E$20,0,'Base Case Inputs'!$B$205/12) -> 0 | J22: =IF(J$4<$E$20,0,'Base Case Inputs'!$B$205/12) -> 0 | K22: =IF(K$4<$E$20,0,'Base Case Inputs'!$B$205/12) -> 0 | L22: =IF(L$4<$E$20,0,'Base Case Inputs'!$B$205/12) -> 0 | M22: =IF(M$4<$E$20,0,'Base Case Inputs'!$B$205/12) -> 0 | N22: =IF(N$4<$E$20,0,'Base Case Inputs'!$B$205/12) -> 0 | ... CL22: =IF(CL$4<$E$20,0,'Base Case Inputs'!$B$205/12) -> 101167.59
B23: kg Market | C23: Production | G23: =IF(G$4<$E$20,0,IF(G$4<EDATE($E$20,6),'Base Case Inputs'!$B$8/12*'Base Case Inputs'!$B$173,'Base Case Inputs'!$B$8/12*'Base Case Inputs'!$B$174)) -> 0 | H23: =IF(H$4<$E$20,0,IF(H$4<EDATE($E$20,6),'Base Case Inputs'!$B$8/12*'Base Case Inputs'!$B$173,'Base Case Inputs'!$B$8/12*'Base Case Inputs'!$B$174)) -> 0 | I23: =IF(I$4<$E$20,0,IF(I$4<EDATE($E$20,6),'Base Case Inputs'!$B$8/12*'Base Case Inputs'!$B$173,'Base Case Inputs'!$B$8/12*'Base Case Inputs'!$B$174)) -> 0 | J23: =IF(J$4<$E$20,0,IF(J$4<EDATE($E$20,6),'Base Case Inputs'!$B$8/12*'Base Case Inputs'!$B$173,'Base Case Inputs'!$B$8/12*'Base Case Inputs'!$B$174)) -> 0 | K23: =IF(K$4<$E$20,0,IF(K$4<EDATE($E$20,6),'Base Case Inputs'!$B$8/12*'Base Case Inputs'!$B$173,'Base Case Inputs'!$B$8/12*'Base Case Inputs'!$B$174)) -> 0 | L23: =IF(L$4<$E$20,0,IF(L$4<EDATE($E$20,6),'Base Case Inputs'!$B$8/12*'Base Case Inputs'!$B$173,'Base Case Inputs'!$B$8/12*'Base Case Inputs'!$B$174)) -> 0 | M23: =IF(M$4<$E$20,0,IF(M$4<EDATE($E$20,6),'Base Case Inputs'!$B$8/12*'Base Case Inputs'!$B$173,'Base Case Inputs'!$B$8/12*'Base Case Inputs'!$B$174)) -> 0 | N23: =IF(N$4<$E$20,0,IF(N$4<EDATE($E$20,6),'Base Case Inputs'!$B$8/12*'Base Case Inputs'!$B$173,'Base Case Inputs'!$B$8/12*'Base Case Inputs'!$B$174)) -> 0 | ... CL23: =IF(CL$4<$E$20,0,IF(CL$4<EDATE($E$20,6),'Base Case Inputs'!$B$8/12*'Base Case Inputs'!$B$173,'Base Case Inputs'!$B$8/12*'Base Case Inputs'!$B$174)) -> 75000
B24: ='Base Case Inputs'!$B$18 -> 25 | C24: Revenue | G24: =G23*$B$16 -> 0 | H24: =H23*$B$16 -> 0 | I24: =I23*$B$16 -> 0 | J24: =J23*$B$16 -> 0 | K24: =K23*$B$16 -> 0 | L24: =L23*$B$16 -> 0 | M24: =M23*$B$16 -> 0 | N24: =N23*$B$16 -> 0 | ... CL24: =CL23*$B$16 -> 1875000
C25: COGS | G25: =G23*('Base Case Inputs'!$B$107*(1+'Base Case Inputs'!$B$88)^(G$1-1)) -> 0 | H25: =H23*('Base Case Inputs'!$B$107*(1+'Base Case Inputs'!$B$88)^(H$1-1)) -> 0 | I25: =I23*('Base Case Inputs'!$B$107*(1+'Base Case Inputs'!$B$88)^(I$1-1)) -> 0 | J25: =J23*('Base Case Inputs'!$B$107*(1+'Base Case Inputs'!$B$88)^(J$1-1)) -> 0 | K25: =K23*('Base Case Inputs'!$B$107*(1+'Base Case Inputs'!$B$88)^(K$1-1)) -> 0 | L25: =L23*('Base Case Inputs'!$B$107*(1+'Base Case Inputs'!$B$88)^(L$1-1)) -> 0 | M25: =M23*('Base Case Inputs'!$B$107*(1+'Base Case Inputs'!$B$88)^(M$1-1)) -> 0 | N25: =N23*('Base Case Inputs'!$B$107*(1+'Base Case Inputs'!$B$88)^(N$1-1)) -> 0 | ... CL25: =CL23*('Base Case Inputs'!$B$107*(1+'Base Case Inputs'!$B$88)^(CL$1-1)) -> 227871.79
C26: Gross Profit | G26: =G23*($B$16-('Base Case Inputs'!$B$107*(1+'Base Case Inputs'!$B$88)^(G$1-1))) -> 0 | H26: =H23*($B$16-('Base Case Inputs'!$B$107*(1+'Base Case Inputs'!$B$88)^(H$1-1))) -> 0 | I26: =I23*($B$16-('Base Case Inputs'!$B$107*(1+'Base Case Inputs'!$B$88)^(I$1-1))) -> 0 | J26: =J23*($B$16-('Base Case Inputs'!$B$107*(1+'Base Case Inputs'!$B$88)^(J$1-1))) -> 0 | K26: =K23*($B$16-('Base Case Inputs'!$B$107*(1+'Base Case Inputs'!$B$88)^(K$1-1))) -> 0 | L26: =L23*($B$16-('Base Case Inputs'!$B$107*(1+'Base Case Inputs'!$B$88)^(L$1-1))) -> 0 | M26: =M23*($B$16-('Base Case Inputs'!$B$107*(1+'Base Case Inputs'!$B$88)^(M$1-1))) -> 0 | N26: =N23*($B$16-('Base Case Inputs'!$B$107*(1+'Base Case Inputs'!$B$88)^(N$1-1))) -> 0 | ... CL26: =CL23*($B$16-('Base Case Inputs'!$B$107*(1+'Base Case Inputs'!$B$88)^(CL$1-1))) -> 1647128.2
S27: =S21*12 -> 3075000 | AE27: =AE21*12 -> 1500000
B28: GH2x3 - Seattle | D28: 46478 | E28: 46844 | F28: =IF(D28<='Base Case Inputs'!$B$124,1,0) -> 1 | S28: =S21*12+S13*12 -> 4075000
B29: kg Opex | C29: Capital Costs | AB29: =('Facility AFE'!$C$53/12) -> 256250 | AC29: =('Facility AFE'!$C$53/12) -> 256250 | AD29: =('Facility AFE'!$C$53/12) -> 256250 | AE29: =('Facility AFE'!$C$53/12) -> 256250 | AF29: =('Facility AFE'!$C$53/12) -> 256250 | AG29: =('Facility AFE'!$C$53/12) -> 256250 | AH29: =('Facility AFE'!$C$53/12) -> 256250 | AI29: =('Facility AFE'!$C$53/12) -> 256250 | ... AM29: =('Facility AFE'!$C$53/12) -> 256250 | AN29: =('Facility AFE'!$C$92/12) -> 125000 | AO29: =('Facility AFE'!$C$92/12) -> 125000 | AP29: =('Facility AFE'!$C$92/12) -> 125000 | AQ29: =('Facility AFE'!$C$92/12) -> 125000 | AR29: =('Facility AFE'!$C$92/12) -> 125000 | AS29: =('Facility AFE'!$C$92/12) -> 125000 | AT29: =('Facility AFE'!$C$92/12) -> 125000 | AU29: =('Facility AFE'!$C$92/12) -> 125000 | ... CI29: =('Facility AFE'!$C$92/12) -> 125000
B30: ='Base Case Inputs'!$B$15 -> 2.62 | C30: Personnel | G30: =IF(G$4<$E$28,0,'Base Case Inputs'!$B$205/12) -> 0 | H30: =IF(H$4<$E$28,0,'Base Case Inputs'!$B$205/12) -> 0 | I30: =IF(I$4<$E$28,0,'Base Case Inputs'!$B$205/12) -> 0 | J30: =IF(J$4<$E$28,0,'Base Case Inputs'!$B$205/12) -> 0 | K30: =IF(K$4<$E$28,0,'Base Case Inputs'!$B$205/12) -> 0 | L30: =IF(L$4<$E$28,0,'Base Case Inputs'!$B$205/12) -> 0 | M30: =IF(M$4<$E$28,0,'Base Case Inputs'!$B$205/12) -> 0 | N30: =IF(N$4<$E$28,0,'Base Case Inputs'!$B$205/12) -> 0 | ... CL30: =IF(CL$4<$E$28,0,'Base Case Inputs'!$B$205/12) -> 101167.59
B31: kg Market | C31: Production | G31: =IF(G$4<$E$28,0,IF(G$4<EDATE($E$28,6),'Base Case Inputs'!$B$8/12*'Base Case Inputs'!$B$173,'Base Case Inputs'!$B$8/12*'Base Case Inputs'!$B$174)) -> 0 | H31: =IF(H$4<$E$28,0,IF(H$4<EDATE($E$28,6),'Base Case Inputs'!$B$8/12*'Base Case Inputs'!$B$173,'Base Case Inputs'!$B$8/12*'Base Case Inputs'!$B$174)) -> 0 | I31: =IF(I$4<$E$28,0,IF(I$4<EDATE($E$28,6),'Base Case Inputs'!$B$8/12*'Base Case Inputs'!$B$173,'Base Case Inputs'!$B$8/12*'Base Case Inputs'!$B$174)) -> 0 | J31: =IF(J$4<$E$28,0,IF(J$4<EDATE($E$28,6),'Base Case Inputs'!$B$8/12*'Base Case Inputs'!$B$173,'Base Case Inputs'!$B$8/12*'Base Case Inputs'!$B$174)) -> 0 | K31: =IF(K$4<$E$28,0,IF(K$4<EDATE($E$28,6),'Base Case Inputs'!$B$8/12*'Base Case Inputs'!$B$173,'Base Case Inputs'!$B$8/12*'Base Case Inputs'!$B$174)) -> 0 | L31: =IF(L$4<$E$28,0,IF(L$4<EDATE($E$28,6),'Base Case Inputs'!$B$8/12*'Base Case Inputs'!$B$173,'Base Case Inputs'!$B$8/12*'Base Case Inputs'!$B$174)) -> 0 | M31: =IF(M$4<$E$28,0,IF(M$4<EDATE($E$28,6),'Base Case Inputs'!$B$8/12*'Base Case Inputs'!$B$173,'Base Case Inputs'!$B$8/12*'Base Case Inputs'!$B$174)) -> 0 | N31: =IF(N$4<$E$28,0,IF(N$4<EDATE($E$28,6),'Base Case Inputs'!$B$8/12*'Base Case Inputs'!$B$173,'Base Case Inputs'!$B$8/12*'Base Case Inputs'!$B$174)) -> 0 | ... CL31: =IF(CL$4<$E$28,0,IF(CL$4<EDATE($E$28,6),'Base Case Inputs'!$B$8/12*'Base Case Inputs'!$B$173,'Base Case Inputs'!$B$8/12*'Base Case Inputs'!$B$174)) -> 75000
B32: ='Base Case Inputs'!$B$18 -> 25 | C32: Revenue | G32: =G31*$B$16 -> 0 | H32: =H31*$B$16 -> 0 | I32: =I31*$B$16 -> 0 | J32: =J31*$B$16 -> 0 | K32: =K31*$B$16 -> 0 | L32: =L31*$B$16 -> 0 | M32: =M31*$B$16 -> 0 | N32: =N31*$B$16 -> 0 | ... CL32: =CL31*$B$16 -> 1875000
C33: COGS | G33: =G31*('Base Case Inputs'!$B$108*(1+'Base Case Inputs'!$B$88)^(G$1-1)) -> 0 | H33: =H31*('Base Case Inputs'!$B$108*(1+'Base Case Inputs'!$B$88)^(H$1-1)) -> 0 | I33: =I31*('Base Case Inputs'!$B$108*(1+'Base Case Inputs'!$B$88)^(I$1-1)) -> 0 | J33: =J31*('Base Case Inputs'!$B$108*(1+'Base Case Inputs'!$B$88)^(J$1-1)) -> 0 | K33: =K31*('Base Case Inputs'!$B$108*(1+'Base Case Inputs'!$B$88)^(K$1-1)) -> 0 | L33: =L31*('Base Case Inputs'!$B$108*(1+'Base Case Inputs'!$B$88)^(L$1-1)) -> 0 | M33: =M31*('Base Case Inputs'!$B$108*(1+'Base Case Inputs'!$B$88)^(M$1-1)) -> 0 | N33: =N31*('Base Case Inputs'!$B$108*(1+'Base Case Inputs'!$B$88)^(N$1-1)) -> 0 | ... CL33: =CL31*('Base Case Inputs'!$B$108*(1+'Base Case Inputs'!$B$88)^(CL$1-1)) -> 329539.9
C34: Gross Profit | G34: =G31*($B$16-('Base Case Inputs'!$B$108*(1+'Base Case Inputs'!$B$88)^(G$1-1))) -> 0 | H34: =H31*($B$16-('Base Case Inputs'!$B$108*(1+'Base Case Inputs'!$B$88)^(H$1-1))) -> 0 | I34: =I31*($B$16-('Base Case Inputs'!$B$108*(1+'Base Case Inputs'!$B$88)^(I$1-1))) -> 0 | J34: =J31*($B$16-('Base Case Inputs'!$B$108*(1+'Base Case Inputs'!$B$88)^(J$1-1))) -> 0 | K34: =K31*($B$16-('Base Case Inputs'!$B$108*(1+'Base Case Inputs'!$B$88)^(K$1-1))) -> 0 | L34: =L31*($B$16-('Base Case Inputs'!$B$108*(1+'Base Case Inputs'!$B$88)^(L$1-1))) -> 0 | M34: =M31*($B$16-('Base Case Inputs'!$B$108*(1+'Base Case Inputs'!$B$88)^(M$1-1))) -> 0 | N34: =N31*($B$16-('Base Case Inputs'!$B$108*(1+'Base Case Inputs'!$B$88)^(N$1-1))) -> 0 | ... CL34: =CL31*($B$16-('Base Case Inputs'!$B$108*(1+'Base Case Inputs'!$B$88)^(CL$1-1))) -> 1545460.1
B36: GH2x4 - Spokane | D36: 46631 | E36: 46935 | F36: =IF(D36<='Base Case Inputs'!$B$124,1,0) -> 1 | AE36: =AE29*12+AE21*12+AE13*12+AE37*12 -> 9150000
B37: kg Opex | C37: Capital Costs | AE37: ='Facility AFE'!$C$53/12 -> 256250 | AF37: ='Facility AFE'!$C$53/12 -> 256250 | AG37: ='Facility AFE'!$C$53/12 -> 256250 | AH37: ='Facility AFE'!$C$53/12 -> 256250 | AI37: ='Facility AFE'!$C$53/12 -> 256250 | AJ37: ='Facility AFE'!$C$53/12 -> 256250 | AK37: ='Facility AFE'!$C$53/12 -> 256250 | AL37: ='Facility AFE'!$C$53/12 -> 256250 | ... AP37: ='Facility AFE'!$C$53/12 -> 256250 | AQ37: ='Facility AFE'!$C$92/12 -> 125000 | AR37: ='Facility AFE'!$C$92/12 -> 125000 | AS37: ='Facility AFE'!$C$92/12 -> 125000 | AT37: ='Facility AFE'!$C$92/12 -> 125000 | AU37: ='Facility AFE'!$C$92/12 -> 125000 | AV37: ='Facility AFE'!$C$92/12 -> 125000 | AW37: ='Facility AFE'!$C$92/12 -> 125000 | AX37: ='Facility AFE'!$C$92/12 -> 125000 | ... BB37: ='Facility AFE'!$C$92/12 -> 125000 | BC37: =0/12 -> 0 | BD37: =0/12 -> 0 | BE37: =0/12 -> 0 | BF37: =0/12 -> 0 | BG37: =0/12 -> 0 | BH37: =0/12 -> 0 | BI37: =0/12 -> 0 | BJ37: =0/12 -> 0 | ... CL37: =0/12 -> 0
B38: ='Base Case Inputs'!$B$15 -> 2.62 | C38: Personnel | G38: =IF(G$4<$E$36,0,'Base Case Inputs'!$B$205/12) -> 0 | H38: =IF(H$4<$E$36,0,'Base Case Inputs'!$B$205/12) -> 0 | I38: =IF(I$4<$E$36,0,'Base Case Inputs'!$B$205/12) -> 0 | J38: =IF(J$4<$E$36,0,'Base Case Inputs'!$B$205/12) -> 0 | K38: =IF(K$4<$E$36,0,'Base Case Inputs'!$B$205/12) -> 0 | L38: =IF(L$4<$E$36,0,'Base Case Inputs'!$B$205/12) -> 0 | M38: =IF(M$4<$E$36,0,'Base Case Inputs'!$B$205/12) -> 0 | N38: =IF(N$4<$E$36,0,'Base Case Inputs'!$B$205/12) -> 0 | ... CL38: =IF(CL$4<$E$36,0,'Base Case Inputs'!$B$205/12) -> 101167.59
B39: kg Market | C39: Production | G39: =IF(G$4<$E$36,0,IF(G$4<EDATE($E$36,5),'Base Case Inputs'!$B$8/12*'Base Case Inputs'!$B$178,'Base Case Inputs'!$B$8/12*'Base Case Inputs'!$B$179)) -> 0 | H39: =IF(H$4<$E$36,0,IF(H$4<EDATE($E$36,5),'Base Case Inputs'!$B$8/12*'Base Case Inputs'!$B$178,'Base Case Inputs'!$B$8/12*'Base Case Inputs'!$B$179)) -> 0 | I39: =IF(I$4<$E$36,0,IF(I$4<EDATE($E$36,5),'Base Case Inputs'!$B$8/12*'Base Case Inputs'!$B$178,'Base Case Inputs'!$B$8/12*'Base Case Inputs'!$B$179)) -> 0 | J39: =IF(J$4<$E$36,0,IF(J$4<EDATE($E$36,5),'Base Case Inputs'!$B$8/12*'Base Case Inputs'!$B$178,'Base Case Inputs'!$B$8/12*'Base Case Inputs'!$B$179)) -> 0 | K39: =IF(K$4<$E$36,0,IF(K$4<EDATE($E$36,5),'Base Case Inputs'!$B$8/12*'Base Case Inputs'!$B$178,'Base Case Inputs'!$B$8/12*'Base Case Inputs'!$B$179)) -> 0 | L39: =IF(L$4<$E$36,0,IF(L$4<EDATE($E$36,5),'Base Case Inputs'!$B$8/12*'Base Case Inputs'!$B$178,'Base Case Inputs'!$B$8/12*'Base Case Inputs'!$B$179)) -> 0 | M39: =IF(M$4<$E$36,0,IF(M$4<EDATE($E$36,5),'Base Case Inputs'!$B$8/12*'Base Case Inputs'!$B$178,'Base Case Inputs'!$B$8/12*'Base Case Inputs'!$B$179)) -> 0 | N39: =IF(N$4<$E$36,0,IF(N$4<EDATE($E$36,5),'Base Case Inputs'!$B$8/12*'Base Case Inputs'!$B$178,'Base Case Inputs'!$B$8/12*'Base Case Inputs'!$B$179)) -> 0 | ... CL39: =IF(CL$4<$E$36,0,IF(CL$4<EDATE($E$36,5),'Base Case Inputs'!$B$8/12*'Base Case Inputs'!$B$178,'Base Case Inputs'!$B$8/12*'Base Case Inputs'!$B$179)) -> 75000
B40: ='Base Case Inputs'!$B$18 -> 25 | C40: Revenue | G40: =G39*$B$16 -> 0 | H40: =H39*$B$16 -> 0 | I40: =I39*$B$16 -> 0 | J40: =J39*$B$16 -> 0 | K40: =K39*$B$16 -> 0 | L40: =L39*$B$16 -> 0 | M40: =M39*$B$16 -> 0 | N40: =N39*$B$16 -> 0 | ... CL40: =CL39*$B$16 -> 1875000
C41: COGS | G41: =G39*('Base Case Inputs'!$B$109*(1+'Base Case Inputs'!$B$88)^(G$1-1)) -> 0 | H41: =H39*('Base Case Inputs'!$B$109*(1+'Base Case Inputs'!$B$88)^(H$1-1)) -> 0 | I41: =I39*('Base Case Inputs'!$B$109*(1+'Base Case Inputs'!$B$88)^(I$1-1)) -> 0 | J41: =J39*('Base Case Inputs'!$B$109*(1+'Base Case Inputs'!$B$88)^(J$1-1)) -> 0 | K41: =K39*('Base Case Inputs'!$B$109*(1+'Base Case Inputs'!$B$88)^(K$1-1)) -> 0 | L41: =L39*('Base Case Inputs'!$B$109*(1+'Base Case Inputs'!$B$88)^(L$1-1)) -> 0 | M41: =M39*('Base Case Inputs'!$B$109*(1+'Base Case Inputs'!$B$88)^(M$1-1)) -> 0 | N41: =N39*('Base Case Inputs'!$B$109*(1+'Base Case Inputs'!$B$88)^(N$1-1)) -> 0 | ... CL41: =CL39*('Base Case Inputs'!$B$109*(1+'Base Case Inputs'!$B$88)^(CL$1-1)) -> 254015.02
C42: Gross Profit | G42: =G39*($B$16-('Base Case Inputs'!$B$109*(1+'Base Case Inputs'!$B$88)^(G$1-1))) -> 0 | H42: =H39*($B$16-('Base Case Inputs'!$B$109*(1+'Base Case Inputs'!$B$88)^(H$1-1))) -> 0 | I42: =I39*($B$16-('Base Case Inputs'!$B$109*(1+'Base Case Inputs'!$B$88)^(I$1-1))) -> 0 | J42: =J39*($B$16-('Base Case Inputs'!$B$109*(1+'Base Case Inputs'!$B$88)^(J$1-1))) -> 0 | K42: =K39*($B$16-('Base Case Inputs'!$B$109*(1+'Base Case Inputs'!$B$88)^(K$1-1))) -> 0 | L42: =L39*($B$16-('Base Case Inputs'!$B$109*(1+'Base Case Inputs'!$B$88)^(L$1-1))) -> 0 | M42: =M39*($B$16-('Base Case Inputs'!$B$109*(1+'Base Case Inputs'!$B$88)^(M$1-1))) -> 0 | N42: =N39*($B$16-('Base Case Inputs'!$B$109*(1+'Base Case Inputs'!$B$88)^(N$1-1))) -> 0 | ... CL42: =CL39*($B$16-('Base Case Inputs'!$B$109*(1+'Base Case Inputs'!$B$88)^(CL$1-1))) -> 1620985
B44: GH2x5 - Albuquerque | D44: 46784 | E44: 47088 | F44: =IF(D44<='Base Case Inputs'!$B$124,1,0) -> 0 | AQ44: =(AQ29+AQ37+AQ45+AQ53)*12 -> 9150000
B45: kg Opex | C45: Capital Costs | AN45: =('Facility AFE'!$C$53/12) -> 256250 | AO45: =('Facility AFE'!$C$53/12) -> 256250 | AP45: =('Facility AFE'!$C$53/12) -> 256250 | AQ45: =('Facility AFE'!$C$53/12) -> 256250 | AR45: =('Facility AFE'!$C$53/12) -> 256250 | AS45: =('Facility AFE'!$C$53/12) -> 256250 | AT45: =('Facility AFE'!$C$53/12) -> 256250 | AU45: =('Facility AFE'!$C$53/12) -> 256250 | ... AY45: =('Facility AFE'!$C$53/12) -> 256250 | AZ45: =('Facility AFE'!$C$92/12) -> 125000 | BA45: =('Facility AFE'!$C$92/12) -> 125000 | BB45: =('Facility AFE'!$C$92/12) -> 125000 | BC45: =('Facility AFE'!$C$92/12) -> 125000 | BD45: =('Facility AFE'!$C$92/12) -> 125000 | BE45: =('Facility AFE'!$C$92/12) -> 125000 | BF45: =('Facility AFE'!$C$92/12) -> 125000 | BG45: =('Facility AFE'!$C$92/12) -> 125000 | ... CL45: =('Facility AFE'!$C$92/12) -> 125000
B46: ='Base Case Inputs'!$B$15 -> 2.62 | C46: Personnel | G46: =IF(G$4<$E$44,0,'Base Case Inputs'!$B$205/12) -> 0 | H46: =IF(H$4<$E$44,0,'Base Case Inputs'!$B$205/12) -> 0 | I46: =IF(I$4<$E$44,0,'Base Case Inputs'!$B$205/12) -> 0 | J46: =IF(J$4<$E$44,0,'Base Case Inputs'!$B$205/12) -> 0 | K46: =IF(K$4<$E$44,0,'Base Case Inputs'!$B$205/12) -> 0 | L46: =IF(L$4<$E$44,0,'Base Case Inputs'!$B$205/12) -> 0 | M46: =IF(M$4<$E$44,0,'Base Case Inputs'!$B$205/12) -> 0 | N46: =IF(N$4<$E$44,0,'Base Case Inputs'!$B$205/12) -> 0 | ... CL46: =IF(CL$4<$E$44,0,'Base Case Inputs'!$B$205/12) -> 101167.59
B47: kg Market | C47: Production | G47: =IF(G$4<$E$44,0,IF(G$4<EDATE($E$44,5),'Base Case Inputs'!$B$8/12*'Base Case Inputs'!$B$178,'Base Case Inputs'!$B$8/12*'Base Case Inputs'!$B$179)) -> 0 | H47: =IF(H$4<$E$44,0,IF(H$4<EDATE($E$44,5),'Base Case Inputs'!$B$8/12*'Base Case Inputs'!$B$178,'Base Case Inputs'!$B$8/12*'Base Case Inputs'!$B$179)) -> 0 | I47: =IF(I$4<$E$44,0,IF(I$4<EDATE($E$44,5),'Base Case Inputs'!$B$8/12*'Base Case Inputs'!$B$178,'Base Case Inputs'!$B$8/12*'Base Case Inputs'!$B$179)) -> 0 | J47: =IF(J$4<$E$44,0,IF(J$4<EDATE($E$44,5),'Base Case Inputs'!$B$8/12*'Base Case Inputs'!$B$178,'Base Case Inputs'!$B$8/12*'Base Case Inputs'!$B$179)) -> 0 | K47: =IF(K$4<$E$44,0,IF(K$4<EDATE($E$44,5),'Base Case Inputs'!$B$8/12*'Base Case Inputs'!$B$178,'Base Case Inputs'!$B$8/12*'Base Case Inputs'!$B$179)) -> 0 | L47: =IF(L$4<$E$44,0,IF(L$4<EDATE($E$44,5),'Base Case Inputs'!$B$8/12*'Base Case Inputs'!$B$178,'Base Case Inputs'!$B$8/12*'Base Case Inputs'!$B$179)) -> 0 | M47: =IF(M$4<$E$44,0,IF(M$4<EDATE($E$44,5),'Base Case Inputs'!$B$8/12*'Base Case Inputs'!$B$178,'Base Case Inputs'!$B$8/12*'Base Case Inputs'!$B$179)) -> 0 | N47: =IF(N$4<$E$44,0,IF(N$4<EDATE($E$44,5),'Base Case Inputs'!$B$8/12*'Base Case Inputs'!$B$178,'Base Case Inputs'!$B$8/12*'Base Case Inputs'!$B$179)) -> 0 | ... CL47: =IF(CL$4<$E$44,0,IF(CL$4<EDATE($E$44,5),'Base Case Inputs'!$B$8/12*'Base Case Inputs'!$B$178,'Base Case Inputs'!$B$8/12*'Base Case Inputs'!$B$179)) -> 75000
B48: ='Base Case Inputs'!$B$18 -> 25 | C48: Revenue | G48: =G47*$B$16 -> 0 | H48: =H47*$B$16 -> 0 | I48: =I47*$B$16 -> 0 | J48: =J47*$B$16 -> 0 | K48: =K47*$B$16 -> 0 | L48: =L47*$B$16 -> 0 | M48: =M47*$B$16 -> 0 | N48: =N47*$B$16 -> 0 | ... CL48: =CL47*$B$16 -> 1875000
C49: COGS | G49: =G47*('Base Case Inputs'!$B$110*(1+'Base Case Inputs'!$B$88)^(G$1-1)) -> 0 | H49: =H47*('Base Case Inputs'!$B$110*(1+'Base Case Inputs'!$B$88)^(H$1-1)) -> 0 | I49: =I47*('Base Case Inputs'!$B$110*(1+'Base Case Inputs'!$B$88)^(I$1-1)) -> 0 | J49: =J47*('Base Case Inputs'!$B$110*(1+'Base Case Inputs'!$B$88)^(J$1-1)) -> 0 | K49: =K47*('Base Case Inputs'!$B$110*(1+'Base Case Inputs'!$B$88)^(K$1-1)) -> 0 | L49: =L47*('Base Case Inputs'!$B$110*(1+'Base Case Inputs'!$B$88)^(L$1-1)) -> 0 | M49: =M47*('Base Case Inputs'!$B$110*(1+'Base Case Inputs'!$B$88)^(M$1-1)) -> 0 | N49: =N47*('Base Case Inputs'!$B$110*(1+'Base Case Inputs'!$B$88)^(N$1-1)) -> 0 | ... CL49: =CL47*('Base Case Inputs'!$B$110*(1+'Base Case Inputs'!$B$88)^(CL$1-1)) -> 326220.13
C50: Gross Profit | G50: =G47*($B$16-('Base Case Inputs'!$B$110*(1+'Base Case Inputs'!$B$88)^(G$1-1))) -> 0 | H50: =H47*($B$16-('Base Case Inputs'!$B$110*(1+'Base Case Inputs'!$B$88)^(H$1-1))) -> 0 | I50: =I47*($B$16-('Base Case Inputs'!$B$110*(1+'Base Case Inputs'!$B$88)^(I$1-1))) -> 0 | J50: =J47*($B$16-('Base Case Inputs'!$B$110*(1+'Base Case Inputs'!$B$88)^(J$1-1))) -> 0 | K50: =K47*($B$16-('Base Case Inputs'!$B$110*(1+'Base Case Inputs'!$B$88)^(K$1-1))) -> 0 | L50: =L47*($B$16-('Base Case Inputs'!$B$110*(1+'Base Case Inputs'!$B$88)^(L$1-1))) -> 0 | M50: =M47*($B$16-('Base Case Inputs'!$B$110*(1+'Base Case Inputs'!$B$88)^(M$1-1))) -> 0 | N50: =N47*($B$16-('Base Case Inputs'!$B$110*(1+'Base Case Inputs'!$B$88)^(N$1-1))) -> 0 | ... CL50: =CL47*($B$16-('Base Case Inputs'!$B$110*(1+'Base Case Inputs'!$B$88)^(CL$1-1))) -> 1548779.9
B52: GH2x6 - Des Moines | D52: 46935 | E52: 47239 | F52: =IF(D52<='Base Case Inputs'!$B$124,1,0) -> 0
B53: kg Opex | C53: Capital Costs | AQ53: ='Facility AFE'!$C$53/12 -> 256250 | AR53: ='Facility AFE'!$C$53/12 -> 256250 | AS53: ='Facility AFE'!$C$53/12 -> 256250 | AT53: ='Facility AFE'!$C$53/12 -> 256250 | AU53: ='Facility AFE'!$C$53/12 -> 256250 | AV53: ='Facility AFE'!$C$53/12 -> 256250 | AW53: ='Facility AFE'!$C$53/12 -> 256250 | AX53: ='Facility AFE'!$C$53/12 -> 256250 | ... BB53: ='Facility AFE'!$C$53/12 -> 256250 | BC53: ='Facility AFE'!$C$92/12 -> 125000 | BD53: ='Facility AFE'!$C$92/12 -> 125000 | BE53: ='Facility AFE'!$C$92/12 -> 125000 | BF53: ='Facility AFE'!$C$92/12 -> 125000 | BG53: ='Facility AFE'!$C$92/12 -> 125000 | BH53: ='Facility AFE'!$C$92/12 -> 125000 | BI53: ='Facility AFE'!$C$92/12 -> 125000 | BJ53: ='Facility AFE'!$C$92/12 -> 125000 | ... BN53: ='Facility AFE'!$C$92/12 -> 125000 | BO53: =0/12 -> 0 | BP53: =0/12 -> 0 | BQ53: =0/12 -> 0 | BR53: =0/12 -> 0 | BS53: =0/12 -> 0 | BT53: =0/12 -> 0 | BU53: =0/12 -> 0 | BV53: =0/12 -> 0 | ... CL53: =0/12 -> 0
B54: ='Base Case Inputs'!$B$15 -> 2.62 | C54: Personnel | G54: =IF(G$4<$E$52,0,'Base Case Inputs'!$B$205/12) -> 0 | H54: =IF(H$4<$E$52,0,'Base Case Inputs'!$B$205/12) -> 0 | I54: =IF(I$4<$E$52,0,'Base Case Inputs'!$B$205/12) -> 0 | J54: =IF(J$4<$E$52,0,'Base Case Inputs'!$B$205/12) -> 0 | K54: =IF(K$4<$E$52,0,'Base Case Inputs'!$B$205/12) -> 0 | L54: =IF(L$4<$E$52,0,'Base Case Inputs'!$B$205/12) -> 0 | M54: =IF(M$4<$E$52,0,'Base Case Inputs'!$B$205/12) -> 0 | N54: =IF(N$4<$E$52,0,'Base Case Inputs'!$B$205/12) -> 0 | ... CL54: =IF(CL$4<$E$52,0,'Base Case Inputs'!$B$205/12) -> 101167.59
